Workbook

Sheet Выходные
A1: 45658
A2: 45659
A3: 45660
A4: 45661
A5: 45662
A6: 45663
A7: 45664
A8: 45665
A9: 45668
A10: 45669
A11: 45675
A12: 45676
... A236: 46387

Sheet history_import_log
A1: ts | B1: level | C1: message
A2: 46117.754 | B2: START | C2: Историческая загрузка. Период: 2026-01-01 - 2026-01-31
A3: 46117.754 | B3: RESULT | C3: Файл 01010404.xls: импортировано строк 572
A4: 46117.754 | B4: SUMMARY | C4: Исторический импорт отчётов: файлов просмотрено 1, файлов с данными 1, строк импортировано 572
A5: 46117.754 | B5: WARN | C5: Не найден лист точки для QR: 0
A6: 46117.757 | B6: SUMMARY | C6: Исторический QR пересчёт завершён. Период: 2026-01-01 - 2026-01-31, режим отметки E: без изменений
A7: 46117.758 | B7: DONE | C7: Финализация листов точек и дашборда завершена
A8: 46117.758 | B8: DONE | C8: Историческая загрузка завершена. Период: 2026-01-01 - 2026-01-31
A9: 46117.76 | B9: START | C9: Историческая загрузка. Период: 2026-01-01 - 2026-04-04
A10: 46117.76 | B10: WARN | C10: Не найден лист точки: 201
A11: 46117.76 | B11: RESULT | C11: Файл 01010404.xls: импортировано строк 1952
A12: 46117.76 | B12: SUMMARY | C12: Исторический импорт отчётов: файлов просмотрено 1, файлов с данными 1, строк импортировано 1952
A13: 46117.76 | B13: WARN | C13: Не найден лист точки для QR: 0
... A44: 46117.786 | B44: DONE | C44: Историческая загрузка завершена. Период: 2026-03-16 - 2026-04-04

Sheet import_log
A1: ts | B1: level | C1: fileName | D1: message | E1: extra
A2: 46112.382 | B2: ERROR | C2: 3424336.xls | D2: Drive.Files.insert is not a function
A3: 46112.382 | B3: SUMMARY | D3: Итог запуска. Всего файлов: 1, успешно: 0, с ошибками: 1, пропущено: 0
A4: 46112.383 | B4: ERROR | C4: 3424336.xls | D4: Drive.Files.insert is not a function
A5: 46112.383 | B5: SUMMARY | D5: Итог запуска. Всего файлов: 1, успешно: 0, с ошибками: 1, пропущено: 0
A6: 46112.383 | B6: ERROR | C6: 3424336.xls | D6: Drive.Files.insert is not a function
A7: 46112.383 | B7: SUMMARY | D7: Итог запуска. Всего файлов: 1, успешно: 0, с ошибками: 1, пропущено: 0
A8: 46112.386 | B8: RESULT | C8: 3424336.xls | D8: Успешно импортировано строк: 21
A9: 46112.386 | B9: WARN | C9: 3424336.xls | D9: Нет прав на удаление файла из папки: Access denied: DriveApp.
A10: 46112.386 | B10: SUMMARY | D10: Итог запуска. Всего файлов: 1, успешно: 1, с ошибками: 0, пропущено: 0
A11: 46112.391 | B11: SUMMARY | D11: Итог запуска. Всего файлов: 1, успешно: 0, с ошибками: 0, пропущено: 1
A12: 46113.266 | B12: SUMMARY | D12: Итог запуска. Всего файлов: 0, успешно: 0, с ошибками: 0, пропущено: 0
A13: 46114.266 | B13: RESULT | C13: 6578358.xls | D13: Успешно импортировано строк: 19
A14: 46114.267 | B14: WARN | C14: 6578358.xls | D14: Нет прав на удаление файла из папки: Access denied: DriveApp.
A15: 46114.267 | B15: RESULT | C15: 4881807.xls | D15: Успешно импортировано строк: 21
A16: 46114.267 | B16: WARN | C16: 4881807.xls | D16: Нет прав на удаление файла из папки: Access denied: DriveApp.
A17: 46114.267 | B17: RESULT | C17: 5770234.xls | D17: Успешно импортировано строк: 21
A18: 46114.267 | B18: WARN | C18: 5770234.xls | D18: Нет прав на удаление файла из папки: Access denied: DriveApp.
A19: 46114.267 | B19: SUMMARY | D19: Итог запуска. Всего файлов: 3, успешно: 3, с ошибками: 0, пропущено: 0
A20: 46114.595 | B20: SUMMARY | D20: Итог запуска. Всего файлов: 3, успешно: 0, с ошибками: 0, пропущено: 3
A21: 46114.596 | B21: SUMMARY | D21: Итог запуска. Всего файлов: 3, успешно: 0, с ошибками: 0, пропущено: 3
A22: 46114.596 | B22: SUMMARY | D22: Итог запуска. Всего файлов: 3, успешно: 0, с ошибками: 0, пропущено: 3
A23: 46114.627 | B23: SUMMARY | D23: Итог запуска. Всего файлов: 0, успешно: 0, с ошибками: 0, пропущено: 0
A24: 46115.355 | B24: RESULT | C24: 6580532.xlsx | D24: Успешно импортировано строк: 21
A25: 46115.355 | B25: WARN | C25: 6580532.xlsx | D25: Нет прав на удаление файла из папки: Доступ запрещен: DriveApp.
A26: 46115.355 | B26: SUMMARY | D26: Итог запуска. Всего файлов: 1, успешно: 1, с ошибками: 0, пропущено: 0
A27: 46115.445 | B27: SUMMARY | D27: Итог запуска. Всего файлов: 1, успешно: 0, с ошибками: 0, пропущено: 1
A28: 46116.266 | B28: SUMMARY | D28: Итог запуска. Всего файлов: 0, успешно: 0, с ошибками: 0, пропущено: 0
A29: 46117.266 | B29: SUMMARY | D29: Итог запуска. Всего файлов: 0, успешно: 0, с ошибками: 0, пропущено: 0
A30: 46118.267 | B30: RESULT | C30: 9683379.xls | D30: Успешно импортировано строк: 20
A31: 46118.267 | B31: WARN | C31: 9683379.xls | D31: Нет прав на удаление файла из папки: Access denied: DriveApp.
A32: 46118.267 | B32: SUMMARY | D32: Итог запуска. Всего файлов: 1, успешно: 1, с ошибками: 0, пропущено: 0
A33: 46118.679 | B33: SUMMARY | D33: Итог запуска. Всего файлов: 1, успешно: 0, с ошибками: 0, пропущено: 1
A34: 46118.693 | B34: RESULT | C34: 03040504.xls | D34: Успешно импортировано строк: 65
A35: 46118.693 | B35: WARN | C35: 03040504.xls | D35: Нет прав на удаление файла из папки: Доступ запрещен: DriveApp.
A36: 46118.693 | B36: SUMMARY | D36: Итог запуска. Всего файлов: 1, успешно: 1, с ошибками: 0, пропущено: 0
A37: 46118.706 | B37: RESULT | C37: 01040504.xlsx | D37: Успешно импортировано строк: 3
A38: 46118.706 | B38: WARN | C38: 01040504.xlsx | D38: Нет прав на удаление файла из папки: Доступ запрещен: DriveApp.
A39: 46118.706 | B39: SUMMARY | D39: Итог запуска. Всего файлов: 1, успешно: 1, с ошибками: 0, пропущено: 0
A40: 46119.27 | B40: RESULT | C40: 1656302.xls | D40: Успешно импортировано строк: 25
A41: 46119.27 | B41: WARN | C41: 1656302.xls | D41: Нет прав на удаление файла из папки: Access denied: DriveApp.
A42: 46119.27 | B42: SUMMARY | D42: Итог запуска. Всего файлов: 2, успешно: 1, с ошибками: 0, пропущено: 1
A43: 46120.269 | B43: RESULT | C43: 6296879.xls | D43: Успешно импортировано строк: 25
A44: 46120.269 | B44: WARN | C44: 6296879.xls | D44: Нет прав на удаление файла из папки: Access denied: DriveApp.
A45: 46120.269 | B45: SUMMARY | D45: Итог запуска. Всего файлов: 1, успешно: 1, с ошибками: 0, пропущено: 0
A46: 46121.268 | B46: RESULT | C46: 6225797.xls | D46: Успешно импортировано строк: 25
A47: 46121.268 | B47: WARN | C47: 6225797.xls | D47: Нет прав на удаление файла из папки: Access denied: DriveApp.
A48: 46121.268 | B48: SUMMARY | D48: Итог запуска. Всего файлов: 2, успешно: 1, с ошибками: 0, пропущено: 1
A49: 46122.67 | B49: RESULT | C49: 1661955.xls | D49: Успешно импортировано строк: 25
A50: 46122.67 | B50: WARN | C50: 1661955.xls | D50: Нет прав на удаление файла из папки: Доступ запрещен: DriveApp.
A51: 46122.67 | B51: SUMMARY | D51: Итог запуска. Всего файлов: 3, успешно: 1, с ошибками: 0, пропущено: 2
A52: 46122.677 | B52: SUMMARY | D52: Итог запуска. Всего файлов: 1, успешно: 0, с ошибками: 0, пропущено: 1
A53: 46122.678 | B53: SUMMARY | D53: Итог запуска. Всего файлов: 1, успешно: 0, с ошибками: 0, пропущено: 1
A54: 46122.678 | B54: SUMMARY | D54: Итог запуска. Всего файлов: 1, успешно: 0, с ошибками: 0, пропущено: 1
A55: 46122.68 | B55: RESULT | C55: 1661955.xls | D55: Успешно импортировано строк: 25
A56: 46122.68 | B56: WARN | C56: 1661955.xls | D56: Нет прав на удаление файла из папки: Доступ запрещен: DriveApp.
A57: 46122.68 | B57: SUMMARY | D57: Итог запуска. Всего файлов: 1, успешно: 1, с ошибками: 0, пропущено: 0
A58: 46122.699 | B58: RESULT | C58: 1661955.xls | D58: Импорт завершён. Прочитано строк: 27, валидных: 25, отброшено: 2, новых: 0, обновлено: 25 | E58: {"totalRows":27,"validRows":25,"skippedTotal":2,"skippedNoDate":0,"skippedNoUnit":0,"skippedWarehouse":2,"skippedBadPointMask":0,"skippedBadDate":0,"newRows":0,"updatedRows":25,"pointSheetsFound":25,"pointSheetsMissing":0}
A59: 46122.699 | B59: WARN | C59: 1661955.xls | D59: Нет прав на удаление файла из папки: Доступ запрещен: DriveApp.
A60: 46122.699 | B60: SUMMARY | D60: Итог запуска. Всего файлов: 1, успешно: 1, с ошибками: 0, пропущено: 0
A61: 46122.706 | B61: RESULT | C61: 1661955.xls | D61: Импорт завершён. Прочитано строк: 27, валидных: 25, отброшено: 2, новых: 0, обновлено: 25 | E61: {"totalRows":27,"validRows":25,"skippedTotal":2,"skippedNoDate":0,"skippedNoUnit":0,"skippedWarehouse":2,"skippedBadPointMask":0,"skippedBadDate":0,"newRows":0,"updatedRows":25,"pointSheetsFound":25,"pointSheetsMissing":0}
A62: 46122.706 | B62: WARN | C62: 1661955.xls | D62: Нет прав на удаление файла из папки: Доступ запрещен: DriveApp.
A63: 46122.706 | B63: SUMMARY | D63: Итог запуска. Всего файлов: 1, успешно: 1, с ошибками: 0, пропущено: 0
A64: 46122.71 | B64: RESULT | C64: Копия 1661955.xlsx | D64: Импорт завершён. Прочитано строк: 27, валидных: 25, отброшено: 2, новых: 0, обновлено: 25 | E64: {"totalRows":27,"validRows":25,"skippedTotal":2,"skippedNoDate":0,"skippedNoUnit":0,"skippedWarehouse":2,"skippedBadPointMask":0,"skippedBadDate":0,"newRows":0,"updatedRows":25,"pointSheetsFound":25,"pointSheetsMissing":0}
A65: 46122.71 | B65: WARN | C65: Копия 1661955.xlsx | D65: Нет прав на удаление файла из папки: Доступ запрещен: DriveApp.
A66: 46122.71 | B66: SUMMARY | D66: Итог запуска. Всего файлов: 1, успешно: 1, с ошибками: 0, пропущено: 0
A67: 46123.266 | B67: SUMMARY | D67: Итог запуска. Всего файлов: 0, успешно: 0, с ошибками: 0, пропущено: 0
A68: 46125.268 | B68: WARN | C68: 9300661.xls | D68: Не найден лист точки: 28
A69: 46125.268 | B69: RESULT | C69: 9300661.xls | D69: Импорт завершён. Прочитано строк: 28, валидных: 26, отброшено: 2, новых: 25, обновлено: 0 | E69: {"totalRows":28,"validRows":26,"skippedTotal":2,"skippedNoDate":0,"skippedNoUnit":0,"skippedWarehouse":2,"skippedBadPointMask":0,"skippedBadDate":0,"newRows":25,"updatedRows":0,"pointSheetsFound":25,"pointSheetsMissing":1}
A70: 46125.268 | B70: WARN | C70: 9300661.xls | D70: Нет прав на удаление файла из папки: Access denied: DriveApp.
A71: 46125.777 | B71: RESULT | C71: Копия 9300661.xls | D71: Импорт завершён. Прочитано строк: 28, валидных: 26, отброшено: 2, новых: 1, обновлено: 25 | E71: {"totalRows":28,"validRows":26,"skippedTotal":2,"skippedNoDate":0,"skippedNoUnit":0,"skippedWarehouse":2,"skippedBadPointMask":0,"skippedBadDate":0,"newRows":1,"updatedRows":25,"pointSheetsFound":26,"pointSheetsMissing":0}
A72: 46125.777 | B72: WARN | C72: Копия 9300661.xls | D72: Нет прав на удаление файла из папки: Доступ запрещен: DriveApp.
A73: 46126.269 | B73: RESULT | C73: 3576452.xls | D73: Импорт завершён. Прочитано строк: 28, валидных: 26, отброшено: 2, новых: 26, обновлено: 0 | E73: {"totalRows":28,"validRows":26,"skippedTotal":2,"skippedNoDate":0,"skippedNoUnit":0,"skippedWarehouse":2,"skippedBadPointMask":0,"skippedBadDate":0,"newRows":26,"updatedRows":0,"pointSheetsFound":26,"pointSheetsMissing":0}
A74: 46126.269 | B74: WARN | C74: 3576452.xls | D74: Нет прав на удаление файла из папки: Access denied: DriveApp.
A75: 46127.268 | B75: RESULT | C75: 131227.xls | D75: Импорт завершён. Прочитано строк: 28, валидных: 26, отброшено: 2, новых: 26, обновлено: 0 | E75: {"totalRows":28,"validRows":26,"skippedTotal":2,"skippedNoDate":0,"skippedNoUnit":0,"skippedWarehouse":2,"skippedBadPointMask":0,"skippedBadDate":0,"newRows":26,"updatedRows":0,"pointSheetsFound":26,"pointSheetsMissing":0}
A76: 46127.268 | B76: WARN | C76: 131227.xls | D76: Нет прав на удаление файла из папки: Access denied: DriveApp.
A77: 46127.269 | B77: RESULT | C77: 514457.xls | D77: Импорт завершён. Прочитано строк: 28, валидных: 26, отброшено: 2, новых: 0, обновлено: 26 | E77: {"totalRows":28,"validRows":26,"skippedTotal":2,"skippedNoDate":0,"skippedNoUnit":0,"skippedWarehouse":2,"skippedBadPointMask":0,"skippedBadDate":0,"newRows":0,"updatedRows":26,"pointSheetsFound":26,"pointSheetsMissing":0}
A78: 46127.269 | B78: WARN | C78: 514457.xls | D78: Нет прав на удаление файла из папки: Access denied: DriveApp.
A79: 46128.27 | B79: RESULT | C79: 4775490.xls | D79: Импорт завершён. Прочитано строк: 28, валидных: 26, отброшено: 2, новых: 26, обновлено: 0 | E79: {"totalRows":28,"validRows":26,"skippedTotal":2,"skippedNoDate":0,"skippedNoUnit":0,"skippedWarehouse":2,"skippedBadPointMask":0,"skippedBadDate":0,"newRows":26,"updatedRows":0,"pointSheetsFound":26,"pointSheetsMissing":0}
A80: 46128.27 | B80: WARN | C80: 4775490.xls | D80: Нет прав на удаление файла из папки: Access denied: DriveApp.
A81: 46129.269 | B81: RESULT | C81: 5502816.xls | D81: Импорт завершён. Прочитано строк: 28, валидных: 26, отброшено: 2, новых: 26, обновлено: 0 | E81: {"totalRows":28,"validRows":26,"skippedTotal":2,"skippedNoDate":0,"skippedNoUnit":0,"skippedWarehouse":2,"skippedBadPointMask":0,"skippedBadDate":0,"newRows":26,"updatedRows":0,"pointSheetsFound":26,"pointSheetsMissing":0}
A82: 46129.269 | B82: WARN | C82: 5502816.xls | D82: Нет прав на удаление файла из папки: Access denied: DriveApp.
A83: 46129.305 | B83: RESULT | C83: Копия 5502816.xls | D83: Импорт завершён. Прочитано строк: 30, валидных: 28, отброшено: 2, новых: 2, обновлено: 26 | E83: {"totalRows":30,"validRows":28,"skippedTotal":2,"skippedNoDate":0,"skippedNoUnit":0,"skippedWarehouse":2,"skippedBadPointMask":0,"skippedBadDate":0,"newRows":2,"updatedRows":26,"pointSheetsFound":28,"pointSheetsMissing":0}
A84: 46130.266 | B84: SUMMARY | D84: Итог запуска. Всего файлов: 0, успешно: 0, с ошибками: 0, пропущено: 0
A85: 46131.266 | B85: SUMMARY | D85: Итог запуска. Всего файлов: 0, успешно: 0, с ошибками: 0, пропущено: 0
A86: 46132.266 | B86: SUMMARY | D86: Итог запуска. Всего файлов: 0, успешно: 0, с ошибками: 0, пропущено: 0
A87: 46133.27 | B87: RESULT | C87: 4766626.xls | D87: Импорт завершён. Прочитано строк: 29, валидных: 28, отброшено: 1, новых: 28, обновлено: 0 | E87: {"totalRows":29,"validRows":28,"skippedTotal":1,"skippedNoDate":0,"skippedNoUnit":0,"skippedWarehouse":1,"skippedBadPointMask":0,"skippedBadDate":0,"newRows":28,"updatedRows":0,"pointSheetsFound":28,"pointSheetsMissing":0}
A88: 46133.27 | B88: WARN | C88: 4766626.xls | D88: Нет прав на удаление файла из папки: Access denied: DriveApp.
A89: 46133.326 | B89: RESULT | C89: 17041904.xls | D89: Импорт завершён. Прочитано строк: 75, валидных: 74, отброшено: 1, новых: 58, обновлено: 16 | E89: {"totalRows":75,"validRows":74,"skippedTotal":1,"skippedNoDate":0,"skippedNoUnit":0,"skippedWarehouse":1,"skippedBadPointMask":0,"skippedBadDate":0,"newRows":58,"updatedRows":16,"pointSheetsFound":28,"pointSheetsMissing":0}
A90: 46133.326 | B90: WARN | C90: 17041904.xls | D90: Нет прав на удаление файла из папки: Доступ запрещен: DriveApp.
A91: 46133.326 | B91: SUMMARY | D91: Итог запуска. Всего файлов: 2, успешно: 1, с ошибками: 0, пропущено: 1
A92: 46134.268 | B92: RESULT | C92: 6879663.xls | D92: Импорт завершён. Прочитано строк: 30, валидных: 28, отброшено: 2, новых: 28, обновлено: 0 | E92: {"totalRows":30,"validRows":28,"skippedTotal":2,"skippedNoDate":0,"skippedNoUnit":0,"skippedWarehouse":2,"skippedBadPointMask":0,"skippedBadDate":0,"newRows":28,"updatedRows":0,"pointSheetsFound":28,"pointSheetsMissing":0}
A93: 46134.268 | B93: WARN | C93: 6879663.xls | D93: Нет прав на удаление файла из папки: Access denied: DriveApp.
A94: 46134.268 | B94: SUMMARY | D94: Итог запуска. Всего файлов: 1, успешно: 1, с ошибками: 0, пропущено: 0
A95: 46136.266 | B95: ERROR | C95: 9291998.xls | D95: API call to drive.files.create failed with error: Conversion of the uploaded content to the requested output type is not supported.
A96: 46136.268 | B96: RESULT | C96: 4608662.xls | D96: Импорт завершён. Прочитано строк: 31, валидных: 29, отброшено: 2, новых: 9, обновлено: 20 | E96: {"totalRows":31,"validRows":29,"skippedTotal":2,"skippedNoDate":0,"skippedNoUnit":0,"skippedWarehouse":2,"skippedBadPointMask":0,"skippedBadDate":0,"newRows":9,"updatedRows":20,"pointSheetsFound":29,"pointSheetsMissing":0}
A97: 46136.268 | B97: WARN | C97: 4608662.xls | D97: Нет прав на удаление файла из папки: Access denied: DriveApp.
A98: 46136.268 | B98: SUMMARY | D98: Итог запуска. Всего файлов: 3, успешно: 1, с ошибками: 1, пропущено: 1
A99: 46137.268 | B99: RESULT | C99: 4222048.xls | D99: Импорт завершён. Прочитано строк: 30, валидных: 29, отброшено: 1, новых: 29, обновлено: 0 | E99: {"totalRows":30,"validRows":29,"skippedTotal":1,"skippedNoDate":0,"skippedNoUnit":0,"skippedWarehouse":1,"skippedBadPointMask":0,"skippedBadDate":0,"newRows":29,"updatedRows":0,"pointSheetsFound":29,"pointSheetsMissing":0}
A100: 46137.268 | B100: WARN | C100: 4222048.xls | D100: Нет прав на удаление файла из папки: Access denied: DriveApp.
...

Sheet Скидки
A1: Точка | B1: Тип периода | C1: Время начала | D1: Время окончания | E1: Механика | F1: Суть акции | G1: Скидка | H1: Цель | I1: Комментарий
A2: 1 | B2: Пик | C2: 0.5 | D2: 0.66666667 | E2: Бандл | F2: Кухня + Напиток | G2: -15% на напиток | H2: Рост среднего чека | I2: Скидка только на доп.позицию
A3: 1 | B3: Пик | C3: 0.75 | D3: 0.79166667 | E3: Бандл | F3: Кухня + Десерт | G3: -15% на десерт | H3: Рост среднего чека | I3: Апселл сладкого
A4: 1 | B4: Просадка | C4: 0.83333333 | D4: 0.91666667 | E4: Скидка категории | F4: Десерты | G4: -0.2 | H4: Стимул покупки | I4: Короткое окно
A7: 2 | B7: Пик | C7: 0.33333333 | D7: 0.41666667 | E7: Бандл | F7: Кухня (завтрак) + Напиток | G7: -15% на напиток | H7: Рост среднего чека | I7: Утренний поток
A8: 2 | B8: Пик | C8: 0.45833333 | D8: 0.54166667 | E8: Бандл | F8: Кухня + Десерт | G8: -10% на десерт | H8: Рост среднего чека | I8: Не резать ядро
A9: 2 | B9: Просадка | C9: 0.58333333 | D9: 0.66666667 | E9: Скидка категории | F9: Десерты | G9: -0.2 | H9: Стимул покупки | I9: Послеобеденный спад
A12: 3 | B12: Пик | C12: 0.33333333 | D12: 0.41666667 | E12: Бандл | F12: Кухня (завтрак) + Напиток | G12: -15% на напиток | H12: Рост среднего чека | I12: Классический апселл
A13: 3 | B13: Пик | C13: 0.5 | D13: 0.58333333 | E13: Бандл | F13: Кухня + Снеки | G13: -15% на снеки | H13: Рост среднего чека | I13: Допродажа к обеду
A14: 3 | B14: Просадка | C14: 0.70833333 | D14: 0.79166667 | E14: Скидка категории | F14: Десерты | G14: -0.2 | H14: Стимул покупки | I14: После работы
A16: 4 | B16: Пик | C16: 0.33333333 | D16: 0.375 | E16: Бандл | F16: Кухня (завтрак) + Напиток | G16: -10% на напиток | H16: Рост среднего чека | I16: Небольшая скидка
A17: 4 | B17: Пик | C17: 0.45833333 | D17: 0.54166667 | E17: Бандл | F17: Япония + Напиток | G17: -10% на напиток | H17: Рост среднего чека | I17: Конкуренция со столовой
A18: 4 | B18: Просадка | C18: 0.58333333 | D18: 0.66666667 | E18: Скидка категории | F18: Десерты | G18: -0.2 | H18: Стимул покупки | I18: Послеобеденный спад
A21: 5 | B21: Пик | C21: 0.375 | D21: 0.41666667 | E21: Бандл | F21: Кухня (завтрак) + Напиток | G21: -15% на напиток | H21: Рост среднего чека | I21: Утренний поток
A22: 5 | B22: Пик | C22: 0.5 | D22: 0.58333333 | E22: Бандл | F22: Кухня + Десерт | G22: -15% на десерт | H22: Рост среднего чека | I22: Обеденный поток
A23: 5 | B23: Просадка | C23: 0.625 | D23: 0.66666667 | E23: Скидка категории | F23: Десерты | G23: -0.2 | H23: Стимул покупки | I23: Перекус
A25: 6 | B25: Пик | C25: 0.33333333 | D25: 0.41666667 | E25: Бандл | F25: Кухня (завтрак) + Напиток | G25: -15% на напиток | H25: Рост среднего чека | I25: Утро
A26: 6 | B26: Пик | C26: 0.45833333 | D26: 0.54166667 | E26: Бандл | F26: Кухня + Снеки | G26: -15% на снеки | H26: Рост среднего чека | I26: Обед
A27: 6 | B27: Просадка | C27: 0.58333333 | D27: 0.66666667 | E27: Скидка категории | F27: Десерты | G27: -0.2 | H27: Стимул покупки | I27: Послеобеденный спад
A30: 7
A31: 7
A32: 7
A34: 8 | B34: Пик | C34: 0.33333333 | D34: 0.375 | E34: Бандл | F34: Кухня (завтрак) + Напиток | G34: -10% на напиток | H34: Рост среднего чека | I34: Сотрудники, утро
A35: 8 | B35: Пик | C35: 0.45833333 | D35: 0.54166667 | E35: Бандл | F35: Кухня + Десерт | G35: -10% на десерт | H35: Рост среднего чека | I35: Обед
A36: 8 | B36: Просадка | C36: 0.58333333 | D36: 0.66666667 | E36: Скидка категории | F36: Десерты | G36: -0.2 | H36: Стимул покупки | I36: Послеобеденный спад
A39: 9 | B39: Пик | C39: 0.33333333 | D39: 0.45833333 | E39: Бандл | F39: Кухня + Напиток | G39: -15% на напиток | H39: Рост среднего чека | I39: Утро
A40: 9 | B40: Пик | C40: 0.5 | D40: 0.58333333 | E40: Бандл | F40: Япония + Напиток | G40: -15% на напиток | H40: Рост среднего чека | I40: Обед
A41: 9 | B41: Просадка | C41: 0.625 | D41: 0.70833333 | E41: Скидка категории | F41: Снеки | G41: -0.2 | H41: Стимул покупки | I41: Перекус
A44: 10 | B44: Пик | C44: 0.29166667 | D44: 0.41666667 | E44: Бандл | F44: Кухня (завтрак) + Напиток | G44: -15% на напиток | H44: Рост среднего чека | I44: Смена/утро
A45: 10 | B45: Пик | C45: 0.45833333 | D45: 0.54166667 | E45: Бандл | F45: Кухня + Десерт | G45: -15% на десерт | H45: Рост среднего чека | I45: Обед
A46: 10 | B46: Просадка | C46: 0 | D46: 0.25 | E46: Скидка категории | F46: Напитки | G46: -0.2 | H46: Стимул покупки | I46: Ночь: дешевле по марже
A47: 10 | B47: Просадка | C47: 0.70833333 | D47: 0.75 | E47: Скидка категории | F47: Десерты или Снеки | G47: -0.2 | H47: Стимул покупки | I47: Перекус
A49: 11
A50: 11
A51: 11
A53: 12 | B53: Пик | C53: 0.33333333 | D53: 0.41666667 | E53: Бандл | F53: Кухня (завтрак) + Напиток | G53: -10% на напиток | H53: Рост среднего чека | I53: Не конфликтовать с комплексами
A54: 12 | B54: Пик | C54: 0.45833333 | D54: 0.54166667 | E54: Бандл | F54: Кухня + Десерт | G54: -10% на десерт | H54: Рост среднего чека | I54: Скидка на доп.позицию
A55: 12 | B55: Просадка | C55: 0.58333333 | D55: 0.66666667 | E55: Скидка категории | F55: Десерты | G55: -0.2 | H55: Стимул покупки | I55: Послеобеденный спад
A58: 13 | B58: Пик | C58: 0.33333333 | D58: 0.41666667 | E58: Бандл | F58: Кухня (завтрак) + Напиток | G58: -10% на напиток | H58: Рост среднего чека | I58: Утро
A59: 13 | B59: Пик | C59: 0.45833333 | D59: 0.54166667 | E59: Бандл | F59: Кухня + Десерт | G59: -10% на десерт | H59: Рост среднего чека | I59: Обед
A60: 13 | B60: Просадка | C60: 0.58333333 | D60: 0.66666667 | E60: Скидка категории | F60: Десерты | G60: -0.2 | H60: Стимул покупки | I60: Перекус
A63: 14 | B63: Пик | C63: 0.41666667 | D63: 0.54166667 | E63: Бандл | F63: Япония + Напиток | G63: -10% на напиток | H63: Рост среднего чека | I63: Офисная точка
A64: 14 | B64: Пик | C64: 0.625 | D64: 0.66666667 | E64: Бандл | F64: Кухня + Десерт | G64: -15% на десерт | H64: Рост среднего чека | I64: Кофе-брейк
A65: 14 | B65: Просадка | C65: 0.54166667 | D65: 0.625 | E65: Скидка категории | F65: Десерты | G65: -0.2 | H65: Стимул покупки | I65: Межобеденное окно
A68: 15 | B68: Пик | C68: 0.33333333 | D68: 0.41666667 | E68: Бандл | F68: Кухня (завтрак) + Напиток | G68: -15% на напиток | H68: Рост среднего чека | I68: Утро
A69: 15 | B69: Пик | C69: 0.5 | D69: 0.54166667 | E69: Бандл | F69: Кухня + Десерт | G69: -15% на десерт | H69: Рост среднего чека | I69: Обед
A70: 15 | B70: Просадка | C70: 0.41666667 | D70: 0.5 | E70: Скидка категории | F70: Снеки | G70: -0.2 | H70: Стимул покупки | I70: Перекус вместо доставок
A71: 15 | B71: Просадка | C71: 0.58333333 | D71: 0.70833333 | E71: Скидка категории | F71: Десерты | G71: -0.2 | H71: Стимул покупки | I71: Послеобеденный спад
A74: 16 | B74: Пик | C74: 0.33333333 | D74: 0.41666667 | E74: Бандл | F74: Кухня (завтрак) + Напиток | G74: -10% на напиток | H74: Рост среднего чека | I74: Есть альтернативы рядом
A75: 16 | B75: Пик | C75: 0.5 | D75: 0.58333333 | E75: Бандл | F75: Япония + Напиток | G75: -10% на напиток | H75: Рост среднего чека | I75: Скидка маленькая
A76: 16 | B76: Просадка | C76: 0.625 | D76: 0.70833333 | E76: Скидка категории | F76: Десерты | G76: -0.2 | H76: Стимул покупки | I76: Кофе-брейк
A79: 17
A80: 17
A81: 17
A83: 18 | B83: Пик | C83: 0.33333333 | D83: 0.41666667 | E83: Бандл | F83: Кухня (завтрак) + Напиток | G83: -15% на напиток | H83: Рост среднего чека | I83: Нет альтернатив
A84: 18 | B84: Пик | C84: 0.45833333 | D84: 0.54166667 | E84: Бандл | F84: Кухня + Десерт | G84: -15% на десерт | H84: Рост среднего чека | I84: Обед
A85: 18 | B85: Просадка | C85: 0.58333333 | D85: 0.66666667 | E85: Скидка категории | F85: Снеки | G85: -0.2 | H85: Стимул покупки | I85: Послеобеденный спад
A88: 19 | B88: Пик | C88: 0.375 | D88: 0.45833333 | E88: Бандл | F88: Япония + Напиток | G88: -15% на напиток | H88: Рост среднего чека | I88: Проходная точка
A89: 19 | B89: Пик | C89: 0.5 | D89: 0.54166667 | E89: Бандл | F89: Кухня + Напиток | G89: -15% на напиток | H89: Рост среднего чека | I89: Быстрый обед
A90: 19 | B90: Просадка | C90: 0.58333333 | D90: 0.66666667 | E90: Скидка категории | F90: Десерты | G90: -0.2 | H90: Стимул покупки | I90: Кофе-брейк
A93: 20 | B93: Пик | C93: 0.33333333 | D93: 0.375 | E93: Бандл | F93: Кухня (завтрак) + Напиток | G93: -15% на напиток | H93: Рост среднего чека | I93: Утро персонал
A94: 20 | B94: Пик | C94: 0.45833333 | D94: 0.54166667 | E94: Бандл | F94: Кухня + Десерт | G94: -15% на десерт | H94: Рост среднего чека | I94: Обед персонал
A95: 20 | B95: Пик | C95: 0.79166667 | D95: 0.875 | E95: Бандл | F95: Салат + Напиток | G95: -15% на напиток | H95: Рост среднего чека | I95: Вечер пациентки
A96: 20 | B96: Просадка | C96: 0.58333333 | D96: 0.70833333 | E96: Скидка категории | F96: Десерты | G96: -0.2 | H96: Стимул покупки | I96: Дневной спад
A99: 21 | B99: Пик | C99: 0.33333333 | D99: 0.41666667 | E99: Бандл | F99: Кухня (завтрак) + Напиток | G99: -15% на напиток | H99: Рост среднего чека | I99: Утро
A100: 21 | B100: Пик | C100: 0.45833333 | D100: 0.54166667 | E100: Бандл | F100: Япония + Напиток | G100: -10% на напиток | H100: Рост среднего чека | I100: Конкуренция с доставкой
A101: 21 | B101: Просадка | C101: 0.625 | D101: 0.70833333 | E101: Скидка категории | F101: Снеки | G101: -0.2 | H101: Стимул покупки | I101: Перекус вместо доставки
A104: 22 | B104: Пик | C104: 0.54166667 | D104: 0.58333333 | E104: Бандл | F104: Кухня + Напиток | G104: -10% на напиток | H104: Рост среднего чека | I104: Сильная столовая рядом
A105: 22 | B105: Пик | C105: 0.79166667 | D105: 0.91666667 | E105: Бандл | F105: Кухня + Напиток | G105: -15% на напиток | H105: Рост среднего чека | I105: Логистика/вечер
A108: 23 | B108: Пик | C108: 0.29166667 | D108: 0.33333333 | E108: Бандл | F108: Кухня (завтрак) + Напиток | G108: -10% на напиток | H108: Рост среднего чека | I108: Ранний пик
A109: 23 | B109: Пик | C109: 0.41666667 | D109: 0.54166667 | E109: Бандл | F109: Кухня + Напиток | G109: -15% на напиток | H109: Рост среднего чека | I109: Главный пик
A110: 23 | B110: Пик | C110: 0.70833333 | D110: 0.75 | E110: Бандл | F110: Кухня + Десерт | G110: -15% на десерт | H110: Рост среднего чека | I110: Вечерний пик
A111: 23 | B111: Просадка | C111: 0.625 | D111: 0.70833333 | E111: Скидка категории | F111: Десерты | G111: -0.2 | H111: Стимул покупки | I111: Дневная просадка
A114: 24 | B114: Пик | C114: 0.41666667 | D114: 0.58333333 | E114: Бандл | F114: Кухня + Напиток | G114: -15% на напиток | H114: Рост среднего чека | I114: Обедной поток
A115: 24 | B115: Пик | C115: 0.41666667 | D115: 0.58333333 | E115: Бандл | F115: Япония + Напиток | G115: -10% на напиток | H115: Рост среднего чека | I115: Второй бандл
A116: 24 | B116: Просадка | C116: 0.79166667 | D116: 0.875 | E116: Скидка категории | F116: Десерты | G116: -0.2 | H116: Стимул покупки | I116: Вечер, если есть смены

Sheet шаблон
A1: Точка | C1: Дата запуска | E1: Тип точки | G1: Активна | K1: Стоимость обслуживания | L1: Аренда | M1: Коммуналка | N1: Клининг
A2: Среднее | K2: =SUM(L2:Q2) -> 0
A3: Дата | B3: $ QR-код | C3: $ Касса | D3: $ Итог | E3: Чеки QR | F3: Чеки Касса | G3: Чеки Итог | H3: Ср.-й чек | I3: Списания | J3: д/н

Sheet Рентабельность точек
A1: Для расчёта приняты средние данные из листа Дашборд
B2: рент.50% | C2: 9500 | F2: 30 | G2: 30 | J2: 24
A3: Точка № | B3: Min выручка для рент 50% | C3: Ср.-я выручка | D3: Логистика | E3: Списания | F3: Аренда в день | G3: Связь в день | H3: Рентабельность | I3: Фин-рез день | J3: Фин-рез мес | L3: Рентабельность точек %
A4: ='Дашборд'!A5 -> 1 | B4: =(D4+E4+F4+G4)/(1-(1/2.8)-0.5) -> 9285.8836 | C4: ='Дашборд'!B5 -> 17400.554 | D4: 550 | E4: ='Дашборд'!E5 -> 699.88813 | F4: ='Дашборд'!AH3/$F$2 -> 76.666667 | H4: =(I4/C4)*100% -> 0.56662079 | I4: =C4-(C4/2.8)-D4-E4-F4-G4 -> 9859.5156 | J4: =I4*$J$2 -> 236628.37
A5: ='Дашборд'!A6 -> 2 | B5: =(D5+E5+F5+G5)/(1-(1/2.8)-0.5) -> 5219.8451 | C5: ='Дашборд'!B6 -> 5056.7733 | D5: 550 | E5: ='Дашборд'!E6 -> 185.69216 | F5: ='Дашборд'!AH4/$F$2 -> 10 | H5: =(I5/C5)*100% -> 0.49539312 | I5: =C5-(C5/2.8)-D5-E5-F5-G5 -> 2505.0907 | J5: =I5*$J$2 -> 60122.176
A6: ='Дашборд'!A7 -> 3 | B6: =(D6+E6+F6+G6)/(1-(1/2.8)-0.5) -> 17523.551 | C6: ='Дашборд'!B7 -> 7694.3712 | D6: 1700 | E6: ='Дашборд'!E7 -> 673.63115 | F6: ='Дашборд'!AH5/$F$2 -> 129.73333 | H6: =(I6/C6)*100% -> 0.31750703 | I6: =C6-(C6/2.8)-D6-E6-F6-G6 -> 2443.017 | J6: =I6*$J$2 -> 58632.407
A7: ='Дашборд'!A8 -> 4 | B7: =(D7+E7+F7+G7)/(1-(1/2.8)-0.5) -> 12589.022 | C7: ='Дашборд'!B8 -> 2941.4374 | D7: 550 | E7: ='Дашборд'!E8 -> 1248.4317 | F7: ='Дашборд'!AH6/$F$2 -> 0 | H7: =(I7/C7)*100% -> 0.031444607 | I7: =C7-(C7/2.8)-D7-E7-F7-G7 -> 92.492343 | J7: =I7*$J$2 -> 2219.8162
A8: ='Дашборд'!A9 -> 5 | B8: =(D8+E8+F8+G8)/(1-(1/2.8)-0.5) -> 7069.0723 | C8: ='Дашборд'!B9 -> 14822.316 | D8: 550 | E8: ='Дашборд'!E9 -> 449.86747 | F8: ='Дашборд'!AH7/$F$2 -> 10 | H8: =(I8/C8)*100% -> 0.57472559 | I8: =C8-(C8/2.8)-D8-E8-F8-G8 -> 8518.7642 | J8: =I8*$J$2 -> 204450.34
A9: ='Дашборд'!A10 -> 6 | B9: =(D9+E9+F9+G9)/(1-(1/2.8)-0.5) -> 8344.8024 | C9: ='Дашборд'!B10 -> 9760.7927 | D9: 550 | E9: ='Дашборд'!E10 -> 520.84796 | F9: ='Дашборд'!AH8/$F$2 -> 121.26667 | H9: =(I9/C9)*100% -> 0.52072417 | I9: =C9-(C9/2.8)-D9-E9-F9-G9 -> 5082.6807 | J9: =I9*$J$2 -> 121984.34
A10: ='Дашборд'!A11 -> 7 | B10: =(D10+E10+F10+G10)/(1-(1/2.8)-0.5) -> 5594.7014 | C10: ='Дашборд'!B11 -> 5577.0686 | D10: 550 | E10: ='Дашборд'!E11 -> 239.24305 | F10: ='Дашборд'!AH9/$F$2 -> 10 | H10: =(I10/C10)*100% -> 0.49954834 | I10: =C10-(C10/2.8)-D10-E10-F10-G10 -> 2786.0153 | J10: =I10*$J$2 -> 66864.368
A11: ='Дашборд'!A12 -> 8 | B11: =(D11+E11+F11+G11)/(1-(1/2.8)-0.5) -> 7007.7844 | C11: ='Дашборд'!B12 -> 7437.8164 | D11: 550 | E11: ='Дашборд'!E12 -> 257.44539 | F11: ='Дашборд'!AH10/$F$2 -> 193.66667 | H11: =(I11/C11)*100% -> 0.50825957 | I11: =C11-(C11/2.8)-D11-E11-F11-G11 -> 3780.3414 | J11: =I11*$J$2 -> 90728.193
A12: ='Дашборд'!A13 -> 9 | B12: =(D12+E12+F12+G12)/(1-(1/2.8)-0.5) -> 7612.9472 | C12: ='Дашборд'!B13 -> 10341.419 | D12: 550 | E12: ='Дашборд'!E13 -> 207.56388 | F12: ='Дашборд'!AH11/$F$2 -> 330 | H12: =(I12/C12)*100% -> 0.53769132 | I12: =C12-(C12/2.8)-D12-E12-F12-G12 -> 5560.4915 | J12: =I12*$J$2 -> 133451.8
A13: ='Дашборд'!A14 -> 10 | B13: =(D13+E13+F13+G13)/(1-(1/2.8)-0.5) -> 8680.3951 | C13: ='Дашборд'!B14 -> 9886.613 | D13: 550 | E13: ='Дашборд'!E14 -> 563.05645 | F13: ='Дашборд'!AH12/$F$2 -> 127 | H13: =(I13/C13)*100% -> 0.51742931 | I13: =C13-(C13/2.8)-D13-E13-F13-G13 -> 5115.6234 | J13: =I13*$J$2 -> 122774.96
A14: ='Дашборд'!A15 -> 11 | B14: =(D14+E14+F14+G14)/(1-(1/2.8)-0.5) -> 0 | C14: ='Дашборд'!B15 | E14: ='Дашборд'!E15 | F14: ='Дашборд'!AH13/$F$2 -> 0 | H14: =(I14/C14)*100% -> #DIV/0! | I14: =C14-(C14/2.8)-D14-E14-F14-G14 -> 0 | J14: =I14*$J$2 -> 0
A15: ='Дашборд'!A16 -> 12 | B15: =(D15+E15+F15+G15)/(1-(1/2.8)-0.5) -> 6527.6113 | C15: ='Дашборд'!B16 -> 6144.2566 | D15: 550 | E15: ='Дашборд'!E16 -> 222.51589 | F15: ='Дашборд'!AH14/$F$2 -> 160 | H15: =(I15/C15)*100% -> 0.49108681 | I15: =C15-(C15/2.8)-D15-E15-F15-G15 -> 3017.3634 | J15: =I15*$J$2 -> 72416.721
A16: ='Дашборд'!A17 -> 13 | B16: =(D16+E16+F16+G16)/(1-(1/2.8)-0.5) -> 6826.9549 | C16: ='Дашборд'!B17 -> 6274.8255 | D16: 550 | E16: ='Дашборд'!E17 -> 265.27927 | F16: ='Дашборд'!AH15/$F$2 -> 160 | H16: =(I16/C16)*100% -> 0.48742983 | I16: =C16-(C16/2.8)-D16-E16-F16-G16 -> 3058.5371 | J16: =I16*$J$2 -> 73404.891
A17: ='Дашборд'!A18 -> 14 | B17: =(D17+E17+F17+G17)/(1-(1/2.8)-0.5) -> 7847.0915 | C17: ='Дашборд'!B18 -> 11786.44 | D17: 550 | E17: ='Дашборд'!E18 -> 345.51307 | F17: ='Дашборд'!AH16/$F$2 -> 225.5 | H17: =(I17/C17)*100% -> 0.54774674 | I17: =C17-(C17/2.8)-D17-E17-F17-G17 -> 6455.984 | J17: =I17*$J$2 -> 154943.62
A18: ='Дашборд'!A19 -> 15 | B18: =(D18+E18+F18+G18)/(1-(1/2.8)-0.5) -> 6663.0202 | C18: ='Дашборд'!B19 -> 8637.9245 | D18: 550 | E18: ='Дашборд'!E19 -> 308.52669 | F18: ='Дашборд'!AH17/$F$2 -> 93.333333 | H18: =(I18/C18)*100% -> 0.53266169 | I18: =C18-(C18/2.8)-D18-E18-F18-G18 -> 4601.0914 | J18: =I18*$J$2 -> 110426.19
A19: ='Дашборд'!A20 -> 16 | B19: =(D19+E19+F19+G19)/(1-(1/2.8)-0.5) -> 5591.8195 | C19: ='Дашборд'!B20 -> 7918.1447 | D19: 550 | E19: ='Дашборд'!E20 -> 238.83135 | F19: ='Дашборд'!AH18/$F$2 -> 10 | H19: =(I19/C19)*100% -> 0.54197097 | I19: =C19-(C19/2.8)-D19-E19-F19-G19 -> 4291.4045 | J19: =I19*$J$2 -> 102993.71
A20: ='Дашборд'!A21 -> 17 | B20: =(D20+E20+F20+G20)/(1-(1/2.8)-0.5) -> 8556.2839 | C20: ='Дашборд'!B21 -> 6951.1225 | D20: 550 | E20: ='Дашборд'!E21 -> 437.35961 | F20: ='Дашборд'!AH19/$F$2 -> 234.96667 | H20: =(I20/C20)*100% -> 0.46701126 | I20: =C20-(C20/2.8)-D20-E20-F20-G20 -> 3246.2525 | J20: =I20*$J$2 -> 77910.06
A21: ='Дашборд'!A22 -> 18 | B21: =(D21+E21+F21+G21)/(1-(1/2.8)-0.5) -> 9795.54 | C21: ='Дашборд'!B22 -> 6322.1 | D21: 550 | E21: ='Дашборд'!E22 -> 839.36286 | F21: ='Дашборд'!AH20/$F$2 -> 10 | H21: =(I21/C21)*100% -> 0.42151252 | I21: =C21-(C21/2.8)-D21-E21-F21-G21 -> 2664.8443 | J21: =I21*$J$2 -> 63956.263
A22: ='Дашборд'!A23 -> 19 | B22: =(D22+E22+F22+G22)/(1-(1/2.8)-0.5) -> 6466.4096 | C22: ='Дашборд'!B23 -> 6887.1429 | D22: 550 | E22: ='Дашборд'!E23 -> 299.13946 | F22: ='Дашборд'!AH21/$F$2 -> 74.633333 | H22: =(I22/C22)*100% -> 0.5087271 | I22: =C22-(C22/2.8)-D22-E22-F22-G22 -> 3503.6762 | J22: =I22*$J$2 -> 84088.228
A23: ='Дашборд'!A24 -> 20 | B23: =(D23+E23+F23+G23)/(1-(1/2.8)-0.5) -> 8965.7968 | C23: ='Дашборд'!B24 -> 15616.147 | D23: 550 | E23: ='Дашборд'!E24 -> 610.62811 | F23: ='Дашборд'!AH22/$F$2 -> 120.2 | H23: =(I23/C23)*100% -> 0.56083767 | I23: =C23-(C23/2.8)-D23-E23-F23-G23 -> 8758.1238 | J23: =I23*$J$2 -> 210194.97 | L23: Рентабельность точек по месяцу в рублях
A24: ='Дашборд'!A25 -> 21 | B24: =(D24+E24+F24+G24)/(1-(1/2.8)-0.5) -> 6209.0328 | C24: ='Дашборд'!B25 -> 7178.7581 | D24: 550 | E24: ='Дашборд'!E25 -> 264.33801 | F24: ='Дашборд'!AH23/$F$2 -> 72.666667 | H24: =(I24/C24)*100% -> 0.51929751 | I24: =C24-(C24/2.8)-D24-E24-F24-G24 -> 3727.9112 | J24: =I24*$J$2 -> 89469.87
A25: ='Дашборд'!A26 -> 22 | B25: =(D25+E25+F25+G25)/(1-(1/2.8)-0.5) -> 7357.6028 | C25: ='Дашборд'!B26 -> 6456.0993 | D25: 550 | E25: ='Дашборд'!E26 -> 424.41945 | F25: ='Дашборд'!AH24/$F$2 -> 76.666667 | H25: =(I25/C25)*100% -> 0.48005201 | I25: =C25-(C25/2.8)-D25-E25-F25-G25 -> 3099.2634 | J25: =I25*$J$2 -> 74382.323
A26: ='Дашборд'!A27 -> 23 | B26: =(D26+E26+F26+G26)/(1-(1/2.8)-0.5) -> 6566.5197 | C26: ='Дашборд'!B27 -> 9432.3562 | D26: 550 | E26: ='Дашборд'!E27 -> 311.40757 | F26: ='Дашборд'!AH25/$F$2 -> 76.666667 | H26: =(I26/C26)*100% -> 0.54340434 | I26: =C26-(C26/2.8)-D26-E26-F26-G26 -> 5125.5833 | J26: =I26*$J$2 -> 123014
A27: ='Дашборд'!A28 -> 24 | B27: =(D27+E27+F27+G27)/(1-(1/2.8)-0.5) -> 7796.5183 | C27: ='Дашборд'!B28 -> 7901.369 | D27: 550 | E27: ='Дашборд'!E28 -> 553.78833 | F27: ='Дашборд'!AH26/$F$2 -> 10 | H27: =(I27/C27)*100% -> 0.50189571 | I27: =C27-(C27/2.8)-D27-E27-F27-G27 -> 3965.6632 | J27: =I27*$J$2 -> 95175.916
A28: ='Дашборд'!A29 -> 25 | B28: =(D28+E28+F28+G28)/(1-(1/2.8)-0.5) -> 6512.5954 | C28: ='Дашборд'!B29 -> 5921.2846 | D28: 550 | E28: ='Дашборд'!E29 -> 370.37077 | F28: ='Дашборд'!AH27/$F$2 -> 10 | H28: =(I28/C28)*100% -> 0.48573401 | I28: =C28-(C28/2.8)-D28-E28-F28-G28 -> 2876.1693 | J28: =I28*$J$2 -> 69028.064
A29: ='Дашборд'!A30 -> 26 | B29: =(D29+E29+F29+G29)/(1-(1/2.8)-0.5) -> 7463.5694 | C29: ='Дашборд'!B30 -> 3501.0025 | D29: 550 | E29: ='Дашборд'!E30 -> 382.55753 | F29: ='Дашборд'!AH28/$F$2 -> 133.66667 | H29: =(I29/C29)*100% -> 0.33830889 | I29: =C29-(C29/2.8)-D29-E29-F29-G29 -> 1184.4202 | J29: =I29*$J$2 -> 28426.086
A30: ='Дашборд'!A31 -> 27 | B30: =(D30+E30+F30+G30)/(1-(1/2.8)-0.5) -> 7955.4959 | C30: ='Дашборд'!B31 -> 9880.7975 | D30: 550 | E30: ='Дашборд'!E31 -> 452.83275 | F30: ='Дашборд'!AH29/$F$2 -> 133.66667 | H30: =(I30/C30)*100% -> 0.52783612 | I30: =C30-(C30/2.8)-D30-E30-F30-G30 -> 5215.4418 | J30: =I30*$J$2 -> 125170.6
A31: ='Дашборд'!A32 -> 28 | B31: =(D31+E31+F31+G31)/(1-(1/2.8)-0.5) -> 8754.69 | C31: ='Дашборд'!B32 -> 7753.8329 | D31: =550+100 -> 650 | E31: ='Дашборд'!E32 -> 600.67 | F31: ='Дашборд'!AH30/$F$2 -> 0 | H31: =(I31/C31)*100% -> 0.48156014 | I31: =C31-(C31/2.8)-D31-E31-F31-G31 -> 3733.9368 | J31: =I31*$J$2 -> 89614.484
A32: ='Дашборд'!A33 -> 901 | B32: =(D32+E32+F32+G32)/(1-(1/2.8)-0.5) -> 38692.748 | C32: ='Дашборд'!B33 -> 15691.747 | D32: 330 | E32: ='Дашборд'!E33 -> 197.53538 | F32: ='Дашборд'!AH32/$F$2 -> 5000 | H32: =(I32/C32)*100% -> 0.29059965 | I32: =C32-(C32/2.8)-D32-E32-F32-G32 -> 4560.0162 | J32: =I32*$J$2 -> 109440.39
A33: ='Дашборд'!A34 -> 29 | B33: =(D33+E33+F33+G33)/(1-(1/2.8)-0.5) -> 7849.3319 | C33: ='Дашборд'!B34 -> 11686.439 | D33: 550 | E33: ='Дашборд'!E34 -> 431.9998 | F33: ='Дашборд'!AH31/$F$2 -> 139.33333 | H33: =(I33/C33)*100% -> 0.54690549 | I33: =C33-(C33/2.8)-D33-E33-F33-G33 -> 6391.3779 | J33: =I33*$J$2 -> 153393.07
A34: ='Дашборд'!A35 | B34: =(D34+E34+F34+G34)/(1-(1/2.8)-0.5) -> 0 | C34: ='Дашборд'!B35 | E34: ='Дашборд'!E35 | F34: ='Дашборд'!AH33/$F$2 -> 0 | H34: =(I34/C34)*100% -> #DIV/0! | I34: =C34-(C34/2.8)-D34-E34-F34-G34 -> 0 | J34: =I34*$J$2 -> 0
A35: ='Дашборд'!A36 | B35: =(D35+E35+F35+G35)/(1-(1/2.8)-0.5) -> 0 | C35: ='Дашборд'!B36 | E35: ='Дашборд'!E36 | F35: ='Дашборд'!AH34/$F$2 -> 0 | H35: =(I35/C35)*100% -> #DIV/0! | I35: =C35-(C35/2.8)-D35-E35-F35-G35 -> 0 | J35: =I35*$J$2 -> 0
A36: ='Дашборд'!A37 | B36: =(D36+E36+F36+G36)/(1-(1/2.8)-0.5) -> 0 | C36: ='Дашборд'!B37 | E36: ='Дашборд'!E37 | F36: ='Дашборд'!AH35/$F$2 -> 0 | H36: =(I36/C36)*100% -> #DIV/0! | I36: =C36-(C36/2.8)-D36-E36-F36-G36 -> 0 | J36: =I36*$J$2 -> 0
A37: ='Дашборд'!A38 | B37: =(D37+E37+F37+G37)/(1-(1/2.8)-0.5) -> 0 | C37: ='Дашборд'!B38 | E37: ='Дашборд'!E38 | F37: ='Дашборд'!AH36/$F$2 -> 0 | H37: =(I37/C37)*100% -> #DIV/0! | I37: =C37-(C37/2.8)-D37-E37-F37-G37 -> 0 | J37: =I37*$J$2 -> 0
A38: ='Дашборд'!A39 | B38: =(D38+E38+F38+G38)/(1-(1/2.8)-0.5) -> 0 | C38: ='Дашборд'!B39 | E38: ='Дашборд'!E39 | F38: ='Дашборд'!AH37/$F$2 -> 0 | H38: =(I38/C38)*100% -> #DIV/0! | I38: =C38-(C38/2.8)-D38-E38-F38-G38 -> 0 | J38: =I38*$J$2 -> 0
A39: ='Дашборд'!A40 | B39: =(D39+E39+F39+G39)/(1-(1/2.8)-0.5) -> 0 | C39: ='Дашборд'!B40 | E39: ='Дашборд'!E40 | F39: ='Дашборд'!AH38/$F$2 -> 0 | H39: =(I39/C39)*100% -> #DIV/0! | I39: =C39-(C39/2.8)-D39-E39-F39-G39 -> 0 | J39: =I39*$J$2 -> 0
A40: ='Дашборд'!A41 | B40: =(D40+E40+F40+G40)/(1-(1/2.8)-0.5) -> 0 | C40: ='Дашборд'!B41 | E40: ='Дашборд'!E41 | F40: ='Дашборд'!AH39/$F$2 -> 0 | H40: =(I40/C40)*100% -> #DIV/0! | I40: =C40-(C40/2.8)-D40-E40-F40-G40 -> 0 | J40: =I40*$J$2 -> 0
A41: ='Дашборд'!A42 | B41: =(D41+E41+F41+G41)/(1-(1/2.8)-0.5) -> 0 | C41: ='Дашборд'!B42 | E41: ='Дашборд'!E42 | F41: ='Дашборд'!AH40/$F$2 -> 0 | H41: =(I41/C41)*100% -> #DIV/0! | I41: =C41-(C41/2.8)-D41-E41-F41-G41 -> 0 | J41: =I41*$J$2 -> 0

Sheet _service_dashboard_vm
A1: Период прошлый | B1: 01.07.2026 - 25.07.2026 | O1: метрика | P1: прошлый | Q1: текущий | R1: разница | S1: разница %
A2: Период текущий | B2: 01.08.2026 - 25.08.2026 | O2: СР. Выручка | P2: =SUM(B6:B1000) -> 246431.49 | Q2: =SUM(C6:C1000) -> 246879.15 | R2: =Q2-P2 -> 447.66772 | S2: =R2/(P2*100%) -> 0.0018166012
A3: Обновлено | B3: 46259.381 | O3: СР. Кол-во чеков | P3: =SUM(E6:E1000) -> 1304.3471 | Q3: =SUM(F6:F1000) -> 1299.811 | R3: =Q3-P3 -> -4.5361307 | S3: =R3/(P3*100%) -> -0.003477702
B4: СР. ВЫРУЧКА | D4: =SUM(D6:D1000) -> -0.76517981 | E4: СР. КОЛ-ВО ЧЕКОВ | G4: =SUM(G6:G1000) -> -1.284705 | H4: СР. СРЕДНИЙ ЧЕК | J4: =SUM(J6:J1000) -> 0.55883108 | K4: СПИСАНИЯ | M4: =SUM(M6:M1000) -> 4.1660626 | O4: СР. Средний чек | P4: =AVERAGE(H6:H1000) -> 171.1788 | Q4: =AVERAGE(I6:I1000) -> 185.52142 | R4: =Q4-P4 -> 14.342627 | S4: =R4/(P4*100%) -> 0.083787407
A5: Точка | B5: Прошлый | C5: Текущий | D5: % | E5: Прошлый | F5: Текущий | G5: % | H5: Прошлый | I5: Текущий | J5: % | K5: Прошлый | L5: Текущий | M5: % | N5: Активна | O5: Списания | P5: =SUM(K6:K1000) -> 267715.48 | Q5: =SUM(L6:L1000) -> 295159.88 | R5: =Q5-P5 -> 27444.4 | S5: =R5/(P5*100%) -> 0.10251331
A6: 0 | B6: 147 | C6: 192 | D6: 0.30612245 | E6: 1 | F6: 1 | G6: 0 | H6: 147 | I6: 192 | J6: 0.30612245 | K6: 0 | L6: 0 | N6: нет
A7: 1 | B7: 16880.844 | C7: 16373.466 | D7: -0.030056483 | E7: 102.27778 | F7: 97 | G7: -0.05160239 | H7: 165.42311 | I7: 168.81742 | J7: 0.020518961 | K7: 42733.01 | L7: 19386.01 | M7: -0.54634579 | N7: да
A8: 2 | B8: 5052.5889 | C8: 4317.1844 | D8: -0.14555004 | E8: 25.055556 | F8: 22.625 | G8: -0.097006652 | H8: 212.7486 | I8: 193.95464 | J8: -0.088338815 | K8: 2732.46 | L8: 4902.85 | M8: 0.79429891 | N8: да
A9: 3 | B9: 7932.37 | C9: 6819.225 | D9: -0.14032943 | E9: 35.8 | F9: 27.875 | G9: -0.22136872 | H9: 200.75378 | I9: 246.18072 | J9: 0.22628189 | K9: 3368.05 | L9: 13321.11 | M9: 2.9551402 | N9: да
A10: 4 | B10: 6476.7556 | C10: 5841.9562 | D10: -0.098011929 | E10: 21.666667 | F10: 21.0625 | G10: -0.027884615 | H10: 301.62883 | I10: 274.84151 | J10: -0.088808897 | K10: 53743.64 | L10: 63490.62 | M10: 0.18136062 | N10: да
A11: 5 | B11: 16444.243 | C11: 17278.991 | D11: 0.05076228 | E11: 79.388889 | F11: 82.125 | G11: 0.034464661 | H11: 207.54699 | I11: 212.99558 | J11: 0.02625232 | K11: 11892.77 | L11: 7012.55 | M11: -0.41035184 | N11: да
A12: 6 | B12: 11145.828 | C12: 13627.487 | D12: 0.22265362 | E12: 59.222222 | F12: 67.866667 | G12: 0.14596623 | H12: 188.48486 | I12: 203.60473 | J12: 0.08021797 | K12: 9008.75 | L12: 14149.55 | M12: 0.57064521 | N12: да
A13: 7 | B13: 7394.3667 | C13: 6334.56 | D13: -0.14332623 | E13: 39.5 | F13: 35.666667 | G13: -0.097046414 | H13: 188.10406 | I13: 176.28677 | J13: -0.06282315 | K13: 2715.03 | L13: 3117.88 | M13: 0.14837773 | N13: да
A14: 8 | B14: 6938.5222 | C14: 7337.0433 | D14: 0.057436021 | E14: 31.333333 | F14: 32.733333 | G14: 0.044680851 | H14: 222.30248 | I14: 224.51128 | J14: 0.0099360104 | K14: 8409.08 | L14: 1600.4 | M14: -0.80968192 | N14: да
A15: 9 | B15: 11186.183 | C15: 9748.8433 | D15: -0.12849244 | E15: 52.388889 | F15: 47.066667 | G15: -0.10159067 | H15: 214.14665 | I15: 207.42265 | J15: -0.031399019 | K15: 4049.89 | L15: 1456.81 | M15: -0.64028406 | N15: да
A16: 10 | B16: 10564.956 | C16: 7592.4667 | D16: -0.28135366 | E16: 63.055556 | F16: 48.2 | G16: -0.23559471 | H16: 167.1535 | I16: 156.87965 | J16: -0.06146355 | K16: 19679.94 | L16: 21956.3 | M16: 0.11566905 | N16: да
A17: 11 | B17: 0 | C17: 0 | E17: 0 | F17: 0 | H17: 0 | I17: 0 | K17: 0 | L17: 0 | N17: нет
A18: 12 | B18: 5559.1361 | C18: 6017.98 | D18: 0.082538704 | E18: 33.944444 | F18: 37.2 | G18: 0.095908347 | H18: 163.24682 | I18: 163.81079 | J18: 0.003454704 | K18: 3461.69 | L18: 1934.66 | M18: -0.44112269 | N18: да
A19: 13 | B19: 6343.775 | C19: 5823.6733 | D19: -0.081986147 | E19: 42.277778 | F19: 36.066667 | G19: -0.14691196 | H19: 149.31188 | I19: 161.39489 | J19: 0.080924643 | K19: 3875.57 | L19: 4249.72 | M19: 0.096540638 | N19: да
A20: 14 | B20: 11110.491 | C20: 10170.987 | D20: -0.084560043 | E20: 64.444444 | F20: 55.6875 | G20: -0.13588362 | H20: 172.60654 | I20: 184.0674 | J20: 0.066398754 | K20: 10102.09 | L20: 9869.35 | M20: -0.023038797 | N20: да
A21: 15 | B21: 8578.525 | C21: 8299.7133 | D21: -0.03250112 | E21: 45.944444 | F21: 47.333333 | G21: 0.030229746 | H21: 187.03881 | I21: 175.24655 | J21: -0.063047145 | K21: 5500.35 | L21: 8273.87 | M21: 0.50424428 | N21: да
A22: 16 | B22: 7906.5139 | C22: 7266.5406 | D22: -0.080942533 | E22: 39.388889 | F22: 35.0625 | G22: -0.1098378 | H22: 203.88829 | I22: 200.5734 | J22: -0.01625834 | K22: 4928.73 | L22: 3491.72 | M22: -0.29155787 | N22: да
A23: 17 | B23: 6578.1556 | C23: 6162.76 | D23: -0.063147725 | E23: 36.055556 | F23: 33.2 | G23: -0.079198767 | H23: 183.75187 | I23: 187.38869 | J23: 0.019792003 | K23: 7991.72 | L23: 6512.89 | M23: -0.18504527 | N23: да
A24: 18 | B24: 0 | C24: 6322.1 | E24: 0 | F24: 33.6 | H24: 0 | I24: 195.03724 | K24: 0 | L24: 6005.39 | N24: да
A25: 19 | B25: 6888.4667 | C25: 6922.72 | D25: 0.0049725628 | E25: 40.5 | F25: 41.266667 | G25: 0.018930041 | H25: 170.76227 | I25: 169.64295 | J25: -0.0065548326 | K25: 5186.97 | L25: 4801.87 | M25: -0.07424373 | N25: да
A26: 20 | B26: 16973.869 | C26: 13149.569 | D26: -0.22530518 | E26: 77.888889 | F26: 58.5 | G26: -0.2489301 | H26: 218.2799 | I26: 227.96209 | J26: 0.04435674 | K26: 9718 | L26: 26531.81 | M26: 1.7301718 | N26: да
A27: 21 | B27: 8048.8618 | C27: 8810.2253 | D27: 0.0945927 | E27: 40.294118 | F27: 40.6 | G27: 0.0075912409 | H27: 200.62658 | I27: 216.57749 | J27: 0.079505439 | K27: 3208.48 | L27: 4568.27 | M27: 0.42381128 | N27: да
A28: 22 | B28: 5974.0794 | C28: 6425.0821 | D28: 0.07549326 | E28: 39.588235 | F28: 41.142857 | G28: 0.039269794 | H28: 151.55568 | I28: 154.94889 | J28: 0.02238925 | K28: 9418.32 | L28: 10573.51 | M28: 0.12265351 | N28: да
A29: 23 | B29: 9269.5029 | C29: 9206.6967 | D29: -0.0067755817 | E29: 46.941176 | F29: 45.666667 | G29: -0.027151211 | H29: 198.69439 | I29: 188.35127 | J29: -0.052055426 | K29: 6662.52 | L29: 8336.8 | M29: 0.25129831 | N29: да
A30: 24 | B30: 6875.1278 | C30: 6917.6769 | D30: 0.0061888516 | E30: 41.444444 | F30: 38.230769 | G30: -0.077541761 | H30: 164.71984 | I30: 181.91781 | J30: 0.10440741 | K30: 13190.15 | L30: 7289 | M30: -0.44739067 | N30: да
A31: 25 | B31: 0 | C31: 5921.2846 | E31: 0 | F31: 36.615385 | H31: 0 | I31: 168.64737 | K31: 0 | L31: 9299.51 | N31: нет
A32: 26 | B32: 3815.7375 | C32: 4032.1538 | D32: 0.05671678 | E32: 22.3125 | F32: 23.846154 | G32: 0.068735186 | H32: 172.9265 | I32: 169.81178 | J32: -0.018011814 | K32: 4668.67 | L32: 4367.15 | M32: -0.064583704 | N32: да
A33: 27 | B33: 10723.4 | C33: 9391.3923 | D33: -0.12421505 | E33: 59.133333 | F33: 55.230769 | G33: -0.065996011 | H33: 181.71871 | I33: 169.73109 | J33: -0.065967966 | K33: 8923.96 | L33: 10637.68 | M33: 0.19203582 | N33: да
A34: 28 | B34: 6886.3429 | C34: 7437.7833 | D34: 0.080077406 | E34: 40.214286 | F34: 46.583333 | G34: 0.15837774 | H34: 170.76955 | I34: 160.17775 | J34: -0.062023908 | K34: 5584.47 | L34: 9421.33 | M34: 0.68705893 | N34: да
A35: 29 | B35: 11937.771 | C35: 9931.2292 | D35: -0.16808349 | E35: 61 | F35: 48.666667 | G35: -0.20218579 | H35: 195.82412 | I35: 204.81608 | J35: 0.045918537 | K35: 6484.66 | L35: 8601.27 | M35: 0.32640262 | N35: да
A36: 901 | B36: 12798.071 | C36: 13206.364 | D36: 0.031902635 | E36: 62.285714 | F36: 62.090909 | G36: -0.0031276063 | H36: 205.52807 | I36: 213.56562 | J36: 0.03910686 | K36: 476.51 | L36: 0 | M36: -1 | N36: да

Sheet Дашборд
A1: >12000 | B1: 9000-12000 | C1: 7000-9000 | D1: <7000 | E1: Точек | X1: Месяц | Y1: Списания | Z1: Выручка | AA1: % списаний | AF1: ИТОГ | AG1: Точка | AH1: Стоимость содержания
A2: 4 | B2: 7 | C2: 7 | D2: 12 | E2: 30 | X2: 46053 | Y2: 158849.28 | Z2: 5017742 | AA2: 0.031657522 | AF2: =SUM(AH2:AH1020) -> 232489 | AG2: 0 | AH2: 0
B3: Средние значения по точкам | I3: ФАКТ | J3: ПЛАН | K3: Отклонение | X3: 46081 | Y3: 237866.45 | Z3: 4999554 | AA3: 0.047577534 | AG3: 1 | AH3: 2300
A4: № точки | B4: Выручка ср.-я | C4: Чеков ср.-е | D4: Ср.-й чек | E4: Списания ср.-е | F4: Среднебудничная выручка на 1 точку | I4: =AVERAGE(B5:B1020) -> 8719.3432 | J4: 9500 | K4: =(I4-J4)/J4 -> -0.082174402 | X4: 46112 | Y4: =247373.84-29449 -> 217924.84 | Z4: 5556634 | AA4: 0.044518649 | AG4: 2 | AH4: 300
A5: 1 | B5: ='1'!D2 -> 17400.554 | C5: ='1'!G$2 -> 106.08387 | D5: ='1'!H$2 -> 165.12835 | E5: ='1'!I$2 -> 699.88813 | X5: 46142 | Y5: =452394.84-47916 -> 404478.84 | Z5: =6979185 -> 6979185 | AA5: 0.067673996 | AG5: 3 | AH5: 3892
A6: 2 | B6: ='2'!D2 -> 5056.7733 | C6: ='2'!G$2 -> 23.625806 | D6: ='2'!H$2 -> 219.14064 | E6: ='2'!I$2 -> 185.69216 | X6: 46173 | Y6: =369911.43-142159 -> 227752.43 | Z6: 7122430 | AA6: =Y6/(Z6/100%) -> 0.031976787 | AG6: 4
A7: 3 | B7: ='3'!D$2 -> 7694.3712 | C7: ='3'!G$2 -> 32 | D7: ='3'!H$2 -> 238.09568 | E7: ='3'!I$2 -> 673.63115 | X7: 46203 | Y7: =359696.35-110000 -> 249696.35 | Z7: 6644976 | AA7: =Y7/(Z7/100%) -> 0.037576712 | AG7: 5 | AH7: 300
A8: 4 | B8: ='4'!D$2-'4'!C2 -> 2941.4374 | C8: ='4'!G$2 -> 32.157895 | D8: ='4'!H$2 -> 248.86864 | E8: ='4'!I$2 -> 1248.4317 | X8: 46234 | Y8: 341983.18 | Z8: 7338851 | AA8: =Y8/(Z8/100%) -> 0.046599008 | AG8: 6 | AH8: 3638
A9: 5 | B9: ='5'!D$2 -> 14822.316 | C9: ='5'!G$2 -> 70.096774 | D9: ='5'!H$2 -> 212.75225 | E9: ='5'!I$2 -> 449.86747 | X9: 46258 | Y9: 295159.88 | AG9: 7 | AH9: 300
A10: 6 | B10: ='6'!D$2 -> 9760.7927 | C10: ='6'!G$2 -> 49.192053 | D10: ='6'!H$2 -> 201.51469 | E10: ='6'!I$2 -> 520.84796 | AG10: 8 | AH10: 5810
A11: 7 | B11: ='7'!D$2 -> 5577.0686 | C11: ='7'!G$2 -> 30.305785 | D11: ='7'!H$2 -> 184.06041 | E11: ='7'!I$2 -> 239.24305 | AG11: 9 | AH11: 9900
A12: 8 | B12: ='8'!D$2 -> 7437.8164 | C12: ='8'!G$2 -> 31.973684 | D12: ='8'!H$2 -> 238.04987 | E12: ='8'!I$2 -> 257.44539 | AG12: 10 | AH12: 3810
A13: 9 | B13: ='9'!D$2 -> 10341.419 | C13: ='9'!G$2 -> 49.058442 | D13: ='9'!H$2 -> 211.44077 | E13: ='9'!I$2 -> 207.56388 | AG13: 11
A14: 10 | B14: ='10'!D$2 -> 9886.613 | C14: ='10'!G$2 -> 59.243421 | D14: ='10'!H$2 -> 168.01002 | E14: ='10'!I$2 -> 563.05645 | AG14: 12 | AH14: 4800
A15: 11 | AG15: 13 | AH15: 4800
A16: 12 | B16: ='12'!D$2 -> 6144.2566 | C16: ='12'!G$2 -> 41.97351 | D16: ='12'!H$2 -> 148.29333 | E16: ='12'!I$2 -> 222.51589 | AG16: 14 | AH16: 6765
A17: 13 | B17: ='13'!D$2 -> 6274.8255 | C17: ='13'!G$2 -> 53.152318 | D17: ='13'!H$2 -> 126.24771 | E17: ='13'!I$2 -> 265.27927 | AG17: 15 | AH17: 2800
A18: 14 | B18: ='14'!D$2 -> 11786.44 | C18: ='14'!G$2 -> 67.631579 | D18: ='14'!H$2 -> 175.50604 | E18: ='14'!I$2 -> 345.51307 | AG18: 16 | AH18: 300
A19: 15 | B19: ='15'!D$2 -> 8637.9245 | C19: ='15'!G$2 -> 49.370861 | D19: ='15'!H$2 -> 176.16397 | E19: ='15'!I$2 -> 308.52669 | AG19: 17 | AH19: 7049
A20: 16 | B20: ='16'!D$2 -> 7918.1447 | C20: ='16'!G$2 -> 39.629139 | D20: ='16'!H$2 -> 200.7958 | E20: ='16'!I$2 -> 238.83135 | AG20: 18 | AH20: 300
A21: 17 | B21: ='17'!D$2 -> 6951.1225 | C21: ='17'!G$2 -> 38.019608 | D21: ='17'!H$2 -> 184.53327 | E21: ='17'!I$2 -> 437.35961 | AG21: 19 | AH21: 2239
A22: 18 | B22: ='18'!D$2 -> 6322.1 | C22: ='18'!G$2 -> 33.6 | D22: ='18'!H$2 -> 195.03724 | E22: ='18'!I$2 -> 839.36286 | AG22: 20 | AH22: 3606
A23: 19 | B23: ='19'!D$2 -> 6887.1429 | C23: ='19'!G$2 -> 39.965986 | D23: ='19'!H$2 -> 173.86633 | E23: ='19'!I$2 -> 299.13946 | AG23: 21 | AH23: 2180
A24: 20 | B24: ='20'!D$2 -> 15616.147 | C24: ='20'!G$2 -> 71.915033 | D24: ='20'!H$2 -> 217.79266 | E24: ='20'!I$2 -> 610.62811 | AG24: 22 | AH24: 2300
A25: 21 | B25: ='21'!D$2 -> 7178.7581 | C25: ='21'!G$2 -> 36.184932 | D25: ='21'!H$2 -> 197.87501 | E25: ='21'!I$2 -> 264.33801 | AG25: 23 | AH25: 2300
A26: 22 | B26: ='22'!D$2 -> 6456.0993 | C26: ='22'!G$2 -> 42.194444 | D26: ='22'!H$2 -> 153.67644 | E26: ='22'!I$2 -> 424.41945 | AG26: 24 | AH26: 300
A27: 23 | B27: ='23'!D$2 -> 9432.3562 | C27: ='23'!G$2 -> 49.8 | D27: ='23'!H$2 -> 189.4962 | E27: ='23'!I$2 -> 311.40757 | AG27: 25 | AH27: 300
A28: 24 | B28: ='24'!D$2 -> 7901.369 | C28: ='24'!G$2 -> 42.325926 | D28: ='24'!H$2 -> 183.87019 | E28: ='24'!I$2 -> 553.78833 | AG28: 26 | AH28: 4010
A29: 25 | B29: ='25'!D$2 -> 5921.2846 | C29: ='25'!G$2 -> 36.615385 | D29: ='25'!H$2 -> 168.64737 | E29: ='25'!I$2 -> 370.37077 | AG29: 27 | AH29: 4010
A30: 26 | B30: ='26'!D$2 -> 3501.0025 | C30: ='26'!G$2 -> 19.876543 | D30: ='26'!H$2 -> 178.63902 | E30: ='26'!I$2 -> 382.55753 | AG30: 28 | AH30: 0
A31: 27 | B31: ='27'!D$2 -> 9880.7975 | C31: ='27'!G$2 -> 58.25641 | D31: ='27'!H$2 -> 171.46891 | E31: ='27'!I$2 -> 452.83275 | AG31: 29 | AH31: 4180
A32: 28 | B32: ='28'!D$2 -> 7753.8329 | C32: ='28'!G$2 -> 46.164384 | D32: ='28'!H$2 -> 168.72576 | E32: ='28'!I$2 -> 600.67 | AG32: 901 | AH32: 150000
A33: 901 | B33: ='901'!D$2 -> 15691.747 | C33: ='901'!G$2 -> 74.936709 | D33: ='901'!H$2 -> 210.01242 | E33: ='901'!I$2 -> 197.53538
A34: 29 | B34: ='29'!D$2 -> 11686.439 | C34: ='29'!G$2 -> 60.319149 | D34: ='29'!H$2 -> 192.62704 | E34: ='29'!I$2 -> 431.9998

Sheet 0
A1: Точка | B1: 0 | C1: Дата запуска | E1: Тип точки | F1: офис | G1: Активна | H1: Нет | K1: Стоимость обслуживания | L1: Аренда | M1: Коммуналка | N1: Клининг
A2: Среднее | B2: 209.08333 | D2: 209.08333 | E2: 1.1666667 | G2: 1.1666667 | H2: 187 | K2: =SUM(L2:Q2) -> 0
A3: Дата | B3: $ QR-код | C3: $ Касса | D3: $ Итог | E3: Чеки QR | F3: Чеки Касса | G3: Чеки Итог | H3: Ср.-й чек | I3: Списания | J3: д/н
A4: 46256 | B4: 172 | D4: 172 | E4: 1 | G4: 1 | H4: 172 | J4: Сб
A5: 46249 | B5: 209.4 | D5: 209.4 | E5: 1 | G5: 1 | H5: 209.4 | J5: Сб
A6: 46237 | B6: 192 | D6: 192 | E6: 1 | G6: 1 | H6: 192 | J6: Пн
A7: 46231 | B7: 98 | D7: 98 | E7: 1 | G7: 1 | H7: 98 | J7: Вт
A8: 46230 | B8: 310 | D8: 310 | E8: 1 | G8: 1 | H8: 310 | J8: Пн
A9: 46221 | B9: 45 | D9: 45 | E9: 1 | G9: 1 | H9: 45 | J9: Сб
A10: 46220 | B10: 98 | D10: 98 | E10: 1 | G10: 1 | H10: 98 | J10: Пт
A11: 46219 | B11: 196 | D11: 196 | E11: 1 | G11: 1 | H11: 196 | J11: Чт
A12: 46198 | B12: 196 | D12: 196 | E12: 2 | G12: 2 | H12: 98 | J12: Чт
A13: 46186 | B13: 160 | D13: 160 | E13: 1 | G13: 1 | H13: 160 | J13: Сб
A14: 46183 | B14: 334 | D14: 334 | E14: 2 | G14: 2 | H14: 167 | J14: Ср
A15: 46180 | B15: 115 | D15: 115 | E15: 1 | G15: 1 | H15: 115 | J15: Вс
... A21: 46148 | B21: 309 | D21: 309 | E21: 1 | G21: 1 | H21: 309 | J21: Ср

Sheet 1
A1: Точка | B1: 1 | C1: Дата запуска | D1: 45901 | E1: Тип точки | F1: офис | G1: Активна | H1: Да | K1: Стоимость обслуживания | L1: Аренда | M1: Коммуналка | N1: Клининг
A2: Среднее | B2: 315.97778 | C2: 17345.513 | D2: 17400.554 | E2: 2 | F2: 105.73548 | G2: 106.08387 | H2: 165.12835 | I2: 699.88813 | K2: =SUM(L2:Q2) -> 2300 | L2: 2000 | M2: 0 | N2: 300
A3: Дата | B3: $ QR-код | C3: $ Касса | D3: $ Итог | E3: Чеки QR | F3: Чеки Касса | G3: Чеки Итог | H3: Ср.-й чек | I3: Списания | J3: д/н
A4: 46257 | B4: 240 | C4: 14075.5 | D4: 14315.5 | E4: 2 | F4: 74 | G4: 76 | H4: 188.36184 | I4: 1097.93 | J4: Вс
A5: 46256 | B5: 380 | C5: 20767.9 | D5: 21147.9 | E5: 4 | F5: 115 | G5: 119 | H5: 177.71345 | I5: 310.02 | J5: Сб
A6: 46255 | B6: 762 | C6: 12203.8 | D6: 12965.8 | E6: 3 | F6: 80 | G6: 83 | H6: 156.21446 | I6: 1132.32 | J6: Пт
A7: 46254 | B7: 845 | C7: 20099 | D7: 20944 | E7: 5 | F7: 109 | G7: 114 | H7: 183.7193 | I7: 111.72 | J7: Чт
A8: 46253 | B8: 229 | C8: 15487.3 | D8: 15716.3 | E8: 1 | F8: 97 | G8: 98 | H8: 160.37041 | I8: 1156.65 | J8: Ср
A9: 46252 | B9: 896 | C9: 12819 | D9: 13715 | E9: 6 | F9: 85 | G9: 91 | H9: 150.71429 | I9: 3079.87 | J9: Вт
A10: 46251 | B10: 740 | C10: 15340.2 | D10: 16080.2 | E10: 5 | F10: 87 | G10: 92 | H10: 174.78478 | I10: 415.18 | J10: Пн
A11: 46250 | B11: 971 | C11: 16874.6 | D11: 17845.6 | E11: 7 | F11: 105 | G11: 112 | H11: 159.33571 | I11: 3202.87 | J11: Вс
A12: 46249 | B12: 1096 | C12: 18017.75 | D12: 19113.75 | E12: 6 | F12: 97 | G12: 103 | H12: 185.57039 | I12: 0 | J12: Сб
A13: 46248 | B13: 205 | C13: 17215 | D13: 17420 | E13: 2 | F13: 106 | G13: 108 | H13: 161.2963 | I13: 248.77 | J13: Пт
A14: 46247 | C14: 15287.4 | D14: 15287.4 | F14: 102 | G14: 102 | H14: 149.87647 | I14: 99.76 | J14: Чт
A15: 46246 | C15: 13514.8 | D15: 13514.8 | F15: 83 | G15: 83 | H15: 162.82892 | I15: 116.88 | J15: Ср
A16: 46245 | C16: 16184.3 | D16: 16184.3 | F16: 105 | G16: 105 | H16: 154.13619 | I16: 259.42 | J16: Вт
A17: 46244 | C17: 16255.55 | D17: 16255.55 | F17: 90 | G17: 90 | H17: 180.61722 | I17: 848.55 | J17: Пн
A18: 46243 | C18: 13416.8 | D18: 13416.8 | F18: 90 | G18: 90 | H18: 149.07556 | I18: 2169.68 | J18: Вс
A19: 46242 | C19: 24837.5 | D19: 24837.5 | F19: 135 | G19: 135 | H19: 183.98148 | I19: 72.44 | J19: Сб
A20: 46241 | C20: 16756.8 | D20: 16756.8 | F20: 108 | G20: 108 | H20: 155.15556 | I20: 508.85 | J20: Пт
A21: 46240 | C21: 22246.4 | D21: 22246.4 | F21: 116 | G21: 116 | H21: 191.77931 | I21: 349.86 | J21: Чт
A22: 46239 | C22: 18712 | D22: 18712 | F22: 101 | G22: 101 | H22: 185.26733 | I22: 295.65 | J22: Ср
A23: 46238 | C23: 17980.6 | D23: 17980.6 | F23: 103 | G23: 103 | H23: 174.56893 | I23: 1028.2 | J23: Вт
A24: 46237 | C24: 15012.5 | D24: 15012.5 | F24: 89 | G24: 89 | H24: 168.67978 | I24: 373.09 | J24: Пн
A25: 46236 | C25: 16361.4 | D25: 16361.4 | F25: 86 | G25: 86 | H25: 190.24884 | I25: 1655.78 | J25: Вс
... A43: 46218 | C43: 15856.8 | D43: 15856.8 | F43: 85 | G43: 85 | H43: 186.55059 | I43: 866.2 | J43: Ср
A44: 46217 | B44: 25 | C44: 13966.8 | D44: 13991.8 | E44: 1 | F44: 96 | G44: 97 | H44: 144.24536 | I44: 6588.86 | J44: Вт
A45: 46216 | C45: 14774.9 | D45: 14774.9 | F45: 94 | G45: 94 | H45: 157.17979 | I45: 262.67 | J45: Пн
A46: 46215 | C46: 17918.2 | D46: 17918.2 | F46: 115 | G46: 115 | H46: 155.81043 | I46: 2176.97 | J46: Вс
A47: 46214 | C47: 22378.2 | D47: 22378.2 | F47: 135 | G47: 135 | H47: 165.76444 | I47: 12716.75 | J47: Сб
A48: 46213 | C48: 18406.8 | D48: 18406.8 | F48: 119 | G48: 119 | H48: 154.67899 | I48: 371.98 | J48: Пт
A49: 46212 | B49: 97 | C49: 19215.6 | D49: 19312.6 | E49: 1 | F49: 105 | G49: 106 | H49: 182.19434 | I49: 252.36 | J49: Чт
A50: 46211 | C50: 14788.8 | D50: 14788.8 | F50: 87 | G50: 87 | H50: 169.98621 | I50: 529.48 | J50: Ср
A51: 46210 | C51: 16779.4 | D51: 16779.4 | F51: 96 | G51: 96 | H51: 174.78542 | I51: 0 | J51: Вт
A52: 46209 | B52: 210 | C52: 14279.4 | D52: 14489.4 | E52: 1 | F52: 85 | G52: 86 | H52: 168.4814 | I52: 171.66 | J52: Пн
A53: 46208 | C53: 17053.4 | D53: 17053.4 | F53: 110 | G53: 110 | H53: 155.03091 | I53: 958.25 | J53: Вс
A54: 46207 | C54: 24853.6 | D54: 24853.6 | F54: 151 | G54: 151 | H54: 164.59338 | I54: 221.91 | J54: Сб
A55: 46206 | C55: 17103.2 | D55: 17103.2 | F55: 117 | G55: 117 | H55: 146.1812 | I55: 79.31 | J55: Пт
A56: 46205 | C56: 19833.5 | D56: 19833.5 | F56: 128 | G56: 128 | H56: 154.94922 | I56: 907.49 | J56: Чт
A57: 46204 | C57: 14773.15 | D57: 14773.15 | F57: 97 | G57: 97 | H57: 152.30052 | I57: 143.23 | J57: Ср
A58: 46203 | C58: 17251.9 | D58: 17251.9 | F58: 117 | G58: 117 | H58: 147.45214 | I58: 1723.52 | J58: Вт
A59: 46202 | C59: 19165.3 | D59: 19165.3 | F59: 118 | G59: 118 | H59: 162.4178 | I59: 854.32 | J59: Пн
A60: 46201 | C60: 15424.1 | D60: 15424.1 | F60: 88 | G60: 88 | H60: 175.27386 | I60: 2030.99 | J60: Вс
A61: 46200 | C61: 19281.3 | D61: 19281.3 | F61: 122 | G61: 122 | H61: 158.04344 | I61: 944.1 | J61: Сб
A62: 46199 | C62: 15307.5 | D62: 15307.5 | F62: 102 | G62: 102 | H62: 150.07353 | I62: 1162.92 | J62: Пт
A63: 46198 | C63: 21518.9 | D63: 21518.9 | F63: 128 | G63: 128 | H63: 168.11641 | I63: 63.17 | J63: Чт
A64: 46197 | B64: 288 | C64: 15301.8 | D64: 15589.8 | E64: 2 | F64: 97 | G64: 99 | H64: 157.47273 | I64: 83.99 | J64: Ср | L64: ТОП-3 Целевой аудитории
A65: 46196 | C65: 14932.2 | D65: 14932.2 | F65: 110 | G65: 110 | H65: 135.74727 | I65: 1151.19 | J65: Вт | L65: пол | M65: возраст | N65: % присутствия | P65: кол-во уникальных гостей
A66: 46195 | C66: 12975.3 | D66: 12975.3 | F66: 82 | G66: 82 | H66: 158.23537 | I66: 279.46 | J66: Пн | L66: женщины | M66: 25-35 | N66: 0.22 | P66: 180
A67: 46194 | C67: 16403.3 | D67: 16403.3 | F67: 114 | G67: 114 | H67: 143.8886 | I67: 2195.02 | J67: Вс | L67: мужчины | M67: 25-35 | N67: 0.16
A68: 46193 | C68: 22971.4 | D68: 22971.4 | F68: 162 | G68: 162 | H68: 141.79877 | I68: 627.73 | J68: Сб | L68: мужчины | M68: 35-45 | N68: 0.13
A69: 46192 | C69: 17524.2 | D69: 17524.2 | F69: 116 | G69: 116 | H69: 151.07069 | I69: 1785 | J69: Пт
A70: 46191 | C70: 18087 | D70: 18087 | F70: 110 | G70: 110 | H70: 164.42727 | I70: 702.6 | J70: Чт | L70: График работы | M70: дней в неделю | N70: часы работы
A71: 46190 | C71: 18274.3 | D71: 18274.3 | F71: 108 | G71: 108 | H71: 169.20648 | I71: 521.32 | J71: Ср | M71: 7 | N71: 08:00-22:00
A72: 46189 | C72: 13787.05 | D72: 13787.05 | F72: 92 | G72: 92 | H72: 149.85924 | I72: 2405.63 | J72: Вт
A73: 46188 | C73: 10922 | D73: 10922 | F73: 76 | G73: 76 | H73: 143.71053 | I73: 709.66 | J73: Пн
A74: 46187 | C74: 16917.3 | D74: 16917.3 | F74: 97 | G74: 97 | H74: 174.40515 | I74: 2470.33 | J74: Вс
A75: 46186 | C75: 20832.7 | D75: 20832.7 | F75: 134 | G75: 134 | H75: 155.46791 | I75: 2721.78 | J75: Сб
A76: 46185 | C76: 16936 | D76: 16936 | F76: 110 | G76: 110 | H76: 153.96364 | I76: 0 | J76: Пт
A77: 46184 | C77: 18909.8 | D77: 18909.8 | F77: 117 | G77: 117 | H77: 161.62222 | I77: 777.3 | J77: Чт
A78: 46183 | C78: 15112.3 | D78: 15112.3 | F78: 93 | G78: 93 | H78: 162.49785 | I78: 141.11 | J78: Ср
A79: 46182 | C79: 17531.4 | D79: 17531.4 | F79: 107 | G79: 107 | H79: 163.84486 | I79: 69.23 | J79: Вт
A80: 46181 | C80: 12232.6 | D80: 12232.6 | F80: 74 | G80: 74 | H80: 165.30541 | I80: 1901.43 | J80: Пн
A81: 46180 | C81: 17037.4 | D81: 17037.4 | F81: 104 | G81: 104 | H81: 163.82115 | I81: 2624 | J81: Вс
A82: 46179 | C82: 27067.8 | D82: 27067.8 | F82: 160 | G82: 160 | H82: 169.17375 | I82: 515.29 | J82: Сб
A83: 46178 | C83: 18741.8 | D83: 18741.8 | F83: 116 | G83: 116 | H83: 161.56724 | I83: 121.22 | J83: Пт
... A91: 46170 | C91: 17732.6 | D91: 17732.6 | F91: 112 | G91: 112 | H91: 158.32679 | I91: 0 | J91: Чт
A92: 46169 | B92: 51 | C92: 19817.45 | D92: 19868.45 | E92: 1 | F92: 121 | G92: 122 | H92: 162.85615 | I92: 680.44 | J92: Ср
A93: 46168 | C93: 16767.85 | D93: 16767.85 | F93: 116 | G93: 116 | H93: 144.55043 | I93: 974.33 | J93: Вт
A94: 46167 | C94: 15534.1 | D94: 15534.1 | F94: 105 | G94: 105 | H94: 147.94381 | I94: 567.62 | J94: Пн
A95: 46166 | C95: 10542 | D95: 10542 | F95: 85 | G95: 85 | H95: 124.02353 | I95: 1719.93 | J95: Вс
A96: 46165 | C96: 11896.8 | D96: 11896.8 | F96: 90 | G96: 90 | H96: 132.18667 | I96: 435.58 | J96: Сб
A97: 46164 | C97: 19826.7 | D97: 19826.7 | F97: 134 | G97: 134 | H97: 147.96045 | I97: 394.27 | J97: Пт
A98: 46163 | C98: 16562.8 | D98: 16562.8 | F98: 108 | G98: 108 | H98: 153.35926 | I98: 1001.08 | J98: Чт
A99: 46162 | C99: 18727 | D99: 18727 | F99: 119 | G99: 119 | H99: 157.36975 | I99: 147.01 | J99: Ср
A100: 46161 | C100: 15243.05 | D100: 15243.05 | F100: 94 | G100: 94 | H100: 162.16011 | I100: 0 | J100: Вт
A101: 46160 | B101: 72 | C101: 16645 | D101: 16717 | E101: 1 | F101: 90 | G101: 91 | H101: 183.7033 | I101: 140.81 | J101: Пн
A102: 46159 | C102: 8109.4 | D102: 8109.4 | F102: 57 | G102: 57 | H102: 142.27018 | I102: 792.59 | J102: Вс
A103: 46158 | C103: 12048.2 | D103: 12048.2 | F103: 82 | G103: 82 | H103: 146.92927 | I103: 148.73 | J103: Сб
A104: 46157 | B104: 103 | C104: 20509.05 | D104: 20612.05 | E104: 2 | F104: 117 | G104: 119 | H104: 173.2105 | I104: 161.77 | J104: Пт
A105: 46156 | C105: 21169.6 | D105: 21169.6 | F105: 126 | G105: 126 | H105: 168.0127 | I105: 636.11 | J105: Чт
A106: 46155 | C106: 16441.1 | D106: 16441.1 | F106: 116 | G106: 116 | H106: 141.73362 | I106: 481.67 | J106: Ср
A107: 46154 | C107: 16589.9 | D107: 16589.9 | F107: 114 | G107: 114 | H107: 145.52544 | I107: 0 | J107: Вт
A108: 46153 | C108: 9216.7 | D108: 9216.7 | F108: 60 | G108: 60 | H108: 153.61167 | I108: 3.98 | J108: Пн
A109: 46152 | C109: 7573.8 | D109: 7573.8 | F109: 53 | G109: 53 | H109: 142.90189 | I109: 1347.3 | J109: Вс
A110: 46151 | C110: 10569.1 | D110: 10569.1 | F110: 75 | G110: 75 | H110: 140.92133 | I110: 1467.8 | J110: Сб
A111: 46150 | C111: 22096.7 | D111: 22096.7 | F111: 136 | G111: 136 | H111: 162.47574 | I111: 162.81 | J111: Пт
A112: 46149 | B112: 40 | C112: 22466.5 | D112: 22506.5 | E112: 1 | F112: 143 | G112: 144 | H112: 156.29514 | I112: 851.96 | J112: Чт
A113: 46148 | C113: 17182 | D113: 17182 | F113: 95 | G113: 95 | H113: 180.86316 | I113: 1022.14 | J113: Ср
A114: 46147 | B114: 187 | C114: 17855.8 | D114: 18042.8 | E114: 1 | F114: 108 | G114: 109 | H114: 165.53028 | I114: 277.98 | J114: Вт
A115: 46146 | B115: 187 | C115: 18842.8 | D115: 19029.8 | E115: 1 | F115: 115 | G115: 116 | H115: 164.05 | I115: 271.73 | J115: Пн
A116: 46145 | C116: 9218.5 | D116: 9218.5 | F116: 60 | G116: 60 | H116: 153.64167 | I116: 665.46 | J116: Вс
A117: 46144 | C117: 10914.2 | D117: 10914.2 | F117: 76 | G117: 76 | H117: 143.60789 | I117: 0 | J117: Сб
A118: 46143 | C118: 15099.7 | D118: 15099.7 | F118: 103 | G118: 103 | H118: 146.59903 | I118: 0 | J118: Пт
A119: 46142 | C119: 20407.1 | D119: 20407.1 | F119: 120 | G119: 120 | H119: 170.05917 | I119: 0 | J119: Чт
A120: 46141 | C120: 17932.7 | D120: 17932.7 | F120: 120 | G120: 120 | H120: 149.43917 | I120: 822.56 | J120: Ср
A121: 46140 | C121: 17689.4 | D121: 17689.4 | F121: 110 | G121: 110 | H121: 160.81273 | I121: 1803.23 | J121: Вт
A122: 46139 | C122: 17590.1 | D122: 17590.1 | F122: 106 | G122: 106 | H122: 165.94434 | I122: 799.81 | J122: Пн
A123: 46138 | C123: 13080.9 | D123: 13080.9 | F123: 98 | G123: 98 | H123: 133.47857 | I123: 2680.34 | J123: Вс
A124: 46137 | C124: 16559 | D124: 16559 | F124: 125 | G124: 125 | H124: 132.472 | I124: 353.33 | J124: Сб
...

Sheet 2
A1: Точка | B1: 2 | C1: Дата запуска | D1: 45914 | E1: Тип точки | F1: офис | G1: Активна | H1: Да | K1: Стоимость обслуживания | L1: Аренда | M1: Коммуналка | N1: Клининг
A2: Среднее | B2: 723.5 | C2: 5038.1023 | D2: 5056.7733 | E2: 1.25 | F2: 23.593548 | G2: 23.625806 | H2: 219.14064 | I2: 185.69216 | K2: =SUM(L2:Q2) -> 300 | L2: 0 | M2: 0 | N2: 300
A3: Дата | B3: $ QR-код | C3: $ Касса | D3: $ Итог | E3: Чеки QR | F3: Чеки Касса | G3: Чеки Итог | H3: Ср.-й чек | I3: Списания | J3: д/н
A4: 46257 | C4: 0 | F4: 0 | I4: 160.39 | J4: Вс
A5: 46256 | C5: 532.2 | D5: 532.2 | F5: 4 | G5: 4 | H5: 133.05 | I5: 54.95 | J5: Сб
A6: 46255 | C6: 3271.4 | D6: 3271.4 | F6: 14 | G6: 14 | H6: 233.67143 | I6: 0 | J6: Пт
A7: 46254 | C7: 4403.6 | D7: 4403.6 | F7: 31 | G7: 31 | H7: 142.05161 | I7: 0 | J7: Чт
A8: 46253 | C8: 3454 | D8: 3454 | F8: 20 | G8: 20 | H8: 172.7 | I8: 40.98 | J8: Ср
A9: 46252 | C9: 5368.4 | D9: 5368.4 | F9: 26 | G9: 26 | H9: 206.47692 | I9: 0 | J9: Вт
A10: 46251 | C10: 6193 | D10: 6193 | F10: 24 | G10: 24 | H10: 258.04167 | I10: 35.95 | J10: Пн
A11: 46250 | C11: 523.9 | D11: 523.9 | F11: 10 | G11: 10 | H11: 52.39 | I11: 517.53 | J11: Вс
A12: 46249 | C12: 562.8 | D12: 562.8 | F12: 3 | G12: 3 | H12: 187.6 | I12: 0 | J12: Сб
A13: 46248 | C13: 5104.75 | D13: 5104.75 | F13: 20 | G13: 20 | H13: 255.2375 | I13: 0 | J13: Пт
A14: 46247 | C14: 3640 | D14: 3640 | F14: 25 | G14: 25 | H14: 145.6 | I14: 108.82 | J14: Чт
A15: 46246 | C15: 4373.3 | D15: 4373.3 | F15: 23 | G15: 23 | H15: 190.14348 | I15: 71.58 | J15: Ср
A16: 46245 | C16: 3286.1 | D16: 3286.1 | F16: 29 | G16: 29 | H16: 113.31379 | I16: 91.54 | J16: Вт
... A24: 46237 | C24: 4836 | D24: 4836 | F24: 22 | G24: 22 | H24: 219.81818 | I24: 0 | J24: Пн
A25: 46236 | C25: 0 | F25: 8 | G25: 8 | H25: 0 | I25: 621.83 | J25: Вс
A26: 46235 | C26: 502.8 | D26: 502.8 | F26: 2 | G26: 2 | H26: 251.4 | I26: 271.01 | J26: Сб
A27: 46234 | C27: 4417.2 | D27: 4417.2 | F27: 17 | G27: 17 | H27: 259.83529 | I27: 85.74 | J27: Пт
A28: 46233 | C28: 3407.2 | D28: 3407.2 | F28: 24 | G28: 24 | H28: 141.96667 | I28: 0 | J28: Чт
A29: 46232 | C29: 5629 | D29: 5629 | F29: 26 | G29: 26 | H29: 216.5 | I29: 139.72 | J29: Ср
A30: 46231 | C30: 6264 | D30: 6264 | F30: 30 | G30: 30 | H30: 208.8 | I30: 0 | J30: Вт
A31: 46230 | C31: 4579 | D31: 4579 | F31: 17 | G31: 17 | H31: 269.35294 | I31: 299.38 | J31: Пн
A32: 46229 | C32: 402.4 | D32: 402.4 | F32: 5 | G32: 5 | H32: 80.48 | I32: 739.62 | J32: Вс
A33: 46228 | C33: 1098.6 | D33: 1098.6 | F33: 5 | G33: 5 | H33: 219.72 | I33: 187.3 | J33: Сб
A34: 46227 | C34: 4303.6 | D34: 4303.6 | F34: 20 | G34: 20 | H34: 215.18 | I34: 837.01 | J34: Пт
A35: 46226 | C35: 3866.4 | D35: 3866.4 | F35: 19 | G35: 19 | H35: 203.49474 | I35: 91.1 | J35: Чт
A36: 46225 | C36: 4779.5 | D36: 4779.5 | F36: 26 | G36: 26 | H36: 183.82692 | I36: 53.43 | J36: Ср
A37: 46224 | C37: 4742 | D37: 4742 | F37: 29 | G37: 29 | H37: 163.51724 | I37: 0 | J37: Вт
... A45: 46216 | C45: 6137.5 | D45: 6137.5 | F45: 29 | G45: 29 | H45: 211.63793 | I45: 0 | J45: Пн
A46: 46215 | C46: 0 | F46: 2 | G46: 2 | H46: 0 | I46: 82.72 | J46: Вс
A47: 46214 | C47: 198.8 | D47: 198.8 | F47: 2 | G47: 2 | H47: 99.4 | I47: 26.47 | J47: Сб
A48: 46213 | C48: 2879.4 | D48: 2879.4 | F48: 7 | G48: 7 | H48: 411.34286 | I48: 0 | J48: Пт
A49: 46212 | C49: 6221.4 | D49: 6221.4 | F49: 30 | G49: 30 | H49: 207.38 | I49: 0 | J49: Чт
A50: 46211 | C50: 6544 | D50: 6544 | F50: 31 | G50: 31 | H50: 211.09677 | I50: 38.22 | J50: Ср
A51: 46210 | C51: 5593.8 | D51: 5593.8 | F51: 28 | G51: 28 | H51: 199.77857 | I51: 0 | J51: Вт
A52: 46209 | C52: 3740 | D52: 3740 | F52: 22 | G52: 22 | H52: 170 | I52: 75.4 | J52: Пн
A53: 46208 | C53: 452.8 | D53: 452.8 | F53: 11 | G53: 11 | H53: 41.163636 | I53: 4 | J53: Вс
A54: 46207 | C54: 98 | D54: 98 | F54: 1 | G54: 1 | H54: 98 | I54: 0 | J54: Сб
A55: 46206 | C55: 4495.5 | D55: 4495.5 | F55: 19 | G55: 19 | H55: 236.60526 | I55: 106.51 | J55: Пт
A56: 46205 | C56: 5351.4 | D56: 5351.4 | F56: 39 | G56: 39 | H56: 137.21538 | I56: 35.72 | J56: Чт
A57: 46204 | C57: 4087.4 | D57: 4087.4 | F57: 24 | G57: 24 | H57: 170.30833 | I57: 189.79 | J57: Ср
A58: 46203 | C58: 4186.6 | D58: 4186.6 | F58: 20 | G58: 20 | H58: 209.33 | I58: 43.41 | J58: Вт
... A63: 46198 | C63: 3314.75 | D63: 3314.75 | F63: 19 | G63: 19 | H63: 174.46053 | I63: 330.02 | J63: Чт
A64: 46197 | C64: 3266.6 | D64: 3266.6 | F64: 23 | G64: 23 | H64: 142.02609 | I64: 180.21 | J64: Ср | L64: ТОП-3 Целевой аудитории
A65: 46196 | C65: 2905 | D65: 2905 | F65: 22 | G65: 22 | H65: 132.04545 | I65: 359.04 | J65: Вт | L65: пол | M65: возраст | N65: % присутствия | P65: кол-во уникальных гостей
A66: 46195 | C66: 2352 | D66: 2352 | F66: 21 | G66: 21 | H66: 112 | I66: 94.45 | J66: Пн | L66: женщины | M66: 35-45 | N66: 0.24 | P66: 258
A67: 46194 | C67: 1496 | D67: 1496 | F67: 9 | G67: 9 | H67: 166.22222 | I67: 793.07 | J67: Вс | L67: мужчины | M67: 35-45 | N67: 0.16
A68: 46193 | C68: 207.4 | D68: 207.4 | F68: 2 | G68: 2 | H68: 103.7 | I68: 323.14 | J68: Сб | L68: мужчины | M68: 45-55 | N68: 0.13
A69: 46192 | C69: 4271.8 | D69: 4271.8 | F69: 18 | G69: 18 | H69: 237.32222 | I69: 164.63 | J69: Пт
A70: 46191 | C70: 2879 | D70: 2879 | F70: 17 | G70: 17 | H70: 169.35294 | I70: 87.03 | J70: Чт | L70: График работы | M70: дней в неделю | N70: часы работы
A71: 46190 | C71: 3591 | D71: 3591 | F71: 25 | G71: 25 | H71: 143.64 | I71: 474.39 | J71: Ср | M71: 5 | N71: 08:00-17:00
A72: 46189 | C72: 1938 | D72: 1938 | F72: 21 | G72: 21 | H72: 92.285714 | I72: 615.41 | J72: Вт
A73: 46188 | C73: 3679.5 | D73: 3679.5 | F73: 23 | G73: 23 | H73: 159.97826 | I73: 710.46 | J73: Пн
A74: 46187 | C74: 270 | D74: 270 | F74: 5 | G74: 5 | H74: 54 | I74: 108.88 | J74: Вс
A75: 46186 | C75: 65 | D75: 65 | F75: 1 | G75: 1 | H75: 65 | I75: 67.39 | J75: Сб
A76: 46185 | C76: 696.2 | D76: 696.2 | F76: 7 | G76: 7 | H76: 99.457143 | I76: 58.24 | J76: Пт
A77: 46184 | C77: 2250.4 | D77: 2250.4 | F77: 27 | G77: 27 | H77: 83.348148 | I77: 109.08 | J77: Чт
A78: 46183 | C78: 5324 | D78: 5324 | F78: 28 | G78: 28 | H78: 190.14286 | I78: 0 | J78: Ср
A79: 46182 | C79: 5793 | D79: 5793 | F79: 25 | G79: 25 | H79: 231.72 | I79: 457.04 | J79: Вт
A80: 46181 | C80: 2669.4 | D80: 2669.4 | F80: 17 | G80: 17 | H80: 157.02353 | I80: 175.28 | J80: Пн
A81: 46180 | C81: 138 | D81: 138 | F81: 6 | G81: 6 | H81: 23 | I81: 906.98 | J81: Вс
A82: 46179 | C82: 117.6 | D82: 117.6 | F82: 1 | G82: 1 | H82: 117.6 | I82: 61.59 | J82: Сб
A83: 46178 | C83: 3184.1 | D83: 3184.1 | F83: 15 | G83: 15 | H83: 212.27333 | I83: 52.66 | J83: Пт
... A132: 46128 | C132: 4566 | D132: 4566 | F132: 28 | G132: 28 | H132: 163.07143 | I132: 4.8 | J132: Чт
A133: 46127 | C133: 5853.8 | D133: 5853.8 | F133: 25 | G133: 25 | H133: 234.152 | J133: Ср
A134: 46126 | C134: 6272.4 | D134: 6272.4 | F134: 39 | G134: 39 | H134: 160.83077 | J134: Вт
A135: 46125 | C135: 5492 | D135: 5492 | F135: 21 | G135: 21 | H135: 261.52381 | I135: 39.27 | J135: Пн
A136: 46124 | C136: 367 | D136: 367 | F136: 2 | G136: 2 | H136: 183.5 | I136: 331 | J136: Вс
A137: 46123 | C137: 310 | D137: 310 | F137: 2 | G137: 2 | H137: 155 | J137: Сб
A138: 46122 | C138: 2836.9 | D138: 2836.9 | F138: 20 | G138: 20 | H138: 141.845 | I138: 0 | J138: Пт
A139: 46121 | C139: 3977.4 | D139: 3977.4 | F139: 16 | G139: 16 | H139: 248.5875 | I139: 226.91 | J139: Чт
A140: 46120 | C140: 9488.2 | D140: 9488.2 | F140: 34 | G140: 34 | H140: 279.06471 | I140: 1514.09 | J140: Ср
A141: 46119 | C141: 6063 | D141: 6063 | F141: 31 | G141: 31 | H141: 195.58065 | I141: 0 | J141: Вт
A142: 46118 | C142: 4553.69 | D142: 4553.69 | F142: 23 | G142: 23 | H142: 197.98652 | I142: 48.32 | J142: Пн
A143: 46117 | B143: 420 | C143: 393 | D143: 813 | E143: 2 | F143: 5 | G143: 7 | H143: 116.14286 | I143: 918.44 | J143: Вс
A144: 46116 | C144: 693.2 | D144: 693.2 | F144: 6 | G144: 6 | H144: 115.53333 | I144: 0 | J144: Сб
A145: 46115 | C145: 4000 | D145: 4000 | F145: 23 | G145: 23 | H145: 173.91304 | I145: 0 | J145: Пт
A146: 46114 | C146: 4013.2 | D146: 4013.2 | F146: 25 | G146: 25 | H146: 160.528 | I146: 60.45 | J146: Чт
A147: 46113 | C147: 8210.8 | D147: 8210.8 | F147: 24 | G147: 24 | H147: 342.11667 | I147: 180.13 | J147: Ср
A148: 46112 | C148: 5362 | D148: 5362 | F148: 25 | G148: 25 | H148: 214.48 | I148: 0 | J148: Вт
A149: 46111 | C149: 8396.5 | D149: 8396.5 | F149: 28 | G149: 28 | H149: 299.875 | I149: 49.74 | J149: Пн
A150: 46110 | C150: 1530.6 | D150: 1530.6 | F150: 7 | G150: 7 | H150: 218.65714 | I150: 436.14 | J150: Вс
A151: 46109 | C151: 258 | D151: 258 | F151: 2 | G151: 2 | H151: 129 | I151: 135.15 | J151: Сб
A152: 46108 | C152: 10502.65 | D152: 10502.65 | F152: 42 | G152: 42 | H152: 250.0631 | I152: 0 | J152: Пт
A153: 46107 | C153: 2736 | D153: 2736 | F153: 12 | G153: 12 | H153: 228 | I153: 565.17 | J153: Чт
A154: 46106 | B154: 172 | C154: 3810.8 | D154: 3982.8 | E154: 1 | F154: 13 | G154: 14 | H154: 284.48571 | I154: 34.43 | J154: Ср
A155: 46105 | C155: 9169.4 | D155: 9169.4 | F155: 23 | G155: 23 | H155: 398.66957 | I155: 67.47 | J155: Вт
A156: 46104 | C156: 5351.4 | D156: 5351.4 | F156: 26 | G156: 26 | H156: 205.82308 | I156: 42.85 | J156: Пн
A157: 46103 | C157: 357 | D157: 357 | F157: 3 | G157: 3 | H157: 119 | I157: 953.66 | J157: Вс
A158: 46102 | C158: 743.6 | D158: 743.6 | F158: 5 | G158: 5 | H158: 148.72 | I158: 749.06 | J158: Сб
A159: 46101 | C159: 5438.6 | D159: 5438.6 | F159: 22 | G159: 22 | H159: 247.20909 | I159: 0 | J159: Пт
A160: 46100 | C160: 6536.2 | D160: 6536.2 | F160: 31 | G160: 31 | H160: 210.84516 | I160: 116.73 | J160: Чт
A161: 46099 | C161: 7626.65 | D161: 7626.65 | F161: 33 | G161: 33 | H161: 231.11061 | I161: 20.28 | J161: Ср
A162: 46098 | C162: 4584 | D162: 4584 | F162: 23 | G162: 23 | H162: 199.30435 | I162: 46.66 | J162: Вт
A163: 46097 | C163: 6016.6 | D163: 6016.6 | F163: 24 | G163: 24 | H163: 250.69167 | I163: 48 | J163: Пн
A164: 46096 | C164: 442 | D164: 442 | F164: 3 | G164: 3 | H164: 147.33333 | I164: 0 | J164: Вс
A165: 46095 | C165: 391.8 | D165: 391.8 | F165: 3 | G165: 3 | H165: 130.6 | I165: 136.97 | J165: Сб
A166: 46094 | C166: 3335.6 | D166: 3335.6 | F166: 17 | G166: 17 | H166: 196.21176 | I166: 460.65 | J166: Пт
...

Sheet 3
A1: Точка | B1: 3 | C1: Дата запуска | D1: 46224 | E1: Тип точки | F1: медицина | G1: Активна | H1: Да | K1: Стоимость обслуживания | L1: Аренда | M1: Коммуналка | N1: Клининг
A2: Среднее | C2: 7694.3712 | D2: 7694.3712 | F2: 32 | G2: 32 | H2: 238.09568 | I2: 673.63115 | K2: =SUM(L2:Q2) -> 3892 | L2: 2013 | M2: 1579 | N2: 300
A3: Дата | B3: $ QR-код | C3: $ Касса | D3: $ Итог | E3: Чеки QR | F3: Чеки Касса | G3: Чеки Итог | H3: Ср.-й чек | I3: Списания | J3: д/н
A4: 46257 | C4: 1237 | D4: 1237 | F4: 5 | G4: 5 | H4: 247.4 | I4: 578.09 | J4: Вс
A5: 46256 | C5: 1639.6 | D5: 1639.6 | F5: 3 | G5: 3 | H5: 546.53333 | I5: 0 | J5: Сб
A6: 46255 | C6: 5839.6 | D6: 5839.6 | F6: 27 | G6: 27 | H6: 216.28148 | I6: 1486.86 | J6: Пт
A7: 46254 | C7: 6965.2 | D7: 6965.2 | F7: 23 | G7: 23 | H7: 302.83478 | I7: 381.51 | J7: Чт
A8: 46253 | C8: 4759.2 | D8: 4759.2 | F8: 21 | G8: 21 | H8: 226.62857 | I8: 348.74 | J8: Ср
A9: 46252 | C9: 5561.2 | D9: 5561.2 | F9: 23 | G9: 23 | H9: 241.7913 | I9: 625.92 | J9: Вт
A10: 46251 | C10: 7333.5 | D10: 7333.5 | F10: 25 | G10: 25 | H10: 293.34 | I10: 267.32 | J10: Пн
A11: 46250 | C11: 1857.6 | D11: 1857.6 | F11: 8 | G11: 8 | H11: 232.2 | I11: 766.13 | J11: Вс
A12: 46249 | C12: 2223.2 | D12: 2223.2 | F12: 5 | G12: 5 | H12: 444.64 | I12: 0 | J12: Сб
A13: 46248 | C13: 9637 | D13: 9637 | F13: 33 | G13: 33 | H13: 292.0303 | I13: 780.64 | J13: Пт
A14: 46247 | C14: 7036.6 | D14: 7036.6 | F14: 30 | G14: 30 | H14: 234.55333 | I14: 180.94 | J14: Чт
A15: 46246 | C15: 7057.4 | D15: 7057.4 | F15: 33 | G15: 33 | H15: 213.86061 | I15: 467.41 | J15: Ср
... A38: 46223 | C38: 287 | D38: 287 | F38: 3 | G38: 3 | H38: 95.666667 | I38: 0 | J38: Пн
J40: Вт
J41: Пн
J42: Вс
J43: Сб
J44: Пт
J45: Чт
J46: Ср
J47: Вт
J48: Пн
J49: Вс
J50: Сб
J51: Пт
... J63: Сб
J64: Пт | L64: ТОП-3 Целевой аудитории
J65: Чт | L65: пол | M65: возраст | N65: % присутствия | P65: кол-во уникальных гостей
J66: Ср | L66: женщины
J67: Вт | L67: мужчины
J68: Пн | L68: мужчины
J69: Вс
J70: Сб | L70: График работы | M70: дней в неделю | N70: часы работы
J71: Пт | M71: 5 | N71: 08:00-17:00
J72: Чт
J73: Ср
J74: Вт
J75: Пн
J76: Вс
J77: Сб
J78: Пт
J79: Чт
J80: Ср
J81: Вт
J82: Пн
J83: Вс
... J184: Ср
A185: 46258 | C185: 7021.9 | D185: 7021.9 | F185: 26 | G185: 26 | H185: 270.07308 | I185: 61.08 | J185: Пн

Sheet 4
A1: Точка | B1: 4 | C1: Дата запуска | D1: 45139 | E1: Тип точки | F1: завод | G1: Активна | H1: Да | K1: Стоимость обслуживания | L1: Аренда | M1: Коммуналка | N1: Клининг | P1: мерчант | Q1: QR мерч
A2: Среднее | B2: 3209.3308 | C2: 4849.0342 | D2: 7790.4716 | E2: 10.901408 | F2: 21.688312 | G2: 32.157895 | H2: 248.86864 | I2: 1248.4317 | K2: =SUM(L2:Q2) -> 4692 | L2: 4392 | M2: 0 | N2: 300
A3: Дата | B3: $ QR-код | C3: $ Касса | D3: $ Итог | E3: Чеки QR | F3: Чеки Касса | G3: Чеки Итог | H3: Ср.-й чек | I3: Списания | J3: д/н | P3: 33978529 | Q3: 33978530
A4: 46257 | B4: 1879.2 | C4: 0 | D4: 1879.2 | E4: 9 | F4: 0 | G4: 9 | H4: 208.8 | I4: 2842 | J4: Вс
A5: 46256 | B5: 4499.4 | C5: 0 | D5: 4499.4 | E5: 17 | F5: 0 | G5: 17 | H5: 264.67059 | I5: 2958.69 | J5: Сб
A6: 46255 | B6: 8751 | C6: 0 | D6: 8751 | E6: 20 | F6: 0 | G6: 20 | H6: 437.55 | I6: 1589.61 | J6: Пт
A7: 46254 | B7: 5667 | C7: 0 | D7: 5667 | E7: 19 | F7: 0 | G7: 19 | H7: 298.26316 | I7: 1321.49 | J7: Чт
A8: 46253 | B8: 5452.8 | C8: 0 | D8: 5452.8 | E8: 26 | F8: 0 | G8: 26 | H8: 209.72308 | I8: 2005.45 | J8: Ср
A9: 46252 | B9: 6011.8 | C9: 0 | D9: 6011.8 | E9: 25 | F9: 0 | G9: 25 | H9: 240.472 | I9: 14731.39 | J9: Вт
A10: 46251 | B10: 5478 | D10: 5478 | E10: 24 | G10: 24 | H10: 228.25 | J10: Пн
A11: 46250 | B11: 2360 | C11: 0 | D11: 2360 | E11: 11 | F11: 0 | G11: 11 | H11: 214.54545 | I11: 121.76 | J11: Вс
A12: 46249 | B12: 3765.8 | D12: 3765.8 | E12: 15 | G12: 15 | H12: 251.05333 | J12: Сб
A13: 46248 | B13: 10528.8 | C13: 0 | D13: 10528.8 | E13: 29 | F13: 0 | G13: 29 | H13: 363.06207 | I13: 135.43 | J13: Пт
A14: 46247 | B14: 5216.5 | C14: 0 | D14: 5216.5 | E14: 21 | F14: 0 | G14: 21 | H14: 248.40476 | I14: 98.57 | J14: Чт
A15: 46246 | B15: 4527 | C15: 0 | D15: 4527 | E15: 21 | F15: 0 | G15: 21 | H15: 215.57143 | I15: 222.83 | J15: Ср
A16: 46245 | B16: =26104-18803 -> 7301 | C16: 0 | D16: 7301 | E16: 25 | F16: 0 | G16: 25 | H16: 292.04 | I16: 3753.01 | J16: Вт
A17: 46244 | B17: 3414 | C17: 0 | D17: 3414 | E17: 18 | F17: 0 | G17: 18 | H17: 189.66667 | I17: 4154 | J17: Пн
A18: 46243 | B18: 4474 | C18: 0 | D18: 4474 | E18: 10 | F18: 0 | G18: 10 | H18: 447.4 | I18: 3409.25 | J18: Вс
A19: 46242 | B19: 3759.4 | C19: 0 | D19: 3759.4 | E19: 17 | F19: 0 | G19: 17 | H19: 221.14118 | I19: 2344.65 | J19: Сб
A20: 46241 | B20: 5099 | C20: 0 | D20: 5099 | E20: 20 | F20: 0 | G20: 20 | H20: 254.95 | I20: 2188.86 | J20: Пт
A21: 46240 | B21: 5026.4 | C21: 0 | D21: 5026.4 | E21: 19 | F21: 0 | G21: 19 | H21: 264.54737 | I21: 1857.02 | J21: Чт
A22: 46239 | B22: 4816 | C22: 0 | D22: 4816 | E22: 16 | F22: 0 | G22: 16 | H22: 301 | I22: 2813.02 | J22: Ср
A23: 46238 | B23: 2171 | C23: 0 | D23: 2171 | E23: 10 | F23: 0 | G23: 10 | H23: 217.1 | I23: 2068.4 | J23: Вт
A24: 46237 | B24: 8447 | C24: 0 | D24: 8447 | E24: 22 | F24: 0 | G24: 22 | H24: 383.95455 | I24: 3800.36 | J24: Пн
A25: 46236 | B25: 2371 | C25: 0 | D25: 2371 | E25: 10 | F25: 0 | G25: 10 | H25: 237.1 | I25: 4038.67 | J25: Вс
A26: 46235 | B26: 1439 | C26: 0 | D26: 1439 | E26: 3 | F26: 0 | G26: 3 | H26: 479.66667 | I26: 2883.09 | J26: Сб
A27: 46234 | B27: 2818 | C27: 0 | D27: 2818 | E27: 12 | F27: 0 | G27: 12 | H27: 234.83333 | I27: 1314.87 | J27: Пт
A28: 46233 | B28: 5089 | C28: 0 | D28: 5089 | E28: 15 | F28: 0 | G28: 15 | H28: 339.26667 | I28: 1451.66 | J28: Чт
... A54: 46207 | B54: 4685.2 | C54: 0 | D54: 4685.2 | E54: 16 | F54: 0 | G54: 16 | H54: 292.825 | I54: 2931.32 | J54: Сб
A55: 46206 | B55: 8974 | C55: 0 | D55: 8974 | F55: 0 | I55: 1223.99 | J55: Пт
A56: 46205 | B56: 6378 | C56: 0 | D56: 6378 | F56: 0 | I56: 1413.58 | J56: Чт
A57: 46204 | B57: 5024 | C57: 0 | D57: 5024 | F57: 0 | I57: 548.49 | J57: Ср
A58: 46203 | B58: 7787 | C58: 0 | D58: 7787 | F58: 0 | I58: 1009.61 | J58: Вт
A59: 46202 | B59: 6067 | C59: 0 | D59: 6067 | E59: 9 | F59: 0 | G59: 9 | H59: 674.11111 | I59: 1220.22 | J59: Пн
A60: 46201 | B60: 4838 | C60: 0 | D60: 4838 | E60: 23 | F60: 0 | G60: 23 | H60: 210.34783 | I60: 802.81 | J60: Вс
A61: 46200 | B61: 2008.9 | C61: 3156.2 | D61: 5165.1 | E61: 12 | F61: 12 | G61: 24 | H61: 215.2125 | I61: 1300.36 | J61: Сб
A62: 46199 | B62: 396 | C62: 8029.7 | D62: 8425.7 | E62: 4 | F62: 37 | G62: 41 | H62: 205.50488 | I62: 1331.46 | J62: Пт
A63: 46198 | B63: 476 | C63: 3777.2 | D63: 4253.2 | E63: 2 | F63: 21 | G63: 23 | H63: 184.92174 | I63: 831.69 | J63: Чт
A64: 46197 | B64: 800 | C64: 6042.5 | D64: 6842.5 | E64: 5 | F64: 32 | G64: 37 | H64: 184.93243 | I64: 418.78 | J64: Ср | L64: ТОП-3 Целевой аудитории
A65: 46196 | B65: 885 | C65: 6180 | D65: 7065 | E65: 4 | F65: 30 | G65: 34 | H65: 207.79412 | I65: 168.85 | J65: Вт | L65: пол | M65: возраст | N65: % присутствия | P65: кол-во уникальных гостей
A66: 46195 | B66: 946 | C66: 5056.5 | D66: 6002.5 | E66: 2 | F66: 28 | G66: 30 | H66: 200.08333 | I66: 1104.72 | J66: Пн | L66: мужчины | M66: 35-45 | N66: 0.32 | P66: 180
A67: 46194 | B67: 500 | C67: 4827.1 | D67: 5327.1 | E67: 1 | F67: 22 | G67: 23 | H67: 231.61304 | I67: 1137.76 | J67: Вс | L67: мужчины | M67: 25-35 | N67: 0.2
A68: 46193 | B68: 781.5 | C68: 7404.4 | D68: 8185.9 | E68: 3 | F68: 31 | G68: 34 | H68: 240.76176 | I68: 1557.31 | J68: Сб | L68: мужчины | M68: 45-55 | N68: 0.12
A69: 46192 | B69: 777 | C69: 5947.4 | D69: 6724.4 | E69: 4 | F69: 28 | G69: 32 | H69: 210.1375 | I69: 2662.2 | J69: Пт
A70: 46191 | B70: 1641 | C70: 5441 | D70: 7082 | E70: 6 | F70: 23 | G70: 29 | H70: 244.2069 | I70: 2257.45 | J70: Чт | L70: График работы | M70: дней в неделю | N70: часы работы
A71: 46190 | B71: 2643 | C71: 2818.6 | D71: 5461.6 | E71: 12 | F71: 17 | G71: 29 | H71: 188.33103 | I71: 1050.65 | J71: Ср | M71: 7 | N71: 08:00-23:00
A72: 46189 | B72: 3481 | C72: 426.5 | D72: 3907.5 | E72: 15 | F72: 7 | G72: 22 | H72: 177.61364 | I72: 525.87 | J72: Вт
A73: 46188 | B73: 3372 | C73: 5207.75 | D73: 8579.75 | E73: 7 | F73: 22 | G73: 29 | H73: 295.85345 | I73: 936 | J73: Пн
A74: 46187 | B74: 455 | C74: 5440.9 | D74: 5895.9 | E74: 3 | F74: 22 | G74: 25 | H74: 235.836 | I74: 1739.29 | J74: Вс
A75: 46186 | B75: 941 | C75: 3335.8 | D75: 4276.8 | E75: 2 | F75: 14 | G75: 16 | H75: 267.3 | I75: 1458.25 | J75: Сб
A76: 46185 | C76: 3988.76 | D76: 3988.76 | F76: 14 | G76: 14 | H76: 284.91143 | I76: 1298.13 | J76: Пт
A77: 46184 | B77: 8628.45 | C77: 8331.09 | D77: 16959.54 | E77: 1 | F77: 32 | G77: 33 | H77: 513.92545 | I77: 394.63 | J77: Чт
A78: 46183 | B78: 1358 | C78: 6420 | D78: 7778 | E78: 5 | F78: 30 | G78: 35 | H78: 222.22857 | I78: 777.06 | J78: Ср
A79: 46182 | B79: 2050.6 | C79: 3261 | D79: 5311.6 | E79: 6 | F79: 17 | G79: 23 | H79: 230.93913 | I79: 1287.65 | J79: Вт
A80: 46181 | B80: 972 | C80: 4122 | D80: 5094 | E80: 4 | F80: 24 | G80: 28 | H80: 181.92857 | I80: 1869.35 | J80: Пн
A81: 46180 | B81: 1345 | C81: 4366.2 | D81: 5711.2 | E81: 4 | F81: 20 | G81: 24 | H81: 237.96667 | I81: 1224.5 | J81: Вс
A82: 46179 | B82: 1906 | C82: 4545 | D82: 6451 | E82: 6 | F82: 17 | G82: 23 | H82: 280.47826 | I82: 4078.17 | J82: Сб
A83: 46178 | B83: 1009 | C83: 4334 | D83: 5343 | E83: 8 | F83: 23 | G83: 31 | H83: 172.35484 | I83: 1728.15 | J83: Пт
A84: 46177 | B84: 2902 | C84: 7013.9 | D84: 9915.9 | E84: 11 | F84: 28 | G84: 39 | H84: 254.25385 | I84: 1292.52 | J84: Чт
A85: 46176 | B85: 3141 | C85: 2887 | D85: 6028 | E85: 18 | F85: 12 | G85: 30 | H85: 200.93333 | I85: 744.27 | J85: Ср
A86: 46175 | B86: 6798.5 | C86: 0 | D86: 6798.5 | E86: 20 | F86: 0 | G86: 20 | H86: 339.925 | I86: 1023.42 | J86: Вт
A87: 46174 | B87: 7382 | C87: 0 | D87: 7382 | E87: 26 | F87: 0 | G87: 26 | H87: 283.92308 | I87: 439.76 | J87: Пн
A88: 46173 | B88: 4757 | D88: 4757 | E88: 12 | G88: 12 | H88: 396.41667 | J88: Вс
A89: 46172 | B89: 6613.2 | C89: 0 | D89: 6613.2 | E89: 8 | F89: 0 | G89: 8 | H89: 826.65 | I89: 3859.09 | J89: Сб
A90: 46171 | B90: 9768.2 | C90: 0 | D90: 9768.2 | E90: 30 | F90: 0 | G90: 30 | H90: 325.60667 | I90: 1899.84 | J90: Пт
A91: 46170 | B91: 6156.75 | C91: 0 | D91: 6156.75 | E91: 17 | F91: 0 | G91: 17 | H91: 362.16176 | I91: 1200 | J91: Чт
A92: 46169 | B92: 10361.7 | C92: 0 | D92: 10361.7 | E92: 31 | F92: 0 | G92: 31 | H92: 334.24839 | I92: 1834.89 | J92: Ср
A93: 46168 | B93: 5496 | C93: 0 | D93: 5496 | E93: 20 | F93: 0 | G93: 20 | H93: 274.8 | I93: 1199.23 | J93: Вт
A94: 46167 | B94: 7863 | C94: 0 | D94: 7863 | E94: 30 | F94: 0 | G94: 30 | H94: 262.1 | I94: 2385.18 | J94: Пн
A95: 46166 | B95: 3647 | C95: 0 | D95: 3647 | E95: 13 | F95: 0 | G95: 13 | H95: 280.53846 | I95: 1804.54 | J95: Вс
A96: 46165 | B96: 4039 | C96: 0 | D96: 4039 | E96: 12 | F96: 0 | G96: 12 | H96: 336.58333 | I96: 2459.21 | J96: Сб
A97: 46164 | B97: 4813.35 | C97: 0 | D97: 4813.35 | E97: 20 | F97: 0 | G97: 20 | H97: 240.6675 | I97: 1451.65 | J97: Пт
A98: 46163 | B98: 8273 | C98: 1975.9 | D98: 10248.9 | E98: 18 | F98: 11 | G98: 29 | H98: 353.41034 | I98: 1044.32 | J98: Чт
A99: 46162 | B99: 6654 | C99: 0 | D99: 6654 | E99: 21 | F99: 0 | G99: 21 | H99: 316.85714 | I99: 2855.74 | J99: Ср
A100: 46161 | B100: 4959.4 | C100: 0 | D100: 4959.4 | E100: 22 | F100: 0 | G100: 22 | H100: 225.42727 | I100: 2210.69 | J100: Вт
... A107: 46154 | B107: 3124 | C107: 0 | D107: 3124 | E107: 17 | F107: 0 | G107: 17 | H107: 183.76471 | I107: 113.45 | J107: Вт
A108: 46153 | C108: 0 | E108: 23 | F108: 0 | G108: 23 | H108: 0 | I108: 167.74 | J108: Пн
A109: 46152 | B109: 4310 | C109: 0 | D109: 4310 | E109: 15 | F109: 0 | G109: 15 | H109: 287.33333 | I109: 908.65 | J109: Вс
A110: 46151 | B110: 4937.2 | C110: 0 | D110: 4937.2 | E110: 14 | F110: 0 | G110: 14 | H110: 352.65714 | I110: 1692.9 | J110: Сб
A111: 46150 | B111: 5489 | C111: 0 | D111: 5489 | E111: 21 | F111: 0 | G111: 21 | H111: 261.38095 | I111: 684.4 | J111: Пт
A112: 46149 | B112: 5726.6 | C112: 0 | D112: 5726.6 | E112: 28 | F112: 0 | G112: 28 | H112: 204.52143 | I112: 1015.72 | J112: Чт
A113: 46148 | B113: 3896 | C113: 2732 | D113: 6628 | E113: 11 | F113: 11 | G113: 22 | H113: 301.27273 | I113: 82.88 | J113: Ср
A114: 46147 | B114: 725 | C114: 4856.8 | D114: 5581.8 | E114: 3 | F114: 20 | G114: 23 | H114: 242.68696 | I114: 1993.56 | J114: Вт
A115: 46146 | B115: 1290 | C115: 6411.6 | D115: 7701.6 | E115: 4 | F115: 35 | G115: 39 | H115: 197.47692 | I115: 586.85 | J115: Пн
A116: 46145 | B116: 2272.4 | C116: 4517 | D116: 6789.4 | E116: 5 | F116: 19 | G116: 24 | H116: 282.89167 | I116: 954.62 | J116: Вс
A117: 46144 | B117: 2679.6 | C117: 4427.4 | D117: 7107 | E117: 8 | F117: 25 | G117: 33 | H117: 215.36364 | I117: 0 | J117: Сб
A118: 46143 | B118: 1148 | C118: 6659 | D118: 7807 | E118: 3 | F118: 23 | G118: 26 | H118: 300.26923 | I118: 211.17 | J118: Пт
A119: 46142 | B119: 1276 | C119: 10028.8 | D119: 11304.8 | E119: 4 | F119: 42 | G119: 46 | H119: 245.75652 | I119: 1485.15 | J119: Чт
A120: 46141 | B120: 1018 | C120: 6330 | D120: 7348 | E120: 5 | F120: 31 | G120: 36 | H120: 204.11111 | I120: 1432.59 | J120: Ср
... A125: 46136 | B125: 554 | C125: 8868.3 | D125: 9422.3 | E125: 1 | F125: 47 | G125: 48 | H125: 196.29792 | I125: 901.26 | J125: Пт
A126: 46135 | B126: 1037 | D126: 1037 | E126: 4 | G126: 4 | H126: 259.25 | J126: Чт
A127: 46134 | B127: 1269 | C127: 7611 | D127: 8880 | E127: 8 | F127: 37 | G127: 45 | H127: 197.33333 | I127: 0 | J127: Ср
A128: 46133 | C128: 4120.15 | D128: 4120.15 | F128: 15 | G128: 15 | H128: 274.67667 | I128: 221.31 | J128: Вт
A129: 46132 | B129: 575 | C129: 4526 | D129: 5101 | E129: 5 | F129: 28 | G129: 33 | H129: 154.57576 | I129: 12 | J129: Пн
A130: 46131 | B130: 2690 | C130: 0 | D130: 2690 | E130: 14 | F130: 0 | G130: 14 | H130: 192.14286 | I130: 296.96 | J130: Вс
A131: 46130 | B131: 2160.8 | C131: 0 | D131: 2160.8 | E131: 14 | F131: 0 | G131: 14 | H131: 154.34286 | I131: 161.85 | J131: Сб
A132: 46129 | B132: 4573 | C132: 2551 | D132: 7124 | E132: 15 | F132: 12 | G132: 27 | H132: 263.85185 | I132: 150.48 | J132: Пт
A133: 46128 | C133: 6516.4 | D133: 6516.4 | F133: 33 | G133: 33 | H133: 197.46667 | I133: 209.44 | J133: Чт
A134: 46127 | B134: 168 | C134: 7993.3 | D134: 8161.3 | E134: 1 | F134: 38 | G134: 39 | H134: 209.2641 | I134: 455.63 | J134: Ср
A135: 46126 | B135: 1142 | C135: 8058 | D135: 9200 | E135: 3 | F135: 44 | G135: 47 | H135: 195.74468 | I135: 408.5 | J135: Вт
...

Sheet 5
A1: Точка | B1: 5 | C1: Дата запуска | D1: 45901 | E1: Тип точки | F1: завод | G1: Активна | H1: Да | K1: Стоимость обслуживания | L1: Аренда | M1: Коммуналка | N1: Клининг
A2: Среднее | B2: 2236.1402 | C2: 13437.485 | D2: 14822.316 | E2: 10.137255 | F2: 63.837662 | G2: 70.096774 | H2: 212.75225 | I2: 449.86747 | K2: =SUM(L2:Q2) -> 300 | M2: 0 | N2: 300
A3: Дата | B3: $ QR-код | C3: $ Касса | D3: $ Итог | E3: Чеки QR | F3: Чеки Касса | G3: Чеки Итог | H3: Ср.-й чек | I3: Списания | J3: д/н
A4: 46257 | C4: 1499.4 | D4: 1499.4 | F4: 5 | G4: 5 | H4: 299.88 | I4: 692.33 | J4: Вс
A5: 46256 | C5: 702.2 | D5: 702.2 | F5: 4 | G5: 4 | H5: 175.55 | I5: 439.03 | J5: Сб
A6: 46255 | B6: 50 | C6: 14525.4 | D6: 14575.4 | E6: 1 | F6: 68 | G6: 69 | H6: 211.23768 | I6: 27.48 | J6: Пт
A7: 46254 | B7: 680 | C7: 22717.4 | D7: 23397.4 | E7: 5 | F7: 105 | G7: 110 | H7: 212.70364 | I7: 202.36 | J7: Чт
A8: 46253 | B8: 25 | C8: 18388 | D8: 18413 | E8: 1 | F8: 89 | G8: 90 | H8: 204.58889 | I8: 335.88 | J8: Ср
A9: 46252 | B9: 255 | C9: 17962.6 | D9: 18217.6 | E9: 3 | F9: 85 | G9: 88 | H9: 207.01818 | I9: 277.81 | J9: Вт
A10: 46251 | B10: 105 | C10: 16093.6 | D10: 16198.6 | E10: 2 | F10: 75 | G10: 77 | H10: 210.37143 | I10: 0 | J10: Пн
A11: 46250 | B11: 728.2 | C11: 4259 | D11: 4987.2 | E11: 3 | F11: 24 | G11: 27 | H11: 184.71111 | I11: 49.02 | J11: Вс
A12: 46249 | C12: 2696.4 | D12: 2696.4 | F12: 17 | G12: 17 | H12: 158.61176 | I12: 0 | J12: Сб
A13: 46248 | B13: 368 | C13: 15752 | D13: 16120 | E13: 5 | F13: 71 | G13: 76 | H13: 212.10526 | I13: 217.99 | J13: Пт
A14: 46247 | B14: 105 | C14: 17832.4 | D14: 17937.4 | E14: 1 | F14: 95 | G14: 96 | H14: 186.84792 | I14: 0 | J14: Чт
A15: 46246 | B15: 731 | C15: 19338.35 | D15: 20069.35 | E15: 5 | F15: 90 | G15: 95 | H15: 211.25632 | I15: 35.8 | J15: Ср
A16: 46245 | B16: 669 | C16: 17499.1 | D16: 18168.1 | E16: 5 | F16: 86 | G16: 91 | H16: 199.64945 | I16: 548.74 | J16: Вт
A17: 46244 | B17: 2825.55 | C17: 15726 | D17: 18551.55 | E17: 9 | F17: 79 | G17: 88 | H17: 210.81307 | I17: 1079.33 | J17: Пн
A18: 46243 | B18: 100 | C18: 357.4 | D18: 457.4 | E18: 1 | F18: 2 | G18: 3 | H18: 152.46667 | I18: 1323.52 | J18: Вс
A19: 46242 | B19: 90 | C19: 2225.6 | D19: 2315.6 | E19: 1 | F19: 18 | G19: 19 | H19: 121.87368 | I19: 495.49 | J19: Сб
A20: 46241 | B20: 4792 | C20: 14155.15 | D20: 18947.15 | E20: 17 | F20: 66 | G20: 83 | H20: 228.27892 | I20: 198.21 | J20: Пт
A21: 46240 | B21: 560 | C21: 21091.3 | D21: 21651.3 | E21: 2 | F21: 101 | G21: 103 | H21: 210.2068 | I21: 130.52 | J21: Чт
A22: 46239 | B22: 644 | C22: 16390.15 | D22: 17034.15 | E22: 5 | F22: 69 | G22: 74 | H22: 230.19122 | I22: 0 | J22: Ср
A23: 46238 | B23: 276 | C23: 16226.6 | D23: 16502.6 | E23: 3 | F23: 73 | G23: 76 | H23: 217.13947 | I23: 0 | J23: Вт
A24: 46237 | C24: 19448.25 | D24: 19448.25 | F24: 93 | G24: 93 | H24: 209.12097 | I24: 98.92 | J24: Пн
A25: 46236 | C25: 1407.4 | D25: 1407.4 | F25: 9 | G25: 9 | H25: 156.37778 | I25: 690.38 | J25: Вс
A26: 46235 | C26: 2973.4 | D26: 2973.4 | F26: 18 | G26: 18 | H26: 165.18889 | I26: 169.74 | J26: Сб
A27: 46234 | B27: 578 | C27: 18599.8 | D27: 19177.8 | E27: 3 | F27: 90 | G27: 93 | H27: 206.2129 | I27: 598.02 | J27: Пт
A28: 46233 | C28: 20723.6 | D28: 20723.6 | F28: 94 | G28: 94 | H28: 220.46383 | I28: 490.89 | J28: Чт
A29: 46232 | B29: 360 | C29: 19706.7 | D29: 20066.7 | E29: 2 | F29: 88 | G29: 90 | H29: 222.96333 | I29: 224.65 | J29: Ср
A30: 46231 | B30: 819 | C30: 14920 | D30: 15739 | E30: 7 | F30: 65 | G30: 72 | H30: 218.59722 | I30: 0 | J30: Вт
A31: 46230 | B31: 200 | C31: 21594 | D31: 21794 | E31: 2 | F31: 102 | G31: 104 | H31: 209.55769 | I31: 87.73 | J31: Пн
A32: 46229 | B32: 80 | C32: 2482 | D32: 2562 | E32: 1 | F32: 13 | G32: 14 | H32: 183 | I32: 423.76 | J32: Вс
A33: 46228 | B33: 85 | C33: 946.6 | D33: 1031.6 | E33: 1 | F33: 10 | G33: 11 | H33: 93.781818 | I33: 414.43 | J33: Сб
A34: 46227 | B34: 839 | C34: 17740.2 | D34: 18579.2 | E34: 7 | F34: 84 | G34: 91 | H34: 204.16703 | I34: 86 | J34: Пт
A35: 46226 | B35: 555 | C35: 20915.15 | D35: 21470.15 | E35: 6 | F35: 97 | G35: 103 | H35: 208.44806 | I35: 332.94 | J35: Чт
A36: 46225 | B36: 1018 | C36: 16095.6 | D36: 17113.6 | E36: 5 | F36: 79 | G36: 84 | H36: 203.73333 | I36: 497.58 | J36: Ср
A37: 46224 | B37: 587 | C37: 13777.2 | D37: 14364.2 | E37: 4 | F37: 71 | G37: 75 | H37: 191.52267 | I37: 540.34 | J37: Вт
A38: 46223 | B38: 90 | C38: 14798.2 | D38: 14888.2 | E38: 1 | F38: 81 | G38: 82 | H38: 181.56341 | I38: 950.98 | J38: Пн
A39: 46222 | C39: 1757.8 | D39: 1757.8 | F39: 5 | G39: 5 | H39: 351.56 | I39: 683.44 | J39: Вс
A40: 46221 | C40: 716.2 | D40: 716.2 | F40: 3 | G40: 3 | H40: 238.73333 | I40: 716.4 | J40: Сб
A41: 46220 | B41: 1923 | C41: 15599.38 | D41: 17522.38 | E41: 11 | F41: 76 | G41: 87 | H41: 201.40667 | I41: 86.04 | J41: Пт
A42: 46219 | B42: 302 | C42: 14474.4 | D42: 14776.4 | E42: 2 | F42: 66 | G42: 68 | H42: 217.3 | I42: 125.65 | J42: Чт
A43: 46218 | B43: 2158 | C43: 17772.3 | D43: 19930.3 | E43: 11 | F43: 77 | G43: 88 | H43: 226.48068 | I43: 0 | J43: Ср
A44: 46217 | B44: 346 | C44: 16331.8 | D44: 16677.8 | E44: 3 | F44: 73 | G44: 76 | H44: 219.44474 | I44: 294.92 | J44: Вт
A45: 46216 | C45: 16637.6 | D45: 16637.6 | F45: 77 | G45: 77 | H45: 216.07273 | I45: 178.32 | J45: Пн
A46: 46215 | C46: 30 | D46: 30 | F46: 1 | G46: 1 | H46: 30 | I46: 1753.43 | J46: Вс
A47: 46214 | C47: 267 | D47: 267 | F47: 2 | G47: 2 | H47: 133.5 | I47: 386.48 | J47: Сб
A48: 46213 | B48: 698 | C48: 14862.3 | D48: 15560.3 | E48: 3 | F48: 74 | G48: 77 | H48: 202.08182 | I48: 357.61 | J48: Пт
A49: 46212 | B49: 652 | C49: 15520.65 | D49: 16172.65 | E49: 5 | F49: 72 | G49: 77 | H49: 210.03442 | I49: 350.65 | J49: Чт
A50: 46211 | B50: 1634 | C50: 12199.8 | D50: 13833.8 | E50: 8 | F50: 52 | G50: 60 | H50: 230.56333 | I50: 481.67 | J50: Ср
A51: 46210 | B51: 1936 | C51: 12021 | D51: 13957 | E51: 10 | F51: 64 | G51: 74 | H51: 188.60811 | I51: 0 | J51: Вт
A52: 46209 | B52: 735 | C52: 14435 | D52: 15170 | E52: 3 | F52: 68 | G52: 71 | H52: 213.66197 | I52: 1036.48 | J52: Пн
A53: 46208 | B53: 778 | C53: 649 | D53: 1427 | E53: 3 | F53: 2 | G53: 5 | H53: 285.4 | I53: 718.45 | J53: Вс
A54: 46207 | B54: 319 | C54: 356.4 | D54: 675.4 | E54: 4 | F54: 2 | G54: 6 | H54: 112.56667 | I54: 554.68 | J54: Сб
A55: 46206 | C55: 16732.2 | D55: 16732.2 | F55: 85 | G55: 85 | H55: 196.84941 | I55: 631.66 | J55: Пт
A56: 46205 | C56: 15748.8 | D56: 15748.8 | F56: 73 | G56: 73 | H56: 215.73699 | I56: 460.24 | J56: Чт
A57: 46204 | C57: 16861.8 | D57: 16861.8 | F57: 81 | G57: 81 | H57: 208.17037 | I57: 254.38 | J57: Ср
A58: 46203 | C58: 15826.6 | D58: 15826.6 | F58: 65 | G58: 65 | H58: 243.48615 | I58: 356.72 | J58: Вт
A59: 46202 | B59: 4793.8 | C59: 8593.8 | D59: 13387.6 | E59: 17 | F59: 49 | G59: 66 | H59: 202.84242 | I59: 2603.94 | J59: Пн
A60: 46201 | C60: 0 | F60: 0 | I60: 944.11 | J60: Вс
A61: 46200 | B61: 226 | C61: 812 | D61: 1038 | E61: 1 | F61: 2 | G61: 3 | H61: 346 | I61: 492.44 | J61: Сб
A62: 46199 | B62: 379 | C62: 16087.6 | D62: 16466.6 | E62: 2 | F62: 76 | G62: 78 | H62: 211.11026 | I62: 280.31 | J62: Пт
A63: 46198 | B63: 376 | C63: 16618.85 | D63: 16994.85 | E63: 1 | F63: 73 | G63: 74 | H63: 229.66014 | I63: 219.5 | J63: Чт
A64: 46197 | B64: 1818 | C64: 14286.8 | D64: 16104.8 | E64: 8 | F64: 65 | G64: 73 | H64: 220.6137 | I64: 342.62 | J64: Ср | L64: ТОП-3 Целевой аудитории
A65: 46196 | B65: 1038 | C65: 17075.1 | D65: 18113.1 | E65: 5 | F65: 85 | G65: 90 | H65: 201.25667 | I65: 286.25 | J65: Вт | L65: пол | M65: возраст | N65: % присутствия | P65: кол-во уникальных гостей
A66: 46195 | B66: 1236 | C66: 13057.5 | D66: 14293.5 | E66: 6 | F66: 68 | G66: 74 | H66: 193.15541 | I66: 46.06 | J66: Пн | L66: мужчины | M66: 35-45 | N66: 0.32 | P66: 180
A67: 46194 | C67: 1951.4 | D67: 1951.4 | F67: 5 | G67: 5 | H67: 390.28 | I67: 731.76 | J67: Вс | L67: мужчины | M67: 25-35 | N67: 0.2
A68: 46193 | B68: 42 | C68: 487.4 | D68: 529.4 | E68: 1 | F68: 5 | G68: 6 | H68: 88.233333 | I68: 89.73 | J68: Сб | L68: мужчины | M68: 45-55 | N68: 0.12
A69: 46192 | B69: 296 | C69: 16057.05 | D69: 16353.05 | E69: 1 | F69: 79 | G69: 80 | H69: 204.41312 | I69: 339 | J69: Пт
A70: 46191 | B70: 1954 | C70: 16875.7 | D70: 18829.7 | E70: 7 | F70: 74 | G70: 81 | H70: 232.46543 | I70: 817.13 | J70: Чт | L70: График работы | M70: дней в неделю | N70: часы работы
A71: 46190 | B71: 312 | C71: 17454.8 | D71: 17766.8 | E71: 2 | F71: 77 | G71: 79 | H71: 224.8962 | I71: 563.37 | J71: Ср | M71: 5 | N71: 08:00-17:00
A72: 46189 | B72: 2475 | C72: 13202.8 | D72: 15677.8 | E72: 10 | F72: 65 | G72: 75 | H72: 209.03733 | I72: 15.35 | J72: Вт
A73: 46188 | B73: 581 | C73: 19288.8 | D73: 19869.8 | E73: 2 | F73: 82 | G73: 84 | H73: 236.54524 | I73: 350.77 | J73: Пн
A74: 46187 | B74: 430 | C74: 1961.8 | D74: 2391.8 | E74: 1 | F74: 10 | G74: 11 | H74: 217.43636 | I74: 643.82 | J74: Вс
A75: 46186 | C75: 1009.6 | D75: 1009.6 | F75: 6 | G75: 6 | H75: 168.26667 | I75: 515.4 | J75: Сб
A76: 46185 | B76: 899 | C76: 1062.8 | D76: 1961.8 | E76: 3 | F76: 6 | G76: 9 | H76: 217.97778 | I76: 185.11 | J76: Пт
A77: 46184 | B77: 430 | C77: 14943.4 | D77: 15373.4 | E77: 3 | F77: 70 | G77: 73 | H77: 210.59452 | I77: 147.76 | J77: Чт
A78: 46183 | C78: 17557.35 | D78: 17557.35 | F78: 74 | G78: 74 | H78: 237.26149 | I78: 0 | J78: Ср
A79: 46182 | B79: 946 | C79: 15640.5 | D79: 16586.5 | E79: 4 | F79: 87 | G79: 91 | H79: 182.26923 | I79: 98.73 | J79: Вт
A80: 46181 | B80: 1340 | C80: 11634 | D80: 12974 | E80: 4 | F80: 55 | G80: 59 | H80: 219.89831 | I80: 207.44 | J80: Пн
A81: 46180 | C81: 873.8 | D81: 873.8 | F81: 4 | G81: 4 | H81: 218.45 | I81: 1092.8 | J81: Вс
A82: 46179 | B82: 621 | C82: 1313.6 | D82: 1934.6 | E82: 4 | F82: 6 | G82: 10 | H82: 193.46 | I82: 622.26 | J82: Сб
A83: 46178 | B83: 1033 | C83: 15104.2 | D83: 16137.2 | E83: 6 | F83: 70 | G83: 76 | H83: 212.33158 | I83: 433.81 | J83: Пт
A84: 46177 | B84: 3153 | C84: 12728 | D84: 15881 | E84: 16 | F84: 62 | G84: 78 | H84: 203.60256 | I84: 243.94 | J84: Чт
A85: 46176 | B85: 895 | C85: 13830.3 | D85: 14725.3 | E85: 3 | F85: 67 | G85: 70 | H85: 210.36143 | I85: 226.9 | J85: Ср
A86: 46175 | B86: 3769 | C86: 15317.65 | D86: 19086.65 | E86: 16 | F86: 73 | G86: 89 | H86: 214.45674 | I86: 98.31 | J86: Вт
A87: 46174 | B87: 926 | C87: 18004.5 | D87: 18930.5 | E87: 6 | F87: 79 | G87: 85 | H87: 222.71176 | I87: 178.05 | J87: Пн
A88: 46172 | C88: 523 | D88: 523 | F88: 3 | G88: 3 | H88: 174.33333 | I88: 2266.82 | J88: Сб
A89: 46171 | B89: 837 | C89: 16455.9 | D89: 17292.9 | E89: 4 | F89: 81 | G89: 85 | H89: 203.44588 | I89: 1448.3 | J89: Пт
A90: 46170 | B90: 746 | C90: 18450.4 | D90: 19196.4 | E90: 2 | F90: 83 | G90: 85 | H90: 225.84 | I90: 1868.62 | J90: Чт
A91: 46169 | B91: 689 | C91: 13023.35 | D91: 13712.35 | E91: 3 | F91: 64 | G91: 67 | H91: 204.66194 | I91: 1305.46 | J91: Ср
A92: 46168 | B92: 1135 | C92: 16638.3 | D92: 17773.3 | E92: 4 | F92: 82 | G92: 86 | H92: 206.66628 | I92: 1283.04 | J92: Вт
A93: 46167 | B93: 12642 | C93: 932 | D93: 13574 | E93: 59 | F93: 7 | G93: 66 | H93: 205.66667 | I93: 431.62 | J93: Пн
A94: 46166 | C94: 1245 | D94: 1245 | F94: 8 | G94: 8 | H94: 155.625 | I94: 983.49 | J94: Вс
A95: 46165 | B95: 155 | C95: 1943.3 | D95: 2098.3 | E95: 1 | F95: 11 | G95: 12 | H95: 174.85833 | I95: 162.43 | J95: Сб
A96: 46164 | C96: 17234.1 | D96: 17234.1 | F96: 84 | G96: 84 | H96: 205.16786 | I96: 704.46 | J96: Пт
A97: 46163 | B97: 439 | C97: 15816.6 | D97: 16255.6 | E97: 1 | F97: 70 | G97: 71 | H97: 228.95211 | I97: 459.29 | J97: Чт
A98: 46162 | C98: 16423.9 | D98: 16423.9 | F98: 74 | G98: 74 | H98: 221.94459 | I98: 191.96 | J98: Ср
A99: 46161 | C99: 13184 | D99: 13184 | F99: 60 | G99: 60 | H99: 219.73333 | I99: 182.73 | J99: Вт
A100: 46160 | C100: 15152.4 | D100: 15152.4 | F100: 67 | G100: 67 | H100: 226.15522 | I100: 192.19 | J100: Пн
...

Sheet 6
A1: Точка | B1: 6 | C1: Дата запуска | D1: 45917 | E1: Тип точки | F1: завод | G1: Активна | H1: Да | K1: Стоимость обслуживания | L1: Аренда | M1: Коммуналка | N1: Клининг
A2: Среднее | B2: 650.26667 | C2: 9606.7375 | D2: 9760.7927 | E2: 1.4761905 | F2: 48.664474 | G2: 49.192053 | H2: 201.51469 | I2: 520.84796 | K2: =SUM(L2:Q2) -> 3638 | L2: 3338 | M2: 0 | N2: 300
A3: Дата | B3: $ QR-код | C3: $ Касса | D3: $ Итог | E3: Чеки QR | F3: Чеки Касса | G3: Чеки Итог | H3: Ср.-й чек | I3: Списания | J3: д/н
A4: 46257 | C4: 3943.8 | D4: 3943.8 | F4: 28 | G4: 28 | H4: 140.85 | I4: 258.12 | J4: Вс
A5: 46256 | C5: 4134.6 | D5: 4134.6 | F5: 36 | G5: 36 | H5: 114.85 | I5: 255.04 | J5: Сб
A6: 46255 | C6: 14426.4 | D6: 14426.4 | F6: 85 | G6: 85 | H6: 169.72235 | I6: 185.63 | J6: Пт
A7: 46254 | C7: 15454.8 | D7: 15454.8 | F7: 75 | G7: 75 | H7: 206.064 | I7: 96.04 | J7: Чт
A8: 46253 | C8: 15485.7 | D8: 15485.7 | F8: 88 | G8: 88 | H8: 175.97386 | I8: 516.25 | J8: Ср
A9: 46252 | C9: 15523.4 | D9: 15523.4 | F9: 85 | G9: 85 | H9: 182.62824 | I9: 2019.46 | J9: Вт
A10: 46251 | C10: 13468 | D10: 13468 | F10: 63 | G10: 63 | H10: 213.77778 | I10: 0 | J10: Пн
A11: 46250 | C11: 6115.6 | D11: 6115.6 | F11: 32 | G11: 32 | H11: 191.1125 | I11: 585.55 | J11: Вс
A12: 46249 | C12: 6446 | D12: 6446 | F12: 31 | G12: 31 | H12: 207.93548 | I12: 0 | J12: Сб
A13: 46248 | B13: 591 | C13: 11827.8 | D13: 12418.8 | E13: 1 | F13: 59 | G13: 60 | H13: 206.98 | I13: 480.37 | J13: Пт
A14: 46247 | B14: 251 | C14: 13319.4 | D14: 13570.4 | E14: 1 | F14: 72 | G14: 73 | H14: 185.89589 | I14: 0 | J14: Чт
A15: 46246 | B15: 1217 | C15: 15267 | D15: 16484 | E15: 4 | F15: 73 | G15: 77 | H15: 214.07792 | I15: 90.15 | J15: Ср
A16: 46245 | C16: 12954.4 | D16: 12954.4 | F16: 68 | G16: 68 | H16: 190.50588 | I16: 1291.19 | J16: Вт
A17: 46244 | C17: 10540.8 | D17: 10540.8 | F17: 60 | G17: 60 | H17: 175.68 | I17: 2142.85 | J17: Пн
A18: 46243 | C18: 3302 | D18: 3302 | F18: 17 | G18: 17 | H18: 194.23529 | I18: 3288.62 | J18: Вс
A19: 46242 | C19: 3453 | D19: 3453 | F19: 18 | G19: 18 | H19: 191.83333 | I19: 409.96 | J19: Сб
A20: 46241 | C20: 12341.6 | D20: 12341.6 | F20: 62 | G20: 62 | H20: 199.05806 | I20: 516.05 | J20: Пт
A21: 46240 | C21: 13887 | D21: 13887 | F21: 60 | G21: 60 | H21: 231.45 | I21: 409.67 | J21: Чт
A22: 46239 | C22: 12203 | D22: 12203 | F22: 51 | G22: 51 | H22: 239.27451 | I22: 134.26 | J22: Ср
A23: 46238 | C23: 13248 | D23: 13248 | F23: 54 | G23: 54 | H23: 245.33333 | I23: 201.44 | J23: Вт
A24: 46237 | C24: 12406 | D24: 12406 | F24: 57 | G24: 57 | H24: 217.64912 | I24: 0 | J24: Пн
A25: 46236 | C25: 1715.2 | D25: 1715.2 | F25: 9 | G25: 9 | H25: 190.57778 | I25: 837.55 | J25: Вс
A26: 46235 | C26: 5137.4 | D26: 5137.4 | F26: 23 | G26: 23 | H26: 223.36522 | I26: 431.35 | J26: Сб
A27: 46234 | C27: 0 | F27: 0 | I27: 627.55 | J27: Пт
A28: 46233 | C28: 11428 | D28: 11428 | F28: 54 | G28: 54 | H28: 211.62963 | I28: 276.22 | J28: Чт
A29: 46232 | C29: 10835.8 | D29: 10835.8 | F29: 53 | G29: 53 | H29: 204.44906 | I29: 831.59 | J29: Ср
A30: 46231 | C30: 12639 | D30: 12639 | F30: 63 | G30: 63 | H30: 200.61905 | I30: 833.51 | J30: Вт
A31: 46230 | C31: 10137.8 | D31: 10137.8 | F31: 49 | G31: 49 | H31: 206.89388 | I31: 674.8 | J31: Пн
A32: 46229 | C32: 4558.6 | D32: 4558.6 | F32: 21 | G32: 21 | H32: 217.07619 | I32: 265.09 | J32: Вс
A33: 46228 | C33: 966.6 | D33: 966.6 | F33: 5 | G33: 5 | H33: 193.32 | I33: 697.63 | J33: Сб
A34: 46227 | C34: 11485.9 | D34: 11485.9 | F34: 54 | G34: 54 | H34: 212.70185 | I34: 256.32 | J34: Пт
A35: 46226 | C35: 14924.4 | D35: 14924.4 | F35: 73 | G35: 73 | H35: 204.44384 | I35: 107.59 | J35: Чт
A36: 46225 | C36: 12223.4 | D36: 12223.4 | F36: 63 | G36: 63 | H36: 194.02222 | I36: 544.63 | J36: Ср
A37: 46224 | C37: 9409.4 | D37: 9409.4 | F37: 56 | G37: 56 | H37: 168.025 | I37: 215.56 | J37: Вт
A38: 46223 | C38: 10359 | D38: 10359 | F38: 57 | G38: 57 | H38: 181.73684 | I38: 204.3 | J38: Пн
A39: 46222 | C39: 2764.8 | D39: 2764.8 | F39: 20 | G39: 20 | H39: 138.24 | I39: 123.43 | J39: Вс
... A63: 46198 | C63: 11848.8 | D63: 11848.8 | F63: 55 | G63: 55 | H63: 215.43273 | I63: 421.6 | J63: Чт
A64: 46197 | C64: 9633.2 | D64: 9633.2 | F64: 51 | G64: 51 | H64: 188.88627 | I64: 75.25 | J64: Ср | L64: ТОП-3 Целевой аудитории
A65: 46196 | C65: 8790 | D65: 8790 | F65: 48 | G65: 48 | H65: 183.125 | I65: 0 | J65: Вт | L65: пол | M65: возраст | N65: % присутствия | P65: кол-во уникальных гостей
A66: 46195 | C66: 8339 | D66: 8339 | F66: 41 | G66: 41 | H66: 203.39024 | I66: 0 | J66: Пн | L66: мужчины | M66: 25-35 | N66: 0.4 | P66: 154
A67: 46194 | C67: 661.1 | D67: 661.1 | F67: 7 | G67: 7 | H67: 94.442857 | I67: 349.85 | J67: Вс | L67: мужчины | M67: 35-45 | N67: 0.32
A68: 46193 | C68: 4366.6 | D68: 4366.6 | F68: 20 | G68: 20 | H68: 218.33 | I68: 61.65 | J68: Сб | L68: мужчины | M68: 18-25 | N68: 0.08
A69: 46192 | C69: 10814.8 | D69: 10814.8 | F69: 54 | G69: 54 | H69: 200.27407 | I69: 1282.64 | J69: Пт
A70: 46191 | C70: 11736 | D70: 11736 | F70: 54 | G70: 54 | H70: 217.33333 | I70: 601.37 | J70: Чт | L70: График работы | M70: дней в неделю | N70: часы работы
A71: 46190 | C71: 11583 | D71: 11583 | F71: 57 | G71: 57 | H71: 203.21053 | I71: 239.55 | J71: Ср | M71: 5 | N71: 08:00-17:00
A72: 46188 | C72: 9372.5 | D72: 9372.5 | F72: 46 | G72: 46 | H72: 203.75 | I72: 459.95 | J72: Пн
A73: 46187 | C73: 2786 | D73: 2786 | F73: 16 | G73: 16 | H73: 174.125 | I73: 1296.95 | J73: Вс
A74: 46186 | C74: 3302.4 | D74: 3302.4 | F74: 17 | G74: 17 | H74: 194.25882 | I74: 293.59 | J74: Сб
A75: 46185 | C75: 6572 | D75: 6572 | F75: 39 | G75: 39 | H75: 168.51282 | I75: 2698.86 | J75: Пт
A76: 46184 | C76: 9382.7 | D76: 9382.7 | F76: 51 | G76: 51 | H76: 183.97451 | I76: 715.13 | J76: Чт
A77: 46183 | C77: 8804.2 | D77: 8804.2 | F77: 48 | G77: 48 | H77: 183.42083 | I77: 798.39 | J77: Ср
A78: 46182 | C78: 9256 | D78: 9256 | F78: 46 | G78: 46 | H78: 201.21739 | I78: 121.2 | J78: Вт
A79: 46181 | C79: 7409 | D79: 7409 | F79: 39 | G79: 39 | H79: 189.97436 | I79: 879.14 | J79: Пн
A80: 46180 | C80: 2495.1 | D80: 2495.1 | F80: 15 | G80: 15 | H80: 166.34 | I80: 1871.55 | J80: Вс
A81: 46179 | C81: 4205.6 | D81: 4205.6 | F81: 32 | G81: 32 | H81: 131.425 | I81: 352.98 | J81: Сб
A82: 46178 | B82: 198 | C82: 8614 | D82: 8812 | E82: 1 | F82: 50 | G82: 51 | H82: 172.78431 | I82: 75.57 | J82: Пт
A83: 46177 | C83: 8981 | D83: 8981 | F83: 47 | G83: 47 | H83: 191.08511 | I83: 181.35 | J83: Чт
A84: 46176 | C84: 11783 | D84: 11783 | F84: 58 | G84: 58 | H84: 203.15517 | I84: 33.93 | J84: Ср
A85: 46175 | C85: 12127.2 | D85: 12127.2 | F85: 57 | G85: 57 | H85: 212.75789 | I85: 1455.66 | J85: Вт
A86: 46174 | C86: 8759.8 | D86: 8759.8 | F86: 46 | G86: 46 | H86: 190.43043 | I86: 196.27 | J86: Пн
A87: 46172 | C87: 4813.7 | D87: 4813.7 | F87: 30 | G87: 30 | H87: 160.45667 | I87: 372.12 | J87: Сб
A88: 46171 | C88: 9024.8 | D88: 9024.8 | F88: 48 | G88: 48 | H88: 188.01667 | I88: 953.45 | J88: Пт
A89: 46170 | B89: 208 | C89: 7756.6 | D89: 7964.6 | E89: 1 | F89: 35 | G89: 36 | H89: 221.23889 | I89: 395.97 | J89: Чт
A90: 46169 | C90: 8865 | D90: 8865 | F90: 43 | G90: 43 | H90: 206.16279 | I90: 457.34 | J90: Ср
A91: 46168 | C91: 9331 | D91: 9331 | F91: 51 | G91: 51 | H91: 182.96078 | I91: 146.19 | J91: Вт
A92: 46166 | B92: 219 | C92: 1636.4 | D92: 1855.4 | E92: 1 | F92: 13 | G92: 14 | H92: 132.52857 | I92: 1747.96 | J92: Вс
A93: 46165 | C93: 2749.8 | D93: 2749.8 | F93: 18 | G93: 18 | H93: 152.76667 | I93: 250.11 | J93: Сб
A94: 46164 | C94: 8574 | D94: 8574 | F94: 46 | G94: 46 | H94: 186.3913 | I94: 208.16 | J94: Пт
A95: 46163 | C95: 9962.6 | D95: 9962.6 | F95: 47 | G95: 47 | H95: 211.97021 | I95: 528.93 | J95: Чт
A96: 46162 | C96: 8406.9 | D96: 8406.9 | F96: 40 | G96: 40 | H96: 210.1725 | I96: 192.7 | J96: Ср
A97: 46161 | C97: 9924.4 | D97: 9924.4 | F97: 62 | G97: 62 | H97: 160.07097 | I97: 206.06 | J97: Вт
A98: 46160 | C98: 9313.4 | D98: 9313.4 | F98: 55 | G98: 55 | H98: 169.33455 | I98: 1064.1 | J98: Пн
A99: 46159 | C99: 2449.8 | D99: 2449.8 | F99: 17 | G99: 17 | H99: 144.10588 | I99: 1984.66 | J99: Вс
A100: 46158 | C100: 3940.4 | D100: 3940.4 | F100: 24 | G100: 24 | H100: 164.18333 | I100: 31.04 | J100: Сб
A101: 46157 | C101: 13017.8 | D101: 13017.8 | F101: 70 | G101: 70 | H101: 185.96857 | I101: 307.55 | J101: Пт
A102: 46156 | C102: 11777.4 | D102: 11777.4 | F102: 60 | G102: 60 | H102: 196.29 | I102: 75.31 | J102: Чт
A103: 46155 | C103: 10878.2 | D103: 10878.2 | F103: 55 | G103: 55 | H103: 197.78545 | I103: 483.21 | J103: Ср
A104: 46154 | C104: 5927.8 | D104: 5927.8 | F104: 32 | G104: 32 | H104: 185.24375 | I104: 1981.4 | J104: Вт
... A123: 46133 | C123: 7801 | D123: 7801 | F123: 37 | G123: 37 | H123: 210.83784 | I123: 476.61 | J123: Вт
A124: 46132 | B124: 198 | C124: 10188 | D124: 10386 | E124: 1 | F124: 54 | G124: 55 | H124: 188.83636 | I124: 630.09 | J124: Пн
A125: 46131 | B125: 735 | C125: 3109.2 | D125: 3844.2 | E125: 4 | F125: 19 | G125: 23 | H125: 167.13913 | I125: 371.02 | J125: Вс
A126: 46130 | C126: 2888.7 | D126: 2888.7 | F126: 24 | G126: 24 | H126: 120.3625 | I126: 705.52 | J126: Сб
A127: 46129 | C127: 9494.9 | D127: 9494.9 | F127: 57 | G127: 57 | H127: 166.57719 | I127: 276.98 | J127: Пт
A128: 46128 | C128: 9417.4 | D128: 9417.4 | F128: 50 | G128: 50 | H128: 188.348 | I128: 487.97 | J128: Чт
A129: 46127 | C129: 10956.8 | D129: 10956.8 | F129: 50 | G129: 50 | H129: 219.136 | I129: 212.98 | J129: Ср
A130: 46126 | C130: 8930 | D130: 8930 | F130: 42 | G130: 42 | H130: 212.61905 | I130: 160.92 | J130: Вт
A131: 46125 | C131: 9566.7 | D131: 9566.7 | F131: 51 | G131: 51 | H131: 187.58235 | I131: 171.52 | J131: Пн
A132: 46124 | C132: 1459.8 | D132: 1459.8 | F132: 9 | G132: 9 | H132: 162.2 | I132: 2172.6 | J132: Вс
A133: 46123 | B133: 155 | C133: 3390.2 | D133: 3545.2 | E133: 1 | F133: 26 | G133: 27 | H133: 131.3037 | I133: 492.03 | J133: Сб
A134: 46122 | C134: 8566.4 | D134: 8566.4 | F134: 46 | G134: 46 | H134: 186.22609 | I134: 246.71 | J134: Пт
A135: 46121 | C135: 8047.8 | D135: 8047.8 | F135: 38 | G135: 38 | H135: 211.78421 | I135: 800.87 | J135: Чт
A136: 46120 | C136: 10678.4 | D136: 10678.4 | F136: 47 | G136: 47 | H136: 227.2 | I136: 4377.71 | J136: Ср
A137: 46119 | C137: 6082.6 | D137: 6082.6 | F137: 31 | G137: 31 | H137: 196.2129 | I137: 589.59 | J137: Вт
A138: 46118 | C138: 8858 | D138: 8858 | F138: 44 | G138: 44 | H138: 201.31818 | I138: 0 | J138: Пн
A139: 46117 | C139: 2112.2 | D139: 2112.2 | F139: 12 | G139: 12 | H139: 176.01667 | I139: 3340.76 | J139: Вс
A140: 46116 | C140: 2918.4 | D140: 2918.4 | F140: 20 | G140: 20 | H140: 145.92 | I140: 799.98 | J140: Сб
A141: 46115 | B141: 1887 | C141: 6514 | D141: 8401 | E141: 6 | F141: 39 | G141: 45 | H141: 186.68889 | I141: 78.73 | J141: Пт
...

Sheet 7
A1: Точка | B1: 7 | C1: Дата запуска | D1: 45495 | E1: Тип точки | F1: офис | G1: Активна | H1: Да | K1: Стоимость обслуживания | L1: Аренда | M1: Коммуналка | N1: Клининг
A2: Среднее | B2: 485.70377 | C2: 5500.7034 | D2: 5577.0686 | E2: 2.3584906 | F2: 30.016949 | G2: 30.305785 | H2: 184.06041 | I2: 239.24305 | K2: =SUM(L2:Q2) -> 300 | L2: 0 | M2: 0 | N2: 300
A3: Дата | B3: $ QR-код | C3: $ Касса | D3: $ Итог | E3: Чеки QR | F3: Чеки Касса | G3: Чеки Итог | H3: Ср.-й чек | I3: Списания | J3: д/н
A4: 46257 | C4: 0 | F4: 2 | G4: 2 | H4: 0 | I4: 332.89 | J4: Вс
A5: 46256 | C5: 140 | D5: 140 | F5: 2 | G5: 2 | H5: 70 | I5: 70.33 | J5: Сб
A6: 46255 | C6: 2883.6 | D6: 2883.6 | F6: 21 | G6: 21 | H6: 137.31429 | I6: 161.52 | J6: Пт
A7: 46254 | C7: 4860 | D7: 4860 | F7: 27 | G7: 27 | H7: 180 | I7: 29.74 | J7: Чт
A8: 46253 | B8: 405 | C8: 8654.4 | D8: 9059.4 | E8: 1 | F8: 48 | G8: 49 | H8: 184.88571 | I8: 282.19 | J8: Ср
A9: 46252 | C9: 5418 | D9: 5418 | F9: 34 | G9: 34 | H9: 159.35294 | I9: 0 | J9: Вт
A10: 46251 | C10: 4140 | D10: 4140 | F10: 28 | G10: 28 | H10: 147.85714 | I10: 8.1 | J10: Пн
A11: 46250 | C11: 0 | F11: 0 | I11: 0 | J11: Вс
A12: 46249 | C12: 150 | D12: 150 | F12: 2 | G12: 2 | H12: 75 | I12: 0 | J12: Сб
A13: 46248 | C13: 5288.8 | D13: 5288.8 | F13: 30 | G13: 30 | H13: 176.29333 | I13: 110.96 | J13: Пт
A14: 46247 | C14: 7974 | D14: 7974 | F14: 41 | G14: 41 | H14: 194.4878 | I14: 0 | J14: Чт
A15: 46246 | B15: 70 | C15: 7277.8 | D15: 7347.8 | E15: 1 | F15: 40 | G15: 41 | H15: 179.21463 | I15: 22.54 | J15: Ср
A16: 46245 | B16: 175 | C16: 5478 | D16: 5653 | E16: 1 | F16: 35 | G16: 36 | H16: 157.02778 | I16: 458.77 | J16: Вт
A17: 46244 | B17: 60 | C17: 4692 | D17: 4752 | E17: 1 | F17: 24 | G17: 25 | H17: 190.08 | I17: 324.59 | J17: Пн
A18: 46243 | C18: 0 | F18: 0 | I18: 228.8 | J18: Вс
A19: 46242 | C19: 480 | D19: 480 | F19: 5 | G19: 5 | H19: 96 | I19: 212.05 | J19: Сб
A20: 46241 | C20: 7800 | D20: 7800 | F20: 51 | G20: 51 | H20: 152.94118 | I20: 390.55 | J20: Пт
A21: 46240 | B21: 933 | C21: 11288.8 | D21: 12221.8 | E21: 2 | F21: 61 | G21: 63 | H21: 193.99683 | I21: 50.46 | J21: Чт
A22: 46239 | B22: 889 | C22: 4191 | D22: 5080 | E22: 2 | F22: 24 | G22: 26 | H22: 195.38462 | I22: 29.79 | J22: Ср
A23: 46238 | B23: 504 | C23: 7252 | D23: 7756 | E23: 2 | F23: 36 | G23: 38 | H23: 204.10526 | I23: 1.8 | J23: Вт
A24: 46237 | B24: 79 | C24: 4705 | D24: 4784 | E24: 1 | F24: 24 | G24: 25 | H24: 191.36 | I24: 93.03 | J24: Пн
A25: 46236 | C25: 0 | F25: 0 | I25: 147.77 | J25: Вс
A26: 46235 | C26: 615 | D26: 615 | F26: 5 | G26: 5 | H26: 123 | I26: 162 | J26: Сб
A27: 46234 | C27: 8619.8 | D27: 8619.8 | F27: 44 | G27: 44 | H27: 195.90455 | I27: 107.16 | J27: Пт
A28: 46233 | C28: 11239.4 | D28: 11239.4 | F28: 56 | G28: 56 | H28: 200.70357 | I28: 276.59 | J28: Чт
A29: 46232 | B29: 586 | C29: 8826 | D29: 9412 | E29: 3 | F29: 51 | G29: 54 | H29: 174.2963 | I29: 0 | J29: Ср
A30: 46231 | B30: 54 | C30: 6974 | D30: 7028 | E30: 1 | F30: 41 | G30: 42 | H30: 167.33333 | I30: 0 | J30: Вт
A31: 46230 | B31: 545 | C31: 7848 | D31: 8393 | E31: 3 | F31: 49 | G31: 52 | H31: 161.40385 | I31: 0 | J31: Пн
A32: 46229 | C32: 90 | D32: 90 | F32: 1 | G32: 1 | H32: 90 | I32: 173.43 | J32: Вс
A33: 46228 | C33: 330 | D33: 330 | F33: 4 | G33: 4 | H33: 82.5 | I33: 256.59 | J33: Сб
A34: 46227 | B34: 956 | C34: 5143.6 | D34: 6099.6 | E34: 2 | F34: 31 | G34: 33 | H34: 184.83636 | I34: 383.96 | J34: Пт
A35: 46226 | C35: 9943.8 | D35: 9943.8 | F35: 53 | G35: 53 | H35: 187.61887 | I35: 134.95 | J35: Чт
A36: 46225 | B36: 218 | C36: 7587 | D36: 7805 | E36: 1 | F36: 41 | G36: 42 | H36: 185.83333 | I36: 71.59 | J36: Ср
A37: 46224 | B37: 830 | C37: 9571 | D37: 10401 | E37: 2 | F37: 54 | G37: 56 | H37: 185.73214 | I37: 0 | J37: Вт
A38: 46223 | C38: 2144 | D38: 2144 | F38: 11 | G38: 11 | H38: 194.90909 | I38: 0 | J38: Пн
A39: 46222 | C39: 0 | F39: 1 | G39: 1 | H39: 0 | I39: 289.82 | J39: Вс
A40: 46221 | C40: 1886 | D40: 1886 | F40: 11 | G40: 11 | H40: 171.45455 | I40: 0 | J40: Сб
A41: 46220 | C41: 7156.8 | D41: 7156.8 | F41: 38 | G41: 38 | H41: 188.33684 | I41: 46.95 | J41: Пт
A42: 46219 | B42: 446 | C42: 8322.8 | D42: 8768.8 | E42: 3 | F42: 41 | G42: 44 | H42: 199.29091 | I42: 341.54 | J42: Чт
A43: 46218 | B43: 87 | C43: 8705 | D43: 8792 | E43: 1 | F43: 45 | G43: 46 | H43: 191.13043 | I43: 27.34 | J43: Ср
A44: 46217 | B44: 527 | C44: 6575 | D44: 7102 | E44: 4 | F44: 36 | G44: 40 | H44: 177.55 | I44: 86.25 | J44: Вт
A45: 46216 | B45: 672 | C45: 5086 | D45: 5758 | E45: 1 | F45: 28 | G45: 29 | H45: 198.55172 | I45: 0 | J45: Пн
A46: 46214 | C46: 1277 | D46: 1277 | F46: 9 | G46: 9 | H46: 141.88889 | I46: 0 | J46: Сб
A47: 46213 | B47: 995 | C47: 6048 | D47: 7043 | E47: 9 | F47: 32 | G47: 41 | H47: 171.78049 | I47: 539.02 | J47: Пт
A48: 46212 | B48: 1040 | C48: 7137.4 | D48: 8177.4 | E48: 7 | F48: 41 | G48: 48 | H48: 170.3625 | I48: 0 | J48: Чт
A49: 46211 | B49: 290 | C49: 6136 | D49: 6426 | E49: 2 | F49: 34 | G49: 36 | H49: 178.5 | I49: 134.8 | J49: Ср
A50: 46210 | C50: 9809 | D50: 9809 | F50: 52 | G50: 52 | H50: 188.63462 | I50: 0 | J50: Вт
A51: 46209 | B51: 95 | C51: 5630 | D51: 5725 | E51: 1 | F51: 35 | G51: 36 | H51: 159.02778 | I51: 56.29 | J51: Пн
A52: 46207 | C52: 1239 | D52: 1239 | F52: 7 | G52: 7 | H52: 177 | I52: 43.4 | J52: Сб
A53: 46206 | C53: 7972.2 | D53: 7972.2 | F53: 38 | G53: 38 | H53: 209.79474 | I53: 0 | J53: Пт
A54: 46205 | C54: 6294 | D54: 6294 | F54: 29 | G54: 29 | H54: 217.03448 | I54: 274.63 | J54: Чт
A55: 46204 | C55: 7681 | D55: 7681 | F55: 39 | G55: 39 | H55: 196.94872 | I55: 27.9 | J55: Ср
A56: 46203 | C56: 8034 | D56: 8034 | F56: 40 | G56: 40 | H56: 200.85 | I56: 318.31 | J56: Вт
A57: 46202 | C57: 6961.5 | D57: 6961.5 | F57: 37 | G57: 37 | H57: 188.14865 | I57: 356.48 | J57: Пн
A58: 46201 | C58: 0 | F58: 0 | I58: 374.73 | J58: Вс
A59: 46200 | C59: 1779 | D59: 1779 | F59: 14 | G59: 14 | H59: 127.07143 | I59: 0 | J59: Сб
A60: 46199 | C60: 7758.9 | D60: 7758.9 | F60: 45 | G60: 45 | H60: 172.42 | I60: 0 | J60: Пт
A61: 46198 | B61: 60 | C61: 6373.8 | D61: 6433.8 | E61: 1 | F61: 37 | G61: 38 | H61: 169.31053 | I61: 340.25 | J61: Чт
A62: 46197 | B62: 60 | C62: 7933 | D62: 7993 | E62: 1 | F62: 42 | G62: 43 | H62: 185.88372 | I62: 58.57 | J62: Ср
A63: 46196 | C63: 5047 | D63: 5047 | F63: 31 | G63: 31 | H63: 162.80645 | I63: 156.47 | J63: Вт
A64: 46195 | C64: 4818 | D64: 4818 | F64: 27 | G64: 27 | H64: 178.44444 | I64: 568.78 | J64: Пн | L64: ТОП-3 Целевой аудитории
A65: 46193 | C65: 586 | D65: 586 | F65: 6 | G65: 6 | H65: 97.666667 | I65: 457.8 | J65: Сб | L65: пол | M65: возраст | N65: % присутствия | P65: кол-во уникальных гостей
A66: 46192 | C66: 7963.6 | D66: 7963.6 | F66: 48 | G66: 48 | H66: 165.90833 | I66: 213.42 | J66: Пт | L66: мужчины | M66: 35-45 | N66: 0.29 | P66: 78
A67: 46191 | C67: 8811 | D67: 8811 | F67: 52 | G67: 52 | H67: 169.44231 | I67: 444.11 | J67: Чт | L67: женщины | M67: 25-35 | N67: 0.13
A68: 46190 | B68: 2336 | C68: 4900.4 | D68: 7236.4 | E68: 9 | F68: 29 | G68: 38 | H68: 190.43158 | I68: 0 | J68: Ср | L68: мужчины | M68: 25-35 | N68: 0.12
A69: 46189 | B69: 158 | D69: 158 | E69: 1 | G69: 1 | H69: 158 | J69: Вт
A70: 46188 | B70: 816 | C70: 7545.5 | D70: 8361.5 | E70: 4 | F70: 38 | G70: 42 | H70: 199.08333 | I70: 0 | J70: Пн | L70: График работы | M70: дней в неделю | N70: часы работы
A71: 46187 | C71: 258 | D71: 258 | F71: 1 | G71: 1 | H71: 258 | I71: 136.16 | J71: Вс | M71: 5 | N71: 08:00-17:00
A72: 46186 | C72: 0 | F72: 0 | I72: 77.72 | J72: Сб
A73: 46185 | B73: 105 | C73: 1929.5 | D73: 2034.5 | E73: 1 | F73: 12 | G73: 13 | H73: 156.5 | I73: 56.41 | J73: Пт
A74: 46184 | B74: 267.1 | C74: 4997.2 | D74: 5264.3 | E74: 2 | F74: 34 | G74: 36 | H74: 146.23056 | I74: 101.67 | J74: Чт
A75: 46183 | C75: 7225 | D75: 7225 | F75: 41 | G75: 41 | H75: 176.21951 | I75: 190.62 | J75: Ср
A76: 46182 | C76: 5457 | D76: 5457 | F76: 34 | G76: 34 | H76: 160.5 | I76: 175.28 | J76: Вт
A77: 46181 | C77: 5228 | D77: 5228 | F77: 29 | G77: 29 | H77: 180.27586 | I77: 570.62 | J77: Пн
A78: 46180 | C78: 0 | F78: 0 | I78: 174.8 | J78: Вс
A79: 46179 | C79: 791 | D79: 791 | F79: 6 | G79: 6 | H79: 131.83333 | I79: 156.66 | J79: Сб
A80: 46178 | C80: 5971.4 | D80: 5971.4 | F80: 32 | G80: 32 | H80: 186.60625 | I80: 125.76 | J80: Пт
A81: 46177 | C81: 7982.6 | D81: 7982.6 | F81: 43 | G81: 43 | H81: 185.64186 | I81: 234.14 | J81: Чт
A82: 46176 | B82: 158 | C82: 5869.8 | D82: 6027.8 | E82: 1 | F82: 31 | G82: 32 | H82: 188.36875 | I82: 477.52 | J82: Ср
A83: 46175 | C83: 4218 | D83: 4218 | F83: 25 | G83: 25 | H83: 168.72 | I83: 333.43 | J83: Вт
A84: 46174 | B84: 60 | C84: 7029 | D84: 7089 | E84: 1 | F84: 40 | G84: 41 | H84: 172.90244 | I84: 132.62 | J84: Пн
A85: 46172 | C85: 1230 | D85: 1230 | F85: 5 | G85: 5 | H85: 246 | I85: 314.69 | J85: Сб
A86: 46171 | C86: 9222.8 | D86: 9222.8 | F86: 44 | G86: 44 | H86: 209.60909 | I86: 80.36 | J86: Пт
A87: 46170 | B87: 195 | C87: 8741.2 | D87: 8936.2 | E87: 1 | F87: 45 | G87: 46 | H87: 194.26522 | I87: 395.05 | J87: Чт
A88: 46169 | B88: 722 | C88: 5052 | D88: 5774 | E88: 1 | F88: 25 | G88: 26 | H88: 222.07692 | I88: 0 | J88: Ср
A89: 46168 | C89: 5881 | D89: 5881 | F89: 27 | G89: 27 | H89: 217.81481 | I89: 319.3 | J89: Вт
A90: 46167 | B90: 155 | D90: 155 | E90: 1 | G90: 1 | H90: 155 | J90: Пн
A91: 46166 | C91: 0 | F91: 0 | I91: 0 | J91: Вс
A92: 46165 | C92: 465 | D92: 465 | F92: 5 | G92: 5 | H92: 93 | I92: 0 | J92: Сб
A93: 46164 | C93: 4957.6 | D93: 4957.6 | F93: 28 | G93: 28 | H93: 177.05714 | I93: 500.18 | J93: Пт
A94: 46163 | C94: 5105.8 | D94: 5105.8 | F94: 26 | G94: 26 | H94: 196.37692 | I94: 521.88 | J94: Чт
A95: 46162 | C95: 5081.9 | D95: 5081.9 | F95: 31 | G95: 31 | H95: 163.93226 | I95: 93.6 | J95: Ср
A96: 46161 | C96: 5571 | D96: 5571 | F96: 31 | G96: 31 | H96: 179.70968 | I96: 0 | J96: Вт
A97: 46160 | C97: 4928 | D97: 4928 | F97: 23 | G97: 23 | H97: 214.26087 | I97: 601.79 | J97: Пн
A98: 46159 | C98: 0 | F98: 0 | I98: 582.72 | J98: Вс
A99: 46158 | C99: 60 | D99: 60 | F99: 1 | G99: 1 | H99: 60 | I99: 0 | J99: Сб
A100: 46157 | C100: 4961.5 | D100: 4961.5 | F100: 28 | G100: 28 | H100: 177.19643 | I100: 240.56 | J100: Пт
...

Sheet 8
A1: Точка | B1: 8 | C1: Дата запуска | D1: 45446 | E1: Тип точки | F1: медицина | G1: Активна | H1: Да | K1: Стоимость обслуживания | L1: Аренда | M1: Коммуналка | N1: Клининг | O1: Клининг 2
A2: Среднее | B2: 316.48125 | C2: 7371.1888 | D2: 7437.8164 | E2: 1.375 | F2: 31.684211 | G2: 31.973684 | H2: 238.04987 | I2: 257.44539 | K2: =SUM(L2:Q2) -> 5810 | L2: 2600 | M2: 1410 | N2: 300 | O2: 1500
A3: Дата | B3: $ QR-код | C3: $ Касса | D3: $ Итог | E3: Чеки QR | F3: Чеки Касса | G3: Чеки Итог | H3: Ср.-й чек | I3: Списания | J3: д/н
A4: 46257 | C4: 0 | F4: 0 | I4: 74.93 | J4: Вс
A5: 46256 | C5: 0 | F5: 0 | I5: 82.66 | J5: Сб
A6: 46255 | C6: 6496.6 | D6: 6496.6 | F6: 33 | G6: 33 | H6: 196.86667 | I6: 93.28 | J6: Пт
A7: 46254 | C7: 9306.4 | D7: 9306.4 | F7: 38 | G7: 38 | H7: 244.90526 | I7: 56.64 | J7: Чт
A8: 46253 | C8: 6640.4 | D8: 6640.4 | F8: 29 | G8: 29 | H8: 228.97931 | I8: 40.98 | J8: Ср
A9: 46252 | C9: 4384 | D9: 4384 | F9: 18 | G9: 18 | H9: 243.55556 | I9: 36.48 | J9: Вт
A10: 46251 | C10: 7080.15 | D10: 7080.15 | F10: 31 | G10: 31 | H10: 228.39194 | I10: 0 | J10: Пн
A11: 46250 | C11: 199 | D11: 199 | F11: 1 | G11: 1 | H11: 199 | I11: 0 | J11: Вс
A12: 46249 | C12: 210 | D12: 210 | F12: 2 | G12: 2 | H12: 105 | I12: 0 | J12: Сб
A13: 46248 | C13: 9329.4 | D13: 9329.4 | F13: 47 | G13: 47 | H13: 198.49787 | I13: 62.43 | J13: Пт
A14: 46247 | B14: 169 | C14: 12399.6 | D14: 12568.6 | E14: 1 | F14: 48 | G14: 49 | H14: 256.50204 | I14: 307.18 | J14: Чт
A15: 46246 | C15: 6619.2 | D15: 6619.2 | F15: 34 | G15: 34 | H15: 194.68235 | I15: 27.94 | J15: Ср
A16: 46245 | C16: 6109.2 | D16: 6109.2 | F16: 27 | G16: 27 | H16: 226.26667 | I16: 0 | J16: Вт
A17: 46244 | B17: 279.4 | C17: 6127.4 | D17: 6406.8 | E17: 1 | F17: 28 | G17: 29 | H17: 220.92414 | I17: 0 | J17: Пн
A18: 46242 | C18: 0 | F18: 0 | I18: 65.5 | J18: Сб
A19: 46241 | C19: 6411.4 | D19: 6411.4 | F19: 31 | G19: 31 | H19: 206.81935 | I19: 291.8 | J19: Пт
A20: 46240 | C20: 8631.5 | D20: 8631.5 | F20: 34 | G20: 34 | H20: 253.86765 | I20: 131.97 | J20: Чт
A21: 46239 | C21: 5681.4 | D21: 5681.4 | F21: 31 | G21: 31 | H21: 183.27097 | I21: 112.92 | J21: Ср
A22: 46238 | C22: 7253.6 | D22: 7253.6 | F22: 33 | G22: 33 | H22: 219.80606 | I22: 0 | J22: Вт
A23: 46237 | C23: 7137 | D23: 7137 | F23: 27 | G23: 27 | H23: 264.33333 | I23: 215.69 | J23: Пн
A24: 46235 | C24: 120 | D24: 120 | F24: 2 | G24: 2 | H24: 60 | I24: 0 | J24: Сб
A25: 46234 | C25: 7242 | D25: 7242 | F25: 32 | G25: 32 | H25: 226.3125 | I25: 130.19 | J25: Пт
A26: 46233 | C26: 9947.2 | D26: 9947.2 | F26: 42 | G26: 42 | H26: 236.8381 | I26: 86.4 | J26: Чт
A27: 46232 | C27: 7975.6 | D27: 7975.6 | F27: 35 | G27: 35 | H27: 227.87429 | I27: 92.65 | J27: Ср
A28: 46231 | C28: 7801.4 | D28: 7801.4 | F28: 36 | G28: 36 | H28: 216.70556 | I28: 222.74 | J28: Вт
A29: 46230 | C29: 6638.7 | D29: 6638.7 | F29: 25 | G29: 25 | H29: 265.548 | I29: 0 | J29: Пн
A30: 46227 | C30: 7024.4 | D30: 7024.4 | F30: 36 | G30: 36 | H30: 195.12222 | I30: 551.63 | J30: Пт
... A41: 46216 | C41: 6118 | D41: 6118 | F41: 26 | G41: 26 | H41: 235.30769 | I41: 62.66 | J41: Пн
A42: 46215 | C42: 0 | F42: 1 | G42: 1 | H42: 0 | I42: 146.89 | J42: Вс
A43: 46214 | C43: 0 | F43: 0 | I43: 282.12 | J43: Сб
A44: 46213 | C44: 5932.6 | D44: 5932.6 | F44: 27 | G44: 27 | H44: 219.72593 | I44: 4053.29 | J44: Пт
A45: 46212 | C45: 7358.8 | D45: 7358.8 | F45: 29 | G45: 29 | H45: 253.75172 | I45: 30.75 | J45: Чт
A46: 46211 | C46: 7599.6 | D46: 7599.6 | F46: 32 | G46: 32 | H46: 237.4875 | I46: 0 | J46: Ср
A47: 46210 | C47: 5229 | D47: 5229 | F47: 27 | G47: 27 | H47: 193.66667 | I47: 0 | J47: Вт
A48: 46209 | C48: 5868 | D48: 5868 | F48: 29 | G48: 29 | H48: 202.34483 | I48: 66.63 | J48: Пн
A49: 46207 | C49: 0 | F49: 0 | I49: 179.48 | J49: Сб
A50: 46206 | C50: 6860.4 | D50: 6860.4 | F50: 39 | G50: 39 | H50: 175.90769 | I50: 340.19 | J50: Пт
A51: 46205 | C51: 7712.8 | D51: 7712.8 | F51: 31 | G51: 31 | H51: 248.8 | I51: 247.35 | J51: Чт
A52: 46204 | C52: 7194.4 | D52: 7194.4 | F52: 34 | G52: 34 | H52: 211.6 | I52: 413.75 | J52: Ср
A53: 46203 | C53: 8426.2 | D53: 8426.2 | F53: 34 | G53: 34 | H53: 247.82941 | I53: 50.05 | J53: Вт
A54: 46202 | C54: 7811 | D54: 7811 | F54: 28 | G54: 28 | H54: 278.96429 | I54: 408.04 | J54: Пн
A55: 46201 | C55: 697 | D55: 697 | F55: 1 | G55: 1 | H55: 697 | I55: 72.58 | J55: Вс
A56: 46200 | C56: 145 | D56: 145 | F56: 1 | G56: 1 | H56: 145 | I56: 0 | J56: Сб
A57: 46199 | C57: 6957.2 | D57: 6957.2 | F57: 28 | G57: 28 | H57: 248.47143 | I57: 175.92 | J57: Пт
A58: 46198 | C58: 9708 | D58: 9708 | F58: 44 | G58: 44 | H58: 220.63636 | I58: 201.81 | J58: Чт
A59: 46197 | C59: 9869.2 | D59: 9869.2 | F59: 43 | G59: 43 | H59: 229.51628 | I59: 94.42 | J59: Ср
A60: 46196 | C60: 7832 | D60: 7832 | F60: 37 | G60: 37 | H60: 211.67568 | I60: 0 | J60: Вт
A61: 46195 | B61: 312 | C61: 8338 | D61: 8650 | E61: 1 | F61: 38 | G61: 39 | H61: 221.79487 | I61: 0 | J61: Пн
A62: 46194 | C62: 389 | D62: 389 | F62: 2 | G62: 2 | H62: 194.5 | I62: 142 | J62: Вс
A63: 46193 | C63: 0 | F63: 0 | I63: 493.06 | J63: Сб
A64: 46192 | C64: 6663.2 | D64: 6663.2 | F64: 38 | G64: 38 | H64: 175.34737 | I64: 69.47 | J64: Пт | L64: ТОП-3 Целевой аудитории
A65: 46191 | C65: 11053.1 | D65: 11053.1 | F65: 52 | G65: 52 | H65: 212.55962 | I65: 823.11 | J65: Чт | L65: пол | M65: возраст | N65: % присутствия | P65: кол-во уникальных гостей
A66: 46190 | C66: 7534.6 | D66: 7534.6 | F66: 36 | G66: 36 | H66: 209.29444 | I66: 0 | J66: Ср | L66: женщины | M66: 35-45 | N66: 0.34 | P66: 180
A67: 46189 | B67: 306 | D67: 306 | E67: 1 | G67: 1 | H67: 306 | J67: Вт | L67: женщины | M67: 45-55 | N67: 0.13
A68: 46188 | C68: 6565.4 | D68: 6565.4 | F68: 32 | G68: 32 | H68: 205.16875 | I68: 0 | J68: Пн | L68: женщины | M68: 25-35 | N68: 0.13
A69: 46187 | C69: 0 | F69: 0 | I69: 724.59 | J69: Вс
A70: 46186 | C70: 0 | F70: 0 | I70: 177.08 | J70: Сб | L70: График работы | M70: дней в неделю | N70: часы работы
A71: 46185 | C71: 277 | D71: 277 | F71: 3 | G71: 3 | H71: 92.333333 | I71: 349.87 | J71: Пт | M71: 5 | N71: 08:00-17:00
A72: 46184 | C72: 7875.2 | D72: 7875.2 | F72: 48 | G72: 48 | H72: 164.06667 | I72: 227 | J72: Чт
A73: 46183 | C73: 4450.15 | D73: 4450.15 | F73: 18 | G73: 18 | H73: 247.23056 | I73: 309.86 | J73: Ср
A74: 46182 | B74: 190 | C74: 9390.1 | D74: 9580.1 | E74: 1 | F74: 42 | G74: 43 | H74: 222.79302 | I74: 0 | J74: Вт
A75: 46181 | B75: 188 | C75: 5993.4 | D75: 6181.4 | E75: 1 | F75: 30 | G75: 31 | H75: 199.4 | I75: 441.58 | J75: Пн
A76: 46180 | C76: 861 | D76: 861 | F76: 2 | G76: 2 | H76: 430.5 | I76: 119.49 | J76: Вс
A77: 46179 | C77: 0 | F77: 0 | I77: 59.77 | J77: Сб
A78: 46178 | C78: 8672 | D78: 8672 | F78: 41 | G78: 41 | H78: 211.5122 | I78: 23.99 | J78: Пт
A79: 46177 | C79: 8847.9 | D79: 8847.9 | F79: 38 | G79: 38 | H79: 232.83947 | I79: 12.34 | J79: Чт
A80: 46176 | C80: 9849.1 | D80: 9849.1 | F80: 40 | G80: 40 | H80: 246.2275 | I80: 1.97 | J80: Ср
A81: 46175 | B81: 291 | C81: 8686.9 | D81: 8977.9 | E81: 1 | F81: 39 | G81: 40 | H81: 224.4475 | I81: 101.86 | J81: Вт
A82: 46174 | C82: 11365.4 | D82: 11365.4 | F82: 46 | G82: 46 | H82: 247.07391 | I82: 46.17 | J82: Пн
A83: 46172 | C83: 0 | F83: 0 | I83: 33.24 | J83: Сб
A84: 46171 | C84: 11040.2 | D84: 11040.2 | F84: 48 | G84: 48 | H84: 230.00417 | I84: 133.66 | J84: Пт
A85: 46170 | B85: 96 | C85: 10108 | D85: 10204 | E85: 1 | F85: 42 | G85: 43 | H85: 237.30233 | I85: 98 | J85: Чт
A86: 46169 | C86: 9458.6 | D86: 9458.6 | F86: 45 | G86: 45 | H86: 210.19111 | I86: 1358.57 | J86: Ср
A87: 46168 | C87: 7995.6 | D87: 7995.6 | F87: 30 | G87: 30 | H87: 266.52 | I87: 887.55 | J87: Вт
A88: 46166 | C88: 0 | F88: 0 | I88: 741.7 | J88: Вс
A89: 46165 | C89: 0 | F89: 0 | I89: 367.32 | J89: Сб
A90: 46164 | C90: 0 | F90: 0 | I90: 281.15 | J90: Пт
A91: 46163 | B91: 366 | C91: 8631 | D91: 8997 | E91: 1 | F91: 31 | G91: 32 | H91: 281.15625 | I91: 298.55 | J91: Чт
A92: 46162 | C92: 9716.35 | D92: 9716.35 | F92: 38 | G92: 38 | H92: 255.69342 | I92: 1426.77 | J92: Ср
A93: 46161 | B93: 277 | C93: 7748.6 | D93: 8025.6 | E93: 1 | F93: 36 | G93: 37 | H93: 216.90811 | I93: 461.28 | J93: Вт
A94: 46160 | C94: 10431.4 | D94: 10431.4 | F94: 45 | G94: 45 | H94: 231.80889 | I94: 592.33 | J94: Пн
A95: 46159 | C95: 583 | D95: 583 | F95: 2 | G95: 2 | H95: 291.5 | I95: 618.53 | J95: Вс
A96: 46158 | C96: 145 | D96: 145 | F96: 1 | G96: 1 | H96: 145 | I96: 0 | J96: Сб
A97: 46157 | C97: 8336.8 | D97: 8336.8 | F97: 40 | G97: 40 | H97: 208.42 | I97: 4.8 | J97: Пт
A98: 46156 | C98: 7007.4 | D98: 7007.4 | F98: 33 | G98: 33 | H98: 212.34545 | I98: 56.35 | J98: Чт
A99: 46155 | C99: 8335.6 | D99: 8335.6 | F99: 43 | G99: 43 | H99: 193.85116 | I99: 393.02 | J99: Ср
A100: 46154 | B100: 209 | C100: 9005.9 | D100: 9214.9 | E100: 1 | F100: 38 | G100: 39 | H100: 236.27949 | I100: 48.11 | J100: Вт
A101: 46153 | C101: 569 | D101: 569 | F101: 3 | G101: 3 | H101: 189.66667 | I101: 5.66 | J101: Пн
A102: 46151 | C102: 100 | D102: 100 | F102: 1 | G102: 1 | H102: 100 | I102: 52.02 | J102: Сб
A103: 46150 | C103: 8916.35 | D103: 8916.35 | F103: 40 | G103: 40 | H103: 222.90875 | I103: 0 | J103: Пт
A104: 46149 | B104: 569 | C104: 8690.2 | D104: 9259.2 | E104: 3 | F104: 40 | G104: 43 | H104: 215.33023 | I104: 484.29 | J104: Чт
A105: 46148 | B105: 98 | C105: 10530 | D105: 10628 | E105: 1 | F105: 46 | G105: 47 | H105: 226.12766 | I105: 48.65 | J105: Ср
A106: 46147 | C106: 9648.9 | D106: 9648.9 | F106: 48 | G106: 48 | H106: 201.01875 | I106: 91.38 | J106: Вт
A107: 46146 | C107: 6346 | D107: 6346 | F107: 27 | G107: 27 | H107: 235.03704 | I107: 0 | J107: Пн
A108: 46145 | C108: 0 | F108: 0 | I108: 0 | J108: Вс
A109: 46143 | C109: 50 | D109: 50 | F109: 1 | G109: 1 | H109: 50 | I109: 94.03 | J109: Пт
A110: 46142 | B110: 612 | C110: 5993.3 | D110: 6605.3 | E110: 3 | F110: 29 | G110: 32 | H110: 206.41563 | I110: 1117.37 | J110: Чт
...

Sheet 9
A1: Точка | B1: 9 | C1: Дата запуска | D1: 45571 | E1: Тип точки | F1: офис | G1: Активна | H1: Да | K1: Стоимость обслуживания | L1: Аренда | M1: Коммуналка | N1: Клининг | O1: Клининг 2
A2: Среднее | B2: 335.04286 | C2: 10323.195 | D2: 10341.419 | E2: 1.6714286 | F2: 48.934211 | G2: 49.058442 | H2: 211.44077 | I2: 207.56388 | K2: =SUM(L2:Q2) -> 9900 | L2: 4300 | M2: 4300 | N2: 300 | O2: 1000
A3: Дата | B3: $ QR-код | C3: $ Касса | D3: $ Итог | E3: Чеки QR | F3: Чеки Касса | G3: Чеки Итог | H3: Ср.-й чек | I3: Списания | J3: д/н
A4: 46257 | C4: 105 | D4: 105 | F4: 1 | G4: 1 | H4: 105 | I4: 0 | J4: Вс
A5: 46255 | C5: 5802.4 | D5: 5802.4 | F5: 32 | G5: 32 | H5: 181.325 | I5: 54.95 | J5: Пт
A6: 46254 | C6: 11218.7 | D6: 11218.7 | F6: 61 | G6: 61 | H6: 183.91311 | I6: 29.24 | J6: Чт
A7: 46253 | C7: 8614.8 | D7: 8614.8 | F7: 44 | G7: 44 | H7: 195.79091 | I7: 76.54 | J7: Ср
A8: 46252 | C8: 7430.4 | D8: 7430.4 | F8: 33 | G8: 33 | H8: 225.16364 | I8: 0 | J8: Вт
A9: 46251 | C9: 10103 | D9: 10103 | F9: 44 | G9: 44 | H9: 229.61364 | I9: 0 | J9: Пн
A10: 46250 | C10: 0 | F10: 0 | I10: 0 | J10: Вс
A11: 46249 | C11: 391 | D11: 391 | F11: 4 | G11: 4 | H11: 97.75 | I11: 0 | J11: Сб
A12: 46248 | B12: 95 | C12: 11758.3 | D12: 11853.3 | E12: 1 | F12: 56 | G12: 57 | H12: 207.95263 | I12: 272.79 | J12: Пт
A13: 46247 | B13: 120 | C13: 10591 | D13: 10711 | E13: 1 | F13: 54 | G13: 55 | H13: 194.74545 | I13: 43.98 | J13: Чт
A14: 46246 | C14: 11591.4 | D14: 11591.4 | F14: 56 | G14: 56 | H14: 206.98929 | I14: 78.64 | J14: Ср
A15: 46245 | C15: 9268.6 | D15: 9268.6 | F15: 45 | G15: 45 | H15: 205.96889 | I15: 94.62 | J15: Вт
A16: 46244 | C16: 7777 | D16: 7777 | F16: 35 | G16: 35 | H16: 222.2 | I16: 30.64 | J16: Пн
A17: 46243 | C17: 285 | D17: 285 | F17: 2 | G17: 2 | H17: 142.5 | I17: 41.94 | J17: Вс
A18: 46242 | C18: 105 | D18: 105 | F18: 1 | G18: 1 | H18: 105 | I18: 0 | J18: Сб
A19: 46241 | C19: 10359.6 | D19: 10359.6 | F19: 49 | G19: 49 | H19: 211.42041 | I19: 229.54 | J19: Пт
A20: 46240 | C20: 13694.2 | D20: 13694.2 | F20: 57 | G20: 57 | H20: 240.24912 | I20: 354.02 | J20: Чт
A21: 46239 | C21: 8815 | D21: 8815 | F21: 44 | G21: 44 | H21: 200.34091 | I21: 54.02 | J21: Ср
A22: 46238 | C22: 9532.6 | D22: 9532.6 | F22: 50 | G22: 50 | H22: 190.652 | I22: 0 | J22: Вт
A23: 46237 | C23: 9460.65 | D23: 9460.65 | F23: 44 | G23: 44 | H23: 215.01477 | I23: 95.89 | J23: Пн
A24: 46236 | C24: 105 | D24: 105 | F24: 1 | G24: 1 | H24: 105 | I24: 0 | J24: Вс
A25: 46235 | C25: 120 | D25: 120 | F25: 2 | G25: 2 | H25: 60 | I25: 0 | J25: Сб
A26: 46234 | C26: 14500.4 | D26: 14500.4 | F26: 65 | G26: 65 | H26: 223.08308 | I26: 100.66 | J26: Пт
A27: 46233 | B27: 376 | C27: 11680.4 | D27: 12056.4 | E27: 1 | F27: 51 | G27: 52 | H27: 231.85385 | I27: 0 | J27: Чт
A28: 46232 | C28: 15724 | D28: 15724 | F28: 74 | G28: 74 | H28: 212.48649 | I28: 180.45 | J28: Ср
A29: 46231 | B29: 98 | C29: 12217 | D29: 12315 | E29: 1 | F29: 53 | G29: 54 | H29: 228.05556 | I29: 182.87 | J29: Вт
A30: 46230 | C30: 6933 | D30: 6933 | F30: 34 | G30: 34 | H30: 203.91176 | I30: 0 | J30: Пн
A31: 46229 | C31: 162 | D31: 162 | F31: 3 | G31: 3 | H31: 54 | I31: 167.99 | J31: Вс
A32: 46228 | C32: 60 | D32: 60 | F32: 1 | G32: 1 | H32: 60 | I32: 55.56 | J32: Сб
A33: 46227 | C33: 9731.2 | D33: 9731.2 | F33: 46 | G33: 46 | H33: 211.54783 | I33: 302.48 | J33: Пт
A34: 46226 | C34: 12666.2 | D34: 12666.2 | F34: 56 | G34: 56 | H34: 226.18214 | I34: 348.97 | J34: Чт
A35: 46225 | C35: 11228.8 | D35: 11228.8 | F35: 53 | G35: 53 | H35: 211.86415 | I35: 116.04 | J35: Ср
A36: 46224 | C36: 9516.1 | D36: 9516.1 | F36: 44 | G36: 44 | H36: 216.275 | I36: 0 | J36: Вт
A37: 46223 | B37: 155 | C37: 8296 | D37: 8451 | E37: 1 | F37: 40 | G37: 41 | H37: 206.12195 | I37: 0 | J37: Пн
A38: 46222 | C38: 210 | D38: 210 | F38: 2 | G38: 2 | H38: 105 | I38: 270.09 | J38: Вс
A39: 46221 | C39: 747 | D39: 747 | F39: 6 | G39: 6 | H39: 124.5 | I39: 253.9 | J39: Сб
A40: 46220 | C40: 12278.6 | D40: 12278.6 | F40: 50 | G40: 50 | H40: 245.572 | I40: 454.74 | J40: Пт
A41: 46219 | C41: 11492.8 | D41: 11492.8 | F41: 50 | G41: 50 | H41: 229.856 | I41: 446.48 | J41: Чт
A42: 46218 | C42: 10610 | D42: 10610 | F42: 50 | G42: 50 | H42: 212.2 | I42: 79.04 | J42: Ср
A43: 46217 | B43: 659 | C43: 12035 | D43: 12694 | E43: 2 | F43: 52 | G43: 54 | H43: 235.07407 | I43: 294.92 | J43: Вт
A44: 46216 | C44: 8420 | D44: 8420 | F44: 38 | G44: 38 | H44: 221.57895 | I44: 0 | J44: Пн
A45: 46215 | C45: 238 | D45: 238 | F45: 1 | G45: 1 | H45: 238 | I45: 76.52 | J45: Вс
A46: 46214 | C46: 45 | D46: 45 | F46: 1 | G46: 1 | H46: 45 | I46: 0 | J46: Сб
A47: 46213 | C47: 13671.6 | D47: 13671.6 | F47: 64 | G47: 64 | H47: 213.61875 | I47: 26.47 | J47: Пт
A48: 46212 | B48: 172 | C48: 12905.3 | D48: 13077.3 | E48: 1 | F48: 54 | G48: 55 | H48: 237.76909 | I48: 83.96 | J48: Чт
A49: 46211 | C49: 9585.9 | D49: 9585.9 | F49: 50 | G49: 50 | H49: 191.718 | I49: 563.63 | J49: Ср
A50: 46210 | C50: 12267.5 | D50: 12267.5 | F50: 57 | G50: 57 | H50: 215.2193 | I50: 208.34 | J50: Вт
A51: 46209 | B51: 98 | C51: 9544.5 | D51: 9642.5 | E51: 1 | F51: 48 | G51: 49 | H51: 196.78571 | I51: 226.2 | J51: Пн
A52: 46208 | C52: 0 | F52: 0 | I52: 103.97 | J52: Вс
A53: 46207 | C53: 45 | D53: 45 | F53: 1 | G53: 1 | H53: 45 | I53: 0 | J53: Сб
A54: 46206 | C54: 12320.5 | D54: 12320.5 | F54: 69 | G54: 69 | H54: 178.55797 | I54: 0 | J54: Пт
A55: 46205 | C55: 12616.9 | D55: 12616.9 | F55: 61 | G55: 61 | H55: 206.83443 | I55: 34.33 | J55: Чт
A56: 46204 | C56: 11080.4 | D56: 11080.4 | F56: 56 | G56: 56 | H56: 197.86429 | I56: 104.25 | J56: Ср
A57: 46203 | C57: 12332.5 | D57: 12332.5 | F57: 58 | G57: 58 | H57: 212.62931 | I57: 173.65 | J57: Вт
A58: 46202 | C58: 12661.5 | D58: 12661.5 | F58: 59 | G58: 59 | H58: 214.60169 | I58: 286.07 | J58: Пн
A59: 46201 | C59: 255 | D59: 255 | F59: 3 | G59: 3 | H59: 85 | I59: 34.33 | J59: Вс
A60: 46200 | C60: 85 | D60: 85 | F60: 1 | G60: 1 | H60: 85 | I60: 0 | J60: Сб
A61: 46199 | B61: 168 | C61: 9480.9 | D61: 9648.9 | E61: 1 | F61: 52 | G61: 53 | H61: 182.05472 | I61: 328.83 | J61: Пт
A62: 46198 | C62: 11513.6 | D62: 11513.6 | F62: 55 | G62: 55 | H62: 209.33818 | I62: 264.58 | J62: Чт
A63: 46197 | C63: 10352 | D63: 10352 | F63: 51 | G63: 51 | H63: 202.98039 | I63: 84.78 | J63: Ср
A64: 46196 | C64: 9591 | D64: 9591 | F64: 52 | G64: 52 | H64: 184.44231 | I64: 0 | J64: Вт | L64: ТОП-3 Целевой аудитории
A65: 46195 | B65: 155 | C65: 11539 | D65: 11694 | E65: 1 | F65: 61 | G65: 62 | H65: 188.6129 | I65: 0 | J65: Пн | L65: пол | M65: возраст | N65: % присутствия | P65: кол-во уникальных гостей
A66: 46192 | B66: 90 | C66: 10299.7 | D66: 10389.7 | E66: 1 | F66: 58 | G66: 59 | H66: 176.09661 | I66: 54.44 | J66: Пт | L66: женщины | M66: 35-45 | N66: 0.33 | P66: 228
A67: 46191 | B67: 138 | C67: 10460 | D67: 10598 | E67: 1 | F67: 53 | G67: 54 | H67: 196.25926 | I67: 819.53 | J67: Чт | L67: мудчины | M67: 35-45 | N67: 0.15
A68: 46190 | B68: 175 | C68: 10148 | D68: 10323 | E68: 1 | F68: 48 | G68: 49 | H68: 210.67347 | I68: 0 | J68: Ср | L68: мужчины | M68: 25-35 | N68: 0.17
A69: 46188 | B69: 60 | C69: 10707.5 | D69: 10767.5 | E69: 1 | F69: 53 | G69: 54 | H69: 199.39815 | I69: 475.09 | J69: Пн
A70: 46187 | C70: 240 | D70: 240 | F70: 2 | G70: 2 | H70: 120 | I70: 196.29 | J70: Вс | L70: График работы | M70: дней в неделю | N70: часы работы
A71: 46186 | C71: 0 | F71: 0 | I71: 133.87 | J71: Сб | M71: 5 | N71: 08:00-17:00
A72: 46185 | C72: 313 | D72: 313 | F72: 3 | G72: 3 | H72: 104.33333 | I72: 59.58 | J72: Пт
A73: 46184 | C73: 8353.9 | D73: 8353.9 | F73: 58 | G73: 58 | H73: 144.03276 | I73: 101.67 | J73: Чт
A74: 46183 | C74: 8516 | D74: 8516 | F74: 38 | G74: 38 | H74: 224.10526 | I74: 0 | J74: Ср
A75: 46182 | C75: 10461.7 | D75: 10461.7 | F75: 62 | G75: 62 | H75: 168.7371 | I75: 0 | J75: Вт
A76: 46181 | C76: 9320.5 | D76: 9320.5 | F76: 50 | G76: 50 | H76: 186.41 | I76: 311.16 | J76: Пн
A77: 46180 | C77: 244 | D77: 244 | F77: 4 | G77: 4 | H77: 61 | I77: 0 | J77: Вс
A78: 46179 | C78: 128 | D78: 128 | F78: 2 | G78: 2 | H78: 64 | I78: 0 | J78: Сб
A79: 46178 | C79: 11725.5 | D79: 11725.5 | F79: 58 | G79: 58 | H79: 202.16379 | I79: 68.94 | J79: Пт
A80: 46177 | C80: 12767.7 | D80: 12767.7 | F80: 58 | G80: 58 | H80: 220.13276 | I80: 92.6 | J80: Чт
A81: 46176 | C81: 12331.8 | D81: 12331.8 | F81: 58 | G81: 58 | H81: 212.61724 | I81: 364.8 | J81: Ср
A82: 46175 | B82: 187 | C82: 8029.5 | D82: 8216.5 | E82: 1 | F82: 40 | G82: 41 | H82: 200.40244 | I82: 102.27 | J82: Вт
A83: 46174 | C83: 10507.5 | D83: 10507.5 | F83: 45 | G83: 45 | H83: 233.5 | I83: 366.98 | J83: Пн
A84: 46172 | C84: 31 | D84: 31 | F84: 1 | G84: 1 | H84: 31 | I84: 66.25 | J84: Сб
A85: 46171 | C85: 8971.4 | D85: 8971.4 | F85: 47 | G85: 47 | H85: 190.88085 | I85: 299.5 | J85: Пт
A86: 46170 | B86: 226 | C86: 9966.2 | D86: 10192.2 | E86: 1 | F86: 52 | G86: 53 | H86: 192.30566 | I86: 112.3 | J86: Чт
A87: 46169 | B87: 178 | C87: 12324.8 | D87: 12502.8 | E87: 1 | F87: 60 | G87: 61 | H87: 204.96393 | I87: 436.77 | J87: Ср
A88: 46168 | B88: 216 | C88: 8953 | D88: 9169 | E88: 1 | F88: 46 | G88: 47 | H88: 195.08511 | I88: 229.78 | J88: Вт
A89: 46167 | B89: 90 | D89: 90 | E89: 1 | G89: 1 | H89: 90 | J89: Пн
A90: 46166 | C90: 189.5 | D90: 189.5 | F90: 3 | G90: 3 | H90: 63.166667 | I90: 0 | J90: Вс
A91: 46165 | C91: 50 | D91: 50 | F91: 1 | G91: 1 | H91: 50 | I91: 251.41 | J91: Сб
A92: 46164 | C92: 10375.3 | D92: 10375.3 | F92: 56 | G92: 56 | H92: 185.27321 | I92: 355.13 | J92: Пт
A93: 46163 | C93: 10953.6 | D93: 10953.6 | F93: 51 | G93: 51 | H93: 214.77647 | I93: 589.47 | J93: Чт
A94: 46162 | B94: 666 | C94: 10075 | D94: 10741 | E94: 4 | F94: 44 | G94: 48 | H94: 223.77083 | I94: 438.35 | J94: Ср
A95: 46161 | B95: 443 | C95: 8949.4 | D95: 9392.4 | E95: 3 | F95: 41 | G95: 44 | H95: 213.46364 | I95: 188.73 | J95: Вт
A96: 46160 | B96: 584 | C96: 8649 | D96: 9233 | E96: 2 | F96: 41 | G96: 43 | H96: 214.72093 | I96: 823.18 | J96: Пн
A97: 46159 | C97: 302 | D97: 302 | F97: 1 | G97: 1 | H97: 302 | I97: 737.23 | J97: Вс
A98: 46158 | C98: 0 | F98: 0 | I98: 147.37 | J98: Сб
A99: 46157 | B99: 214 | C99: 9558.4 | D99: 9772.4 | E99: 2 | F99: 38 | G99: 40 | H99: 244.31 | I99: 439.53 | J99: Пт
A100: 46156 | B100: 1233 | C100: 8318.6 | D100: 9551.6 | E100: 4 | F100: 35 | G100: 39 | H100: 244.91282 | I100: 65.55 | J100: Чт
...

Sheet 10
A1: Точка | B1: 10 | C1: Дата запуска | D1: 45357 | E1: Тип точки | F1: медицина | G1: Активна | H1: Да | K1: Стоимость обслуживания | L1: Аренда | M1: Коммуналка | N1: Клининг
A2: Среднее | B2: 200.82353 | C2: 9864.1525 | D2: 9886.613 | E2: 1.2352941 | F2: 59.105263 | G2: 59.243421 | H2: 168.01002 | I2: 563.05645 | K2: =SUM(L2:Q2) -> 3810 | L2: 3510 | N2: 300
A3: Дата | B3: $ QR-код | C3: $ Касса | D3: $ Итог | E3: Чеки QR | F3: Чеки Касса | G3: Чеки Итог | H3: Ср.-й чек | I3: Списания | J3: д/н
A4: 46257 | C4: 2857.4 | D4: 2857.4 | F4: 23 | G4: 23 | H4: 124.23478 | I4: 511.54 | J4: Вс
A5: 46256 | C5: 5140.4 | D5: 5140.4 | F5: 29 | G5: 29 | H5: 177.25517 | I5: 807.71 | J5: Сб
A6: 46255 | C6: 8234.2 | D6: 8234.2 | F6: 55 | G6: 55 | H6: 149.71273 | I6: 400.1 | J6: Пт
A7: 46254 | C7: 6944 | D7: 6944 | F7: 40 | G7: 40 | H7: 173.6 | I7: 71.02 | J7: Чт
A8: 46253 | C8: 6081 | D8: 6081 | F8: 38 | G8: 38 | H8: 160.02632 | I8: 149.09 | J8: Ср
A9: 46252 | C9: 9704 | D9: 9704 | F9: 62 | G9: 62 | H9: 156.51613 | I9: 2317.17 | J9: Вт
A10: 46251 | B10: 178 | C10: 6319.8 | D10: 6497.8 | E10: 1 | F10: 43 | G10: 44 | H10: 147.67727 | I10: 233.17 | J10: Пн
A11: 46250 | C11: 2401 | D11: 2401 | F11: 23 | G11: 23 | H11: 104.3913 | I11: 2534.44 | J11: Вс
A12: 46249 | C12: 4722.4 | D12: 4722.4 | F12: 34 | G12: 34 | H12: 138.89412 | I12: 1918.52 | J12: Сб
A13: 46248 | C13: 6292.8 | D13: 6292.8 | F13: 52 | G13: 52 | H13: 121.01538 | I13: 0 | J13: Пт
A14: 46247 | C14: 8622 | D14: 8622 | F14: 50 | G14: 50 | H14: 172.44 | I14: 99.51 | J14: Чт
A15: 46246 | C15: 6523.6 | D15: 6523.6 | F15: 42 | G15: 42 | H15: 155.32381 | I15: 0 | J15: Ср
A16: 46245 | C16: 4139.8 | D16: 4139.8 | F16: 37 | G16: 37 | H16: 111.88649 | I16: 259.42 | J16: Вт
A17: 46244 | C17: 9873.2 | D17: 9873.2 | F17: 56 | G17: 56 | H17: 176.30714 | I17: 1374.83 | J17: Пн
A18: 46243 | C18: 4174 | D18: 4174 | F18: 24 | G18: 24 | H18: 173.91667 | I18: 1221.43 | J18: Вс
A19: 46242 | C19: 4063.8 | D19: 4063.8 | F19: 34 | G19: 34 | H19: 119.52353 | I19: 2200.04 | J19: Сб
A20: 46241 | C20: 5548.8 | D20: 5548.8 | F20: 39 | G20: 39 | H20: 142.27692 | I20: 964.79 | J20: Пт
A21: 46240 | C21: 9788 | D21: 9788 | F21: 55 | G21: 55 | H21: 177.96364 | I21: 843.24 | J21: Чт
A22: 46239 | C22: 8953.4 | D22: 8953.4 | F22: 47 | G22: 47 | H22: 190.49787 | I22: 67.47 | J22: Ср
... A29: 46232 | C29: 13533.8 | D29: 13533.8 | F29: 81 | G29: 81 | H29: 167.08395 | I29: 92.65 | J29: Ср
A30: 46231 | B30: 120 | C30: 9613.2 | D30: 9733.2 | E30: 1 | F30: 47 | G30: 48 | H30: 202.775 | I30: 939.69 | J30: Вт
A31: 46230 | C31: 8529 | D31: 8529 | F31: 56 | G31: 56 | H31: 152.30357 | I31: 681.77 | J31: Пн
A32: 46229 | C32: 5392 | D32: 5392 | F32: 37 | G32: 37 | H32: 145.72973 | I32: 1311.15 | J32: Вс
A33: 46228 | C33: 8425.4 | D33: 8425.4 | F33: 60 | G33: 60 | H33: 140.42333 | I33: 1694.08 | J33: Сб
A34: 46227 | C34: 11537.2 | D34: 11537.2 | F34: 74 | G34: 74 | H34: 155.90811 | I34: 922.73 | J34: Пт
A35: 46226 | C35: 9815.8 | D35: 9815.8 | F35: 59 | G35: 59 | H35: 166.36949 | I35: 25.16 | J35: Чт
A36: 46225 | C36: 8127.2 | D36: 8127.2 | F36: 50 | G36: 50 | H36: 162.544 | I36: 696.68 | J36: Ср
A37: 46224 | C37: 10410.4 | D37: 10410.4 | F37: 60 | G37: 60 | H37: 173.50667 | I37: 1704.61 | J37: Вт
A38: 46223 | C38: 9777 | D38: 9777 | F38: 53 | G38: 53 | H38: 184.4717 | I38: 247.57 | J38: Пн
A39: 46222 | C39: 4945.4 | D39: 4945.4 | F39: 35 | G39: 35 | H39: 141.29714 | I39: 709.32 | J39: Вс
A40: 46221 | C40: 7698 | D40: 7698 | F40: 56 | G40: 56 | H40: 137.46429 | I40: 1655.06 | J40: Сб
A41: 46220 | C41: 9460.2 | D41: 9460.2 | F41: 59 | G41: 59 | H41: 160.34237 | I41: 847.94 | J41: Пт
A42: 46219 | C42: 12338.2 | D42: 12338.2 | F42: 70 | G42: 70 | H42: 176.26 | I42: 556.64 | J42: Чт
... A44: 46217 | C44: 9138.8 | D44: 9138.8 | F44: 58 | G44: 58 | H44: 157.56552 | I44: 1128.74 | J44: Вт
A45: 46216 | B45: 200 | C45: 6816.6 | D45: 7016.6 | E45: 1 | F45: 43 | G45: 44 | H45: 159.46818 | I45: 189.99 | J45: Пн
A46: 46215 | C46: 8060 | D46: 8060 | F46: 44 | G46: 44 | H46: 183.18182 | I46: 445.42 | J46: Вс
A47: 46214 | C47: 6514.6 | D47: 6514.6 | F47: 48 | G47: 48 | H47: 135.72083 | I47: 1272.45 | J47: Сб
A48: 46213 | C48: 7704.4 | D48: 7704.4 | F48: 53 | G48: 53 | H48: 145.36604 | I48: 100.77 | J48: Пт
A49: 46212 | B49: 190 | C49: 14529.4 | D49: 14719.4 | E49: 2 | F49: 81 | G49: 83 | H49: 177.34217 | I49: 0 | J49: Чт
A50: 46211 | C50: 10566 | D50: 10566 | F50: 63 | G50: 63 | H50: 167.71429 | I50: 169.61 | J50: Ср
A51: 46210 | C51: 11327 | D51: 11327 | F51: 69 | G51: 69 | H51: 164.15942 | I51: 93.85 | J51: Вт
A52: 46209 | C52: 14570.4 | D52: 14570.4 | F52: 85 | G52: 85 | H52: 171.41647 | I52: 1890.87 | J52: Пн
A53: 46208 | C53: 7031.6 | D53: 7031.6 | F53: 48 | G53: 48 | H53: 146.49167 | I53: 2416.33 | J53: Вс
A54: 46207 | C54: 6809.2 | D54: 6809.2 | F54: 52 | G54: 52 | H54: 130.94615 | I54: 192.13 | J54: Сб
A55: 46206 | C55: 11157.4 | D55: 11157.4 | F55: 64 | G55: 64 | H55: 174.33437 | I55: 2692.09 | J55: Пт
A56: 46205 | C56: 10571 | D56: 10571 | F56: 60 | G56: 60 | H56: 176.18333 | I56: 27.9 | J56: Чт
A57: 46204 | C57: 13079 | D57: 13079 | F57: 79 | G57: 79 | H57: 165.55696 | I57: 0 | J57: Ср
A58: 46203 | C58: 12710 | D58: 12710 | F58: 73 | G58: 73 | H58: 174.10959 | I58: 378.24 | J58: Вт
A59: 46202 | C59: 11385.2 | D59: 11385.2 | F59: 67 | G59: 67 | H59: 169.92836 | I59: 1883.39 | J59: Пн
A60: 46201 | C60: 9181.8 | D60: 9181.8 | F60: 59 | G60: 59 | H60: 155.62373 | I60: 2148.24 | J60: Вс
A61: 46200 | C61: 8973.6 | D61: 8973.6 | F61: 58 | G61: 58 | H61: 154.71724 | I61: 1429 | J61: Сб
... A63: 46198 | C63: 9473.8 | D63: 9473.8 | F63: 56 | G63: 56 | H63: 169.175 | I63: 576.21 | J63: Чт
A64: 46197 | C64: 9428 | D64: 9428 | F64: 60 | G64: 60 | H64: 157.13333 | I64: 776.39 | J64: Ср | L64: ТОП-3 Целевой аудитории
A65: 46196 | C65: 9412.1 | D65: 9412.1 | F65: 61 | G65: 61 | H65: 154.29672 | I65: 296.66 | J65: Вт | L65: пол | M65: возраст | N65: % присутствия | P65: кол-во уникальных гостей
A66: 46195 | B66: 159 | C66: 12546.6 | D66: 12705.6 | E66: 1 | F66: 81 | G66: 82 | H66: 154.94634 | I66: 1289.61 | J66: Пн | L66: женщины | M66: 25-35 | N66: 0.23 | P66: 290
A67: 46194 | C67: 4949 | D67: 4949 | F67: 33 | G67: 33 | H67: 149.9697 | I67: 57.36 | J67: Вс | L67: мужчины | M67: 25-35 | N67: 0.17
A68: 46193 | C68: 8943.6 | D68: 8943.6 | F68: 56 | G68: 56 | H68: 159.70714 | I68: 1085.12 | J68: Сб | L68: женщины | M68: 18-25 | N68: 0.12
A69: 46192 | C69: 10359.4 | D69: 10359.4 | F69: 68 | G69: 68 | H69: 152.34412 | I69: 304.27 | J69: Пт
A70: 46191 | C70: 12601.8 | D70: 12601.8 | F70: 69 | G70: 69 | H70: 182.63478 | I70: 890.41 | J70: Чт | L70: График работы | M70: дней в неделю | N70: часы работы
A71: 46190 | C71: 9634.4 | D71: 9634.4 | F71: 51 | G71: 51 | H71: 188.9098 | I71: 0 | J71: Ср | M71: 7 | N71: 00:00-23:00
A72: 46188 | C72: 10248.4 | D72: 10248.4 | F72: 62 | G72: 62 | H72: 165.29677 | I72: 1003.63 | J72: Пн
A73: 46187 | B73: 212 | C73: 7519.4 | D73: 7731.4 | E73: 1 | F73: 39 | G73: 40 | H73: 193.285 | I73: 1950.55 | J73: Вс
A74: 46186 | B74: 200 | C74: 5872.9 | D74: 6072.9 | E74: 1 | F74: 44 | G74: 45 | H74: 134.95333 | I74: 1228.42 | J74: Сб
A75: 46185 | C75: 9246.5 | D75: 9246.5 | F75: 58 | G75: 58 | H75: 159.42241 | I75: 1067.9 | J75: Пт
A76: 46184 | C76: 9452.3 | D76: 9452.3 | F76: 56 | G76: 56 | H76: 168.79107 | I76: 333.06 | J76: Чт
A77: 46183 | C77: 11488.3 | D77: 11488.3 | F77: 69 | G77: 69 | H77: 166.4971 | I77: 61.42 | J77: Ср
A78: 46182 | C78: 8558.55 | D78: 8558.55 | F78: 50 | G78: 50 | H78: 171.171 | I78: 60.04 | J78: Вт
A79: 46181 | C79: 9533.5 | D79: 9533.5 | F79: 56 | G79: 56 | H79: 170.24107 | I79: 484.53 | J79: Пн
A80: 46180 | C80: 6004.3 | D80: 6004.3 | F80: 40 | G80: 40 | H80: 150.1075 | I80: 1216.82 | J80: Вс
A81: 46179 | C81: 5903.6 | D81: 5903.6 | F81: 38 | G81: 38 | H81: 155.35789 | I81: 1033.9 | J81: Сб
A82: 46178 | C82: 12617.75 | D82: 12617.75 | F82: 67 | G82: 67 | H82: 188.32463 | I82: 0 | J82: Пт
A83: 46177 | C83: 13048.34 | D83: 13048.34 | F83: 70 | G83: 70 | H83: 186.40486 | I83: 72.36 | J83: Чт
A84: 46176 | C84: 9394.5 | D84: 9394.5 | F84: 61 | G84: 61 | H84: 154.0082 | I84: 62.41 | J84: Ср
A85: 46175 | C85: 10497.25 | D85: 10497.25 | F85: 61 | G85: 61 | H85: 172.08607 | I85: 0 | J85: Вт
A86: 46174 | B86: 610 | C86: 11470.3 | D86: 12080.3 | E86: 2 | F86: 56 | G86: 58 | H86: 208.28103 | I86: 144.67 | J86: Пн
A87: 46172 | C87: 7455 | D87: 7455 | F87: 50 | G87: 50 | H87: 149.1 | I87: 998.66 | J87: Сб
A88: 46171 | B88: 208 | C88: 11520.9 | D88: 11728.9 | E88: 1 | F88: 69 | G88: 70 | H88: 167.55571 | I88: 179.42 | J88: Пт
A89: 46170 | C89: 8184.5 | D89: 8184.5 | F89: 49 | G89: 49 | H89: 167.03061 | I89: 446.91 | J89: Чт
A90: 46169 | B90: 25 | C90: 11703 | D90: 11728 | E90: 1 | F90: 71 | G90: 72 | H90: 162.88889 | I90: 171.24 | J90: Ср
A91: 46168 | C91: 9436.9 | D91: 9436.9 | F91: 62 | G91: 62 | H91: 152.20806 | I91: 1683.41 | J91: Вт
A92: 46166 | C92: 4593.5 | D92: 4593.5 | F92: 36 | G92: 36 | H92: 127.59722 | I92: 728.62 | J92: Вс
A93: 46165 | C93: 6538.3 | D93: 6538.3 | F93: 49 | G93: 49 | H93: 133.43469 | I93: 1321.68 | J93: Сб
A94: 46164 | C94: 11515.2 | D94: 11515.2 | F94: 72 | G94: 72 | H94: 159.93333 | I94: 364.34 | J94: Пт
A95: 46163 | C95: 10629 | D95: 10629 | F95: 64 | G95: 64 | H95: 166.07812 | I95: 476.79 | J95: Чт
A96: 46162 | C96: 11298 | D96: 11298 | F96: 62 | G96: 62 | H96: 182.22581 | I96: 0 | J96: Ср
A97: 46161 | C97: 10866.6 | D97: 10866.6 | F97: 70 | G97: 70 | H97: 155.23714 | I97: 1159.19 | J97: Вт
A98: 46160 | C98: 10729.2 | D98: 10729.2 | F98: 61 | G98: 61 | H98: 175.88852 | I98: 576.8 | J98: Пн
A99: 46159 | C99: 5146.1 | D99: 5146.1 | F99: 33 | G99: 33 | H99: 155.94242 | I99: 1259.31 | J99: Вс
A100: 46158 | C100: 7585.3 | D100: 7585.3 | F100: 37 | G100: 37 | H100: 205.00811 | I100: 2440.86 | J100: Сб
A101: 46157 | C101: 10496 | D101: 10496 | F101: 63 | G101: 63 | H101: 166.60317 | I101: 388.54 | J101: Пт
A102: 46156 | C102: 12196.9 | D102: 12196.9 | F102: 73 | G102: 73 | H102: 167.08082 | I102: 122.24 | J102: Чт
... A120: 46137 | C120: 10647.9 | D120: 10647.9 | F120: 64 | G120: 64 | H120: 166.37344 | I120: 1360.53 | J120: Сб
A121: 46136 | B121: 178 | C121: 10661.6 | D121: 10839.6 | E121: 1 | F121: 62 | G121: 63 | H121: 172.05714 | I121: 658.24 | J121: Пт
A122: 46134 | C122: 6810.5 | D122: 6810.5 | F122: 52 | G122: 52 | H122: 130.97115 | I122: 397.6 | J122: Ср
A123: 46133 | C123: 10700.4 | D123: 10700.4 | F123: 54 | G123: 54 | H123: 198.15556 | I123: 1286.22 | J123: Вт
A124: 46132 | B124: 240 | C124: 7837.5 | D124: 8077.5 | E124: 1 | F124: 45 | G124: 46 | H124: 175.59783 | I124: 237.25 | J124: Пн
A125: 46131 | C125: 7724.9 | D125: 7724.9 | F125: 57 | G125: 57 | H125: 135.52456 | I125: 320.39 | J125: Вс
...

Sheet 11
A1: Точка | B1: 11 | C1: Дата запуска | E1: Тип точки | F1: завод | G1: Активна | H1: Нет | K1: Стоимость обслуживания | L1: Аренда | M1: Коммуналка | N1: Клининг
A2: Среднее | C2: 0 | F2: 0 | I2: 94.223333 | L2: 0 | M2: 0 | N2: 300
A3: Дата | B3: $ QR-код | C3: $ Касса | D3: $ Итог | E3: Чеки QR | F3: Чеки Касса | G3: Чеки Итог | H3: Ср.-й чек | I3: Списания | J3: д/н
A4: 46232 | C4: 0 | F4: 0 | I4: 92.65 | J4: Ср
A5: 46231 | C5: 0 | F5: 0 | I5: 87.73 | J5: Вт
A6: 46230 | C6: 0 | F6: 0 | I6: 102.29 | J6: Пн
L64: ТОП-3 Целевой аудитории
L65: пол | M65: возраст | N65: % присутствия | P65: кол-во уникальных гостей
L66: женщины
L67: женщины
L68: женщины
L70: График работы | M70: дней в неделю | N70: часы работы

Sheet 12
A1: Точка | B1: 12 | C1: Дата запуска | D1: 45509 | E1: Тип точки | F1: завод | G1: Активна | H1: Да | K1: Стоимость обслуживания | L1: Аренда | M1: Коммуналка | N1: Клининг
A2: Среднее | B2: 113.66667 | C2: 6141.9983 | D2: 6144.2566 | E2: 1 | F2: 41.953642 | G2: 41.97351 | H2: 148.29333 | I2: 222.51589 | K2: =SUM(L2:Q2) -> 4800 | L2: 4500 | M2: 0 | N2: 300
A3: Дата | B3: $ QR-код | C3: $ Касса | D3: $ Итог | E3: Чеки QR | F3: Чеки Касса | G3: Чеки Итог | H3: Ср.-й чек | I3: Списания | J3: д/н
A4: 46257 | C4: 0 | F4: 1 | G4: 1 | H4: 0 | I4: 0 | J4: Вс
A5: 46255 | C5: 6039.2 | D5: 6039.2 | F5: 36 | G5: 36 | H5: 167.75556 | I5: 23.76 | J5: Пт
A6: 46254 | C6: 6358 | D6: 6358 | F6: 41 | G6: 41 | H6: 155.07317 | I6: 83.72 | J6: Чт
A7: 46253 | C7: 6537.4 | D7: 6537.4 | F7: 39 | G7: 39 | H7: 167.62564 | I7: 0 | J7: Ср
A8: 46252 | C8: 6900 | D8: 6900 | F8: 42 | G8: 42 | H8: 164.28571 | I8: 0 | J8: Вт
A9: 46251 | C9: 6098 | D9: 6098 | F9: 41 | G9: 41 | H9: 148.73171 | I9: 0 | J9: Пн
A10: 46250 | C10: 153 | D10: 153 | F10: 1 | G10: 1 | H10: 153 | I10: 0 | J10: Вс
A11: 46248 | C11: 5643.8 | D11: 5643.8 | F11: 45 | G11: 45 | H11: 125.41778 | I11: 294.1 | J11: Пт
A12: 46247 | C12: 6195.4 | D12: 6195.4 | F12: 39 | G12: 39 | H12: 158.85641 | I12: 168.83 | J12: Чт
A13: 46246 | C13: 6189 | D13: 6189 | F13: 33 | G13: 33 | H13: 187.54545 | I13: 433.65 | J13: Ср
A14: 46245 | C14: 6264.4 | D14: 6264.4 | F14: 34 | G14: 34 | H14: 184.24706 | I14: 0 | J14: Вт
A15: 46244 | C15: 4485 | D15: 4485 | F15: 24 | G15: 24 | H15: 186.875 | I15: 87.08 | J15: Пн
A16: 46243 | C16: 90 | D16: 90 | F16: 1 | G16: 1 | H16: 90 | I16: 0 | J16: Вс
... A22: 46237 | C22: 5411 | D22: 5411 | F22: 31 | G22: 31 | H22: 174.54839 | I22: 309.79 | J22: Пн
A23: 46236 | C23: 0 | F23: 1 | G23: 1 | H23: 0 | I23: 63.31 | J23: Вс
A24: 46235 | C24: 450 | D24: 450 | F24: 5 | G24: 5 | H24: 90 | I24: 0 | J24: Сб
A25: 46234 | C25: 5087.6 | D25: 5087.6 | F25: 38 | G25: 38 | H25: 133.88421 | I25: 493.81 | J25: Пт
A26: 46233 | C26: 9306.4 | D26: 9306.4 | F26: 54 | G26: 54 | H26: 172.34074 | I26: 251.62 | J26: Чт
A27: 46232 | C27: 6185 | D27: 6185 | F27: 38 | G27: 38 | H27: 162.76316 | I27: 260.83 | J27: Ср
A28: 46231 | C28: 6583 | D28: 6583 | F28: 41 | G28: 41 | H28: 160.56098 | I28: 290.03 | J28: Вт
A29: 46230 | C29: 6715 | D29: 6715 | F29: 36 | G29: 36 | H29: 186.52778 | I29: 0 | J29: Пн
A30: 46229 | C30: 0 | F30: 0 | I30: 151.2 | J30: Вс
A31: 46228 | C31: 42 | D31: 42 | F31: 1 | G31: 1 | H31: 42 | I31: 163.19 | J31: Сб
A32: 46227 | C32: 3888.4 | D32: 3888.4 | F32: 28 | G32: 28 | H32: 138.87143 | I32: 789.4 | J32: Пт
A33: 46226 | C33: 6222.4 | D33: 6222.4 | F33: 36 | G33: 36 | H33: 172.84444 | I33: 399.48 | J33: Чт
A34: 46225 | C34: 4564.2 | D34: 4564.2 | F34: 25 | G34: 25 | H34: 182.568 | I34: 23.56 | J34: Ср
A35: 46224 | C35: 3044.8 | D35: 3044.8 | F35: 19 | G35: 19 | H35: 160.25263 | I35: 0 | J35: Вт
A36: 46223 | C36: 5800 | D36: 5800 | F36: 34 | G36: 34 | H36: 170.58824 | I36: 74.71 | J36: Пн
A37: 46222 | C37: 92 | D37: 92 | F37: 1 | G37: 1 | H37: 92 | I37: 73.74 | J37: Вс
A38: 46221 | C38: 0 | F38: 0 | I38: 52.92 | J38: Сб
A39: 46220 | C39: 8310.4 | D39: 8310.4 | F39: 46 | G39: 46 | H39: 180.66087 | I39: 194.85 | J39: Пт
A40: 46219 | C40: 6812.6 | D40: 6812.6 | F40: 35 | G40: 35 | H40: 194.64571 | I40: 33.54 | J40: Чт
A41: 46218 | C41: 5865 | D41: 5865 | F41: 36 | G41: 36 | H41: 162.91667 | I41: 0 | J41: Ср
A42: 46217 | C42: 5848.65 | D42: 5848.65 | F42: 36 | G42: 36 | H42: 162.4625 | I42: 0 | J42: Вт
A43: 46216 | C43: 5609.3 | D43: 5609.3 | F43: 33 | G43: 33 | H43: 169.97879 | I43: 0 | J43: Пн
A44: 46215 | C44: 90 | D44: 90 | F44: 1 | G44: 1 | H44: 90 | I44: 0 | J44: Вс
A45: 46214 | C45: 30 | D45: 30 | F45: 1 | G45: 1 | H45: 30 | I45: 358.56 | J45: Сб
A46: 46213 | C46: 4619.1 | D46: 4619.1 | F46: 33 | G46: 33 | H46: 139.97273 | I46: 268.85 | J46: Пт
A47: 46212 | C47: 7083.2 | D47: 7083.2 | F47: 41 | G47: 41 | H47: 172.76098 | I47: 0 | J47: Чт
A48: 46211 | C48: 5424.3 | D48: 5424.3 | F48: 37 | G48: 37 | H48: 146.6027 | I48: 0 | J48: Ср
A49: 46210 | C49: 5755.5 | D49: 5755.5 | F49: 37 | G49: 37 | H49: 155.55405 | I49: 69.45 | J49: Вт
A50: 46209 | C50: 4678.5 | D50: 4678.5 | F50: 31 | G50: 31 | H50: 150.91935 | I50: 0 | J50: Пн
A51: 46208 | B51: 242.5 | D51: 242.5 | E51: 1 | G51: 1 | H51: 242.5 | J51: Вс
A52: 46206 | C52: 6272.1 | D52: 6272.1 | F52: 36 | G52: 36 | H52: 174.225 | I52: 544.41 | J52: Пт
A53: 46205 | C53: 5373.3 | D53: 5373.3 | F53: 33 | G53: 33 | H53: 162.82727 | I53: 343.29 | J53: Чт
A54: 46204 | C54: 4892.7 | D54: 4892.7 | F54: 35 | G54: 35 | H54: 139.79143 | I54: 71.74 | J54: Ср
A55: 46203 | C55: 5031 | D55: 5031 | F55: 28 | G55: 28 | H55: 179.67857 | I55: 0 | J55: Вт
A56: 46202 | C56: 6201 | D56: 6201 | F56: 34 | G56: 34 | H56: 182.38235 | I56: 56.5 | J56: Пн
A57: 46201 | C57: 309 | D57: 309 | F57: 1 | G57: 1 | H57: 309 | I57: 0 | J57: Вс
A58: 46200 | C58: 95 | D58: 95 | F58: 1 | G58: 1 | H58: 95 | I58: 17.71 | J58: Сб
A59: 46199 | C59: 4027.5 | D59: 4027.5 | F59: 29 | G59: 29 | H59: 138.87931 | I59: 0 | J59: Пт
A60: 46198 | C60: 7168.8 | D60: 7168.8 | F60: 44 | G60: 44 | H60: 162.92727 | I60: 563.32 | J60: Чт
A61: 46197 | C61: 6174.5 | D61: 6174.5 | F61: 42 | G61: 42 | H61: 147.0119 | I61: 29.29 | J61: Ср
A62: 46196 | C62: 6579 | D62: 6579 | F62: 40 | G62: 40 | H62: 164.475 | I62: 0 | J62: Вт
A63: 46195 | C63: 7209 | D63: 7209 | F63: 36 | G63: 36 | H63: 200.25 | I63: 0 | J63: Пн
A64: 46194 | C64: 143 | D64: 143 | F64: 1 | G64: 1 | H64: 143 | I64: 0 | J64: Вс | L64: ТОП-3 Целевой аудитории
A65: 46193 | C65: 0 | F65: 0 | I65: 34.64 | J65: Сб | L65: пол | M65: возраст | N65: % присутствия | P65: кол-во уникальных гостей
A66: 46192 | C66: 6557.7 | D66: 6557.7 | F66: 43 | G66: 43 | H66: 152.50465 | I66: 268.32 | J66: Пт | L66: женщины | M66: 35-45 | N66: 0.3 | P66: 125
A67: 46191 | C67: 8203 | D67: 8203 | F67: 44 | G67: 44 | H67: 186.43182 | I67: 733.3 | J67: Чт | L67: мужчины | M67: 35-45 | N67: 0.17
A68: 46190 | C68: 4163 | D68: 4163 | F68: 28 | G68: 28 | H68: 148.67857 | I68: 84.08 | J68: Ср | L68: женщины | M68: 45-55 | N68: 0.13
A69: 46188 | C69: 8631 | D69: 8631 | F69: 48 | G69: 48 | H69: 179.8125 | I69: 0 | J69: Пн
A70: 46187 | C70: 0 | F70: 0 | I70: 58.07 | J70: Вс | L70: График работы | M70: дней в неделю | N70: часы работы
A71: 46184 | C71: 6660.6 | D71: 6660.6 | F71: 54 | G71: 54 | H71: 123.34444 | I71: 275.08 | J71: Чт | M71: 5 | N71: 08:00-17:00
A72: 46183 | C72: 5779 | D72: 5779 | F72: 38 | G72: 38 | H72: 152.07895 | I72: 63.6 | J72: Ср
A73: 46182 | C73: 6773.5 | D73: 6773.5 | F73: 36 | G73: 36 | H73: 188.15278 | I73: 0 | J73: Вт
A74: 46181 | C74: 6785 | D74: 6785 | F74: 42 | G74: 42 | H74: 161.54762 | I74: 311.16 | J74: Пн
A75: 46180 | C75: 0 | F75: 0 | I75: 0 | J75: Вс
A76: 46179 | C76: 0 | F76: 0 | I76: 1049.55 | J76: Сб
A77: 46178 | C77: 7218.1 | D77: 7218.1 | F77: 43 | G77: 43 | H77: 167.86279 | I77: 0 | J77: Пт
A78: 46177 | C78: 4769.65 | D78: 4769.65 | F78: 33 | G78: 33 | H78: 144.53485 | I78: 68.57 | J78: Чт
A79: 46176 | C79: 6444.6 | D79: 6444.6 | F79: 46 | G79: 46 | H79: 140.1 | I79: 187.1 | J79: Ср
A80: 46174 | C80: 7639 | D80: 7639 | F80: 44 | G80: 44 | H80: 173.61364 | I80: 35.32 | J80: Пн
A81: 46171 | C81: 6456.7 | D81: 6456.7 | F81: 41 | G81: 41 | H81: 157.48049 | I81: 767.99 | J81: Пт
A82: 46170 | C82: 7145.3 | D82: 7145.3 | F82: 43 | G82: 43 | H82: 166.16977 | I82: 236.97 | J82: Чт
A83: 46169 | C83: 7420.1 | D83: 7420.1 | F83: 43 | G83: 43 | H83: 172.56047 | I83: 0 | J83: Ср
A84: 46168 | C84: 7735.5 | D84: 7735.5 | F84: 48 | G84: 48 | H84: 161.15625 | I84: 0 | J84: Вт
A85: 46166 | C85: 0 | F85: 0 | I85: 79.42 | J85: Вс
A86: 46164 | C86: 6062.2 | D86: 6062.2 | F86: 41 | G86: 41 | H86: 147.85854 | I86: 1133.35 | J86: Пт
A87: 46163 | C87: 7093.2 | D87: 7093.2 | F87: 51 | G87: 51 | H87: 139.08235 | I87: 629.71 | J87: Чт
A88: 46162 | C88: 5283 | D88: 5283 | F88: 39 | G88: 39 | H88: 135.46154 | I88: 0 | J88: Ср
A89: 46161 | C89: 7681 | D89: 7681 | F89: 47 | G89: 47 | H89: 163.42553 | I89: 0 | J89: Вт
A90: 46160 | C90: 7507.5 | D90: 7507.5 | F90: 44 | G90: 44 | H90: 170.625 | I90: 0 | J90: Пн
A91: 46159 | C91: 0 | F91: 0 | I91: 0 | J91: Вс
A92: 46157 | C92: 8094.1 | D92: 8094.1 | F92: 54 | G92: 54 | H92: 149.89074 | I92: 633.25 | J92: Пт
A93: 46156 | C93: 7579.3 | D93: 7579.3 | F93: 48 | G93: 48 | H93: 157.90208 | I93: 234.12 | J93: Чт
A94: 46155 | C94: 5977.5 | D94: 5977.5 | F94: 42 | G94: 42 | H94: 142.32143 | I94: 393.02 | J94: Ср
A95: 46154 | C95: 3712.5 | D95: 3712.5 | F95: 26 | G95: 26 | H95: 142.78846 | I95: 0 | J95: Вт
A96: 46151 | C96: 0 | F96: 0 | I96: 40.17 | J96: Сб
A97: 46150 | C97: 5850.4 | D97: 5850.4 | F97: 42 | G97: 42 | H97: 139.29524 | I97: 763.17 | J97: Пт
A98: 46149 | C98: 9144.5 | D98: 9144.5 | F98: 54 | G98: 54 | H98: 169.34259 | I98: 930.55 | J98: Чт
A99: 46148 | C99: 6221 | D99: 6221 | F99: 42 | G99: 42 | H99: 148.11905 | I99: 0 | J99: Ср
A100: 46147 | C100: 5622.5 | D100: 5622.5 | F100: 38 | G100: 38 | H100: 147.96053 | I100: 143.32 | J100: Вт
A101: 46146 | C101: 8880 | D101: 8880 | F101: 56 | G101: 56 | H101: 158.57143 | I101: 0 | J101: Пн
A102: 46142 | C102: 8611.3 | D102: 8611.3 | F102: 53 | G102: 53 | H102: 162.47736 | I102: 1022.95 | J102: Чт
A103: 46141 | C103: 7088.9 | D103: 7088.9 | F103: 54 | G103: 54 | H103: 131.27593 | I103: 0 | J103: Ср
A104: 46140 | C104: 9178.5 | D104: 9178.5 | F104: 63 | G104: 63 | H104: 145.69048 | I104: 97.84 | J104: Вт
A105: 46139 | C105: 6413 | D105: 6413 | F105: 32 | G105: 32 | H105: 200.40625 | I105: 0 | J105: Пн
...

Sheet 13
A1: Точка | B1: 13 | C1: Дата запуска | D1: 45523 | E1: Тип точки | F1: завод | G1: Активна | H1: Да | K1: Стоимость обслуживания | L1: Аренда | M1: Коммуналка | N1: Клининг
A2: Среднее | B2: 266.875 | C2: 6260.6864 | D2: 6274.8255 | E2: 1.5 | F2: 53.072848 | G2: 53.152318 | H2: 126.24771 | I2: 265.27927 | K2: =SUM(L2:Q2) -> 4800 | L2: 4500 | M2: 0 | N2: 300
A3: Дата | B3: $ QR-код | C3: $ Касса | D3: $ Итог | E3: Чеки QR | F3: Чеки Касса | G3: Чеки Итог | H3: Ср.-й чек | I3: Списания | J3: д/н
A4: 46257 | C4: 257 | D4: 257 | F4: 2 | G4: 2 | H4: 128.5 | I4: 0 | J4: Вс
A5: 46256 | C5: 103 | D5: 103 | F5: 2 | G5: 2 | H5: 51.5 | I5: 623.22 | J5: Сб
A6: 46255 | C6: 5886.2 | D6: 5886.2 | F6: 33 | G6: 33 | H6: 178.3697 | I6: 503.92 | J6: Пт
A7: 46254 | C7: 7379.35 | D7: 7379.35 | F7: 42 | G7: 42 | H7: 175.69881 | I7: 95.54 | J7: Чт
A8: 46253 | C8: 6747.1 | D8: 6747.1 | F8: 38 | G8: 38 | H8: 177.55526 | I8: 40.98 | J8: Ср
A9: 46252 | C9: 5806.65 | D9: 5806.65 | F9: 34 | G9: 34 | H9: 170.78382 | I9: 0 | J9: Вт
A10: 46251 | C10: 5071 | D10: 5071 | F10: 32 | G10: 32 | H10: 158.46875 | I10: 0 | J10: Пн
A11: 46250 | C11: 0 | F11: 0 | I11: 0 | J11: Вс
A12: 46248 | C12: 5266.4 | D12: 5266.4 | F12: 36 | G12: 36 | H12: 146.28889 | I12: 0 | J12: Пт
A13: 46247 | C13: 5557 | D13: 5557 | F13: 38 | G13: 38 | H13: 146.23684 | I13: 0 | J13: Чт
A14: 46246 | C14: 4017 | D14: 4017 | F14: 33 | G14: 33 | H14: 121.72727 | I14: 0 | J14: Ср
A15: 46245 | C15: 6365 | D15: 6365 | F15: 41 | G15: 41 | H15: 155.2439 | I15: 491.77 | J15: Вт
A16: 46244 | C16: 6026 | D16: 6026 | F16: 32 | G16: 32 | H16: 188.3125 | I16: 216.19 | J16: Пн
A17: 46243 | C17: 0 | F17: 0 | I17: 331.21 | J17: Вс
A18: 46242 | C18: 95 | D18: 95 | F18: 1 | G18: 1 | H18: 95 | I18: 428.08 | J18: Сб
A19: 46241 | C19: 7081.6 | D19: 7081.6 | F19: 46 | G19: 46 | H19: 153.94783 | I19: 373.83 | J19: Пт
A20: 46240 | C20: 5942.4 | D20: 5942.4 | F20: 35 | G20: 35 | H20: 169.78286 | I20: 45.21 | J20: Чт
A21: 46239 | C21: 4067.4 | D21: 4067.4 | F21: 32 | G21: 32 | H21: 127.10625 | I21: 0 | J21: Ср
A22: 46238 | B22: 189 | C22: 6589 | D22: 6778 | E22: 1 | F22: 37 | G22: 38 | H22: 178.36842 | I22: 307.6 | J22: Вт
A23: 46237 | C23: 5364 | D23: 5364 | F23: 31 | G23: 31 | H23: 173.03226 | I23: 0 | J23: Пн
A24: 46236 | C24: 0 | F24: 0 | I24: 632.92 | J24: Вс
A25: 46235 | C25: 161 | D25: 161 | F25: 1 | G25: 1 | H25: 161 | I25: 159.25 | J25: Сб
A26: 46234 | C26: 5293.8 | D26: 5293.8 | F26: 34 | G26: 34 | H26: 155.7 | I26: 1275.15 | J26: Пт
A27: 46233 | C27: 6014.4 | D27: 6014.4 | F27: 39 | G27: 39 | H27: 154.21538 | I27: 486.91 | J27: Чт
A28: 46232 | C28: 3988.4 | D28: 3988.4 | F28: 28 | G28: 28 | H28: 142.44286 | I28: 109.41 | J28: Ср
A29: 46231 | C29: 4220 | D29: 4220 | F29: 25 | G29: 25 | H29: 168.8 | I29: 159.58 | J29: Вт
A30: 46230 | B30: 1066 | C30: 4532 | D30: 5598 | E30: 3 | F30: 27 | G30: 30 | H30: 186.6 | I30: 145.34 | J30: Пн
A31: 46229 | C31: 0 | F31: 0 | I31: 203.34 | J31: Вс
A32: 46228 | C32: 0 | F32: 0 | I32: 336.29 | J32: Сб
A33: 46227 | C33: 3719.6 | D33: 3719.6 | F33: 28 | G33: 28 | H33: 132.84286 | I33: 686.16 | J33: Пт
A34: 46226 | C34: 5792.4 | D34: 5792.4 | F34: 34 | G34: 34 | H34: 170.36471 | I34: 456.11 | J34: Чт
A35: 46225 | C35: 5417.6 | D35: 5417.6 | F35: 37 | G35: 37 | H35: 146.42162 | I35: 226.61 | J35: Ср
A36: 46224 | C36: 5764 | D36: 5764 | F36: 35 | G36: 35 | H36: 164.68571 | I36: 76.33 | J36: Вт
A37: 46223 | C37: 4683 | D37: 4683 | F37: 36 | G37: 36 | H37: 130.08333 | I37: 0 | J37: Пн
A38: 46222 | C38: 754 | D38: 754 | F38: 6 | G38: 6 | H38: 125.66667 | I38: 76.43 | J38: Вс
A39: 46221 | C39: 100 | D39: 100 | F39: 4 | G39: 4 | H39: 25 | I39: 0 | J39: Сб
A40: 46220 | C40: 8172.6 | D40: 8172.6 | F40: 47 | G40: 47 | H40: 173.88511 | I40: 174.95 | J40: Пт
A41: 46219 | C41: 8207.4 | D41: 8207.4 | F41: 48 | G41: 48 | H41: 170.9875 | I41: 390.92 | J41: Чт
A42: 46218 | C42: 8908.6 | D42: 8908.6 | F42: 47 | G42: 47 | H42: 189.54468 | I42: 172.19 | J42: Ср
A43: 46217 | C43: 5792.55 | D43: 5792.55 | F43: 42 | G43: 42 | H43: 137.91786 | I43: 48.16 | J43: Вт
A44: 46216 | C44: 5342 | D44: 5342 | F44: 39 | G44: 39 | H44: 136.97436 | I44: 119.65 | J44: Пн
A45: 46215 | C45: 50 | D45: 50 | F45: 2 | G45: 2 | H45: 25 | I45: 155.14 | J45: Вс
A46: 46214 | C46: 0 | F46: 0 | I46: 117.25 | J46: Сб
A47: 46213 | C47: 5304.2 | D47: 5304.2 | F47: 42 | G47: 42 | H47: 126.29048 | I47: 102.88 | J47: Пт
A48: 46212 | C48: 5549.6 | D48: 5549.6 | F48: 41 | G48: 41 | H48: 135.3561 | I48: 28.27 | J48: Чт
A49: 46211 | C49: 5425.2 | D49: 5425.2 | F49: 49 | G49: 49 | H49: 110.71837 | I49: 0 | J49: Ср
A50: 46210 | C50: 7438 | D50: 7438 | F50: 46 | G50: 46 | H50: 161.69565 | I50: 0 | J50: Вт
A51: 46209 | C51: 6532 | D51: 6532 | F51: 47 | G51: 47 | H51: 138.97872 | I51: 281.45 | J51: Пн
A52: 46208 | C52: 87 | D52: 87 | F52: 2 | G52: 2 | H52: 43.5 | I52: 146.26 | J52: Вс
A53: 46207 | C53: 75 | D53: 75 | F53: 3 | G53: 3 | H53: 25 | I53: 177.94 | J53: Сб
A54: 46206 | C54: 9029.8 | D54: 9029.8 | F54: 50 | G54: 50 | H54: 180.596 | I54: 33.92 | J54: Пт
A55: 46205 | C55: 5554 | D55: 5554 | F55: 43 | G55: 43 | H55: 129.16279 | I55: 68.66 | J55: Чт
A56: 46204 | C56: 7555.4 | D56: 7555.4 | F56: 50 | G56: 50 | H56: 151.108 | I56: 0 | J56: Ср
A57: 46203 | C57: 6862 | D57: 6862 | F57: 46 | G57: 46 | H57: 149.17391 | I57: 86.83 | J57: Вт
A58: 46202 | C58: 7441 | D58: 7441 | F58: 45 | G58: 45 | H58: 165.35556 | I58: 282.47 | J58: Пн
... A63: 46196 | C63: 7077 | D63: 7077 | F63: 45 | G63: 45 | H63: 157.26667 | I63: 0 | J63: Вт
A64: 46195 | C64: 7826.35 | D64: 7826.35 | F64: 42 | G64: 42 | H64: 186.34167 | I64: 0 | J64: Пн | L64: ТОП-3 Целевой аудитории
A65: 46194 | C65: 196 | D65: 196 | F65: 3 | G65: 3 | H65: 65.333333 | I65: 0 | J65: Вс | L65: пол | M65: возраст | N65: % присутствия | P65: кол-во уникальных гостей
A66: 46193 | C66: 0 | F66: 0 | I66: 123.27 | J66: Сб | L66: женщины | M66: 25-35 | N66: 0.24 | P66: 129
A67: 46192 | C67: 8472.2 | D67: 8472.2 | F67: 48 | G67: 48 | H67: 176.50417 | I67: 298.58 | J67: Пт | L67: мужчины | M67: 35-45 | N67: 0.23
A68: 46191 | C68: 4995 | D68: 4995 | F68: 32 | G68: 32 | H68: 156.09375 | I68: 813.67 | J68: Чт | L68: женщины | M68: 35-45 | N68: 0.13
A69: 46190 | C69: 7881 | D69: 7881 | F69: 48 | G69: 48 | H69: 164.1875 | I69: 69.61 | J69: Ср
A70: 46188 | C70: 5631 | D70: 5631 | F70: 39 | G70: 39 | H70: 144.38462 | I70: 75.42 | J70: Пн | L70: График работы | M70: дней в неделю | N70: часы работы
A71: 46187 | C71: 643 | D71: 643 | F71: 2 | G71: 2 | H71: 321.5 | I71: 0 | J71: Вс | M71: 5 | N71: 08:00-17:00
A72: 46186 | C72: 152 | D72: 152 | F72: 2 | G72: 2 | H72: 76 | I72: 143.45 | J72: Сб
A73: 46185 | C73: 75 | D73: 75 | F73: 1 | G73: 1 | H73: 75 | I73: 59.58 | J73: Пт
A74: 46184 | C74: 4666.2 | D74: 4666.2 | F74: 43 | G74: 43 | H74: 108.51628 | I74: 203.34 | J74: Чт
A75: 46183 | B75: 336 | C75: 7175 | D75: 7511 | E75: 1 | F75: 51 | G75: 52 | H75: 144.44231 | I75: 54.47 | J75: Ср
A76: 46182 | C76: 4902 | D76: 4902 | F76: 38 | G76: 38 | H76: 129 | I76: 0 | J76: Вт
A77: 46181 | C77: 6841 | D77: 6841 | F77: 49 | G77: 49 | H77: 139.61224 | I77: 311.16 | J77: Пн
A78: 46180 | C78: 0 | F78: 0 | I78: 33.65 | J78: Вс
A79: 46179 | C79: 50 | D79: 50 | F79: 2 | G79: 2 | H79: 25 | I79: 759.83 | J79: Сб
A80: 46178 | C80: 7172.2 | D80: 7172.2 | F80: 43 | G80: 43 | H80: 166.79535 | I80: 0 | J80: Пт
A81: 46177 | C81: 8401.4 | D81: 8401.4 | F81: 56 | G81: 56 | H81: 150.025 | I81: 258.19 | J81: Чт
A82: 46176 | C82: 8014.35 | D82: 8014.35 | F82: 48 | G82: 48 | H82: 166.96563 | I82: 167.26 | J82: Ср
A83: 46174 | C83: 7772.5 | D83: 7772.5 | F83: 47 | G83: 47 | H83: 165.37234 | I83: 68.12 | J83: Пн
A84: 46172 | C84: 0 | F84: 0 | I84: 202.75 | J84: Сб
A85: 46171 | C85: 7512.35 | D85: 7512.35 | F85: 48 | G85: 48 | H85: 156.50729 | I85: 645.23 | J85: Пт
A86: 46170 | C86: 9374.7 | D86: 9374.7 | F86: 59 | G86: 59 | H86: 158.89322 | I86: 74.79 | J86: Чт
A87: 46169 | C87: 8899.55 | D87: 8899.55 | F87: 51 | G87: 51 | H87: 174.50098 | I87: 87.65 | J87: Ср
A88: 46168 | C88: 6163 | D88: 6163 | F88: 44 | G88: 44 | H88: 140.06818 | I88: 196.89 | J88: Вт
A89: 46166 | C89: 0 | F89: 0 | I89: 199.41 | J89: Вс
A90: 46165 | C90: 125 | D90: 125 | F90: 4 | G90: 4 | H90: 31.25 | I90: 114.72 | J90: Сб
A91: 46164 | C91: 7717.4 | D91: 7717.4 | F91: 54 | G91: 54 | H91: 142.91481 | I91: 162.57 | J91: Пт
A92: 46163 | C92: 7620.4 | D92: 7620.4 | F92: 53 | G92: 53 | H92: 143.78113 | I92: 665.63 | J92: Чт
A93: 46162 | C93: 8055.3 | D93: 8055.3 | F93: 53 | G93: 53 | H93: 151.98679 | I93: 106.27 | J93: Ср
A94: 46161 | C94: 5481 | D94: 5481 | F94: 31 | G94: 31 | H94: 176.80645 | I94: 0 | J94: Вт
A95: 46160 | C95: 7585 | D95: 7585 | F95: 52 | G95: 52 | H95: 145.86538 | I95: 0 | J95: Пн
A96: 46159 | C96: 0 | F96: 0 | I96: 87.08 | J96: Вс
A97: 46158 | C97: 0 | F97: 0 | I97: 138.03 | J97: Сб
A98: 46157 | C98: 6865.2 | D98: 6865.2 | F98: 50 | G98: 50 | H98: 137.304 | I98: 827.3 | J98: Пт
A99: 46156 | C99: 6013.6 | D99: 6013.6 | F99: 45 | G99: 45 | H99: 133.63556 | I99: 220.28 | J99: Чт
A100: 46155 | B100: 98 | C100: 3663.5 | D100: 3761.5 | E100: 1 | F100: 32 | G100: 33 | H100: 113.98485 | I100: 393.02 | J100: Ср
A101: 46154 | C101: 4543 | D101: 4543 | F101: 38 | G101: 38 | H101: 119.55263 | I101: 77.61 | J101: Вт
A102: 46153 | C102: 30 | D102: 30 | F102: 1 | G102: 1 | H102: 30 | I102: 132.14 | J102: Пн
A103: 46151 | C103: 0 | F103: 0 | I103: 309.55 | J103: Сб
A104: 46150 | C104: 5397.1 | D104: 5397.1 | F104: 37 | G104: 37 | H104: 145.86757 | I104: 482.04 | J104: Пт
...

Sheet 14
A1: Точка | B1: 14 | C1: Дата запуска | D1: 45692 | E1: Тип точки | F1: офис | G1: Активна | H1: Да | K1: Стоимость обслуживания | L1: Аренда | M1: Коммуналка | N1: Клининг
A2: Среднее | B2: 252.91579 | C2: 11911.556 | D2: 11786.44 | E2: 1.3684211 | F2: 68.36 | G2: 67.631579 | H2: 175.50604 | I2: 345.51307 | K2: =SUM(L2:Q2) -> 6765 | L2: 6465 | M2: 0 | N2: 300
A3: Дата | B3: $ QR-код | C3: $ Касса | D3: $ Итог | E3: Чеки QR | F3: Чеки Касса | G3: Чеки Итог | H3: Ср.-й чек | I3: Списания | J3: д/н
A4: 46257 | C4: 1202.4 | D4: 1202.4 | F4: 11 | G4: 11 | H4: 109.30909 | I4: 586.39 | J4: Вс
A5: 46256 | C5: 791 | D5: 791 | F5: 6 | G5: 6 | H5: 131.83333 | I5: 156.2 | J5: Сб
A6: 46255 | C6: 8977 | D6: 8977 | F6: 47 | G6: 47 | H6: 191 | I6: 169.12 | J6: Пт
A7: 46254 | C7: 12512.6 | D7: 12512.6 | F7: 64 | G7: 64 | H7: 195.50938 | I7: 239.12 | J7: Чт
A8: 46253 | C8: 9436.8 | D8: 9436.8 | F8: 55 | G8: 55 | H8: 171.57818 | I8: 140.44 | J8: Ср
A9: 46252 | C9: 10258 | D9: 10258 | F9: 50 | G9: 50 | H9: 205.16 | I9: 55.94 | J9: Вт
A10: 46251 | C10: 9993.4 | D10: 9993.4 | F10: 61 | G10: 61 | H10: 163.82623 | I10: 45.95 | J10: Пн
A11: 46250 | C11: 706.4 | D11: 706.4 | F11: 7 | G11: 7 | H11: 100.91429 | I11: 860.16 | J11: Вс
A12: 46249 | C12: 1693 | D12: 1693 | F12: 13 | G12: 13 | H12: 130.23077 | I12: 0 | J12: Сб
A13: 46248 | C13: 11086.8 | D13: 11086.8 | F13: 66 | G13: 66 | H13: 167.98182 | I13: 11.32 | J13: Пт
A14: 46247 | C14: 14130.8 | D14: 14130.8 | F14: 82 | G14: 82 | H14: 172.32683 | I14: 49.75 | J14: Чт
A15: 46246 | C15: 11143.8 | D15: 11143.8 | F15: 57 | G15: 57 | H15: 195.50526 | I15: 209.27 | J15: Ср
... A23: 46238 | C23: 10412 | D23: 10412 | F23: 54 | G23: 54 | H23: 192.81481 | I23: 222.55 | J23: Вт
A24: 46237 | B24: 477 | C24: 9439.8 | D24: 9916.8 | E24: 2 | F24: 53 | G24: 55 | H24: 180.30545 | I24: 204.57 | J24: Пн
A25: 46236 | C25: 548.8 | D25: 548.8 | F25: 4 | G25: 4 | H25: 137.2 | I25: 2157.02 | J25: Вс
A26: 46235 | C26: 1078.2 | D26: 1078.2 | F26: 11 | G26: 11 | H26: 98.018182 | I26: 26.32 | J26: Сб
A27: 46234 | C27: 10975.8 | D27: 10975.8 | F27: 58 | G27: 58 | H27: 189.23793 | I27: 993.46 | J27: Пт
A28: 46233 | C28: 13907 | D28: 13907 | F28: 69 | G28: 69 | H28: 201.55072 | I28: 0 | J28: Чт
A29: 46232 | C29: 11166.4 | D29: 11166.4 | F29: 63 | G29: 63 | H29: 177.24444 | I29: 86.94 | J29: Ср
A30: 46231 | C30: 12931 | D30: 12931 | F30: 75 | G30: 75 | H30: 172.41333 | I30: 515.69 | J30: Вт
A31: 46230 | C31: 12785.8 | D31: 12785.8 | F31: 64 | G31: 64 | H31: 199.77812 | I31: 34.22 | J31: Пн
A32: 46229 | C32: 1425.8 | D32: 1425.8 | F32: 8 | G32: 8 | H32: 178.225 | I32: 734.95 | J32: Вс
A33: 46228 | C33: 1067.8 | D33: 1067.8 | F33: 8 | G33: 8 | H33: 133.475 | I33: 0 | J33: Сб
A34: 46227 | C34: 12455 | D34: 12455 | F34: 63 | G34: 63 | H34: 197.69841 | I34: 354.53 | J34: Пт
A35: 46226 | C35: 10333.6 | D35: 10333.6 | F35: 54 | G35: 54 | H35: 191.36296 | I35: 571.87 | J35: Чт
A36: 46225 | C36: 12555.8 | D36: 12555.8 | F36: 66 | G36: 66 | H36: 190.23939 | I36: 104.52 | J36: Ср
A37: 46224 | B37: 126 | C37: 10083.4 | D37: 10209.4 | E37: 1 | F37: 53 | G37: 54 | H37: 189.06296 | I37: 0 | J37: Вт
A38: 46223 | C38: 9366.4 | D38: 9366.4 | F38: 53 | G38: 53 | H38: 176.72453 | I38: 181.26 | J38: Пн
A39: 46222 | C39: 968 | D39: 968 | F39: 10 | G39: 10 | H39: 96.8 | I39: 276.99 | J39: Вс
A40: 46221 | C40: 1080 | D40: 1080 | F40: 6 | G40: 6 | H40: 180 | I40: 20.53 | J40: Сб
A41: 46220 | C41: 10233.2 | D41: 10233.2 | F41: 65 | G41: 65 | H41: 157.43385 | I41: 70.36 | J41: Пт
A42: 46219 | C42: 14774.6 | D42: 14774.6 | F42: 78 | G42: 78 | H42: 189.41795 | I42: 688.64 | J42: Чт
A43: 46218 | C43: 11362.6 | D43: 11362.6 | F43: 65 | G43: 65 | H43: 174.80923 | I43: 42.63 | J43: Ср
A44: 46217 | C44: 11423.44 | D44: 11423.44 | F44: 68 | G44: 68 | H44: 167.99176 | I44: 370.41 | J44: Вт
A45: 46216 | C45: 12890 | D45: 12890 | F45: 75 | G45: 75 | H45: 171.86667 | I45: 177.07 | J45: Пн
A46: 46215 | C46: 538 | D46: 538 | F46: 7 | G46: 7 | H46: 76.857143 | I46: 247.41 | J46: Вс
A47: 46214 | C47: 1192 | D47: 1192 | F47: 8 | G47: 8 | H47: 149 | I47: 132.02 | J47: Сб
A48: 46213 | B48: 227.4 | C48: 12442.4 | D48: 12669.8 | E48: 1 | F48: 82 | G48: 83 | H48: 152.64819 | I48: 878.42 | J48: Пт
A49: 46212 | B49: 98 | C49: 12059.6 | D49: 12157.6 | E49: 1 | F49: 61 | G49: 62 | H49: 196.09032 | I49: 140.2 | J49: Чт
A50: 46211 | C50: 10040.2 | D50: 10040.2 | F50: 60 | G50: 60 | H50: 167.33667 | I50: 120.78 | J50: Ср
A51: 46210 | C51: 11337.2 | D51: 11337.2 | F51: 65 | G51: 65 | H51: 174.41846 | I51: 173.62 | J51: Вт
A52: 46209 | C52: 11221.4 | D52: 11221.4 | F52: 67 | G52: 67 | H52: 167.48358 | I52: 1090.37 | J52: Пн
A53: 46208 | C53: 895 | D53: 895 | F53: 10 | G53: 10 | H53: 89.5 | I53: 2465.29 | J53: Вс
A54: 46207 | C54: 1055.6 | D54: 1055.6 | F54: 10 | G54: 10 | H54: 105.56 | I54: 619.19 | J54: Сб
A55: 46206 | C55: 8890 | D55: 8890 | F55: 56 | G55: 56 | H55: 158.75 | I55: 595.31 | J55: Пт
A56: 46205 | C56: 10939.8 | D56: 10939.8 | F56: 70 | G56: 70 | H56: 156.28286 | I56: 542.83 | J56: Чт
A57: 46204 | C57: 7128.8 | D57: 7128.8 | F57: 56 | G57: 56 | H57: 127.3 | I57: 237.84 | J57: Ср
A58: 46203 | C58: 11925.6 | D58: 11925.6 | F58: 66 | G58: 66 | H58: 180.69091 | I58: 100.09 | J58: Вт
A59: 46202 | C59: 11095.4 | D59: 11095.4 | F59: 63 | G59: 63 | H59: 176.11746 | I59: 873.24 | J59: Пн
A60: 46201 | C60: 364 | D60: 364 | F60: 6 | G60: 6 | H60: 60.666667 | I60: 1279.71 | J60: Вс
A61: 46200 | C61: 790 | D61: 790 | F61: 9 | G61: 9 | H61: 87.777778 | I61: 273.37 | J61: Сб
... A63: 46198 | C63: 13023.6 | D63: 13023.6 | F63: 76 | G63: 76 | H63: 171.36316 | I63: 706.14 | J63: Чт
A64: 46197 | C64: 12933.4 | D64: 12933.4 | F64: 79 | G64: 79 | H64: 163.71392 | I64: 231.73 | J64: Ср | L64: ТОП-3 Целевой аудитории
A65: 46196 | C65: 10085.8 | D65: 10085.8 | F65: 64 | G65: 64 | H65: 157.59062 | I65: 100.99 | J65: Вт | L65: пол | M65: возраст | N65: % присутствия | P65: кол-во уникальных гостей
A66: 46195 | C66: 10428.6 | D66: 10428.6 | F66: 62 | G66: 62 | H66: 168.20323 | I66: 0 | J66: Пн | L66: женщины | M66: 35-45 | N66: 0.36 | P66: 363
A67: 46194 | C67: 1301 | D67: 1301 | F67: 14 | G67: 14 | H67: 92.928571 | I67: 326.74 | J67: Вс | L67: женщины | M67: 25-35 | N67: 0.19
A68: 46193 | C68: 1077 | D68: 1077 | F68: 8 | G68: 8 | H68: 134.625 | I68: 74.3 | J68: Сб | L68: женщины | M68: 45-55 | N68: 0.18
A69: 46192 | C69: 10721.8 | D69: 10721.8 | F69: 67 | G69: 67 | H69: 160.02687 | I69: 460.04 | J69: Пт
A70: 46191 | C70: 12690.8 | D70: 12690.8 | F70: 69 | G70: 69 | H70: 183.92464 | I70: 929.71 | J70: Чт | L70: График работы | M70: дней в неделю | N70: часы работы
A71: 46190 | C71: 12998.6 | D71: 12998.6 | F71: 76 | G71: 76 | H71: 171.03421 | I71: 171.24 | J71: Ср | M71: 5 | N71: 08:00-17:00
A72: 46188 | C72: 11219.76 | D72: 11219.76 | F72: 61 | G72: 61 | H72: 183.93049 | I72: 207.39 | J72: Пн
A73: 46187 | C73: 1295.8 | D73: 1295.8 | F73: 11 | G73: 11 | H73: 117.8 | I73: 1210.81 | J73: Вс
A74: 46186 | C74: 1543.8 | D74: 1543.8 | F74: 15 | G74: 15 | H74: 102.92 | I74: 71.19 | J74: Сб
A75: 46185 | C75: 1984.8 | D75: 1984.8 | F75: 14 | G75: 14 | H75: 141.77143 | I75: 946.37 | J75: Пт
A76: 46184 | C76: 13478.8 | D76: 13478.8 | F76: 67 | G76: 67 | H76: 201.17612 | I76: 315.62 | J76: Чт
A77: 46183 | C77: 11182.4 | D77: 11182.4 | F77: 62 | G77: 62 | H77: 180.36129 | I77: 143.75 | J77: Ср
A78: 46182 | C78: 12017.15 | D78: 12017.15 | F78: 66 | G78: 66 | H78: 182.07803 | I78: 130.11 | J78: Вт
A79: 46181 | B79: 99 | C79: 12972.3 | D79: 13071.3 | E79: 1 | F79: 75 | G79: 76 | H79: 171.99079 | I79: 726.65 | J79: Пн
A80: 46180 | C80: 1642.6 | D80: 1642.6 | F80: 11 | G80: 11 | H80: 149.32727 | I80: 1569.32 | J80: Вс
A81: 46179 | C81: 560.6 | D81: 560.6 | F81: 8 | G81: 8 | H81: 70.075 | I81: 187.56 | J81: Сб
A82: 46178 | C82: 12571.3 | D82: 12571.3 | F82: 70 | G82: 70 | H82: 179.59 | I82: 16.42 | J82: Пт
A83: 46177 | C83: 12038.8 | D83: 12038.8 | F83: 71 | G83: 71 | H83: 169.56056 | I83: 562.7 | J83: Чт
A84: 46176 | B84: 186 | D84: 186 | E84: 1 | G84: 1 | H84: 186 | J84: Ср
A85: 46174 | C85: 14222.26 | D85: 14222.26 | F85: 78 | G85: 78 | H85: 182.33667 | I85: 1859.66 | J85: Пн
A86: 46172 | C86: 2379.4 | D86: 2379.4 | F86: 17 | G86: 17 | H86: 139.96471 | I86: 0 | J86: Сб
A87: 46171 | C87: 11391.6 | D87: 11391.6 | F87: 65 | G87: 65 | H87: 175.25538 | I87: 1067.3 | J87: Пт
A88: 46170 | C88: 13715.6 | D88: 13715.6 | F88: 76 | G88: 76 | H88: 180.46842 | I88: 114.48 | J88: Чт
A89: 46169 | C89: 9882.8 | D89: 9882.8 | F89: 64 | G89: 64 | H89: 154.41875 | I89: 63 | J89: Ср
A90: 46168 | C90: 12509.55 | D90: 12509.55 | F90: 72 | G90: 72 | H90: 173.74375 | I90: 0 | J90: Вт
A91: 46166 | C91: 752 | D91: 752 | F91: 5 | G91: 5 | H91: 150.4 | I91: 101.06 | J91: Вс
A92: 46165 | C92: 1211.8 | D92: 1211.8 | F92: 10 | G92: 10 | H92: 121.18 | I92: 223.12 | J92: Сб
A93: 46164 | C93: 12592.8 | D93: 12592.8 | F93: 83 | G93: 83 | H93: 151.72048 | I93: 376.9 | J93: Пт
A94: 46163 | C94: 15248.1 | D94: 15248.1 | F94: 84 | G94: 84 | H94: 181.525 | I94: 209.23 | J94: Чт
A95: 46162 | C95: 12480 | D95: 12480 | F95: 75 | G95: 75 | H95: 166.4 | I95: 0 | J95: Ср
A96: 46161 | C96: 11751.8 | D96: 11751.8 | F96: 73 | G96: 73 | H96: 160.98356 | I96: 0 | J96: Вт
... A101: 46156 | C101: 15220.2 | D101: 15220.2 | F101: 89 | G101: 89 | H101: 171.01348 | I101: 0 | J101: Чт
A102: 46155 | B102: 190 | C102: 11604.4 | D102: 11794.4 | E102: 1 | F102: 63 | G102: 64 | H102: 184.2875 | I102: 462.49 | J102: Ср
A103: 46154 | C103: 9478.4 | D103: 9478.4 | F103: 64 | G103: 64 | H103: 148.1 | I103: 0 | J103: Вт
A104: 46153 | C104: 601.5 | D104: 601.5 | F104: 8 | G104: 8 | H104: 75.1875 | I104: 0 | J104: Пн
A105: 46151 | C105: 100 | D105: 100 | F105: 3 | G105: 3 | H105: 33.333333 | I105: 0 | J105: Сб
A106: 46150 | C106: 12948 | D106: 12948 | F106: 77 | G106: 77 | H106: 168.15584 | I106: 148.94 | J106: Пт
A107: 46149 | C107: 14007.9 | D107: 14007.9 | F107: 70 | G107: 70 | H107: 200.11286 | I107: 617.74 | J107: Чт
A108: 46148 | C108: 12667 | D108: 12667 | F108: 69 | G108: 69 | H108: 183.57971 | I108: 6.56 | J108: Ср
A109: 46147 | C109: 9240.2 | D109: 9240.2 | F109: 53 | G109: 53 | H109: 174.3434 | I109: 45.69 | J109: Вт
A110: 46146 | C110: 10277 | D110: 10277 | F110: 61 | G110: 61 | H110: 168.47541 | I110: 0 | J110: Пн
A111: 46145 | C111: 465 | D111: 465 | F111: 6 | G111: 6 | H111: 77.5 | I111: 0 | J111: Вс
A112: 46144 | C112: 277 | D112: 277 | F112: 5 | G112: 5 | H112: 55.4 | I112: 0 | J112: Сб
...

Sheet 15
A1: Точка | B1: 15 | C1: Дата запуска | D1: 45551 | E1: Тип точки | F1: офис | G1: Активна | H1: Да | K1: Стоимость обслуживания | L1: Аренда | M1: Коммуналка | N1: Клининг
A2: Среднее | B2: 508.0766 | C2: 8651.6689 | D2: 8637.9245 | E2: 2.6808511 | F2: 49.52027 | G2: 49.370861 | H2: 176.16397 | I2: 308.52669 | K2: =SUM(L2:Q2) -> 2800 | L2: 2500 | M2: 0 | N2: 300
A3: Дата | B3: $ QR-код | C3: $ Касса | D3: $ Итог | E3: Чеки QR | F3: Чеки Касса | G3: Чеки Итог | H3: Ср.-й чек | I3: Списания | J3: д/н
A4: 46257 | C4: 45 | D4: 45 | F4: 1 | G4: 1 | H4: 45 | I4: 135.07 | J4: Вс
A5: 46256 | C5: 80 | D5: 80 | F5: 1 | G5: 1 | H5: 80 | I5: 218.25 | J5: Сб
A6: 46255 | B6: 172 | C6: 7326.6 | D6: 7498.6 | E6: 1 | F6: 42 | G6: 43 | H6: 174.38605 | I6: 682.02 | J6: Пт
A7: 46254 | B7: 369 | C7: 10079.2 | D7: 10448.2 | E7: 2 | F7: 51 | G7: 53 | H7: 197.13585 | I7: 249.89 | J7: Чт
A8: 46253 | B8: 2821 | C8: 6835.2 | D8: 9656.2 | E8: 14 | F8: 41 | G8: 55 | H8: 175.56727 | I8: 436.78 | J8: Ср
A9: 46252 | B9: 160 | C9: 8208.8 | D9: 8368.8 | E9: 1 | F9: 48 | G9: 49 | H9: 170.79184 | I9: 101.55 | J9: Вт
A10: 46251 | C10: 6576 | D10: 6576 | F10: 40 | G10: 40 | H10: 164.4 | I10: 0 | J10: Пн
A11: 46249 | C11: 25 | D11: 25 | F11: 1 | G11: 1 | H11: 25 | I11: 0 | J11: Сб
A12: 46248 | C12: 7663 | D12: 7663 | F12: 47 | G12: 47 | H12: 163.04255 | I12: 864.28 | J12: Пт
A13: 46247 | C13: 9761.4 | D13: 9761.4 | F13: 62 | G13: 62 | H13: 157.44194 | I13: 340.41 | J13: Чт
A14: 46246 | B14: 90 | C14: 9641.2 | D14: 9731.2 | E14: 1 | F14: 53 | G14: 54 | H14: 180.20741 | I14: 131.73 | J14: Ср
A15: 46245 | C15: 7363.2 | D15: 7363.2 | F15: 47 | G15: 47 | H15: 156.66383 | I15: 0 | J15: Вт
A16: 46244 | B16: 90 | C16: 7198.2 | D16: 7288.2 | E16: 1 | F16: 41 | G16: 42 | H16: 173.52857 | I16: 0 | J16: Пн
A17: 46243 | C17: 45 | D17: 45 | F17: 1 | G17: 1 | H17: 45 | I17: 0 | J17: Вс
A18: 46242 | C18: 179 | D18: 179 | F18: 2 | G18: 2 | H18: 89.5 | I18: 15.8 | J18: Сб
A19: 46241 | C19: 6776 | D19: 6776 | F19: 39 | G19: 39 | H19: 173.74359 | I19: 1039.73 | J19: Пт
A20: 46240 | C20: 10632.2 | D20: 10632.2 | F20: 56 | G20: 56 | H20: 189.86071 | I20: 281.77 | J20: Чт
A21: 46239 | C21: 7806.9 | D21: 7806.9 | F21: 42 | G21: 42 | H21: 185.87857 | I21: 1525.18 | J21: Ср
A22: 46238 | C22: 8740 | D22: 8740 | F22: 45 | G22: 45 | H22: 194.22222 | I22: 408.56 | J22: Вт
A23: 46237 | B23: 170 | C23: 6015.8 | D23: 6185.8 | E23: 1 | F23: 35 | G23: 36 | H23: 171.82778 | I23: 1104.96 | J23: Пн
A24: 46236 | C24: 49 | D24: 49 | F24: 1 | G24: 1 | H24: 49 | I24: 326.12 | J24: Вс
A25: 46235 | C25: 105 | D25: 105 | F25: 1 | G25: 1 | H25: 105 | I25: 411.77 | J25: Сб
A26: 46234 | C26: 0 | F26: 0 | I26: 559.85 | J26: Пт
A27: 46233 | C27: 9117.2 | D27: 9117.2 | F27: 54 | G27: 54 | H27: 168.83704 | I27: 549.79 | J27: Чт
A28: 46232 | B28: 98 | C28: 11560 | D28: 11658 | E28: 1 | F28: 55 | G28: 56 | H28: 208.17857 | I28: 0 | J28: Ср
A29: 46231 | B29: 538 | C29: 9695.2 | D29: 10233.2 | E29: 3 | F29: 49 | G29: 52 | H29: 196.79231 | I29: 142.42 | J29: Вт
A30: 46230 | C30: 5282.2 | D30: 5282.2 | F30: 29 | G30: 29 | H30: 182.14483 | I30: 0 | J30: Пн
A31: 46229 | C31: 125 | D31: 125 | F31: 2 | G31: 2 | H31: 62.5 | I31: 177.2 | J31: Вс
A32: 46228 | C32: 0 | F32: 0 | I32: 161.91 | J32: Сб
A33: 46227 | B33: 146 | C33: 9603.4 | D33: 9749.4 | E33: 1 | F33: 46 | G33: 47 | H33: 207.43404 | I33: 725.61 | J33: Пт
A34: 46226 | C34: 9762.8 | D34: 9762.8 | F34: 49 | G34: 49 | H34: 199.24082 | I34: 493.45 | J34: Чт
A35: 46225 | B35: 139 | C35: 8511.8 | D35: 8650.8 | E35: 1 | F35: 48 | G35: 49 | H35: 176.54694 | I35: 70.69 | J35: Ср
A36: 46224 | C36: 9017.05 | D36: 9017.05 | F36: 44 | G36: 44 | H36: 204.93295 | I36: 0 | J36: Вт
A37: 46223 | B37: 217 | C37: 7656.8 | D37: 7873.8 | E37: 1 | F37: 45 | G37: 46 | H37: 171.16957 | I37: 0 | J37: Пн
A38: 46222 | C38: 0 | F38: 0 | I38: 73.74 | J38: Вс
A39: 46221 | C39: 30 | D39: 30 | F39: 1 | G39: 1 | H39: 30 | I39: 544.74 | J39: Сб
A40: 46220 | C40: 9704.2 | D40: 9704.2 | F40: 54 | G40: 54 | H40: 179.70741 | I40: 247.34 | J40: Пт
A41: 46219 | C41: 7586 | D41: 7586 | F41: 42 | G41: 42 | H41: 180.61905 | I41: 289.26 | J41: Чт
A42: 46218 | C42: 7861.7 | D42: 7861.7 | F42: 42 | G42: 42 | H42: 187.18333 | I42: 0 | J42: Ср
A43: 46217 | C43: 9855.3 | D43: 9855.3 | F43: 48 | G43: 48 | H43: 205.31875 | I43: 196.61 | J43: Вт
A44: 46216 | C44: 7116.2 | D44: 7116.2 | F44: 39 | G44: 39 | H44: 182.46667 | I44: 119.65 | J44: Пн
A45: 46215 | C45: 67 | D45: 67 | F45: 2 | G45: 2 | H45: 33.5 | I45: 722.4 | J45: Вс
A46: 46214 | C46: 60 | D46: 60 | F46: 1 | G46: 1 | H46: 60 | I46: 410 | J46: Сб
A47: 46213 | C47: 11555.9 | D47: 11555.9 | F47: 64 | G47: 64 | H47: 180.56094 | I47: 48.75 | J47: Пт
A48: 46212 | B48: 1191 | C48: 7343.6 | D48: 8534.6 | E48: 4 | F48: 39 | G48: 43 | H48: 198.47907 | I48: 140.01 | J48: Чт
A49: 46211 | B49: 675 | C49: 8104.2 | D49: 8779.2 | E49: 4 | F49: 43 | G49: 47 | H49: 186.79149 | I49: 0 | J49: Ср
A50: 46210 | B50: 464 | C50: 7066.1 | D50: 7530.1 | E50: 3 | F50: 42 | G50: 45 | H50: 167.33556 | I50: 0 | J50: Вт
A51: 46209 | C51: 5296.2 | D51: 5296.2 | F51: 28 | G51: 28 | H51: 189.15 | I51: 367.44 | J51: Пн
A52: 46208 | C52: 0 | F52: 0 | I52: 277.66 | J52: Вс
A53: 46207 | C53: 25 | D53: 25 | F53: 1 | G53: 1 | H53: 25 | I53: 143.81 | J53: Сб
A54: 46206 | C54: 9684.4 | D54: 9684.4 | F54: 55 | G54: 55 | H54: 176.08 | I54: 142.01 | J54: Пт
A55: 46205 | C55: 7208.4 | D55: 7208.4 | F55: 38 | G55: 38 | H55: 189.69474 | I55: 171.64 | J55: Чт
A56: 46204 | C56: 8647.4 | D56: 8647.4 | F56: 47 | G56: 47 | H56: 183.98723 | I56: 153.63 | J56: Ср
A57: 46203 | C57: 7746.6 | D57: 7746.6 | F57: 51 | G57: 51 | H57: 151.89412 | I57: 217.07 | J57: Вт
A58: 46202 | C58: 8908 | D58: 8908 | F58: 50 | G58: 50 | H58: 178.16 | I58: 585.85 | J58: Пн
A59: 46200 | C59: 42 | D59: 42 | F59: 1 | G59: 1 | H59: 42 | I59: 0 | J59: Сб
A60: 46199 | C60: 6433.4 | D60: 6433.4 | F60: 40 | G60: 40 | H60: 160.835 | I60: 342.64 | J60: Пт
A61: 46198 | C61: 9809.1 | D61: 9809.1 | F61: 51 | G61: 51 | H61: 192.33529 | I61: 185.39 | J61: Чт
A62: 46197 | C62: 6910.8 | D62: 6910.8 | F62: 42 | G62: 42 | H62: 164.54286 | I62: 0 | J62: Ср
A63: 46196 | C63: 8926.7 | D63: 8926.7 | F63: 51 | G63: 51 | H63: 175.03333 | I63: 116.24 | J63: Вт
A64: 46195 | B64: 168 | C64: 5420.4 | D64: 5588.4 | E64: 1 | F64: 35 | G64: 36 | H64: 155.23333 | I64: 0 | J64: Пн | L64: ТОП-3 Целевой аудитории
A65: 46194 | C65: 45 | D65: 45 | F65: 2 | G65: 2 | H65: 22.5 | I65: 2006.65 | J65: Вс | L65: пол | M65: возраст | N65: % присутствия | P65: кол-во уникальных гостей
A66: 46193 | C66: 87 | D66: 87 | F66: 1 | G66: 1 | H66: 87 | I66: 680.13 | J66: Сб | L66: женщины | M66: 35-45 | N66: 0.44 | P66: 138
A67: 46192 | B67: 1241 | C67: 6566.2 | D67: 7807.2 | E67: 7 | F67: 39 | G67: 46 | H67: 169.72174 | I67: 893.22 | J67: Пт | L67: женщины | M67: 25-35 | N67: 0.19
A68: 46191 | B68: 3220 | C68: 2838.8 | D68: 6058.8 | E68: 15 | F68: 13 | G68: 28 | H68: 216.38571 | I68: 1442.45 | J68: Чт | L68: женщины | M68: 45-55 | N68: 0.13
A69: 46190 | C69: 7794.1 | D69: 7794.1 | F69: 50 | G69: 50 | H69: 155.882 | I69: 47.28 | J69: Ср
A70: 46189 | B70: 158 | D70: 158 | E70: 1 | G70: 1 | H70: 158 | J70: Вт | L70: График работы | M70: дней в неделю | N70: часы работы
A71: 46188 | B71: 470 | D71: 470 | E71: 2 | G71: 2 | H71: 235 | J71: Пн | M71: 5 | N71: 08:00-17:00
A72: 46187 | C72: 0 | F72: 0 | I72: 151.01 | J72: Вс
A73: 46186 | C73: 0 | F73: 0 | I73: 133.3 | J73: Сб
A74: 46185 | C74: 0 | F74: 0 | I74: 258.75 | J74: Пт
A75: 46184 | C75: 9583.3 | D75: 9583.3 | F75: 75 | G75: 75 | H75: 127.77733 | I75: 317.37 | J75: Чт
A76: 46183 | B76: 1058 | C76: 6652.2 | D76: 7710.2 | E76: 6 | F76: 38 | G76: 44 | H76: 175.23182 | I76: 401.38 | J76: Ср
A77: 46182 | C77: 6236.8 | D77: 6236.8 | F77: 37 | G77: 37 | H77: 168.56216 | I77: 424.7 | J77: Вт
A78: 46181 | C78: 7081.4 | D78: 7081.4 | F78: 39 | G78: 39 | H78: 181.57436 | I78: 516.79 | J78: Пн
A79: 46180 | C79: 0 | F79: 0 | I79: 413.61 | J79: Вс
A80: 46179 | C80: 0 | F80: 0 | I80: 737.53 | J80: Сб
A81: 46178 | C81: 7989.4 | D81: 7989.4 | F81: 48 | G81: 48 | H81: 166.44583 | I81: 254.6 | J81: Пт
A82: 46177 | C82: 7085 | D82: 7085 | F82: 41 | G82: 41 | H82: 172.80488 | I82: 105.32 | J82: Чт
A83: 46176 | B83: 813 | D83: 813 | E83: 5 | G83: 5 | H83: 162.6 | J83: Ср
A84: 46174 | C84: 8846.35 | D84: 8846.35 | F84: 54 | G84: 54 | H84: 163.8213 | I84: 300.34 | J84: Пн
A85: 46172 | C85: 0 | F85: 0 | I85: 225.96 | J85: Сб
A86: 46171 | B86: 1214 | C86: 7349.6 | D86: 8563.6 | E86: 7 | F86: 40 | G86: 47 | H86: 182.20426 | I86: 235.33 | J86: Пт
A87: 46170 | C87: 9864.8 | D87: 9864.8 | F87: 52 | G87: 52 | H87: 189.70769 | I87: 394.54 | J87: Чт
A88: 46169 | B88: 98 | C88: 6440.8 | D88: 6538.8 | E88: 1 | F88: 37 | G88: 38 | H88: 172.07368 | I88: 343.99 | J88: Ср
A89: 46168 | B89: 228 | C89: 7262.8 | D89: 7490.8 | E89: 2 | F89: 49 | G89: 51 | H89: 146.87843 | I89: 207.73 | J89: Вт
A90: 46166 | C90: 0 | F90: 0 | I90: 56.31 | J90: Вс
A91: 46165 | C91: 537.8 | D91: 537.8 | F91: 3 | G91: 3 | H91: 179.26667 | I91: 327.79 | J91: Сб
A92: 46164 | B92: 1467 | C92: 7198 | D92: 8665 | E92: 8 | F92: 39 | G92: 47 | H92: 184.3617 | I92: 583.81 | J92: Пт
A93: 46163 | C93: 8336.2 | D93: 8336.2 | F93: 44 | G93: 44 | H93: 189.45909 | I93: 700.98 | J93: Чт
A94: 46162 | C94: 10710.7 | D94: 10710.7 | F94: 56 | G94: 56 | H94: 191.2625 | I94: 160.65 | J94: Ср
A95: 46161 | C95: 5794.8 | D95: 5794.8 | F95: 33 | G95: 33 | H95: 175.6 | I95: 0 | J95: Вт
A96: 46160 | B96: 2115 | C96: 7571.4 | D96: 9686.4 | E96: 9 | F96: 43 | G96: 52 | H96: 186.27692 | I96: 0 | J96: Пн
A97: 46159 | B97: 30 | C97: 0 | D97: 30 | E97: 1 | F97: 0 | G97: 1 | H97: 30 | I97: 0 | J97: Вс
A98: 46158 | C98: 0 | F98: 0 | I98: 217.75 | J98: Сб
A99: 46157 | C99: 9029 | D99: 9029 | F99: 51 | G99: 51 | H99: 177.03922 | I99: 162.17 | J99: Пт
A100: 46156 | C100: 10531 | D100: 10531 | F100: 59 | G100: 59 | H100: 178.49153 | I100: 0 | J100: Чт
...

Sheet 16
A1: Точка | B1: 16 | C1: Дата запуска | D1: 45630 | E1: Тип точки | F1: офис | G1: Активна | H1: Да | K1: Стоимость обслуживания | L1: Аренда | M1: Коммуналка | N1: Клининг
A2: Среднее | B2: 383.06429 | C2: 7975.4507 | D2: 7918.1447 | E2: 1.5238095 | F2: 40 | G2: 39.629139 | H2: 200.7958 | I2: 238.83135 | K2: =SUM(L2:Q2) -> 300 | M2: 0 | N2: 300
A3: Дата | B3: $ QR-код | C3: $ Касса | D3: $ Итог | E3: Чеки QR | F3: Чеки Касса | G3: Чеки Итог | H3: Ср.-й чек | I3: Списания | J3: д/н
A4: 46257 | C4: 0 | F4: 0 | I4: 182.69 | J4: Вс
A5: 46256 | C5: 0 | F5: 0 | I5: 223.78 | J5: Сб
A6: 46255 | B6: 658 | C6: 6080.6 | D6: 6738.6 | E6: 2 | F6: 29 | G6: 31 | H6: 217.37419 | I6: 227.69 | J6: Пт
A7: 46254 | C7: 7185.5 | D7: 7185.5 | F7: 32 | G7: 32 | H7: 224.54688 | I7: 302.96 | J7: Чт
A8: 46253 | C8: 5307 | D8: 5307 | F8: 32 | G8: 32 | H8: 165.84375 | I8: 141.46 | J8: Ср
A9: 46252 | B9: 45 | C9: 4790 | D9: 4835 | E9: 1 | F9: 22 | G9: 23 | H9: 210.21739 | I9: 0 | J9: Вт
A10: 46251 | C10: 7133 | D10: 7133 | F10: 37 | G10: 37 | H10: 192.78378 | I10: 0 | J10: Пн
A11: 46250 | C11: 0 | F11: 0 | I11: 0 | J11: Вс
A12: 46248 | C12: 7314.2 | D12: 7314.2 | F12: 40 | G12: 40 | H12: 182.855 | I12: 37.27 | J12: Пт
A13: 46247 | B13: 650 | C13: 10426.85 | D13: 11076.85 | E13: 2 | F13: 50 | G13: 52 | H13: 213.01635 | I13: 32.86 | J13: Чт
A14: 46246 | C14: 9759.1 | D14: 9759.1 | F14: 46 | G14: 46 | H14: 212.15435 | I14: 0 | J14: Ср
A15: 46245 | C15: 8280.25 | D15: 8280.25 | F15: 47 | G15: 47 | H15: 176.17553 | I15: 0 | J15: Вт
A16: 46244 | C16: 9320 | D16: 9320 | F16: 42 | G16: 42 | H16: 221.90476 | I16: 0 | J16: Пн
A17: 46243 | C17: 45 | D17: 45 | F17: 1 | G17: 1 | H17: 45 | I17: 48.05 | J17: Вс
A18: 46242 | C18: 0 | F18: 0 | I18: 110.83 | J18: Сб
A19: 46241 | C19: 7459.8 | D19: 7459.8 | F19: 37 | G19: 37 | H19: 201.61622 | I19: 420.35 | J19: Пт
A20: 46240 | C20: 8819 | D20: 8819 | F20: 39 | G20: 39 | H20: 226.12821 | I20: 488.54 | J20: Чт
A21: 46239 | C21: 8082.4 | D21: 8082.4 | F21: 33 | G21: 33 | H21: 244.92121 | I21: 398.08 | J21: Ср
A22: 46238 | B22: 412 | C22: 7266 | D22: 7678 | E22: 1 | F22: 38 | G22: 39 | H22: 196.87179 | I22: 428.66 | J22: Вт
A23: 46237 | C23: 7192.95 | D23: 7192.95 | F23: 30 | G23: 30 | H23: 239.765 | I23: 277.51 | J23: Пн
A24: 46236 | C24: 315 | D24: 315 | F24: 1 | G24: 1 | H24: 315 | I24: 29.09 | J24: Вс
A25: 46235 | C25: 98 | D25: 98 | F25: 1 | G25: 1 | H25: 98 | I25: 141.9 | J25: Сб
A26: 46234 | C26: 4466.6 | D26: 4466.6 | F26: 27 | G26: 27 | H26: 165.42963 | I26: 215.26 | J26: Пт
A27: 46233 | C27: 8363 | D27: 8363 | F27: 34 | G27: 34 | H27: 245.97059 | I27: 0 | J27: Чт
A28: 46232 | B28: 1204 | C28: 9638 | D28: 10842 | E28: 1 | F28: 44 | G28: 45 | H28: 240.93333 | I28: 0 | J28: Ср
A29: 46231 | B29: 606 | C29: 8540 | D29: 9146 | E29: 1 | F29: 42 | G29: 43 | H29: 212.69767 | I29: 69.03 | J29: Вт
A30: 46230 | C30: 8525 | D30: 8525 | F30: 41 | G30: 41 | H30: 207.92683 | I30: 238.61 | J30: Пн
A31: 46229 | C31: 0 | F31: 1 | G31: 1 | H31: 0 | I31: 137.41 | J31: Вс
A32: 46227 | C32: 5745 | D32: 5745 | F32: 32 | G32: 32 | H32: 179.53125 | I32: 317.3 | J32: Пт
A33: 46226 | C33: 10510 | D33: 10510 | F33: 56 | G33: 56 | H33: 187.67857 | I33: 239.21 | J33: Чт
A34: 46225 | C34: 8424 | D34: 8424 | F34: 45 | G34: 45 | H34: 187.2 | I34: 576.07 | J34: Ср
A35: 46224 | B35: 174 | C35: 5769 | D35: 5943 | E35: 1 | F35: 32 | G35: 33 | H35: 180.09091 | I35: 81.8 | J35: Вт
A36: 46223 | B36: 174 | C36: 6297 | D36: 6471 | E36: 1 | F36: 31 | G36: 32 | H36: 202.21875 | I36: 0 | J36: Пн
A37: 46222 | C37: 84 | D37: 84 | F37: 1 | G37: 1 | H37: 84 | I37: 71.72 | J37: Вс
A38: 46221 | C38: 0 | F38: 0 | I38: 18.97 | J38: Сб
A39: 46220 | C39: 6295.4 | D39: 6295.4 | F39: 32 | G39: 32 | H39: 196.73125 | I39: 371.71 | J39: Пт
A40: 46219 | C40: 10738.4 | D40: 10738.4 | F40: 50 | G40: 50 | H40: 214.768 | I40: 49.79 | J40: Чт
A41: 46218 | C41: 7111.75 | D41: 7111.75 | F41: 34 | G41: 34 | H41: 209.16912 | I41: 86.93 | J41: Ср
A42: 46217 | C42: 7105 | D42: 7105 | F42: 24 | G42: 24 | H42: 296.04167 | I42: 196.61 | J42: Вт
A43: 46216 | B43: 287 | C43: 7075.1 | D43: 7362.1 | E43: 2 | F43: 46 | G43: 48 | H43: 153.37708 | I43: 0 | J43: Пн
A44: 46214 | C44: 0 | F44: 0 | I44: 36.51 | J44: Сб
A45: 46213 | C45: 8437.25 | D45: 8437.25 | F45: 39 | G45: 39 | H45: 216.33974 | I45: 72.46 | J45: Пт
A46: 46212 | B46: 128 | C46: 8447 | D46: 8575 | E46: 1 | F46: 42 | G46: 43 | H46: 199.4186 | I46: 78.92 | J46: Чт
A47: 46211 | C47: 9105.65 | D47: 9105.65 | F47: 41 | G47: 41 | H47: 222.08902 | I47: 807.78 | J47: Ср
A48: 46210 | C48: 7546.5 | D48: 7546.5 | F48: 37 | G48: 37 | H48: 203.95946 | I48: 71.79 | J48: Вт
A49: 46209 | C49: 7512 | D49: 7512 | F49: 33 | G49: 33 | H49: 227.63636 | I49: 160.98 | J49: Пн
A50: 46208 | C50: 0 | F50: 1 | G50: 1 | H50: 0 | I50: 42.62 | J50: Вс
A51: 46207 | C51: 234 | D51: 234 | F51: 3 | G51: 3 | H51: 78 | I51: 103.41 | J51: Сб
A52: 46206 | C52: 8745.8 | D52: 8745.8 | F52: 49 | G52: 49 | H52: 178.48571 | I52: 763.65 | J52: Пт
A53: 46205 | C53: 9803.7 | D53: 9803.7 | F53: 49 | G53: 49 | H53: 200.07551 | I53: 361 | J53: Чт
A54: 46204 | C54: 6885.7 | D54: 6885.7 | F54: 32 | G54: 32 | H54: 215.17812 | I54: 419.5 | J54: Ср
A55: 46203 | C55: 6424 | D55: 6424 | F55: 30 | G55: 30 | H55: 214.13333 | I55: 80.49 | J55: Вт
A56: 46202 | B56: 374 | C56: 6569 | D56: 6943 | E56: 1 | F56: 36 | G56: 37 | H56: 187.64865 | I56: 174.99 | J56: Пн
A57: 46201 | C57: 0 | F57: 0 | I57: 152.36 | J57: Вс
A58: 46199 | C58: 6935.7 | D58: 6935.7 | F58: 35 | G58: 35 | H58: 198.16286 | I58: 427.47 | J58: Пт
A59: 46198 | C59: 6944.8 | D59: 6944.8 | F59: 30 | G59: 30 | H59: 231.49333 | I59: 257.27 | J59: Чт
A60: 46197 | B60: 60 | C60: 8719.2 | D60: 8779.2 | E60: 1 | F60: 43 | G60: 44 | H60: 199.52727 | I60: 368.3 | J60: Ср
A61: 46196 | C61: 6465 | D61: 6465 | F61: 31 | G61: 31 | H61: 208.54839 | I61: 379.13 | J61: Вт
A62: 46195 | B62: 522 | C62: 6767 | D62: 7289 | E62: 1 | F62: 38 | G62: 39 | H62: 186.89744 | I62: 211.29 | J62: Пн
A63: 46194 | C63: 89 | D63: 89 | F63: 1 | G63: 1 | H63: 89 | I63: 85.44 | J63: Вс
A64: 46193 | C64: 339 | D64: 339 | F64: 3 | G64: 3 | H64: 113 | I64: 40.89 | J64: Сб | L64: ТОП-3 Целевой аудитории
A65: 46192 | B65: 467 | C65: 7624.05 | D65: 8091.05 | E65: 1 | F65: 38 | G65: 39 | H65: 207.46282 | I65: 358.4 | J65: Пт | L65: пол | M65: возраст | N65: % присутствия | P65: кол-во уникальных гостей
A66: 46191 | B66: 288 | C66: 7452.5 | D66: 7740.5 | E66: 1 | F66: 38 | G66: 39 | H66: 198.47436 | I66: 953.67 | J66: Чт | L66: женщины | M66: 35-45 | N66: 0.34 | P66: 125
A67: 46190 | B67: 308 | C67: 9960.5 | D67: 10268.5 | E67: 2 | F67: 52 | G67: 54 | H67: 190.15741 | I67: 0 | J67: Ср | L67: женщины | M67: 25-35 | N67: 0.2
A68: 46188 | C68: 8791 | L68: мужчины | M68: 35-45 | N68: 0.14
A69: 46187 | C69: 134 | D69: 134 | F69: 4 | G69: 4 | H69: 33.5 | I69: 112.35 | J69: Вс
A70: 46186 | C70: 42 | D70: 42 | F70: 1 | G70: 1 | H70: 42 | I70: 73.98 | J70: Сб | L70: График работы | M70: дней в неделю | N70: часы работы
