Workbook
Name MY_FUNCTION1: LAMBDA(#REF!/#REF!*100%)

Sheet Оборудование Очаково
C1: Кол-во | F1: ИТОГ | G1: =SUM(G3:G202) -> 1195960
A2: № | B2: Наименование | C2: Надо | D2: Есть | E2: Купить | F2: Цена | G2: Стоимость | H2: Ссылка
A3: 1 | B3: Сковорода опрокидывающаяся | C3: 2 | D3: 1 | E3: =C3-D3 -> 1 | F3: 74000 | G3: =E3*F3 -> 74000 | H3: https://www.avito.ru/kirovskaya_oblast_kirov/oborudovanie_dlya_biznesa/skovoroda_oprokidyvayuschayasya_tula_sesm-03n_4167586681?context=H4sIAAAAAAAA_wE_AMD_YToyOntzOjEzOiJsb2NhbFByaW9yaXR5IjtiOjA7czoxOiJ4IjtzOjE2OiJzRUtOdmRzT0cyZnNXUWhPIjt9leFoFz8AAAA
A4: 2 | B4: Тестомес 60л Abbat | C4: 1 | D4: 1 | E4: =C4-D4 -> 0 | F4: 157000 | G4: =E4*F4 -> 0 | H4: https://abat.ru/catalog/testomesy/spiralnyy-testomes-tms-60nn-1r-serii-light/
A5: 3 | B5: Тестомесильная машина Miratek PX-40 | C5: 1 | D5: 0 | E5: =C5-D5 -> 1 | F5: 157000 | G5: =E5*F5 -> 157000
A6: 4 | B6: Мясорубка мим-600 | C6: 1 | D6: 0 | E6: =C6-D6 -> 1 | F6: 30000 | G6: =E6*F6 -> 30000 | H6: https://www.avito.ru/sankt-peterburg/bytovaya_tehnika/myasorubka_mim-600_7269946449?slocation=659020&context=H4sIAAAAAAAA_wE_AMD_YToyOntzOjEzOiJsb2NhbFByaW9yaXR5IjtiOjE7czoxOiJ4IjtzOjE2OiI4QlZRbWxyWHpSd2dDREF1Ijt9SgdCXT8AAAA
A7: 5 | B7: RobotCoupe CL50 E | C7: 1 | D7: 0 | E7: =C7-D7 -> 1 | F7: 75000 | G7: =E7*F7 -> 75000 | H7: https://www.avito.ru/samara/oborudovanie_dlya_biznesa/ovoscherezka_robot_coupe_cl50e_s_diskami_4605343063?segment=avitoForBusiness&slocation=659020&context=H4sIAAAAAAAA_wGDAHz_YTo0OntzOjk6ImZyb21TcGFjZSI7czoxNjoiYXZpdG9Gb3JCdXNpbmVzcyI7czoxMzoibG9jYWxQcmlvcml0eSI7YjoxO3M6Mzoic3JjIjtzOjEwOiJhZmJfc2VhcmNoIjtzOjE6IngiO3M6MTY6ImtjdlZxbkR6WkFQRzZoMmEiO31KVkvkgwAAAA
A8: 6 | B8: Индукционная конфорка | C8: 7 | D8: 4 | E8: =C8-D8 -> 3 | F8: 17000 | G8: =E8*F8 -> 51000 | H8: https://www.avito.ru/tyumen/oborudovanie_dlya_biznesa/plita_induktsionnaya_indokor_in3500_4613302168?context=H4sIAAAAAAAA_wE_AMD_YToyOntzOjEzOiJsb2NhbFByaW9yaXR5IjtiOjE7czoxOiJ4IjtzOjE2OiJPQ2JtbUtuWFpMUGdtZ3piIjt9gk7aRj8AAAA
A9: 7 | B9: Фильт для воды | C9: 1 | D9: 0 | E9: =C9-D9 -> 1 | F9: 40000 | G9: =E9*F9 -> 40000 | H9: https://vodni-standart.ru/?utm_source=yandex&utm_medium=cpc&utm_campaign=115908423&utm_term=---autotargeting&utm_banner=1859837756768689779&utm_phrase=53670918000&utm_content=premium/5&calltouch_tm=yd_c:115908423_gb:5512460668_ad:1859837756768689779_ph:53670918000_st:search_pt:premium_p:5_s:none_dt:desktop_reg:55_ret:53670918000_apt:none&yclid=9140691686113411071#rec837852192
A10: 8 | B10: Холодильник Polair 700 л | C10: 8 | D10: 6 | E10: =C10-D10 -> 2 | F10: 30000 | G10: =E10*F10 -> 60000 | H10: https://www.avito.ru/tyumen/oborudovanie_dlya_biznesa/holodilnyy_shkaf_polair_07_3875580478?context=H4sIAAAAAAAA_wE_AMD_YToyOntzOjEzOiJsb2NhbFByaW9yaXR5IjtiOjE7czoxOiJ4IjtzOjE2OiJOQnRNcWE2cWZpbVBTazd6Ijt9_C3HcD8AAAA
A11: 9 | B11: Стол нержавейка 1500х700мм | C11: 26 | D11: 8 | E11: =C11-D11 -> 18 | F11: 10100 | G11: =E11*F11 -> 181800 | H11: https://www.avito.ru/tyumen?cd=1&context=H4sIAAAAAAAA_0SRwXKbMBCG38XXHrLYdVycycERkSIiKRXjgOBmRIJxMEktgcCdvntHtWd6hF3tfP_379bB-rdZB7Ce6c_T6U3b5rOb3Zn17XdYz2hnNT3iQ0XaoWxd89K6Rh9TVxJ8KFLXMOyaQu39d5-r5KucLzU9fGlqUQXskOxDFAD7KYcmkkOFAvX06jh5dMAW0ghCgQ1ysOQBclcDu5FDOwY8ethzgRbAIjmEZANsldQViSh_PkH-lNQWfQNman_DVn5eSiPQBEzJvkK3wDY13746LggW541zJ9MrPPYQ38jB-nkkbYg8Q9JMUVILz_ie1CFaQX729x3kzM-kFf7fj9r9GjwDAraS_XTJAnkkrd9lTNoKLYGdpEGbUWw3jgqCaaQd588r1l48aTLu83lqi2wJCtFbheKmyMahCq4eSXreZVWfHtNJz__7Lo_hVGbYsAybQsX-rVEoNrtsedKB37ErheKpUDgolPh3-y1wjVZpq7v22od3zHz-FRUoBKZ87rl3YazP38neIkejx4BHUbLfasfxhask4eHabZxg17wc8uBlu5n4E3gOKNT-mofJznpHZ-8j9P3XlvArry1U8lnOkwtPJ0aNw0W5iD_yLm7zzLa6DT92WfVVYde8p0FI6_v72d2fvwEAAP__xFx2vaECAAA&q=стол+нержавейка+1500+х+700
A12: 10 | B12: Стол нержавейка 1200х700мм | C12: 11 | D12: 7 | E12: =C12-D12 -> 4 | F12: 9400 | G12: =E12*F12 -> 37600 | H12: https://www.avito.ru/tyumen?q=стол+нержавейка+1200+х+700
A13: 11 | B13: Стол нержавейка 600х600мм | C13: 2 | D13: 6 | E13: =C13-D13 -> -4 | F13: 5000 | G13: =E13*F13 -> -20000 | H13: У Олега их как грязи
A14: 12 | B14: Блинница автоматическая Sikom рк-1.2.20 | C14: 1 | D14: 1 | E14: =C14-D14 -> 0 | F14: 230000 | G14: =E14*F14 -> 0 | H14: https://www.avito.ru/ryazan/bytovaya_tehnika/blinnyy_apparat_sikom_7309630210
A15: 13 | B15: Ванна моечная 700х700 | C15: 6 | D15: 2 | E15: =C15-D15 -> 4 | F15: 9000 | G15: =E15*F15 -> 36000 | H15: https://www.avito.ru/tyumen/oborudovanie_dlya_biznesa/pishevoe/neitralnoe/moecnoe_oborudovanie-ASgBAgICA0TqAvpPkKUU5vaOA6ylFPj3jgM?q=ванна+моечная+70
A16: 14 | B16: Ванна моечная двойная 1150х700 | C16: 3 | D16: 3
A17: 15 | B17: Автоматический жироуловитель СПБ 1,0-70 Автосбор | C17: 4 | D17: 0 | E17: =C17-D17 -> 4 | F17: 49500 | G17: =E17*F17 -> 198000 | H17: https://polyfacture.ru/catalog/zhirouloviteli-avtosbor/23355/
A18: 16 | B18: Шкаф для одежды ШМ-24 | C18: 8 | D18: 4 | E18: =C18-D18 -> 4 | F18: 16390 | G18: =E18*F18 -> 65560 | H18: https://тюмень.железная-мебель.рф/catalog/metallicheskie-shkafy/shkafy-metallicheskie-dlya-razdevalok/shkafy-dlya-odezhdy/shkaf-dlya-odezhdy-shm-24/
A19: 17 | B19: Ванна моечная большая | C19: 5 | D19: 0 | E19: =C19-D19 -> 5 | G19: =E19*F19 -> 0
A20: 18 | B20: Слайсер | C20: 3 | D20: 1 | E20: =C20-D20 -> 2 | F20: 25000 | G20: =E20*F20 -> 50000
A21: 19 | B21: Тележка-шпилька 16уровней | C21: 8 | D21: 4 | E21: =C21-D21 -> 4 | G21: =E21*F21 -> 0
A22: 20 | B22: Весы напольные | C22: 6 | D22: 5 | E22: =C22-D22 -> 1 | F22: 5000 | G22: =E22*F22 -> 5000 | H22: https://www.avito.ru/tyumen/oborudovanie_dlya_biznesa/vesy_napolnye_elektronnye_torgovye_7509978347?segment=avitoForBusiness&utm_campaign=native&utm_medium=item_page_android&utm_source=soc_sharing
A23: 21 | B23: Рукомойник | C23: 8 | D23: 4 | E23: =C23-D23 -> 4 | G23: =E23*F23 -> 0
A24: 22 | B24: Зонт вытяжной, островной | C24: 1 | D24: 0 | E24: =C24-D24 -> 1 | F24: 70000 | G24: =E24*F24 -> 70000
A25: 23 | B25: Печь пекарская с растойкой 10 уровней | C25: 1 | D25: 1 | E25: =C25-D25 -> 0 | F25: 270000 | G25: =E25*F25 -> 0
A26: 24 | B26: Машина стиральная | C26: 1 | D26: 0 | E26: =C26-D26 -> 1 | F26: 25000 | G26: =E26*F26 -> 25000
A27: 25 | B27: Машина сушильная | C27: 1 | D27: 0 | E27: =C27-D27 -> 1 | F27: 20000 | G27: =E27*F27 -> 20000
A28: 26 | B28: Керхер | C28: 1 | D28: 0 | E28: =C28-D28 -> 1 | F28: 5000 | G28: =E28*F28 -> 5000
A29: 27 | B29: Планетарный миксер, дежа 10 литров | C29: 1 | D29: 0 | E29: =C29-D29 -> 1 | F29: 35000 | G29: =E29*F29 -> 35000 | H29: https://www.avito.ru/tyumen/oborudovanie_dlya_biznesa/mikser_planetarnyy_foodatlas_b-20ba_eco20l_4679194856?utm_campaign=native&utm_medium=item_page_android&utm_source=soc_sharing
A30: 28 | B30: Котел пищеварочный | C30: 1 | E30: =C30-D30 -> 1 | G30: =E30*F30 -> 0 | H30: https://www.avito.ru/ekaterinburg/oborudovanie_dlya_biznesa/kotel_varochnyy_abat_kpem-160-o_4254362678?utm_campaign=native&utm_medium=item_page_android&utm_source=soc_sharing
A31: 29 | B31: Погружной блендер | E31: =C31-D31 -> 0 | G31: =E31*F31 -> 0
E32: =C32-D32 -> 0 | G32: =E32*F32 -> 0
G33: =C33*F33 -> 0

Sheet Факт очаково
A1: Наименование | B1: Кол-во
A2: - [ ] Мойка двойная 135х70 | B2: 1
A3: - [ ] Мойка двух секционная 115х70 | B3: 3
A4: - [ ] Мойка 70х70 | B4: 2
A5: - [ ] Рукомойник 50х50 | B5: 3
A6: - [ ] Рукомойник 40х40 | B6: 1
A8: - [ ] Стол 150х70 деревянная столешница | B8: 2
A9: - [ ] Стол 150х70 | B9: 8
A10: - [ ] Стол 150х60 | B10: 1
A11: - [ ] Стол 120х70 | B11: 7
A12: - [ ] Стол 120х70 состояние плохое | B12: 1
A13: - [ ] Стол 120х60 | B13: 1
A14: - [ ] Стол 70х90 | B14: 2
... A54: - [ ] Блок раздачи с полкой 112х73 с внутренними шкафами | B54: 1

Sheet Бинятов ассортимент
A1: БИНЯТОВСКИЙ ХЛЕБОКОМБИНАТ
A3: Адрес: г.Тюмень, Судостроителей 42
A5: Колл-центр: +7(3452)48-10-24, +7(922)489-6207
A7: Менеджер: +7 902 551-15-51
A9: Прайс-лист Хлебобулочной продукции 25.10.2024г.
A11: Наименование товаров | B11: Срок хранения (часов) | C11: Цена за шт./руб. | D11: Кол-во, шт
A12: ХЛЕБ Пшеничный
A13: Хлеб Пшеничный из муки первого сорта 0,5кг неупак. | B13: 24 | C13: 33
A14: Хлеб Пшеничный из муки первого сорта 0,5кг нарезка упак. | B14: 72 | C14: 36
A15: Хлеб Пшеничный из муки первого сорта 0,250 кг неупак. | B15: 24 | C15: 22
A16: Хлеб Пшеничный из муки первого сорта 0,250 кг упак. | B16: 72 | C16: 26
A17: Хлеб Тартин 0,4кг упак. | B17: 72 | C17: 44
A18: Хлеб Тартин 0,4кг неупак. | B18: 24 | C18: 40
A19: Хлеб Тостовый из муки высшего сорта 0,4кг нарезка упак. | B19: 72 | C19: 40
A20: Мини багет 0,200 кг неупак, шт. | B20: 24 | C20: 27
A21: Чиабатта пшеничная 0,250 кг неупак. шт. | B21: 24 | C21: 32
A22: ХЛЕБ пшенично-ржаной
A23: Хлеб Дарницкий 0,6кг неупак | B23: 24 | C23: 39
A24: Хлеб Дарницкий 0,6кг нарезка упак. | B24: 72 | C24: 44
A25: Хлеб Дарницкий 0,28кг нарезка упак. | B25: 72 | C25: 29
A26: Хлеб Бородинский 0,4кг неупак. | B26: 24 | C26: 37
A27: Хлеб Бородинский 0,4кг нарезка упак. | B27: 72 | C27: 40
A28: Хлеб ржано-пшеничный «Николаевский» 0,5кг неупак | B28: 24 | C28: 40
A29: Хлеб ржано-пшеничный «Николаевский» 0,5кг нарезка упак | B29: 96 | C29: 47
A30: Хлеб ржано-пшеничный «Николаевский» 0,24кг нарезка упак | B30: 96 | C30: 29
A31: Хлеб «Тостовый ржаной» 0,3кг нарезка упак. | B31: 96 | C31: 32
A32: Хлеб «Украинский новый» 0,55кг неупак | B32: 24 | C32: 38
A33: Хлеб «Украинский новый» 0,55кг нарезка упак. | B33: 72 | C33: 45
A34: Хлеб «Гречневый» 0,2 кг. упак. шт. | B34: 72 | C34: 38
... A37: Хлеб пшенично-ржаной "Купеческий" 0,250 кг упак. | B37: 72 | C37: 38
A38: ХЛЕБ Диетический/обогащенный
A39: Хлеб Бурже 0,3кг упак | B39: 96 | C39: 74
A40: Хлеб с отрубями 0,3кг неупак. | B40: 24 | C40: 32
A41: Хлеб с отрубями 0,3кг нарезка упак. | B41: 72 | C41: 36
A42: Хлеб Кукурузный 0,3кг неупак. | B42: 24 | C42: 62
A43: Хлеб Кукурузный 0,3кг упак. | B43: 72 | C43: 68
A44: Хлеб "Трапезный" бездрожжевой 0,25 кг неупак., шт | B44: 24 | C44: 43
A45: Хлеб "Трапезный" бездрожжевой 0,25 кг упак., шт | B45: 72 | C45: 45
A46: Батон с отрубями 0,3кг нарезка упак. | B46: 96 | C46: 38
A47: БУЛОЧНЫЕ изделия
A48: Батон особый 0,4кг нарезка упак. | B48: 72 | C48: 35
A49: Батон нарезной молочный 0,3кг упак. | B49: 72 | C49: 40
A50: Батон Столичный упак 0,4кг | B50: 72 | C50: 33
A51: Булочка «Ромашка с маком» 0,3кг упак. | B51: 72 | C51: 65
A52: МЕЛКОШТУЧНЫЕ изделия сдобные
A53: Булочка домашняя 0,08кг упак. | B53: 72 | C53: 24 | D53: 280
A54: Булочка ромашка 0,08кг упак. | B54: 72 | C54: 25 | F54: в 280 шт "сдидит" 195 шт СПК и по 5 шт на каждый маркет (17 шт)
A55: Булочка с повидлом 0,08кг упак. | B55: 120 | C55: 25 | D55: 280
A56: Рулетик с корицей 0,1кг упак. | B56: 72 | C56: 34 | D56: 280
A57: Сырные палочки 0,08кг упак | B57: 72 | C57: 28
A58: Ватрушка с творогом и вишней 0,130 кг упак, шт. | B58: 72 | C58: 41
A59: Булочка "Творожная" 0,100 кг упак, шт. | B59: 72 | C59: 29
A60: Булочка с маком, 0,100 кг упак, шт. | B60: 72 | C60: 31 | D60: 280
A61: МЕЛКОШТУЧНЫЕ изделия из Слоеного теста
A62: Слойка Свердловская 0,1кг упак. | B62: 72 | C62: 30
A63: Слойка с яблоками 0,1кг упак | B63: 72 | C63: 39
A64: Слойка с малиной 0,1кг упак | B64: 72 | C64: 43
A65: Слойка с творогом 0,1кг упак | B65: 24 | C65: 40
A66: Слойка «Нежная» (с сыром) 0,1кг упак. | B66: 72 | C66: 41
A67: Слойка с ветчиной и сыром 0,100кг, упак, шт. | B67: 72 | C67: 43
A68: Слойка со шпинатом 0,100кг, упак, шт. | B68: 72 | C68: 41 | D68: 280
A69: Хачапури слоенный 0,1кг упак,шт | B69: 72 | C69: 48 | D69: 280
A70: НАЦИОНАЛЬНЫЕ изделия
A71: Лепешка с сыром 0,3кг упак. | B71: 72 | C71: 54
A72: Лепешка пшеничная 0,25 упак, шт | B72: 72 | C72: 26
A73: КУЛИНАРИЯ
A74: Пицца с колбасой 0,15кг упак | B74: 48ч t от 0 до+5 | C74: 76
A75: Сосиска в тесте 0,110кг упак | B75: 48ч t от 0 до+5 | C75: 40 | D75: 280
A76: Самса с куриной грудкой упак 0,15кг упак | B76: 48ч t от 0 до+5 | C76: 54
A77: ТЕСТО
A78: Тесто дрожжевое 1кг упак. | B78: 24ч t от 0 до+5 | C78: 75
A79: Тесто сдобное 1кг упак. | B79: 24ч t от 0 до+5 | C79: 81
A80: Тесто слоеное дрожжевое 0,5кг упак. | B80: 30 дней t -18 | C80: 64

Sheet Расчет Реском
B2: Матрица блюд ПЕРВАЯ неделя
C3: код | D3: Завтрак | E3: Шт | F3: код | G3: Салат | H3: Шт | I3: код | J3: Суп | K3: Шт | L3: код | M3: Второе | N3: Шт | O3: код | P3: Выпечка | Q3: Шт | R3: код | S3: Сэндвич | T3: Шт | U3: код | V3: Япония | W3: Шт
A4: 46145 | B4: Вс. | C4: 385 | D4: Омлет воздушный | E4: 83 | F4: 3076 | G4: Салат ''Оливье'' (колбаса варен) | H4: 98 | I4: 793 | J4: Борщ с курицей | K4: 106 | L4: 4013 | M4: Свинина с тмином со сложным гарниром | N4: 187 | X4: Птица
C5: 4036 | D5: Каша рисовая с вишней | E5: 114 | F5: 4009 | G5: Салат ''Винегрет'' (без капусты) 120 г | H5: 98 | I5: 822 | J5: Хлеб пшеничный | K5: 5 | L5: 4014 | M5: Филе с сыром и макаронами | N5: 205 | X5: Свинина
X6: Рыба
X7: Покупное
X8: Говядина
C12: код | D12: Завтрак | E12: Шт | F12: код | G12: Салат | H12: Шт | I12: код | J12: Суп | K12: Шт | L12: код | M12: Второе | N12: Шт | O12: код | P12: Выпечка | Q12: Шт | R12: код | S12: Сэндвич | T12: Шт | U12: код | V12: Япония | W12: Шт
A13: 46146 | B13: пн | C13: 2730 | D13: Блины со сгущенкой | F13: 4024 | G13: Салат "Чешский" (колбаса п/к) | I13: 8 | J13: Суп гороховый 250 мл | L13: 48 | M13: Голубец с картофельным пюре | O13: 3435 | P13: Булочка с повидлом 80 г | R13: 654 | S13: Сэндвич с бужениной и соусом Релиш | U13: 2943 | V13: Онигири с куриным филе в соусе спайси
C14: 1550 | D14: Омлет с овощами и сыром | F14: 3379 | G14: Салат ''Зайка'' 120 г | L14: 4026 | M14: Минтай в сырной корочке с рисом радуга | O14: 3455 | P14: Слойка с ветчиной и сыром 100г | R14: 2083 | S14: Сэндвич ''Цезарь''
F15: 3244 | G15: Салат ''Крабик'' с рисом | I15: 822 | J15: Хлеб пшеничный | L15: 4030 | M15: Курочка с овощной сальсой и спагетти | U15: 4000 | V15: Компот из сухофруктов 0,5 л
F16: 3343 | G16: Боул с тунцом , бобами эдамаме и овощами | L16: 859 | M16: Бедро запеченное с макаронами | N16: только СПК
L17: 958 | M17: Поджарка из курицы с рисом
L18: 4029 | M18: Жаркое по-домашнему со свининой | N18: только СПК
L19: 238 | M19: Жаркое по-домашнему 400 грамм | N19: СПК
C21: код | D21: Завтрак | E21: Шт | F21: код | G21: Салат | H21: Шт | I21: код | J21: Суп | K21: Шт | L21: код | M21: Второе | N21: Шт | O21: код | P21: Выпечка | Q21: Шт | R21: код | S21: Сэндвич | T21: Шт | U21: код | V21: Япония | W21: Шт
A22: 46147 | B22: Вт. | C22: 4035 | D22: Драники с сырной начинкой | F22: 3233 | G22: Салат ''Винегрет'' (без капусты) 120 г | I22: 386 | J22: Суп ''Харчо'' с курицей | L22: 761 | M22: Бризоль с рисом и овощами | O22: 3375 | P22: Самса с куриной грудкой 150 грамм | R22: 3486 | S22: Сэндвич с курицей и соусом карри | U22: 3722 | V22: Онигири с куриным филе в соусе том ям
C23: 4036 | D23: Каша рисовая с вишней | F23: 3301 | G23: Салат ''Блинный'' (ветчина куриная) | I23: 822 | J23: Хлеб пшеничный | L23: 4172 | M23: Свинина в соусе тонкацу со спагетти | R23: 2782 | S23: Сэндвич с пепперони и сыром
C24: 3045 | D24: Сырники с вишневой начинкой | F24: 4038 | G24: Салат "Гавайский" (курица, ананас) | L24: 4031 | M24: Мясо по-французски (свинина) | N24: спк | U24: 3997 | V24: Морс облепиховый 0,5 л
L25: 3437 | M25: Макароны по-флотски | N25: СПК
F26: 4034 | G26: Гранатовый браслет 220гр | L26: 763 | M26: Котлета куриная с картофельным пюре | N26: только СПК
L28: 3827 | M28: Курица Пармиджано с фарфале
L29: 3883 | M29: Аджапсандал
C30: код | D30: Завтрак | E30: Шт | F30: код | G30: Салат | H30: Шт | I30: код | J30: Суп | K30: Шт | L30: код | M30: Второе | N30: Шт | O30: код | P30: Выпечка | Q30: Шт | R30: код | S30: Сэндвич | T30: Шт | U30: код | V30: Япония | W30: Шт
A31: 46148 | B31: Ср. | C31: 4045 | D31: Панкейки шоколадные с вареньем | F31: 4048 | G31: Салат "Капустный" в маринаде | I31: 380 | J31: Солянка | L31: 4120 | M31: Курочка в сливочном соусе со спагетти | N31: СПК | O31: 3527 | P31: Хачапури 100 гр | R31: 3330 | S31: Сэндвич с курицей и соусом Барбекю | U31: 3723 | V31: Онигири с лососем и крем чиз
C32: 4056 | D32: Блинчики с курицей и грибами | F32: 4053 | G32: Салат "Арлекино" (колбаса вар.) | I32: 3752 | J32: Солянка мясная Комбо | L32: 1873 | M32: Колбаса ''Баварская'' с пюре и тушеной капустой | O32: 3454 | P32: Рулетик с корицей 100 гр | R32: 4051 | S32: Сэндвич с бужениной и горчичным соусом
F33: 4055 | G33: Салат "Чикаго" (кура копченая) | I33: 822 | J33: Хлеб пшеничный | L33: 1151 | M33: Тефтели куриные с гречкой | N33: СПК | O33: 2079 | P33: Вафельная трубочка с вареной сгущенкой | Q33: 200 | U33: 1474 | V33: Морс ягодный 0,5 л
F34: 3339 | G34: Боул ''Курица в имбирном соусе с овощами'' | L34: 1073 | M34: Горбуша запеченная с картофельным пюре
L35: 3663 | M35: Горбуша запеченная с рисом светофор | N35: только СПК
L37: 4032 | M37: Печень по-царски со сливочным пюре
C39: код | D39: Завтрак | E39: Шт | F39: код | G39: Салат | H39: Шт | I39: код | J39: Суп | K39: Шт | L39: код | M39: Второе | N39: Шт | O39: код | P39: Выпечка | Q39: Шт | R39: код | S39: Сэндвич | T39: Шт | U39: код | V39: Япония | W39: Шт
A40: 46149 | B40: Чт. | C40: 2951 | D40: Каша овсяная с яблоком и корицей | F40: 3323 | G40: Салат ''Морковь с чесноком'' 120гр | I40: 2288 | J40: Суп картофельный с курицей | O40: 3528 | P40: Сырная палочка | R40: 3223 | S40: Сэндвич с индейкой су-вид и овощами | U40: 3996 | V40: Морс вишневый 0,5 л
C41: 4037 | D41: Шарлотка с яблоком | F41: 4058 | G41: Салат "Городской"(колбаса вареная) | I41: 822 | J41: Хлеб пшеничный | L41: 4069 | M41: Бефстроганов (говядина) с картофелем | N41: пюре | R41: 5 | S41: Сэндвич с ветчиной и сыром | U41: 3021 | V41: Морс из ч/смородины 0,5 л
C42: 4070 | D42: Скрембл с сосиской и соусом | F42: 2706 | G42: Салат ''Фасолька'' с курицей | L42: 4067 | M42: Бефстроганов (говядина) с рисом | N42: рис
F43: 3823 | G43: Салат "Мимоза" с рыбой 220гр | L43: 4068 | M43: Бефстроганов (говядина) с макаронами | N43: макарон
L44: 547 | M44: Куриные шашлычки с картофелем запеченным
L45: 26 | M45: Плов по-узбекски с цыпленком б/250гр
L47: 3328 | M47: Спагетти с соусом ''Болоньезе'' 400 г
N48: ,
B49: Матрица блюд ВТОРАЯ неделя
C50: код | D50: Завтрак | E50: Шт | F50: код | G50: Салат | H50: Шт | I50: код | J50: Суп | K50: Шт | M50: Второе | N50: Шт | O50: код | P50: Выпечка | Q50: Шт | R50: код | S50: Сэндвич | T50: Шт | U50: код | V50: Япония | W50: Шт
A51: 46152 | B51: Вс. | C51: 3290 | D51: Каша пшенная с курагой | E51: 137 | F51: 2686 | G51: Салат ''Коул Слоу'' 120 гр | H51: 217 | I51: 793 | J51: Борщ с курицей | K51: 209 | L51: 3737 | M51: Чкмерули из курицы со спагетти | N51: СПК | Q51: 206 | R51: 3 | S51: Сэндвич с курочкой и скремблом | T51: 94 | W51: 91 | X51: Птица
C52: 3045 | D52: Сырники с вишневой начинкой | E52: 142 | F52: 3147 | G52: Салат ''Столичный'' (филе кур) | H52: 200 | I52: 822 | J52: Хлеб пшеничный | L52: 1009 | M52: Свинина по-баварски с картофелем | N52: 106 | Q52: 25 | R52: 2364 | S52: Сэндвич с ветчиной и томатом | T52: 99 | X52: Свинина
E53: 79 | H53: 132 | L53: 546 | M53: Филе с грибами и рисом | N53: СПК | U53: 3996 | V53: Морс вишневый 0,5 л | X53: Рыба
H54: 57 | N54: 108 | X54: Покупное
N55: СПК | X55: Говядина
N57: 75
C59: код | D59: Завтрак | E59: Шт | F59: код | G59: Салат | H59: Шт | I59: код | J59: Суп | K59: Шт | L59: код | M59: Второе | N59: Шт | O59: код | P59: Выпечка | Q59: Шт | R59: код | S59: Сэндвич | T59: Шт | U59: код | V59: Япония | W59: Шт
A60: 46153 | B60: Пн. | C60: 1287 | D60: Блины со сметаной | E60: 110 | F60: 3080 | G60: Салат ''Спаржа с морковью'' 110 гр | H60: 159 | I60: 1394 | J60: Суп-харчо с говядиной | K60: 181 | L60: 4080 | M60: Мясные гнёзда с овощами и картофелем | N60: СПК | O60: 3455 | P60: Слойка с ветчиной и сыром 100г | Q60: 20 | R60: 4050 | S60: Клаб-сэндвич с курицей и беконом | T60: 84 | U60: 2929 | V60: Ролл сэндвич с курицей | W60: 76
C61: 3426 | D61: Ленивые хачапури | E61: 94 | F61: 2175 | G61: Салат ''Баварский'' (колбаса в/к) | H61: 159 | I61: 3782 | J61: Борщ с говядиной комбо | K61: 25 | L61: 1939 | M61: Котлета из щуки с пюре картофельным | N61: 194 | O61: 3435 | P61: Булочка с повидлом 80 г | Q61: 25 | R61: 2904 | S61: Ассорти сэндвич (пепперони/ветчина) | T61: 114 | U61: 3996 | V61: Морс вишневый 0,5 л | W61: 61
C62: 4098 | D62: Шоколадный пирог с вишней | E62: 69 | F62: 3814 | G62: Салат Фаворит (филе кур., грибы) | H62: 158 | L62: 1982 | M62: Вок с курицей и рисом | N62: СПК | O62: 2079 | P62: Вафельная трубочка с вареной сгущенкой | U62: 3998 | V62: Морс из ч/смородины 0,5 л
F63: 3327 | G63: Салат из свеклы, печеной тыквы и мягким сыром | H63: 82 | L63: 1267 | M63: Печень куриная с овощами с гречкой | N63: СПК
L64: 2976 | M64: Курочка в томатном соусе с рисом | N64: 41
L66: 3266 | M66: Чахохбили с макаронами 400гр | N66: 55
C68: код | D68: Завтрак | E68: Шт | F68: код | G68: Салат | H68: Шт | I68: код | J68: Суп | K68: Шт | L68: код | M68: Второе | N68: Шт | O68: код | P68: Выпечка | Q68: Шт | R68: код | S68: Сэндвич | T68: Шт | U68: код | V68: Япония | W68: Шт
A69: 46154 | B69: Вт. | D69: Венские вафли с повидлом | F69: 3189 | G69: Салат Свекла с сыром и чесноком 120гр | I69: 2288 | J69: Суп картофельный с курицей | L69: 813 | M69: Котлета по-киевски с макаронами | O69: 3375 | P69: Самса с куриной грудкой 150 грамм | Q69: 20 | R69: 4051 | S69: Сэндвич с бужениной и горчичным соусом | U69: 4086 | V69: Онигири с курицей в ореховом соусе | W69: ?
C70: 3253 | D70: Шакшука с томатом | F70: 3216 | G70: Салат ''Таврия'' (колбаса вареная) | L70: 4105 | M70: Свинина по-гавайски с картофелем | R70: 3140 | S70: Сэндвич ''Снежный краб'' с соусом спайси | W70: 78
F71: 2303 | G71: Салат ''Жар-птица'' (филе кур) | L71: 26 | M71: Плов по-узбекски с цыпленком б/250гр | N71: СПК | R71: 4000 | S71: Компот из сухофруктов 0,5 л
F72: 4089 | G72: Салат "Генеральский" (курица, грецкий орех) 220гр | L72: 4100 | M72: Курочка по-купечески с гречкой | N72: Спк
L73: 3474 | M73: Свинина в томатном соусе с макаронами | N73: спк
L74: 3872 | M74: Запеченый баклажан с перцем рамиро
L75: 4102 | M75: Соба с индейкой в устричном соусе
C77: код | D77: Завтрак | E77: Шт | F77: код | G77: Салат | H77: Шт | I77: код | J77: Суп | K77: Шт | L77: код | M77: Второе | N77: Шт | O77: код | P77: Выпечка | Q77: Шт | R77: код | S77: Сэндвич | T77: Шт | U77: код | V77: Япония | W77: Шт
A78: 46043 | B78: Ср. | C78: 3014 | D78: Драники картофельные с цукини со сметаной | E78: 94 | F78: 4088 | G78: Салат "Морской" (капуста морская) | I78: 380 | J78: Солянка | L78: 3889 | M78: Купаты куриные с овощным гарниром | O78: 3454 | P78: Рулетик с корицей 100 гр | R78: 2083 | S78: Сэндвич ''Цезарь'' | U78: 3738 | V78: Ролл сэндвич с крабом | W78: 70
C79: 2980 | D79: Каша овсяная с курагой и изюмом | E79: 124 | F79: 1160 | G79: Салат ''Пикник'' (печень) | I79: 3799 | J79: Лагман с говядиной комбо | L79: 1899 | M79: Горбуша в сырной корочке с картофелем | O79: 3527 | P79: Хачапури 100 гр | R79: 2782 | S79: Сэндвич с пепперони и сыром | U79: 2079 | V79: Вафельная трубочка с вареной сгущенкой
C80: 2423 | D80: Сырники со сгущенкой | E80: 84 | F80: 31 | G80: Салат ''Прага'' (ветчина кур.) | L80: 965 | M80: Гуляш ''по-домашнему'' с макаронами | N80: СПК | O80: 2079 | P80: Вафельная трубочка с вареной сгущенкой | U80: 3999 | V80: Морс ягодный 0,5 л
F81: 3306 | G81: Боул с курицей, бобами эдамаме и овощами | L81: 1168 | M81: Наггетсы с соусом
L82: 4099 | M82: Курочка в сырном соусе со спагетти | N82: Спк
L83: 2631 | M83: Минтай по-московски с запеченным картофелем | N83: СПК
L84: 4104 | M84: Чанахи из свинины 400гр
C86: код | D86: Завтрак | E86: Шт | F86: код | G86: Салат | H86: Шт | I86: код | J86: Суп | K86: Шт | L86: код | M86: Второе | N86: Шт | O86: код | P86: Выпечка | Q86: Шт | R86: код | S86: Сэндвич | T86: Шт | U86: код | V86: Япония | W86: Шт
A87: 46044 | B87: Чт. | C87: 89 | D87: Блин с ветчиной и сыром | F87: 3654 | G87: Салат ''Зимний'' (колбаса варен) | I87: 8 | J87: Суп гороховый 250 мл | L87: 3768 | M87: Паприкаш из говядины с гречкой | O87: 3528 | P87: Сырная палочка 80 гр | R87: 5 | S87: Сэндвич с ветчиной и сыром | U87: 3996 | V87: Морс вишневый 0,5 л | W87: 70
C88: 4111 | D88: Оладьи со сгущенкой | F88: 3180 | G88: Салат ''Морковь по-корейски'' 120 г | L88: 3770 | M88: Паприкаш из говядины с картофельным пюре | R88: 3330 | S88: Сэндвич с курицей и соусом Барбекю | U88: 3998 | V88: Морс из ч/смородины 0,5 л
C89: 2936 | D89: Манник | F89: 3141 | G89: Салат из свежей капусты 120 г | L89: 3769 | M89: Паприкаш из говядины с макаронами
F90: 2067 | G90: Салат "Греческий'' | L90: 2859 | M90: Обед ''Студенческий''
L91: 898 | M91: Лазанья ''Аппетитная''
L92: 763 | M92: Котлета куриная с картофельным пюре | N92: 111
L93: 3798 | M93: Говядина томленая с рисом
B96: Матрица блюд ТРЕТЬЯ неделя
C97: код | D97: Завтрак | E97: Шт | F97: код | G97: Салат | H97: Шт | I97: код | J97: Суп | K97: Шт | L97: код | M97: Второе | N97: Шт | O97: код | P97: Выпечка | Q97: Шт | R97: код | S97: Сэндвич | T97: Шт | U97: код | V97: Япония | W97: Шт
A98: 46103 | B98: Вс. | C98: 3341 | D98: Запеканка творожная с персиком | E98: 113 | F98: 3076 | G98: Салат ''Оливье'' (колбаса варен) | H98: 172 | I98: 793 | J98: Борщ с курицей | K98: 177 | L98: 4013 | M98: Куриная ножка с макаронами | N98: 118 | O98: 3518 | P98: Слойка ''Нежная'' с сыром 100 г | Q98: 0 | R98: 2364 | S98: Сэндвич с ветчиной и томатом | T98: 119 | U98: 3998 | V98: Морс из ч/смородины 0,5 л | W98: 110 | X98: Птица
C99: 4019 | D99: Каша пшенная с киноа и изюмом | E99: 90 | F99: 4009 | G99: Салат "Маковый" (курица, мак) | H99: 174 | J99: Хлеб пшеничный | K99: 42 | L99: 4014 | M99: Филе с сыром и печеным картофелем | N99: СПК | O99: 2079 | P99: Вафельная трубочка с вареной сгущенкой | R99: 33 | S99: Сэндвич с копчёной курицей и сыром | T99: 122 | U99: 3630 | V99: Онигири с чукой и ореховым соусом | W99: 91 | X99: Свинина
C100: 3446 | D100: Блинчики с мясом и рисом | E100: 118 | F100: 3170 | G100: Салат ''Фунчоза'' 120 г | H100: 182 | L100: 3054 | M100: Минтай под овощами с желтым рисом | N100: СПК | X100: Рыба
F101: 2621 | G101: Салат ''Цезарь с курицей'' | H101: 66 | L101: 4015 | M101: Свинина с тмином со сложным гарниром | N101: СПК | X101: Покупное
X102: Говядина
L103: 4016 | M103: Плов с грибами | X103: Премиум
L104: 2931 | M104: Паста Карбонара с беконом | N104: 76
F105: 1050 | G105: Азу ''По-татарски''
C106: код | D106: Завтрак | E106: Шт | F106: код | G106: Салат | H106: Шт | I106: код | J106: Суп | K106: Шт | L106: код | M106: Второе | N106: Шт | Q106: Шт | R106: код | S106: Сэндвич | T106: Шт | U106: код | V106: Япония | W106: Шт
A107: 46104 | B107: пн | C107: 2730 | D107: Блины со сгущенкой | E107: 118 | F107: 4024 | G107: Салат "Чешский" (колбаса п/к) | H107: 180 | I107: 8 | J107: Суп гороховый 250 мл | K107: 182 | L107: 48 | M107: Голубец с картофельным пюре | O107: 3435 | P107: Булочка с повидлом 80 г | Q107: 25 | R107: 3330 | S107: Сэндвич с курицей и соусом Барбекю | T107: 118 | U107: 4000 | V107: Компот из сухофруктов 0,5 л | W107: 118
C108: 1550 | D108: Омлет с овощами и сыром | E108: 72 | F108: 3379 | G108: Салат ''Зайка'' 120 г | H108: 194 | L108: 4026 | M108: Минтай в сырной корочке с рисом радуга | N108: 119 | O108: 3455 | P108: Слойка с ветчиной и сыром 100г | Q108: 25 | R108: 54 | S108: Сэндвич с тунцом с соусом Том Ям | T108: 117 | U108: 2943 | V108: Онигири с куриным филе в соусе спайси | W108: 83
E109: 136 | F109: 3244 | G109: Салат ''Крабик'' с рисом | H109: 173 | L109: 4030 | M109: Курочка с овощной сальсой и спагетти | Q109: 150
F110: 3343 | G110: Боул с тунцом , бобами эдамаме и овощами | H110: 87 | L110: 4025 | M110: Бедро в пряном соусе с гречкой | N110: СПК
L111: 958 | M111: Поджарка из курицы с рисом | N111: СПК
L113: 4029 | M113: Жаркое по-домашнему со свининой | N113: СПК
L114: 238 | M114: Жаркое по-домашнему 400 грамм | N114: 92
C115: код | D115: Завтрак | E115: Шт | F115: код | G115: Салат | H115: Шт | I115: код | J115: Суп | K115: Шт | L115: код | M115: Второе | N115: Шт | O115: код | P115: Выпечка | Q115: Шт | R115: код | S115: Сэндвич | T115: Шт | U115: код | V115: Япония | W115: Шт
A116: 46105 | B116: Вт. | C116: 4035 | D116: Драники с сырной начинкой | E116: 125 | G116: Салат ''Винегрет с капустой'' 120 г | H116: 140 | I116: 386 | J116: Суп ''Харчо'' с курицей | K116: 161 | L116: 761 | M116: Бризоль с рисом и овощами | O116: 3375 | P116: Самса с куриной грудкой 150 грамм | Q116: 20 | R116: 3486 | S116: Сэндвич с курицей и соусом карри | T116: 109 | V116: Морс ягодный 0,5 л | W116: 108
C117: 4036 | D117: Каша рисовая с вишней | E117: 82 | F117: 3301 | G117: Салат ''Блинный'' (ветчина куриная) | H117: 175 | K117: 41 | L117: 4172 | M117: Свинина в соусе тонкацу со спагетти | N117: 140 | R117: 3140 | S117: Сэндвич ''Снежный краб'' с соусом спайси | T117: 79 | U117: 3723 | V117: Онигири с лососем и крем чиз | W117: 82
C118: 3045 | D118: Сырники с вишневой начинкой | E118: 97 | F118: 4038 | G118: Салат "Гавайский" (курица, ананас) | H118: 170 | L118: 4031 | M118: Мясо по-французски (свинина) | N118: СПК
...

Sheet Ёмкость точек
E1: Точки и ёмкость по категориям
A2: Ёмкость = макс. количество порций/единиц в холодильнике точки по категории. 0 = категория не везётся.
A3: № ТОЧКИ | B3: НАИМЕНОВАНИЕ ТОЧКИ | C3: Супы | D3: Салаты | E3: Вторые блюда | F3: Сэндвичи | G3: Завтраки | H3: Япония | I3: Напитки | J3: Десерты | K3: АКТИВНА
A4: 01 | B4: ЛеманаПРО Тобольский | C4: 3 | D4: 25 | E4: 32 | F4: 17 | G4: 17 | H4: 9 | I4: 12 | J4: 9 | K4: Да
A5: 02 | B5: Очаково | C5: 1 | D5: 7 | E5: 10 | F5: 4 | G5: 5 | H5: 3 | I5: 2 | J5: 2 | K5: Да
A6: 03 | B6: ЗапСибГазпром | C6: 1 | D6: 4 | E6: 8 | F6: 6 | G6: 5 | H6: 1 | I6: 2 | J6: 1 | K6: Да
A7: 04 | B7: Технологии ОФС | C7: 2 | D7: 7 | E7: 24 | F7: 8 | G7: 12 | H7: 2 | I7: 11 | J7: 4 | K7: Да
A8: 05 | B8: Бентек | C8: 2 | D8: 20 | E8: 29 | F8: 11 | G8: 15 | H8: 2 | I8: 13 | J8: 5 | K8: Да
A9: 06 | B9: ОФС Тобольский тр-т | C9: 1 | D9: 12 | E9: 18 | F9: 8 | G9: 4 | H9: 1 | I9: 7 | J9: 1 | K9: Да
A10: 07 | B10: Металл Профиль | C10: 1 | D10: 8 | E10: 9 | F10: 6 | G10: 5 | H10: 0 | I10: 6 | J10: 2 | K10: Да
A11: 08 | B11: ТубДиспансер | C11: 2 | D11: 13 | E11: 15 | F11: 7 | G11: 10 | H11: 2 | I11: 6 | J11: 3 | K11: Да
A12: 09 | B12: АИРТО | C12: 1 | D12: 15 | E12: 18 | F12: 8 | G12: 13 | H12: 3 | I12: 6 | J12: 4 | K12: Да
A13: 10 | B13: Скорая Суходольская | C13: 1 | D13: 11 | E13: 16 | F13: 9 | G13: 11 | H13: 3 | I13: 15 | J13: 6 | K13: Да
A14: 11 | B14: КАТРЕН | C14: 0 | D14: 6 | E14: 17 | F14: 5 | G14: 7 | H14: 0 | I14: 5 | J14: 5 | K14: Да
A15: 12 | B15: СПК АБК малое | C15: 1 | D15: 9 | E15: 11 | F15: 8 | G15: 10 | H15: 3 | I15: 5 | J15: 6 | K15: Да
... A32: 29 | B32: Поликлиника 17 (Монтажников) | C32: 1 | D32: 25 | E32: 29 | F32: 23 | G32: 20 | H32: 10 | I32: 18 | J32: 5 | K32: Да

Sheet карта готовности
A1: Общая рабочая таблица для пароконвектомата
A3: Температура по щупу — точка немедленной выгрузки.
A5: Тип сырья / изделия | B5: Температура камеры | C5: Влажность | D5: Температура готовности по щупу
A6: Курица, филе бедра | B6: 150 °C | C6: 0.6 | D6: 74 °C
A7: Курица, филе грудки | B7: 140 °C | C7: 0.8 | D7: 74 °C
A8: Свинина, порционные куски без кости | B8: 145 °C | C8: 0.6 | D8: 70 °C
A9: Говядина, порционные куски без кости | B9: 140 °C | C9: 0.7 | D9: 70 °C
A10: Баранина, порционные куски без кости | B10: 140 °C | C10: 0.7 | D10: 70 °C
A11: Рыба, филе или порционные куски | B11: 130 °C | C11: 0.8 | D11: 63 °C
A12: Фарш из говядины, свинины, смешанный фарш | B12: 140 °C | C12: 0.8 | D12: 72 °C
A13: Фарш из курицы или индейки | B13: 140 °C | C13: 0.8 | D13: 74 °C
A14: Котлеты из говядины, свинины, смешанного фарша | B14: 150 °C | C14: 0.6 | D14: 72 °C
A15: Котлеты из курицы или индейки | B15: 150 °C | C15: 0.6 | D15: 74 °C
A16: Котлеты рыбные | B16: 140 °C | C16: 0.7 | D16: 70 °C
A17: Запеканка с сырым мясом, птицей, рыбой или фаршем | B17: 140 °C | C17: 0.8 | D17: 74 °C
A18: Запеканка творожная или яичная | B18: 140 °C | C18: 0.7 | D18: 72 °C
A20: Температуру щупа не снижать при корректировке режима.
A22: Правила применения
A23: Камера должна быть предварительно разогрета.
A24: Сырьё — охлаждённое, полностью размороженное.
A25: Куски размещать в один слой без наложения.
A26: Щуп вводить в геометрический центр самого толстого изделия.
A27: Для запеканки щуп ставить в центр формы, в наиболее толстую часть.
A28: При достижении температуры по щупу продукт немедленно выгрузить.
A29: Если в смешанном составе присутствует сырая курица или индейка, устанавливать 74 °C.

Sheet Справочник + атрибуты
A1: По названию
A2: код | B2: Цена | C2: Название блюда | E2: Категория | F2: Атрибут 1 | G2: Атрибут 2 | H2: Атрибут 3 | I2: Эксперимент | J2: Комментарий | K2: Статус атрибутов | L2: Дата добавления | M2: Источник добавления | N2: Дата последней проверки
A3: 4013 | B3: 258 | C3: Фаршированная куриная ножка с макаронами | E3: Вторые блюда | F3: макароны | G3: курица | H3: кусок
A4: 4014 | B4: 210 | C4: Филе с сыром и печеным картофелем | E4: Вторые блюда | F4: картофель | G4: курица | H4: кусок
A5: 4015 | B5: 187 | C5: Свинина с тмином со сложным гарниром | E5: Вторые блюда | F5: овощи | G5: свинина | H5: соусное
A6: 4016 | B6: 148 | C6: Плов с грибами | E6: Вторые блюда | F6: моно-блюдо | G6: без мяса
A7: 1333 | B7: 188 | C7: Горбуша под овощной шапкой с рисом | E7: Вторые блюда | F7: рис | G7: рыба | H7: кусок
A8: 4196 | B8: 205 | C8: Филе с сыром и макаронами | E8: Вторые блюда | F8: макароны | G8: курица | H8: кусок
A9: 2931 | B9: 273 | C9: Паста Карбонара с беконом | E9: Вторые блюда | F9: макароны | G9: свинина | H9: соусное
A10: 763 | B10: 198 | C10: Котлета куриная с картофельным пюре | E10: Вторые блюда | F10: картофель | G10: курица | H10: фарш
A11: 48 | B11: 198 | C11: Голубец с картофельным пюре | E11: Вторые блюда | F11: картофель | G11: свинина | H11: фарш
A12: 4026 | B12: 232 | C12: Минтай в сырной корочке с рисом радуга | E12: Вторые блюда | F12: рис | G12: рыба | H12: кусок
A13: 4030 | B13: 198 | C13: Курочка с овощной сальсой и спагетти | E13: Вторые блюда | F13: макароны | G13: курица | H13: соусное
A14: 859 | B14: 198 | C14: Бедро запеченное с макаронами | E14: Вторые блюда | F14: макароны | G14: курица | H14: кусок
A15: 958 | B15: 180 | C15: Поджарка из курицы с рисом | E15: Вторые блюда | F15: рис | G15: курица | H15: соусное
A16: 4029 | B16: 198 | C16: Жаркое по-домашнему со свининой | E16: Вторые блюда | F16: моно-блюдо | G16: свинина
A17: 238 | B17: 198 | C17: Жаркое по-домашнему 400 грамм | E17: Вторые блюда | F17: моно-блюдо | G17: свинина
A18: 761 | B18: 180 | C18: Бризоль с рисом и овощами | E18: Вторые блюда | F18: рис | G18: курица | H18: кусок
A19: 4172 | B19: 203 | C19: Свинина в соусе тонкацу со спагетти | E19: Вторые блюда | F19: макароны | G19: свинина | H19: соусное
A20: 18 | B20: 198 | C20: Мясо по-французски | E20: Вторые блюда | F20: картофель | G20: курица
A21: 4031 | B21: 211 | C21: Мясо по-французски (свинина) | E21: Вторые блюда | F21: картофель | G21: свинина
A22: 3437 | B22: 188 | C22: Макароны по-флотски | E22: Вторые блюда | F22: макароны | G22: курица
A23: 102 | B23: 264 | C23: Соба с курицей в устричном соусе | E23: Вторые блюда | F23: макароны | G23: курица | H23: соусное
A24: 3517 | B24: 215 | C24: Тилапия в соусе сальса с рисом | E24: Вторые блюда | F24: рис | G24: рыба | H24: кусок
A25: 1873 | B25: 188 | C25: Колбаса ''Баварская'' с пюре и тушеной капустой | E25: Вторые блюда | F25: овощи | G25: свинина | H25: кусок
A26: 1151 | B26: 198 | C26: Тефтели куриные с гречкой | E26: Вторые блюда | F26: крупа | G26: курица | H26: фарш
A27: 1073 | B27: 188 | C27: Горбуша запеченная с картофельным пюре | E27: Вторые блюда | F27: картофель | G27: рыба | H27: кусок
A28: 3239 | B28: 215 | C28: Минтай под овощами с рисом Радуга | E28: Вторые блюда | F28: рис | G28: рыба | H28: кусок
A29: 4032 | B29: 210 | C29: Печень по-царски со сливочным пюре | E29: Вторые блюда | F29: картофель | G29: говядина | H29: соусное
A30: 1327 | B30: 188 | C30: Манты по-дагестански | E30: Вторые блюда | F30: без гарнира | G30: свинина
A31: 4069 | B31: 265 | C31: Бефстроганов (говядина) с картофелем | E31: Вторые блюда | F31: картофель | G31: говядина | H31: соусное
A32: 4067 | B32: 265 | C32: Бефстроганов (говядина) с рисом | E32: Вторые блюда | F32: рис | G32: говядина | H32: соусное
A33: 4068 | B33: 265 | C33: Бефстроганов (говядина) с макаронами | E33: Вторые блюда | F33: макароны | G33: говядина | H33: соусное
A34: 547 | B34: 215 | C34: Куриные шашлычки с картофелем запеченным | E34: Вторые блюда | F34: картофель | G34: курица | H34: кусок
A35: 26 | B35: 165 | C35: Плов по-узбекски с цыпленком б/250гр | E35: Вторые блюда | F35: моно-блюдо | G35: курица
A36: 2687 | B36: 188 | C36: Котлета куриная с картофелем | E36: Вторые блюда | F36: картофель | G36: курица | H36: фарш
A37: 113 | B37: 198 | C37: Спагетти ''Болоньезе'' | E37: Вторые блюда | F37: моно-блюдо | G37: свинина
A38: 3737 | B38: 208 | C38: Чкмерули из курицы со спагетти | E38: Вторые блюда | F38: макароны | G38: курица | H38: соусное
A39: 1009 | B39: 160 | C39: Свинина по-баварски с картофелем | E39: Вторые блюда | F39: картофель | G39: курица | H39: соусное
A40: 980 | B40: 188 | C40: Филе с грибами и картофельным пюре | E40: Вторые блюда | F40: картофель | G40: курица | H40: кусок
A41: 4175 | B41: 198 | C41: Минтай в маринаде с картофельным пюре | E41: Вторые блюда | F41: картофель | G41: рыба | H41: кусок
A42: 2841 | B42: 198 | C42: Минтай в маринаде с желтым рисом | E42: Вторые блюда | F42: рис | G42: рыба | H42: кусок
A43: 4080 | B43: 209 | C43: Мясные гнёзда с овощами и картофелем | E43: Вторые блюда | F43: картофель | G43: свинина | H43: фарш
A44: 1939 | B44: 188 | C44: Котлета из щуки с пюре картофельным | E44: Вторые блюда | F44: картофель | G44: рыба | H44: фарш
A45: 1982 | B45: 188 | C45: Вок с курицей и рисом | E45: Вторые блюда | F45: моно-блюдо | G45: курица
A46: 1267 | B46: 198 | C46: Печень куриная с овощами с гречкой | E46: Вторые блюда | F46: крупа | G46: курица | H46: соусное
A47: 967 | B47: 188 | C47: Курочка в томатном соусе со спагетти | E47: Вторые блюда | F47: макароны | G47: курица | H47: соусное
A48: 3266 | B48: 198 | C48: Чахохбили с макаронами 400гр | E48: Вторые блюда | F48: макароны | G48: курица | H48: соусное
A49: 813 | B49: 160 | C49: Котлета по-киевски с макаронами | E49: Вторые блюда | F49: макароны | G49: курица | H49: фарш
A50: 4105 | B50: 234 | C50: Свинина по-гавайски с картофелем | E50: Вторые блюда | F50: картофель | G50: свинина | H50: кусок
A51: 4100 | B51: 198 | C51: Курочка по-купечески с гречкой | E51: Вторые блюда | F51: крупа | G51: курица | H51: соусное
A52: 3474 | B52: 187 | C52: Свинина в томатном соусе с макаронами | E52: Вторые блюда | F52: макароны | G52: свинина | H52: соусное
A53: 3872 | B53: 275 | C53: Запеченый баклажан с перцем рамиро | E53: Вторые блюда | F53: овощи | G53: без мяса
A54: 4102 | B54: 282 | C54: Соба с индейкой в устричном соусе | E54: Вторые блюда | F54: макароны | G54: курица | H54: соусное
A55: 3889 | B55: 198 | C55: Купаты куриные с овощным гарниром | E55: Вторые блюда | F55: овощи | G55: курица
A56: 1899 | B56: 229 | C56: Горбуша в сырной корочке с картофелем | E56: Вторые блюда | F56: картофель | G56: рыба | H56: кусок
A57: 965 | B57: 188 | C57: Гуляш ''по-домашнему'' с макаронами | E57: Вторые блюда | F57: макароны | G57: свинина | H57: соусное
A58: 1168 | B58: 198 | C58: Наггетсы с соусом | E58: Вторые блюда | F58: без гарнира | G58: курица
A59: 4099 | B59: 212 | C59: Курочка в сырном соусе со спагетти | E59: Вторые блюда | F59: макароны | G59: курица | H59: соусное
A60: 2029 | B60: 188 | C60: Горбуша в сырной корочке с булгуром | E60: Вторые блюда | F60: крупа | G60: рыба | H60: кусок
A61: 4104 | B61: 212 | C61: Чанахи из свинины 400гр | E61: Вторые блюда | F61: моно-блюдо | G61: свинина
A62: 4176 | B62: 220 | C62: Курочка в сырном соусе с картофелем | E62: Вторые блюда | F62: картофель | G62: курица | H62: соусное
A63: 3768 | B63: 221 | C63: Паприкаш из говядины с гречкой | E63: Вторые блюда | F63: крупа | G63: говядина | H63: соусное
A64: 3770 | B64: 237 | C64: Паприкаш из говядины с картофельным пюре | E64: Вторые блюда | F64: картофель | G64: говядина | H64: соусное
A65: 3769 | B65: 236 | C65: Паприкаш из говядины с макаронами | E65: Вторые блюда | F65: макароны | G65: говядина | H65: соусное
A66: 2859 | B66: 230 | C66: Обед ''Студенческий'' | E66: Вторые блюда | F66: макароны | G66: курица | H66: кусок
A67: 898 | B67: 245 | C67: Лазанья ''Аппетитная'' | E67: Вторые блюда | F67: моно-блюдо | G67: курица | H67: фарш
A68: 4025 | B68: 193 | C68: Бедро в пряном соусе с гречкой | E68: Вторые блюда | F68: крупа | G68: курица | H68: кусок
A69: 4033 | B69: 183 | C69: Куриные котлеты с рисом и овощами | E69: Вторые блюда | F69: рис | G69: курица | H69: фарш
A70: 3705 | B70: 198 | C70: Курочка в соусе тонкацу со спагетти | E70: Вторые блюда | F70: макароны | G70: курица | H70: соусное
A71: 3883 | B71: 257 | C71: Аджапсандал | E71: Вторые блюда | F71: овощи | G71: без мяса
A72: 3612 | B72: 198 | C72: Курочка в сливочном соусе с макаронами | E72: Вторые блюда | F72: макароны | G72: курица | H72: соусное
A73: 3494 | B73: 198 | C73: Курочка гриль с макаронами | E73: Вторые блюда | F73: макароны | G73: курица | H73: кусок
A74: 3740 | B74: 210 | C74: Запеканка с курицей и овощами | E74: Вторые блюда | F74: моно-блюдо | G74: курица | H74: фарш
A75: 3328 | B75: 198 | C75: Спагетти с соусом ''Болоньезе'' 400 г | E75: Вторые блюда | F75: макароны | G75: курица | H75: фарш
A76: 1293 | B76: 238 | C76: Свинина по-боярски (грибы) с пюре | E76: Вторые блюда | F76: картофель | G76: свинина | H76: кусок
A77: 3707 | B77: 198 | C77: Котлета по-домашнему с макаронами | E77: Вторые блюда | F77: макароны | G77: свинина | H77: фарш
A78: 1896 | B78: 198 | C78: Манты со сметаной б/шт | E78: Вторые блюда | F78: без гарнира | G78: свинина
A79: 3410 | B79: 223 | C79: Минтай под овощами с пюре | E79: Вторые блюда | F79: картофель | G79: рыба | H79: кусок
A80: 2932 | B80: 250 | C80: Лагман жареный с говядиной | E80: Вторые блюда | F80: моно-блюдо | G80: говядина
A81: 481 | B81: 218 | C81: Отбивная (свинина) с картофельным пюре | E81: Вторые блюда | F81: картофель | G81: свинина | H81: кусок
A82: 3783 | B82: 215 | C82: Мясные гнезда с томатом и макаронами | E82: Вторые блюда | F82: макароны | G82: свинина | H82: фарш
A83: 3608 | B83: 215 | C83: Мясные гнезда с томатом и пюре | E83: Вторые блюда | F83: картофель | G83: свинина | H83: фарш
A84: 3460 | B84: 198 | C84: Оджахури из свинины б/400гр | E84: Вторые блюда | F84: моно-блюдо | G84: свинина | H84: соусное
A85: 3776 | B85: 253 | C85: Индейка с булгуром и овощами | E85: Вторые блюда | F85: овощи | G85: курица | H85: соусное
A86: 2467 | B86: 110 | C86: Овощное рагу | E86: Вторые блюда | F86: овощи | G86: без мяса
A87: 3786 | B87: 198 | C87: Отбивная куриная с томатом и макаронами | E87: Вторые блюда | F87: макароны | G87: курица | H87: кусок
A88: 1105 | B88: 198 | C88: Тефтели мясные с гречкой | E88: Вторые блюда | F88: крупа | G88: свинина | H88: фарш
A89: 219 | B89: 205 | C89: Азу из свинины с грибами с рисом | E89: Вторые блюда | F89: рис | G89: свинина | H89: соусное
A90: 3895 | B90: 210 | C90: Азу из свинины с грибами с пюре | E90: Вторые блюда | F90: картофель | G90: свинина | H90: соусное
A91: 2541 | B91: 178 | C91: Тефтели мясные со спагетти | E91: Вторые блюда | F91: макароны | G91: свинина | H91: фарш
A92: 3787 | B92: 198 | C92: Тефтели (рыбные ) с рисом | E92: Вторые блюда | F92: рис | G92: рыба | H92: фарш
A93: 3798 | B93: 228 | C93: Говядина томленая с рисом | E93: Вторые блюда | F93: рис | G93: говядина | H93: соусное
A94: 3439 | B94: 220 | C94: Филе ''Сочное с сыром'' с картофелем | E94: Вторые блюда | F94: картофель | G94: курица | H94: кусок
A95: 3552 | B95: 250 | C95: Говядина по-венгерски с пюре | E95: Вторые блюда | F95: картофель | G95: говядина | H95: соусное
A96: 3031 | B96: 230 | C96: Говядина по-венгерски с макаронами | E96: Вторые блюда | F96: макароны | G96: говядина | H96: соусное
A97: 3524 | B97: 198 | C97: Говядина по-венгерски с гречкой | E97: Вторые блюда | F97: крупа | G97: говядина | H97: соусное
A98: 1149 | B98: 228 | C98: Люля-кебаб куриный с картофелем | E98: Вторые блюда | F98: картофель | G98: курица | H98: фарш
A99: 69 | B99: 198 | C99: Плов со свининой б/250гр | E99: Вторые блюда | F99: моно-блюдо | G99: свинина
A100: 3704 | B100: 198 | C100: Курочка в азиатском соусе с рисом | E100: Вторые блюда | F100: рис | G100: курица | H100: соусное
...

Sheet Справочник атрибутов
A1: Категория | B1: Атрибут 1 | C1: Атрибут 2 | D1: Атрибут 3 | E1: Эксперимент | F1: Комментарий
A2: Десерты | B2: выпечка | C2: лёгкий
B3: кремовый | C3: сытный
B4: творожный
B5: фруктовый
B6: шоколадный
A8: Категория | B8: Атрибут 1 | C8: Атрибут 2 | D8: Атрибут 3 | E8: Эксперимент | F8: Комментарий
A9: Завтраки | B9: каша | C9: лёгкий
B10: блины сладкие | C10: сытный
B11: блины сытные
B12: сырники
B13: вафли
B14: выпечка
B15: яичное блюдо
A17: Категория | B17: Атрибут 1 | C17: Атрибут 2 | D17: Атрибут 3 | E17: Эксперимент | F17: Комментарий
A18: Салаты | B18: овощной | C18: овощи
B19: слоёный | C19: курица
B20: майонезный | C20: мясо
B21: премиальный | C21: рыба
B22: боул | C22: без белка
B23: масляный | C23: морепрод.
B24: азиатский
A26: Категория | B26: Атрибут 1 | C26: Атрибут 2 | D26: Атрибут 3 | E26: Эксперимент | F26: Комментарий
A27: Супы | B27: бульон | C27: курица
B28: крем-суп | C28: мясо
B29: густой | C29: рыба
B30: лёгкий | C30: без мяса
A32: Категория | B32: Атрибут 1 | C32: Атрибут 2 | D32: Атрибут 3 | E32: Эксперимент | F32: Комментарий
A33: Вторые блюда | B33: картофель | C33: курица | D33: кусок
B34: макароны | C34: свинина | D34: фарш
B35: рис | C35: говядина | D35: соусное
B36: крупа | C36: рыба
B37: овощи | C37: без мяса
B38: без гарнира
B39: моно-блюдо
A41: Категория | B41: Атрибут 1 | C41: Атрибут 2 | D41: Атрибут 3 | E41: Эксперимент | F41: Комментарий
A42: Сэндвичи | B42: куриный | C42: лёгкий
B43: мясной | C43: сытный
B44: рыбный
B45: овощной
A47: Категория | B47: Атрибут 1 | C47: Атрибут 2 | D47: Атрибут 3 | E47: Эксперимент | F47: Комментарий
A48: Япония | B48: онигири | C48: курица
B49: ролл | C49: рыба
B50: ролл-сэндвич | C50: овощи
A52: Категория | B52: Атрибут 1 | C52: Атрибут 2 | D52: Атрибут 3 | E52: Эксперимент | F52: Комментарий
A53: Напитки | B53: морс | C53: ягодный
B54: компот | C54: фруктовый
C55: смешанный
A57: Категория | B57: Атрибут 1 | C57: Атрибут 2 | D57: Атрибут 3 | E57: Эксперимент | F57: Комментарий
A58: Выпечка | B58: Сытная | C58: лёгкий
B59: сладкая | C59: сытный

Sheet Меню НА СЛЕДУЮЩИЙ МЕСЯЦ
B1: ЭТОТ ЛИСТ ДЛЯ ОЛИ ТЕХНОЛОГА БОЛЬШЕ НИКТО СЮДА НЕ ЛЕЗЕТ!!!
B2: Матрица блюд ПЕРВАЯ неделя
B3: день | C3: Завтрак | D3: Цена | E3: Салат | F3: Цена | G3: Суп | I3: Второе | K3: десерты | L3: Цена | M3: гарнир | N3: Цена | O3: Сэндвич | P3: Цена | R3: .
A4: 46024 | G4: Тыквенный крем-суп с имбирём | I4: Котлета домашняя с пюре | Q4: Птица
A5: ост | I5: Отбивная из курицы с Фарфале | Q5: Свинина
I6: Сердечки | Q6: Рыба
I7: Манты
I9: Говядина в имбирном соусе | Q9: Покупное
Q11: Говядина
A12: 46027 | Q12: япошка
A13: шад
A19: 46030
A20: ост.шад
Q42: Птица
A43: 45753 | Q43: Свинина
Q44: Рыба
Q48: овощное
Q49: Говядина
Q82: Птица
A83: 45761 | Q83: Свинина
Q84: Рыба
Q85: Покупное
Q86: Говядина
Q110: Птица
A111: 20.04 | Q111: Свинина
Q112: Рыба
Q113: Покупное
Q114: Говядина
A115: 45768
A120: 45769
A125: 45770
A130: 45771
C140: Вот ингредиенты на 4 персоны: 1 литр томатного соуса; 50 г сливочного масла; 50 г муки; 500 мл молока; половинка луковицы; несколько листьев базилика; соль, черный перец, тертый мускатный орех и масло по вкусу. В кастрюле с высокими бортами приготовьте томатный соус. Налейте масло и добавьте нарезанную половину лука. Когда он станет золотистым, добавьте помидор, соль и дайте ему приготовиться, добавьте свежие листьями базилика. Тем временем приготовьте соус бешамель в небольшой кастрюле: дайте маслу растаять и медленно добавьте просеянную муку, хорошо перемешивая — обратите на этот шаг пристальное внимание, потому что могут легко образовываться комочки. Когда мука станет золотистой, понемногу вливайте молоко и перемешивайте венчиком; уменьшите огонь и часто помешивайте, пока молоко не загустеет и не образуется бархатистый крем. На этом этапе добавьте соль, перец и много тертого мускатного ореха, чтобы придать бешамелю характерный вкус. Вы можете смешать соус бешамель с томатным, чтобы консистенция получилась более однородной, или вылить оба соуса на пасту отдельно.

Sheet новогодние прзд.
G1: 12 | I1: 11 | K1: 53 | M1: 35 | O1: 85 | Q1: ? | S1: 16 | U1: 19 | W1: 13 | Y1: 14 | AA1: 17 | AC1: 19 | AE1: 27 | AG1: 14 | AI1: 11
A2: Дата: | C2: 45659 | D2: План на день кухня ПЯТНИЦА | N2: - РАБОТАЕТ | T2: - ВЫХОДНОЙ
A3: № | B3: Код | C3: Вид | D3: Название блюда | E3: Т 1 | F3: Ф 1 | G3: Т2 | H3: Ф2 | I3: Т 3 | J3: Ф 3 | K3: Т 4 | L3: Ф 4 | M3: Т 5 | N3: Ф 5 | O3: Т 6 | P3: Ф 6 | Q3: Т 7 | R3: Ф7 | S3: Т8 | T3: Ф8 | U3: Т9 | V3: Ф9 | W3: Т10 | X3: Ф10 | Y3: Т11 | Z3: Ф11 | AA3: Т12 | AB3: Ф12 | AC3: Т13 | AD3: Ф13 | AE3: Т14 | AF3: Ф14 | AG3: Т15 | AH3: Ф15 | AI3: Т16 | AJ3: Ф16 | AK3: Т17 | AL3: Ф17 | AM3: Т18 | AN3: Ф18 | AO3: Т19 | AP3: Ф19 | AQ3: Т20 | AR3: Ф20 | AS3: Т21 | AT3: Ф21 | AU3: Т22 | AV3: Ф22 | AW3: БПЮ | AX3: ФБПЮ | AY3: ПЛАН | AZ3: ФАКТ | BA3: ВМ | BB3: СПК | BC3: Выход | BD3: Масса
D4: Кол-во человек | E4: ОБЫЧ РЕЖ | K4: 40 | S4: ПО ВЫХ ДН | W4: ОБЫЧ РЕЖ | AE4: 15-20 | AK4: 30-50 | AQ4: ОБЫЧ РЕЖ | AS4: 20 | AU4: ОБЫЧ РЕЖ | AW4: 45780
D5: Когда выходят работать | AS5: С 04.01
A6: 1 | B6: 2423 | C6: ='Матрица 4 недели'!D3 -> Завтрак | D6: ='Меню НА СЛЕДУЮЩИЙ МЕСЯЦ'!C4 | E6: 20 | F6: 20 | K6: 10 | L6: 10 | O6: 9 | P6: 9 | S6: 5 | T6: 5 | W6: 10 | X6: 10 | Y6: 5 | Z6: 5 | AE6: 5 | AF6: 5 | AK6: 5 | AL6: 5 | AQ6: 10 | AR6: 10 | AU6: 8 | AV6: 8 | AY6: =(E6+G6+I6+K6+M6+O6+Q6+S6+U6+W6+Y6+AA6+AC6+AE6+AG6+AI6+AK6+AM6+AW6+AO6+AQ6+AS6+AU6)+1 -> 88 | AZ6: =F6+H6+J6+L6+N6+P6+R6+T6+V6+X6+Z6+AD6+AB6+AF6+AH6+AJ6+AL6+AR6+AX6+AN6+AP6+AT6+AV6 -> 87 | BA6: =111*AZ6 -> 9657 | BC6: 0.15 | BD6: =AY6*BC6 -> 13.2
A7: 2 | B7: 3624 | C7: ='Матрица 4 недели'!D145 -> Завтрак | D7: ='Меню НА СЛЕДУЮЩИЙ МЕСЯЦ'!C5 | E7: 20 | F7: 20 | K7: 10 | L7: 10 | O7: 9 | P7: 9 | S7: 5 | T7: 5 | W7: 10 | X7: 10 | Y7: 5 | Z7: 5 | AE7: 5 | AF7: 5 | AK7: 5 | AL7: 5 | AQ7: 10 | AR7: 10 | AU7: 8 | AV7: 8 | AY7: =(E7+G7+I7+K7+M7+O7+Q7+S7+U7+W7+Y7+AA7+AC7+AE7+AG7+AI7+AK7+AM7+AW7+AO7+AQ7+AS7+AU7)+1 -> 88 | AZ7: =F7+H7+J7+L7+N7+P7+R7+T7+V7+X7+Z7+AD7+AB7+AF7+AH7+AJ7+AL7+AR7+AX7+AN7+AP7+AT7+AV7 -> 87 | BA7: =97*AZ7 -> 8439
A8: 3 | B8: 3170 | C8: салат | D8: ='Меню НА СЛЕДУЮЩИЙ МЕСЯЦ'!E6 | E8: 30 | F8: 30 | L8: 5 | X8: 5 | AQ8: 20 | AR8: 20 | AY8: =(E8+G8+I8+K8+M8+O8+Q8+S8+U8+W8+Y8+AA8+AC8+AE8+AG8+AI8+AK8+AM8+AW8+AO8+AQ8+AS8+AU8)+1 -> 51 | AZ8: =F8+H8+J8+L8+N8+P8+R8+T8+V8+X8+Z8+AD8+AB8+AF8+AH8+AJ8+AL8+AR8+AX8+AN8+AP8+AT8+AV8 -> 60 | BA8: =85*AZ8 -> 5100
A9: 4 | B9: 47 | C9: ='Матрица 4 недели'!G3 -> Салат | D9: ='Меню НА СЛЕДУЮЩИЙ МЕСЯЦ'!E4 | E9: 30 | F9: 30 | K9: 15 | L9: 10 | O9: 15 | P9: 15 | S9: 5 | T9: 5 | W9: 18 | X9: 13 | Y9: 5 | Z9: 5 | AE9: 10 | AF9: 10 | AK9: 8 | AL9: 7 | AQ9: 20 | AR9: 20 | AU9: 20 | AV9: 20 | AY9: =(E9+G9+I9+K9+M9+O9+Q9+S9+U9+W9+Y9+AA9+AC9+AE9+AG9+AI9+AK9+AM9+AW9+AO9+AQ9+AS9+AU9)+1 -> 147 | AZ9: =F9+H9+J9+L9+N9+P9+R9+T9+V9+X9+Z9+AD9+AB9+AF9+AH9+AJ9+AL9+AR9+AX9+AN9+AP9+AT9+AV9 -> 135 | BA9: =98*AZ9 -> 13230 | BB9: =60*AX9 -> 0 | BC9: 0.1 | BD9: =AY9*BC9 -> 14.7
A10: 5 | B10: 3651 | C10: ='Матрица 4 недели'!G3 -> Салат | D10: ='Меню НА СЛЕДУЮЩИЙ МЕСЯЦ'!E5 | E10: 30 | F10: 35 | K10: 15 | L10: 20 | O10: 15 | P10: 15 | S10: 5 | T10: 5 | W10: 18 | X10: 23 | Y10: 5 | Z10: 5 | AE10: 10 | AF10: 10 | AK10: 8 | AL10: 8 | AQ10: 20 | AR10: 25 | AU10: 20 | AV10: 23 | AY10: =(E10+G10+I10+K10+M10+O10+Q10+S10+U10+W10+Y10+AA10+AC10+AE10+AG10+AI10+AK10+AM10+AW10+AO10+AQ10+AS10+AU10)+1 -> 147 | AZ10: =F10+H10+J10+L10+N10+P10+R10+T10+V10+X10+Z10+AD10+AB10+AF10+AH10+AJ10+AL10+AR10+AX10+AN10+AP10+AT10+AV10 -> 169 | BA10: =98*(AZ10-AX10) -> 16562 | BB10: =60*AX10 -> 0 | BC10: 0.1 | BD10: =AY10*BC10 -> 14.7
A11: 6 | C11: ='Матрица 4 недели'!G3 -> Салат | AY11: =(E11+G11+I11+K11+M11+O11+Q11+S11+U11+W11+Y11+AA11+AC11+AE11+AG11+AI11+AK11+AM11+AW11+AO11+AQ11+AS11+AU11)+1 -> 1 | AZ11: =F11+H11+J11+L11+N11+P11+R11+T11+V11+X11+Z11+AD11+AB11+AF11+AH11+AJ11+AL11+AR11+AX11+AN11+AP11+AT11+AV11 -> 0 | BA11: =98*(AZ11-AX11) -> 0 | BB11: =60*AX11 -> 0 | BC11: 0.1 | BD11: =AY11*BC11 -> 0.1
A12: 10 | B12: 380 | C12: ='Матрица 4 недели'!J145 -> Суп | D12: ='Меню НА СЛЕДУЮЩИЙ МЕСЯЦ'!G4 -> Тыквенный крем-суп с имбирём | E12: 2 | F12: 2 | K12: 2 | L12: 2 | O12: 2 | P12: 2 | S12: 2 | T12: 2 | W12: 2 | X12: 2 | Y12: 2 | Z12: 2 | AE12: 2 | AF12: 2 | AK12: 2 | AL12: 2 | AQ12: 2 | AR12: 2 | AU12: 2 | AV12: 2 | AY12: =(E12+G12+I12+K12+M12+O12+Q12+S12+U12+W12+Y12+AA12+AC12+AE12+AG12+AI12+AK12+AM12+AW12+AO12+AQ12+AS12+AU12)+1 -> 21 | AZ12: =F12+H12+J12+L12+N12+P12+R12+T12+V12+X12+Z12+AD12+AB12+AF12+AH12+AJ12+AL12+AR12+AX12+AN12+AP12+AT12+AV12 -> 20 | BB12: =AZ12*60 -> 1200
A13: 12 | B13: 69 | C13: ='Матрица 4 недели'!M3 -> Второе | D13: ='Меню НА СЛЕДУЮЩИЙ МЕСЯЦ'!I4 -> Котлета домашняя с пюре | E13: 25 | F13: 20 | K13: 15 | L13: 13 | O13: 12 | P13: 12 | S13: 4 | T13: 4 | W13: 23 | X13: 20 | Y13: 4 | Z13: 4 | AE13: 8 | AF13: 8 | AK13: 4 | AL13: 4 | AQ13: 30 | AR13: 30 | AU13: 15 | AV13: 15 | AY13: =(E13+G13+I13+K13+M13+O13+Q13+S13+U13+W13+Y13+AA13+AC13+AE13+AG13+AI13+AK13+AM13+AW13+AO13+AQ13+AS13+AU13)+1 -> 141 | AZ13: =F13+H13+J13+L13+N13+P13+R13+T13+V13+X13+Z13+AD13+AB13+AF13+AH13+AJ13+AL13+AR13+AX13+AN13+AP13+AT13+AV13 -> 130 | BA13: =198*(AZ13-AX13) -> 25740 | BB13: =160*AX13 -> 0 | BC13: 0.3 | BD13: =AY13*BC13 -> 42.3
A14: 13 | B14: 3732 | C14: ='Матрица 4 недели'!M3 -> Второе | D14: ='Меню НА СЛЕДУЮЩИЙ МЕСЯЦ'!I5 -> Отбивная из курицы с Фарфале | E14: 20 | F14: 20 | K14: 10 | L14: 10 | O14: 7 | P14: 7 | S14: 2 | T14: 2 | W14: 18 | X14: 18 | Y14: 2 | Z14: 2 | AE14: 4 | AF14: 4 | AK14: 2 | AL14: 2 | AQ14: 25 | AR14: 25 | AU14: 10 | AV14: 10 | AY14: =(E14+G14+I14+K14+M14+O14+Q14+S14+U14+W14+Y14+AA14+AC14+AE14+AG14+AI14+AK14+AM14+AW14+AO14+AQ14+AS14+AU14)+1 -> 101 | AZ14: =F14+H14+J14+L14+N14+P14+R14+T14+V14+X14+Z14+AD14+AB14+AF14+AH14+AJ14+AL14+AR14+AX14+AN14+AP14+AT14+AV14 -> 100 | BA14: =AZ14*198 -> 19800 | BC14: 0.3 | BD14: =AY14*BC14 -> 30.3
A15: 14 | B15: 3731 | C15: =#REF! -> #REF! | D15: Биточки куриные с гречкой | E15: 25 | F15: 25 | K15: 15 | L15: 15 | O15: 12 | P15: 12 | S15: 4 | T15: 4 | W15: 23 | X15: 23 | Y15: 4 | Z15: 4 | AE15: 8 | AF15: 8 | AK15: 4 | AL15: 4 | AQ15: 30 | AR15: 30 | AU15: 15 | AV15: 15 | AY15: =(E15+G15+I15+K15+M15+O15+Q15+S15+U15+W15+Y15+AA15+AC15+AE15+AG15+AI15+AK15+AM15+AW15+AO15+AQ15+AS15+AU15)+1 -> 141 | AZ15: =F15+H15+J15+L15+N15+P15+R15+T15+V15+X15+Z15+AD15+AB15+AF15+AH15+AJ15+AL15+AR15+AX15+AN15+AP15+AT15+AV15 -> 140 | BA15: =198*AZ15 -> 27720
A16: 15 | B16: 3672 | C16: ='Матрица 4 недели'!M3 -> Второе | D16: ='Меню НА СЛЕДУЮЩИЙ МЕСЯЦ'!I9 -> Говядина в имбирном соусе | E16: 25 | F16: 24 | K16: 15 | L16: 12 | O16: 12 | P16: 9 | S16: 4 | T16: 3 | W16: 23 | X16: 20 | Y16: 4 | Z16: 3 | AE16: 8 | AF16: 4 | AK16: 4 | AL16: 3 | AQ16: 30 | AR16: 30 | AU16: 15 | AV16: 11 | AY16: =(E16+G16+I16+K16+M16+O16+Q16+S16+U16+W16+Y16+AA16+AC16+AE16+AG16+AI16+AK16+AM16+AW16+AO16+AQ16+AS16+AU16)+1 -> 141 | AZ16: =F16+H16+J16+L16+N16+P16+R16+T16+V16+X16+Z16+AD16+AB16+AF16+AH16+AJ16+AL16+AR16+AX16+AN16+AP16+AT16+AV16 -> 119 | BA16: =198*(AZ16-AX16) -> 23562 | BB16: =160*AX16 -> 0 | BC16: 0.3 | BD16: =AY16*BC16 -> 42.3
A17: 16 | B17: 3537 | C17: сэндвич | D17: ='Меню НА СЛЕДУЮЩИЙ МЕСЯЦ'!O4 | E17: 20 | F17: 26 | K17: 20 | L17: 26 | O17: 5 | P17: 8 | S17: 3 | T17: 6 | W17: 10 | X17: 17 | Y17: 4 | Z17: 7 | AE17: 4 | AF17: 7 | AQ17: 15 | AR17: 22 | AU17: 4 | AV17: 6 | AY17: =(E17+G17+I17+K17+M17+O17+Q17+S17+U17+W17+Y17+AA17+AC17+AE17+AG17+AI17+AK17+AM17+AW17+AO17+AQ17+AS17+AU17)+1 -> 86 | AZ17: =F17+H17+J17+L17+N17+P17+R17+T17+V17+X17+Z17+AD17+AB17+AF17+AH17+AJ17+AL17+AR17+AX17+AN17+AP17+AT17+AV17 -> 125 | BA17: =188*(AZ17-AX17) -> 23500 | BB17: =160*AX17 -> 0
A18: 17 | B18: 3733 | D18: Чкмерули из курицы с гречкой | E18: 5 | F18: 5 | K18: 5 | L18: 5 | O18: 4 | P18: 4 | S18: 2 | T18: 2 | W18: 5 | X18: 5 | Y18: 2 | Z18: 3 | AE18: 4 | AF18: 4 | AK18: 2 | AL18: 2 | AQ18: 5 | AR18: 5 | AU18: 5 | AV18: 4 | AY18: =(E18+G18+I18+K18+M18+O18+Q18+S18+U18+W18+Y18+AA18+AC18+AE18+AG18+AI18+AK18+AM18+AW18+AO18+AQ18+AS18+AU18)+1 -> 40 | AZ18: =F18+H18+J18+L18+N18+P18+R18+T18+V18+X18+Z18+AD18+AB18+AF18+AH18+AJ18+AL18+AR18+AX18+AN18+AP18+AT18+AV18 -> 39 | BA18: =188*(AZ18-AX18) -> 7332
A19: 18 | AY19: =(E19+G19+I19+K19+M19+O19+Q19+S19+U19+W19+Y19+AA19+AC19+AE19+AG19+AI19+AK19+AM19+AW19+AO19+AQ19+AS19+AU19)+1 -> 1 | AZ19: =F19+H19+J19+L19+N19+P19+R19+T19+V19+X19+Z19+AD19+AB19+AF19+AH19+AJ19+AL19+AR19+AX19+AN19+AP19+AT19+AV19 -> 0 | BA19: =188*(AZ19-AX19) -> 0
A20: 19 | C20: Доп-но | AY20: =(E20+G20+I20+K20+M20+O20+Q20+S20+U20+W20+Y20+AA20+AC20+AE20+AG20+AI20+AK20+AM20+AW20+AO20+AQ20+AS20+AU20)+1 -> 1 | AZ20: =F20+H20+J20+L20+N20+P20+R20+T20+V20+X20+Z20+AD20+AB20+AF20+AH20+AJ20+AL20+AR20+AX20+AN20+AP20+AT20+AV20 -> 0 | BA20: =188*(AZ20-AX20) -> 0 | BC20: 0.3 | BD20: =AY20*BC20 -> 0.3
A21: 20 | B21: 3691 | C21: Доп-но | D21: Свинина по тайски с рисом | E21: 26 | F21: 26 | AY21: =(E21+G21+I21+K21+M21+O21+Q21+S21+U21+W21+Y21+AA21+AC21+AE21+AG21+AI21+AK21+AM21+AW21+AO21+AQ21+AS21+AU21)+1 -> 27 | AZ21: =F21+H21+J21+L21+N21+P21+R21+T21+V21+X21+Z21+AD21+AB21+AF21+AH21+AJ21+AL21+AR21+AX21+AN21+AP21+AT21+AV21 -> 26 | BA21: =188*(AZ21-AX21) -> 4888
A22: 21 | B22: 3517 | C22: Доп-но | D22: Тефтели рыбные с пюре | E22: 25 | F22: 28 | AY22: =(E22+G22+I22+K22+M22+O22+Q22+S22+U22+W22+Y22+AA22+AC22+AE22+AG22+AI22+AK22+AM22+AW22+AO22+AQ22+AS22+AU22)+1 -> 26 | AZ22: =F22+H22+J22+L22+N22+P22+R22+T22+V22+X22+Z22+AD22+AB22+AF22+AH22+AJ22+AL22+AR22+AX22+AN22+AP22+AT22+AV22 -> 28 | BA22: =188*(AZ22-AX22) -> 5264
A23: 22 | B23: 2531 | C23: Доп-но | D23: Хлеб | E23: 10 | F23: 11 | K23: 15 | L23: 15 | O23: 5 | P23: 5 | S23: 5 | T23: 5 | W23: 5 | X23: 5 | Y23: 3 | Z23: 3 | AE23: 3 | AF23: 3 | AK23: 3 | AL23: 3 | AQ23: 0 | AU23: 0 | AY23: =(E23+G23+I23+K23+M23+O23+Q23+S23+U23+W23+Y23+AA23+AC23+AE23+AG23+AI23+AK23+AM23+AW23+AO23+AQ23+AS23+AU23)+1 -> 50 | AZ23: =F23+H23+J23+L23+N23+P23+R23+T23+V23+X23+Z23+AD23+AB23+AF23+AH23+AJ23+AL23+AR23+AX23+AN23+AP23+AT23+AV23 -> 50 | BA23: =198*AZ23 -> 9900
A24: 23 | B24: 5 | C24: ='Матрица 4 недели'!S3 -> Сэндвич | AY24: =(E24+G24+I24+K24+M24+O24+Q24+S24+U24+W24+Y24+AA24+AC24+AE24+AG24+AI24+AK24+AM24+AW24+AO24+AQ24+AS24+AU24)+1 -> 1 | AZ24: =F24+H24+J24+L24+N24+P24+R24+T24+V24+X24+Z24+AD24+AB24+AF24+AH24+AJ24+AL24+AR24+AX24+AN24+AP24+AT24+AV24 -> 0 | BA24: =160*AZ24 -> 0 | BC24: 0.16 | BD24: =AY24*BC24 -> 0.16
A25: 24 | C25: ='Матрица 4 недели'!S145 -> Сэндвич | AY25: =(E25+G25+I25+K25+M25+O25+Q25+S25+U25+W25+Y25+AA25+AC25+AE25+AG25+AI25+AK25+AM25+AW25+AO25+AQ25+AS25+AU25)+1 -> 1 | AZ25: =F25+H25+J25+L25+N25+P25+R25+T25+V25+X25+Z25+AD25+AB25+AF25+AH25+AJ25+AL25+AR25+AX25+AN25+AP25+AT25+AV25 -> 0 | BA25: =155*AZ25 -> 0
A26: 25 | B26: 3518 | C26: Выпечка | AY26: =(E26+G26+I26+K26+M26+O26+Q26+S26+U26+W26+Y26+AA26+AC26+AE26+AG26+AI26+AK26+AM26+AW26+AO26+AQ26+AS26+AU26)+1 -> 1 | AZ26: =F26+H26+J26+L26+N26+P26+R26+T26+V26+X26+Z26+AD26+AB26+AF26+AH26+AJ26+AL26+AR26+AX26+AN26+AP26+AT26+AV26 -> 0
A27: 26 | C27: Выпечка | AY27: =(E27+G27+I27+K27+M27+O27+Q27+S27+U27+W27+Y27+AA27+AC27+AE27+AG27+AI27+AK27+AM27+AW27+AO27+AQ27+AS27+AU27)+1 -> 1 | AZ27: =F27+H27+J27+L27+N27+P27+R27+T27+V27+X27+Z27+AD27+AB27+AF27+AH27+AJ27+AL27+AR27+AX27+AN27+AP27+AT27+AV27 -> 0
A28: 27 | C28: ='Матрица 4 недели'!P145 -> Выпечка | AY28: =(E28+G28+I28+K28+M28+O28+Q28+S28+U28+W28+Y28+AA28+AC28+AE28+AG28+AI28+AK28+AM28+AW28+AO28+AQ28+AS28+AU28)+1 -> 1 | AZ28: =F28+H28+J28+L28+N28+P28+R28+T28+V28+X28+Z28+AD28+AB28+AF28+AH28+AJ28+AL28+AR28+AX28+AN28+AP28+AT28+AV28 -> 0
A29: 28 | B29: 822 | C29: Внеплан | AY29: =(E29+G29+I29+K29+M29+O29+Q29+S29+U29+W29+Y29+AA29+AC29+AE29+AG29+AI29+AK29+AM29+AW29+AO29+AQ29+AS29+AU29)+1 -> 1 | AZ29: =F29+H29+J29+L29+N29+P29+R29+T29+V29+X29+Z29+AD29+AB29+AF29+AH29+AJ29+AL29+AR29+AX29+AN29+AP29+AT29+AV29 -> 0 | BB29: =AX29*5 -> 0
A30: 29 | C30: Внеплан | AY30: =(E30+G30+I30+K30+M30+O30+Q30+S30+U30+W30+Y30+AA30+AC30+AE30+AG30+AI30+AK30+AM30+AW30+AO30+AQ30+AS30+AU30)+1 -> 1 | AZ30: =F30+H30+J30+L30+N30+P30+R30+T30+V30+X30+Z30+AD30+AB30+AF30+AH30+AJ30+AL30+AR30+AX30+AN30+AP30+AT30+AV30 -> 0
A31: 30 | C31: Внеплан | AY31: =(E31+G31+I31+K31+M31+O31+Q31+S31+U31+W31+Y31+AA31+AC31+AE31+AG31+AI31+AK31+AM31+AW31+AO31+AQ31+AS31+AU31)+1 -> 1 | AZ31: =F31+H31+J31+L31+N31+P31+R31+T31+V31+X31+Z31+AD31+AB31+AF31+AH31+AJ31+AL31+AR31+AX31+AN31+AP31+AT31+AV31 -> 0
A32: 31 | C32: Внеплан | AY32: =(E32+G32+I32+K32+M32+O32+Q32+S32+U32+W32+Y32+AA32+AC32+AE32+AG32+AI32+AK32+AM32+AW32+AO32+AQ32+AS32+AU32)+1 -> 1 | AZ32: =F32+H32+J32+L32+N32+P32+R32+T32+V32+X32+Z32+AD32+AB32+AF32+AH32+AJ32+AL32+AR32+AX32+AN32+AP32+AT32+AV32 -> 0
AY33: =SUM(AY6:AY32) -> 1307 | AZ33: =SUM(AZ6:AZ32) -> 1315 | BA33: =SUM(BA6:BA32) -> 200694 | BB33: =SUM(BB6:BB32) -> 1200 | BC33: вес | BD33: =SUM(BD6:BD24) -> 158.06
C34: ______________________________________________________________________________________ | BA34: =BA33+BB33 -> 201894
A36: Дата: | C36: =C2 -> 45659 | D36: Загрузка в аппараты | I36: Выгружаем дату производства:
A37: № | B37: =B3 -> Код | C37: Вид | D37: Название блюда | E37: Т1 | G37: Т2 | I37: Т3 | K37: Т4 | M37: Т5 | O37: Т6 | Q37: Т7 | S37: Т8 | U37: Т9 | W37: Т10 | Y37: Т11 | AA37: Т12 | AC37: Т13 | AE37: Т14 | AG37: Т15 | AI37: Т16 | AK37: Т17 | AM37: Т18 | AO37: Т19 | AQ37: Т20 | AS37: Т21 | AU37: Т22 | AW37: СПК | AY37: ИТОГ
A38: =A6 -> 1 | B38: =B6 -> 2423 | C38: =C6 -> Завтрак | D38: =D6 | E38: =F6 -> 20 | G38: =H6 | I38: =J6 | K38: =L6 -> 10 | M38: =N6 | O38: =P6 -> 9 | Q38: =R6 | S38: =T6 -> 5 | U38: =V6 | W38: =X6 -> 10 | Y38: =Z6 -> 5 | AA38: =AB6 | AC38: =AD6 | AE38: =AF6 -> 5 | AG38: =AH6 | AI38: =AJ6 | AK38: =AL6 -> 5 | AM38: =AN6 | AO38: =AP6 | AQ38: =AR6 -> 10 | AS38: =AT6 | AU38: =AV6 -> 8 | AW38: =AX6 | AY38: =SUM(E38:AX38) -> 87
A39: =A7 -> 2 | B39: =B7 -> 3624 | C39: =C7 -> Завтрак | D39: =D7 | E39: =F7 -> 20 | G39: =H7 | I39: =J7 | K39: =L7 -> 10 | M39: =N7 | O39: =P7 -> 9 | Q39: =R7 | S39: =T7 -> 5 | U39: =V7 | W39: =X7 -> 10 | Y39: =Z7 -> 5 | AA39: =AB7 | AC39: =AD7 | AE39: =AF7 -> 5 | AG39: =AH7 | AI39: =AJ7 | AK39: =AL7 -> 5 | AM39: =AN7 | AO39: =AP7 | AQ39: =AR7 -> 10 | AS39: =AT7 | AU39: =AV7 -> 8 | AW39: =AX7 | AY39: =SUM(E39:AX39) -> 87
A40: =A8 -> 3 | B40: =B8 -> 3170 | C40: =C8 -> салат | D40: =D8 | E40: =F8 -> 30 | G40: =H8 | I40: =J8 | K40: =L8 -> 5 | M40: =N8 | O40: =P8 | Q40: =R8 | S40: =T8 | U40: =V8 | W40: =X8 -> 5 | Y40: =Z8 | AA40: =AB8 | AC40: =AD8 | AE40: =AF8 | AG40: =AH8 | AI40: =AJ8 | AK40: =AL8 | AM40: =AN8 | AO40: =AP8 | AQ40: =AR8 -> 20 | AS40: =AT8 | AU40: =AV8 | AW40: =AX8 | AY40: =SUM(E40:AX40) -> 60
A41: =A9 -> 4 | B41: =B9 -> 47 | C41: =C9 -> Салат | D41: =D9 | E41: =F9 -> 30 | G41: =H9 | I41: =J9 | K41: =L9 -> 10 | M41: =N9 | O41: =P9 -> 15 | Q41: =R9 | S41: =T9 -> 5 | U41: =V9 | W41: =X9 -> 13 | Y41: =Z9 -> 5 | AA41: =AB9 | AC41: =AD9 | AE41: =AF9 -> 10 | AG41: =AH9 | AI41: =AJ9 | AK41: =AL9 -> 7 | AM41: =AN9 | AO41: =AP9 | AQ41: =AR9 -> 20 | AS41: =AT9 | AU41: =AV9 -> 20 | AW41: =AX9 | AY41: =SUM(E41:AX41) -> 135
A42: =A10 -> 5 | B42: =B10 -> 3651 | C42: =C10 -> Салат | D42: =D10 | E42: =F10 -> 35 | G42: =H10 | I42: =J10 | K42: =L10 -> 20 | M42: =N10 | O42: =P10 -> 15 | Q42: =R10 | S42: =T10 -> 5 | U42: =V10 | W42: =X10 -> 23 | Y42: =Z10 -> 5 | AA42: =AB10 | AC42: =AD10 | AE42: =AF10 -> 10 | AG42: =AH10 | AI42: =AJ10 | AK42: =AL10 -> 8 | AM42: =AN10 | AO42: =AP10 | AQ42: =AR10 -> 25 | AS42: =AT10 | AU42: =AV10 -> 23 | AW42: =AX10 | AY42: =SUM(E42:AX42) -> 169
A43: =A11 -> 6 | B43: =B11 | C43: =C11 -> Салат | D43: =D11 | E43: =F11 | G43: =H11 | I43: =J11 | K43: =L11 | M43: =N11 | O43: =P11 | Q43: =R11 | S43: =T11 | U43: =V11 | W43: =X11 | Y43: =Z11 | AA43: =AB11 | AC43: =AD11 | AE43: =AF11 | AG43: =AH11 | AI43: =AJ11 | AK43: =AL11 | AM43: =AN11 | AO43: =AP11 | AQ43: =AR11 | AS43: =AT11 | AU43: =AV11 | AW43: =AX11 | AY43: =SUM(E43:AX43) -> 0
A44: =A12 -> 10 | B44: =B12 -> 380 | C44: =C12 -> Суп | D44: =D12 -> Тыквенный крем-суп с имбирём | E44: =F12 -> 2 | G44: =H12 | I44: =J12 | K44: =L12 -> 2 | M44: =N12 | O44: =P12 -> 2 | Q44: =R12 | S44: =T12 -> 2 | U44: =V12 | W44: =X12 -> 2 | Y44: =Z12 -> 2 | AA44: =AB12 | AC44: =AD12 | AE44: =AF12 -> 2 | AG44: =AH12 | AI44: =AJ12 | AK44: =AL12 -> 2 | AM44: =AN12 | AO44: =AP12 | AQ44: =AR12 -> 2 | AS44: =AT12 | AU44: =AV12 -> 2 | AW44: =AX12 | AY44: =SUM(E44:AX44) -> 20
A45: =A13 -> 12 | B45: =B13 -> 69 | C45: =C13 -> Второе | D45: =D13 -> Котлета домашняя с пюре | E45: =F13 -> 20 | G45: =H13 | I45: =J13 | K45: =L13 -> 13 | M45: =N13 | O45: =P13 -> 12 | Q45: =R13 | S45: =T13 -> 4 | U45: =V13 | W45: =X13 -> 20 | Y45: =Z13 -> 4 | AA45: =AB13 | AC45: =AD13 | AE45: =AF13 -> 8 | AG45: =AH13 | AI45: =AJ13 | AK45: =AL13 -> 4 | AM45: =AN13 | AO45: =AP13 | AQ45: =AR13 -> 30 | AS45: =AT13 | AU45: =AV13 -> 15 | AW45: =AX13 | AY45: =SUM(E45:AX45) -> 130
A46: =A14 -> 13 | B46: =B14 -> 3732 | C46: =C14 -> Второе | D46: =D14 -> Отбивная из курицы с Фарфале | E46: =F14 -> 20 | G46: =H14 | I46: =J14 | K46: =L14 -> 10 | M46: =N14 | O46: =P14 -> 7 | Q46: =R14 | S46: =T14 -> 2 | U46: =V14 | W46: =X14 -> 18 | Y46: =Z14 -> 2 | AA46: =AB14 | AC46: =AD14 | AE46: =AF14 -> 4 | AG46: =AH14 | AI46: =AJ14 | AK46: =AL14 -> 2 | AM46: =AN14 | AO46: =AP14 | AQ46: =AR14 -> 25 | AS46: =AT14 | AU46: =AV14 -> 10 | AW46: =AX14 | AY46: =SUM(E46:AX46) -> 100
A47: =A15 -> 14 | B47: =B15 -> 3731 | C47: =C15 -> #REF! | D47: =D15 -> Биточки куриные с гречкой | E47: =F15 -> 25 | G47: =H15 | I47: =J15 | K47: =L15 -> 15 | M47: =N15 | O47: =P15 -> 12 | Q47: =R15 | S47: =T15 -> 4 | U47: =V15 | W47: =X15 -> 23 | Y47: =Z15 -> 4 | AA47: =AB15 | AC47: =AD15 | AE47: =AF15 -> 8 | AG47: =AH15 | AI47: =AJ15 | AK47: =AL15 -> 4 | AM47: =AN15 | AO47: =AP15 | AQ47: =AR15 -> 30 | AS47: =AT15 | AU47: =AV15 -> 15 | AW47: =AX15 | AY47: =SUM(E47:AX47) -> 140
A48: =A16 -> 15 | B48: =B16 -> 3672 | C48: =C16 -> Второе | D48: =D16 -> Говядина в имбирном соусе | E48: =F16 -> 24 | G48: =H16 | I48: =J16 | K48: =L16 -> 12 | M48: =N16 | O48: =P16 -> 9 | Q48: =R16 | S48: =T16 -> 3 | U48: =V16 | W48: =X16 -> 20 | Y48: =Z16 -> 3 | AA48: =AB16 | AC48: =AD16 | AE48: =AF16 -> 4 | AG48: =AH16 | AI48: =AJ16 | AK48: =AL16 -> 3 | AM48: =AN16 | AO48: =AP16 | AQ48: =AR16 -> 30 | AS48: =AT16 | AU48: =AV16 -> 11 | AW48: =AX16 | AY48: =SUM(E48:AX48) -> 119
A49: =A17 -> 16 | B49: =B17 -> 3537 | C49: =C17 -> сэндвич | D49: =D17 | E49: =F17 -> 26 | G49: =H17 | I49: =J17 | K49: =L17 -> 26 | M49: =N17 | O49: =P17 -> 8 | Q49: =R17 | S49: =T17 -> 6 | U49: =V17 | W49: =X17 -> 17 | Y49: =Z17 -> 7 | AA49: =AB17 | AC49: =AD17 | AE49: =AF17 -> 7 | AG49: =AH17 | AI49: =AJ17 | AK49: =AL17 | AM49: =AN17 | AO49: =AP17 | AQ49: =AR17 -> 22 | AS49: =AT17 | AU49: =AV17 -> 6 | AW49: =AX17 | AY49: =SUM(E49:AX49) -> 125
... A63: =A31 -> 30 | B63: =B31 | C63: =C31 -> Внеплан | D63: =D31 | E63: =F31 | G63: =H31 | I63: =J31 | K63: =L31 | M63: =N31 | O63: =P31 | Q63: =R31 | S63: =T31 | U63: =V31 | W63: =X31 | Y63: =Z31 | AA63: =AB31 | AC63: =AD31 | AE63: =AF31 | AG63: =AH31 | AI63: =AJ31 | AK63: =AL31 | AM63: =AN31 | AO63: =AP31 | AQ63: =AR31 | AS63: =AT31 | AU63: =AV31 | AW63: =AX31 | AY63: =SUM(E63:AX63) -> 0
A64: =A32 -> 31 | B64: =B32 | C64: =C32 -> Внеплан | D64: =D32 | E64: =F32 | G64: =H32 | I64: =J32 | K64: =L32 | M64: =N32 | O64: =P32 | Q64: =R32 | S64: =T30 | U64: =V32 | W64: =X32 | Y64: =Z32 | AA64: =AB32 | AC64: =AD32 | AE64: =AF32 | AG64: =AH30 | AI64: =AJ32 | AK64: =AL32 | AM64: =AN32 | AO64: =AP32 | AQ64: =AR32 | AS64: =AT32 | AU64: =AV32 | AW64: =AX32 | AY64: =SUM(E64:AX64) -> 0
S65: =T32 | AW65: ИТОГО | AY65: =SUM(E65:AX65) -> 0
A67: Дата: | C67: 45662 | D67: План на день кухня ПОНЕДЕЛЬНИК
A68: № | B68: Код | C68: Вид | D68: Название блюда | E68: Т 1 | F68: Ф 1 | G68: Т2 | H68: Ф2 | I68: Т 3 | J68: Ф 3 | K68: Т 4 | L68: Ф 4 | M68: Т 5 | N68: Ф 5 | O68: Т 6 | P68: Ф 6 | Q68: Т 7 | R68: Ф7 | S68: Т8 | T68: Ф8 | U68: Т9 | V68: Ф9 | W68: Т10 | X68: Ф10 | Y68: Т11 | Z68: Ф11 | AA68: Т12 | AB68: Ф12 | AC68: Т13 | AD68: Ф13 | AE68: Т14 | AF68: Ф14 | AG68: Т15 | AH68: Ф15 | AI68: Т16 | AJ68: Ф16 | AK68: Т17 | AL68: Ф17 | AM68: Т18 | AN68: Ф18 | AO68: Т19 | AP68: Ф19 | AQ68: Т20 | AR68: Ф20 | AS68: Т21 | AT68: Ф21 | AU68: Т22 | AV68: Ф22 | AW68: БПЮ | AX68: ФБПЮ | AY68: ПЛАН | AZ68: ФАКТ | BC68: Выход | BD68: Масса
D69: Кол-во человек | E69: ОБЫЧ РЕЖ | K69: 40 | M69: 20 | S69: ПО ВЫХ ДН | W69: ОБЫЧ РЕЖ | AE69: 15-20 | AK69: 30-50 | AQ69: ОБЫЧ РЕЖ | AS69: 20 | AU69: ОБЫЧ РЕЖ | AW69: 45780
D70: Когда выходят работать | G70: 45813 | M70: с 05.01 | Y70: 7-ВЫХОДНОЙ
A71: 1 | B71: 3038 | C71: =C6 -> Завтрак | D71: ='Меню НА СЛЕДУЮЩИЙ МЕСЯЦ'!C12 | E71: 14 | F71: 14 | G71: 2 | H71: 2 | K71: 15 | L71: 15 | M71: 2 | N71: 2 | O71: 4 | P71: 4 | W71: 5 | X71: 5 | AE71: 3 | AF71: 3 | AQ71: 20 | AR71: 20 | AY71: =(E71+G71+I71+K71+M71+O71+Q71+S71+U71+W71+Y71+AA71+AC572+AC71+AE71+AG71+AI71+AK71+AM71+AW71+AO71+AQ71+AS71+AU71)+1 -> 66 | AZ71: =F71+H71+J71+L71+N71+P71+R71+T71+V71+X71+Z71+AD71+AF71+AH71+AJ71+AL71+AB71+AR71+AX71+AN71+AP71+AT71+AV71 -> 65 | BC71: 0.1 | BD71: =AY71*BC71 -> 6.6
A72: 2 | B72: 3735 | C72: Завтрак | D72: ='Меню НА СЛЕДУЮЩИЙ МЕСЯЦ'!C13 | E72: 10 | F72: 10 | G72: 2 | H72: 2 | K72: 15 | L72: 15 | M72: 3 | N72: 3 | O72: 9 | P72: 9 | W72: 8 | X72: 8 | AE72: 3 | AF72: 3 | AK72: 2 | AL72: 2 | AQ72: 10 | AR72: 10 | AS72: 4 | AT72: 4 | AU72: 4 | AV72: 4 | AY72: =(E72+G72+I72+K72+M72+O72+Q72+S72+U72+W72+Y72+AA72+AC573+AC72+AE72+AG72+AI72+AK72+AM72+AW72+AO72+AQ72+AS72+AU72)+1 -> 71 | AZ72: =F72+H72+J72+L72+N72+P72+R72+T72+V72+X72+Z72+AD72+AF72+AH72+AJ72+AL72+AB72+AR72+AX72+AN72+AP72+AT72+AV72 -> 70
A73: 3 | C73: Завтрак | AY73: =(E73+G73+I73+K73+M73+O73+Q73+S73+U73+W73+Y73+AA73+AC574+AC73+AE73+AG73+AI73+AK73+AM73+AW73+AO73+AQ73+AS73+AU73)+1 -> 1 | AZ73: =F73+H73+J73+L73+N73+P73+R73+T73+V73+X73+Z73+AD73+AF73+AH73+AJ73+AL73+AB73+AR73+AX73+AN73+AP73+AT73+AV73 -> 0
A74: 4 | B74: 3301 | C74: =C9 -> Салат | D74: ='Меню НА СЛЕДУЮЩИЙ МЕСЯЦ'!E12 | E74: 20 | F74: 20 | G74: 2 | H74: 3 | K74: 12 | L74: 12 | M74: 10 | N74: 10 | O74: 5 | P74: 5 | W74: 15 | X74: 15 | AE74: 3 | AF74: 3 | AK74: 3 | AL74: 3 | AQ74: 20 | AR74: 20 | AS74: 10 | AT74: 10 | AU74: 8 | AV74: 8 | AY74: =(E74+G74+I74+K74+M74+O74+Q74+S74+U74+W74+Y74+AA74+AC575+AC74+AE74+AG74+AI74+AK74+AM74+AW74+AO74+AQ74+AS74+AU74)+1 -> 109 | AZ74: =F74+H74+J74+L74+N74+P74+R74+T74+V74+X74+Z74+AD74+AF74+AH74+AJ74+AL74+AB74+AR74+AX74+AN74+AP74+AT74+AV74 -> 109 | BA74: =AY74*AZ74 -> 11881 | BC74: 0.1 | BD74: =AY74*BC74 -> 10.9
A75: 5 | B75: 3660 | C75: =C10 -> Салат | D75: ='Меню НА СЛЕДУЮЩИЙ МЕСЯЦ'!E13 | E75: 20 | F75: 20 | G75: 2 | H75: 3 | K75: 12 | L75: 12 | M75: 10 | N75: 10 | O75: 5 | P75: 5 | W75: 15 | X75: 15 | AE75: 3 | AF75: 3 | AK75: 3 | AL75: 3 | AQ75: 20 | AR75: 20 | AS75: 10 | AT75: 10 | AU75: 8 | AV75: 8 | AY75: =(E75+G75+I75+K75+M75+O75+Q75+S75+U75+W75+Y75+AA75+AC576+AC75+AE75+AG75+AI75+AK75+AM75+AW75+AO75+AQ75+AS75+AU75)+1 -> 109 | AZ75: =F75+H75+J75+L75+N75+P75+R75+T75+V75+X75+Z75+AD75+AF75+AH75+AJ75+AL75+AB75+AR75+AX75+AN75+AP75+AT75+AV75 -> 109 | BA75: =AY75*AZ75 -> 11881 | BC75: 0.1 | BD75: =AY75*BC75 -> 10.9
A76: 6 | B76: 3141 | C76: =C11 -> Салат | D76: Салат капустный | AQ76: 20 | AR76: 22 | AY76: =(E76+G76+I76+K76+M76+O76+Q76+S76+U76+W76+Y76+AA76+AC577+AC76+AE76+AG76+AI76+AK76+AM76+AW76+AO76+AQ76+AS76+AU76)+1 -> 21 | AZ76: =F76+H76+J76+L76+N76+P76+R76+T76+V76+X76+Z76+AD76+AF76+AH76+AJ76+AL76+AB76+AR76+AX76+AN76+AP76+AT76+AV76 -> 22 | BA76: =AY76*AZ76 -> 462 | BC76: 0.1 | BD76: =AY76*BC76 -> 2.1
A77: 8 | B77: 793 | C77: суп | D77: ='Меню НА СЛЕДУЮЩИЙ МЕСЯЦ'!G12 | E77: 2 | F77: 2 | G77: 2 | H77: 2 | K77: 2 | L77: 2 | M77: 2 | N77: 2 | O77: 2 | P77: 2 | W77: 2 | X77: 2 | AE77: 2 | AF77: 2 | AK77: 2 | AL77: 2 | AQ77: 2 | AR77: 2 | AS77: 2 | AT77: 2 | AU77: 2 | AV77: 2 | AY77: =(E77+G77+I77+K77+M77+O77+Q77+S77+U77+W77+Y77+AA77+AC579+AC77+AE77+AG77+AI77+AK77+AM77+AW77+AO77+AQ77+AS77+AU77)+1 -> 23 | AZ77: =F77+H77+J77+L77+N77+P77+R77+T77+V77+X77+Z77+AD77+AF77+AH77+AJ77+AL77+AB77+AR77+AX77+AN77+AP77+AT77+AV77 -> 22 | BA77: =AY77*AZ77 -> 506 | BC77: 0.25 | BD77: =AY77*BC77 -> 5.75
A78: 9 | B78: 3276 | C78: Второе | D78: ='Меню НА СЛЕДУЮЩИЙ МЕСЯЦ'!I12 | E78: 15 | F78: 15 | G78: 7 | H78: 7 | K78: 20 | L78: 20 | M78: 3 | N78: 3 | O78: 5 | P78: 5 | W78: 20 | X78: 20 | AE78: 3 | AF78: 3 | AK78: 3 | AL78: 3 | AQ78: 20 | AR78: 20 | AS78: 8 | AT78: 8 | AU78: 8 | AV78: 8 | AY78: =(E78+G78+I78+K78+M78+O78+Q78+S78+U78+W78+Y78+AA78+AC580+AC78+AE78+AG78+AI78+AK78+AM78+AW78+AO78+AQ78+AS78+AU78)+1 -> 113 | AZ78: =F78+H78+J78+L78+N78+P78+R78+T78+V78+X78+Z78+AD78+AF78+AH78+AJ78+AL78+AB78+AR78+AX78+AN78+AP78+AT78+AV78 -> 112 | BA78: =AY78*AZ78 -> 12656 | BC78: 0.3 | BD78: =AY78*BC78 -> 33.9
A79: 10 | B79: 3734 | C79: Второе | D79: ='Меню НА СЛЕДУЮЩИЙ МЕСЯЦ'!I13 | E79: 15 | F79: 15 | G79: 7 | H79: 7 | K79: 20 | L79: 20 | M79: 3 | N79: 3 | O79: 5 | P79: 5 | W79: 20 | X79: 20 | AE79: 3 | AF79: 3 | AK79: 3 | AL79: 3 | AQ79: 20 | AR79: 20 | AS79: 8 | AT79: 8 | AU79: 8 | AV79: 8 | AY79: =(E79+G79+I79+K79+M79+O79+Q79+S79+U79+W79+Y79+AA79+AC581+AC79+AE79+AG79+AI79+AK79+AM79+AW79+AO79+AQ79+AS79+AU79)+1 -> 113 | AZ79: =F79+H79+J79+L79+N79+P79+R79+T79+V79+X79+Z79+AD79+AF79+AH79+AJ79+AL79+AB79+AR79+AX79+AN79+AP79+AT79+AV79 -> 112 | BA79: =AY79*AZ79 -> 12656
A80: 11 | B80: 3703 | C80: Второе | D80: ='Меню НА СЛЕДУЮЩИЙ МЕСЯЦ'!I14 | E80: 15 | F80: 15 | G80: 7 | H80: 6 | K80: 20 | L80: 20 | M80: 3 | N80: 3 | O80: 5 | P80: 5 | W80: 20 | X80: 20 | AE80: 3 | AF80: 3 | AK80: 3 | AL80: 3 | AQ80: 20 | AR80: 20 | AS80: 8 | AT80: 8 | AU80: 8 | AV80: 8 | AY80: =(E80+G80+I80+K80+M80+O80+Q80+S80+U80+W80+Y80+AA80+AC582+AC80+AE80+AG80+AI80+AK80+AM80+AW80+AO80+AQ80+AS80+AU80)+1 -> 113 | AZ80: =F80+H80+J80+L80+N80+P80+R80+T80+V80+X80+Z80+AD80+AF80+AH80+AJ80+AL80+AB80+AR80+AX80+AN80+AP80+AT80+AV80 -> 111 | BA80: =AY80*AZ80 -> 12543 | BC80: 0.3 | BD80: =AY80*BC80 -> 33.9
A81: 12 | B81: 3532 | C81: сэндвич | D81: ='Меню НА СЛЕДУЮЩИЙ МЕСЯЦ'!O12 | E81: 8 | F81: 8 | K81: 5 | L81: 8 | M81: 3 | N81: 3 | O81: 3 | P81: 3 | W81: 3 | X81: 3 | AE81: 3 | AF81: 3 | AQ81: 8 | AR81: 9 | AS81: 2 | AT81: 2 | AU81: 2 | AV81: 2 | AY81: =(E81+G81+I81+K81+M81+O81+Q81+S81+U81+W81+Y81+AA81+AC583+AC81+AE81+AG81+AI81+AK81+AM81+AW81+AO81+AQ81+AS81+AU81)+1 -> 38 | AZ81: =F81+H81+J81+L81+N81+P81+R81+T81+V81+X81+Z81+AD81+AF81+AH81+AJ81+AL81+AB81+AR81+AX81+AN81+AP81+AT81+AV81 -> 41 | BA81: =AY81*AZ81 -> 1558
A82: 13 | B82: 822 | D82: Хлеб | E82: 15 | F82: 10 | K82: 20 | L82: 13 | M82: 3 | N82: 3 | O82: 10 | P82: 8 | W82: 10 | X82: 8 | AE82: 5 | AF82: 5 | AS82: 3 | AT82: 3 | AU82: 3 | AV82: 3 | AY82: =(E82+G82+I82+K82+M82+O82+Q82+S82+U82+W82+Y82+AA82+AC584+AC82+AE82+AG82+AI82+AK82+AM82+AW82+AO82+AQ82+AS82+AU82)+1 -> 70 | AZ82: =F82+H82+J82+L82+N82+P82+R82+T82+V82+X82+Z82+AD82+AF82+AH82+AJ82+AL82+AB82+AR82+AX82+AN82+AP82+AT82+AV82 -> 53 | BA82: =AY82*AZ82 -> 3710 | BC82: 0.3 | BD82: =AY82*BC82 -> 21
A83: 14 | AY83: =(E83+G83+I83+K83+M83+O83+Q83+S83+U83+W83+Y83+AA83+AC585+AC83+AE83+AG83+AI83+AK83+AM83+AW83+AO83+AQ83+AS83+AU83)+1 -> 1 | AZ83: =F83+H83+J83+L83+N83+P83+R83+T83+V83+X83+Z83+AD83+AF83+AH83+AJ83+AL83+AB83+AR83+AX83+AN83+AP83+AT83+AV83 -> 0 | BC83: 0.03 | BD83: =AY83*BC83 -> 0.03
A84: 15 | AY84: =(E84+G84+I84+K84+M84+O84+Q84+S84+U84+W84+Y84+AA84+AC586+AC84+AE84+AG84+AI84+AK84+AM84+AW84+AO84+AQ84+AS84+AU84)+1 -> 1 | AZ84: =F84+H84+J84+L84+N84+P84+R84+T84+V84+X84+Z84+AD84+AF84+AH84+AJ84+AL84+AB84+AR84+AX84+AN84+AP84+AT84+AV84 -> 0
A85: 16 | AY85: =(E85+G85+I85+K85+M85+O85+Q85+S85+U85+W85+Y85+AA85+AC587+AC85+AE85+AG85+AI85+AK85+AM85+AW85+AO85+AQ85+AS85+AU85)+1 -> 1 | AZ85: =F85+H85+J85+L85+N85+P85+R85+T85+V85+X85+Z85+AD85+AF85+AH85+AJ85+AL85+AB85+AR85+AX85+AN85+AP85+AT85+AV85 -> 0 | BC85: 0.3 | BD85: =AY85*BC85 -> 0.3
A86: 17 | AY86: =(E86+G86+I86+K86+M86+O86+Q86+S86+U86+W86+Y86+AA86+AC588+AC86+AE86+AG86+AI86+AK86+AM86+AW86+AO86+AQ86+AS86+AU86)+1 -> 1 | AZ86: =F86+H86+J86+L86+N86+P86+R86+T86+V86+X86+Z86+AD86+AF86+AH86+AJ86+AL86+AB86+AR86+AX86+AN86+AP86+AT86+AV86 -> 0
A87: 18 | AY87: =(E87+G87+I87+K87+M87+O87+Q87+S87+U87+W87+Y87+AA87+AC589+AC87+AE87+AG87+AI87+AK87+AM87+AW87+AO87+AQ87+AS87+AU87)+1 -> 1 | AZ87: =F87+H87+J87+L87+N87+P87+R87+T87+V87+X87+Z87+AD87+AF87+AH87+AJ87+AL87+AB87+AR87+AX87+AN87+AP87+AT87+AV87 -> 0 | BC87: 0.16 | BD87: =AY87*BC87 -> 0.16
A88: 19 | AY88: =(E88+G88+I88+K88+M88+O88+Q88+S88+U88+W88+Y88+AA88+AC590+AC88+AE88+AG88+AI88+AK88+AM88+AW88+AO88+AQ88+AS88+AU88)+1 -> 1 | AZ88: =F88+H88+J88+L88+N88+P88+R88+T88+V88+X88+Z88+AD88+AF88+AH88+AJ88+AL88+AB88+AR88+AX88+AN88+AP88+AT88+AV88 -> 0
A89: 20 | AY89: =(E89+G89+I89+K89+M89+O89+Q89+S89+U89+W89+Y89+AA89+AC591+AC89+AE89+AG89+AI89+AK89+AM89+AW89+AO89+AQ89+AS89+AU89)+1 -> 1 | AZ89: =F89+H89+J89+L89+N89+P89+R89+T89+V89+X89+Z89+AD89+AF89+AH89+AJ89+AL89+AB89+AR89+AX89+AN89+AP89+AT89+AV89 -> 0
A90: 21 | AY90: =(E90+G90+I90+K90+M90+O90+Q90+S90+U90+W90+Y90+AA90+AC592+AC90+AE90+AG90+AI90+AK90+AM90+AW90+AO90+AQ90+AS90+AU90)+1 -> 1 | AZ90: =F90+H90+J90+L90+N90+P90+R90+T90+V90+X90+Z90+AD90+AF90+AH90+AJ90+AL90+AB90+AR90+AX90+AN90+AP90+AT90+AV90 -> 0
A91: 22 | AY91: =(E91+G91+I91+K91+M91+O91+Q91+S91+U91+W91+Y91+AA91+AC593+AC91+AE91+AG91+AI91+AK91+AM91+AW91+AO91+AQ91+AS91+AU91)+1 -> 1 | AZ91: =F91+H91+J91+L91+N91+P91+R91+T91+V91+X91+Z91+AD91+AF91+AH91+AJ91+AL91+AB91+AR91+AX91+AN91+AP91+AT91+AV91 -> 0
A92: 23 | AY92: =(E92+G92+I92+K92+M92+O92+Q92+S92+U92+W92+Y92+AA92+AC594+AC92+AE92+AG92+AI92+AK92+AM92+AW92+AO92+AQ92+AS92+AU92)+1 -> 1 | AZ92: =F92+H92+J92+L92+N92+P92+R92+T92+V92+X92+Z92+AD92+AF92+AH92+AJ92+AL92+AB92+AR92+AX92+AN92+AP92+AT92+AV92 -> 0
A93: 24 | AY93: =(E93+G93+I93+K93+M93+O93+Q93+S93+U93+W93+Y93+AA93+AC595+AC93+AE93+AG93+AI93+AK93+AM93+AW93+AO93+AQ93+AS93+AU93)+1 -> 1 | AZ93: =F93+H93+J93+L93+N93+P93+R93+T93+V93+X93+Z93+AD93+AF93+AH93+AJ93+AL93+AB93+AR93+AX93+AN93+AP93+AT93+AV93 -> 0
A94: 25 | AY94: =(E94+G94+I94+K94+M94+O94+Q94+S94+U94+W94+Y94+AA94+AC596+AC94+AE94+AG94+AI94+AK94+AM94+AW94+AO94+AQ94+AS94+AU94)+1 -> 1 | AZ94: =F94+H94+J94+L94+N94+P94+R94+T94+V94+X94+Z94+AD94+AF94+AH94+AJ94+AL94+AB94+AR94+AX94+AN94+AP94+AT94+AV94 -> 0
A95: 26 | AY95: =(E95+G95+I95+K95+M95+O95+Q95+S95+U95+W95+Y95+AA95+AC597+AC95+AE95+AG95+AI95+AK95+AM95+AW95+AO95+AQ95+AS95+AU95)+1 -> 1 | AZ95: =F95+H95+J95+L95+N95+P95+R95+T95+V95+X95+Z95+AD95+AF95+AH95+AJ95+AL95+AB95+AR95+AX95+AN95+AP95+AT95+AV95 -> 0
AY96: =SUM(AY71:AY92) -> 857 | AZ96: =SUM(AZ71:AZ92) -> 826 | BC96: вес | BD96: =SUM(BD71:BD87) -> 125.54
C97: ______________________________________________________________________________________
A99: Дата: | C99: =C67 -> 45662 | D99: Загрузка в аппараты | I99: Выгружаем дату производства:
A100: № | B100: =B68 -> Код | C100: Вид | D100: Название блюда | E100: Т1 | G100: Т2 | I100: Т3 | K100: Т4 | M100: Т5 | O100: Т6 | Q100: Т7 | S100: Т8 | U100: Т9 | W100: Т10 | Y100: Т11 | AA100: Т12 | AC100: Т13 | AE100: Т14 | AG100: Т15 | AI100: Т16 | AK100: Т17 | AM100: Т18 | AO100: Т19 | AQ100: Т20 | AS100: Т21 | AU100: Т22 | AW100: ТСПК | AY100: ИТОГ
A101: =A71 -> 1 | B101: =B71 -> 3038 | C101: =C71 -> Завтрак | D101: =D71 | E101: =F71 -> 14 | G101: =H71 -> 2 | I101: =J71 | K101: =L71 -> 15 | M101: =N71 -> 2 | O101: =P71 -> 4 | Q101: =R71 | S101: =T71 | U101: =V71 | W101: =X71 -> 5 | Y101: =Z71 | AA101: =AB71 | AC101: =AD71 | AE101: =AF71 -> 3 | AG101: =AH71 | AI101: =AJ71 | AK101: =AL71 | AM101: =AN71 | AO101: =AP71 | AQ101: =AR71 -> 20 | AS101: =AT71 | AU101: =AV71 | AW101: =AX71 | AY101: =SUM(E101:AX101) -> 65
A102: =A72 -> 2 | B102: =B72 -> 3735 | C102: =C72 -> Завтрак | D102: =D72 | E102: =F72 -> 10 | G102: =H72 -> 2 | I102: =J72 | K102: =L72 -> 15 | M102: =N72 -> 3 | O102: =P72 -> 9 | Q102: =R72 | S102: =T72 | U102: =V72 | W102: =X72 -> 8 | Y102: =Z72 | AA102: =AB72 | AC102: =AD72 | AE102: =AF72 -> 3 | AG102: =AH72 | AI102: =AJ72 | AK102: =AL72 -> 2 | AM102: =AN72 | AO102: =AP72 | AQ102: =AR72 -> 10 | AS102: =AT72 -> 4 | AU102: =AV72 -> 4 | AW102: =AX72 | AY102: =SUM(E102:AX102) -> 70
A103: =A73 -> 3 | B103: =B73 | C103: =C73 -> Завтрак | D103: =D73 | E103: =F73 | G103: =H73 | I103: =J73 | K103: =L73 | M103: =N73 | O103: =P73 | Q103: =R73 | S103: =T73 | U103: =V73 | W103: =X73 | Y103: =Z73 | AA103: =AB73 | AC103: =AD73 | AE103: =AF73 | AG103: =AH73 | AI103: =AJ73 | AK103: =AL73 | AM103: =AN73 | AO103: =AP73 | AQ103: =AR73 | AS103: =AT73 | AU103: =AV73 | AW103: =AX73 | AY103: =SUM(E103:AX103) -> 0
A104: =A74 -> 4 | B104: =B74 -> 3301 | C104: =C74 -> Салат | D104: =D74 | E104: =F74 -> 20 | G104: =H74 -> 3 | I104: =J74 | K104: =L74 -> 12 | M104: =N74 -> 10 | O104: =P74 -> 5 | Q104: =R74 | S104: =T74 | U104: =V74 | W104: =X74 -> 15 | Y104: =Z74 | AA104: =AB74 | AC104: =AD74 | AE104: =AF74 -> 3 | AG104: =AH74 | AI104: =AJ74 | AK104: =AL74 -> 3 | AM104: =AN74 | AO104: =AP74 | AQ104: =AR74 -> 20 | AS104: =AT74 -> 10 | AU104: =AV74 -> 8 | AW104: =AX74 | AY104: =SUM(E104:AX104) -> 109
A105: =A75 -> 5 | B105: =B75 -> 3660 | C105: =C75 -> Салат | D105: =D75 | E105: =F75 -> 20 | G105: =H75 -> 3 | I105: =J75 | K105: =L75 -> 12 | M105: =N75 -> 10 | O105: =P75 -> 5 | Q105: =R75 | S105: =T75 | U105: =V75 | W105: =X75 -> 15 | Y105: =Z75 | AA105: =AB75 | AC105: =AD75 | AE105: =AF75 -> 3 | AG105: =AH75 | AI105: =AJ75 | AK105: =AL75 -> 3 | AM105: =AN75 | AO105: =AP75 | AQ105: =AR75 -> 20 | AS105: =AT75 -> 10 | AU105: =AV75 -> 8 | AW105: =AX75 | AY105: =SUM(E105:AX105) -> 109
A106: =A76 -> 6 | B106: =B76 -> 3141 | C106: =C76 -> Салат | D106: =D76 -> Салат капустный | E106: =F76 | G106: =H76 | I106: =J76 | K106: =L76 | M106: =N76 | O106: =P76 | Q106: =R76 | S106: =T76 | U106: =V76 | W106: =X76 | Y106: =Z76 | AA106: =AB76 | AC106: =AD76 | AE106: =AF76 | AG106: =AH76 | AI106: =AJ76 | AK106: =AL76 | AM106: =AN76 | AO106: =AP76 | AQ106: =AR76 -> 22 | AS106: =AT76 | AU106: =AV76 | AW106: =AX76 | AY106: =SUM(E106:AX106) -> 22
A107: =A77 -> 8 | B107: =B77 -> 793 | C107: =C77 -> суп | D107: =D77 | E107: =F77 -> 2 | G107: =H77 -> 2 | I107: =J77 | K107: =L77 -> 2 | M107: =N77 -> 2 | O107: =P77 -> 2 | Q107: =R77 | S107: =T77 | U107: =V77 | W107: =X77 -> 2 | Y107: =Z77 | AA107: =AB77 | AC107: =AD77 | AE107: =AF77 -> 2 | AG107: =AH77 | AI107: =AJ77 | AK107: =AL77 -> 2 | AM107: =AN77 | AO107: =AP77 | AQ107: =AR77 -> 2 | AS107: =AT77 -> 2 | AU107: =AV77 -> 2 | AW107: =AX77 | AY107: =SUM(E107:AX107) -> 22
A108: =A78 -> 9 | B108: =B78 -> 3276 | C108: =C78 -> Второе | D108: =D78 | E108: =F78 -> 15 | G108: =H78 -> 7 | I108: =J78 | K108: =L78 -> 20 | M108: =N78 -> 3 | O108: =P78 -> 5 | Q108: =R78 | S108: =T78 | U108: =V78 | W108: =X78 -> 20 | Y108: =Z78 | AA108: =AB78 | AC108: =AD78 | AE108: =AF78 -> 3 | AG108: =AH78 | AI108: =AJ78 | AK108: =AL78 -> 3 | AM108: =AN78 | AO108: =AP78 | AQ108: =AR78 -> 20 | AS108: =AT78 -> 8 | AU108: =AV78 -> 8 | AW108: =AX78 | AY108: =SUM(E108:AX108) -> 112
A109: =A79 -> 10 | B109: =B79 -> 3734 | C109: =C79 -> Второе | D109: =D79 | E109: =F79 -> 15 | G109: =H79 -> 7 | I109: =J79 | K109: =L79 -> 20 | M109: =N79 -> 3 | O109: =P79 -> 5 | Q109: =R79 | S109: =T79 | U109: =V79 | W109: =X79 -> 20 | Y109: =Z79 | AA109: =AB79 | AC109: =AD79 | AE109: =AF79 -> 3 | AG109: =AH79 | AI109: =AJ79 | AK109: =AL79 -> 3 | AM109: =AN79 | AO109: =AP79 | AQ109: =AR79 -> 20 | AS109: =AT79 -> 8 | AU109: =AV79 -> 8 | AW109: =AX79 | AY109: =SUM(E109:AX109) -> 112
A110: =A80 -> 11 | B110: =B80 -> 3703 | C110: =C80 -> Второе | D110: =D80 | E110: =F80 -> 15 | G110: =H80 -> 6 | I110: =J80 | K110: =L80 -> 20 | M110: =N80 -> 3 | O110: =P80 -> 5 | Q110: =R80 | S110: =T80 | U110: =V80 | W110: =X80 -> 20 | Y110: =Z80 | AA110: =AB80 | AC110: =AD80 | AE110: =AF80 -> 3 | AG110: =AH80 | AI110: =AJ80 | AK110: =AL80 -> 3 | AM110: =AN80 | AO110: =AP80 | AQ110: =AR80 -> 20 | AS110: =AT80 -> 8 | AU110: =AV80 -> 8 | AW110: =AX80 | AY110: =SUM(E110:AX110) -> 111
A111: =A81 -> 12 | B111: =B81 -> 3532 | C111: =C81 -> сэндвич | D111: =D81 | E111: =F81 -> 8 | G111: =H81 | I111: =J81 | K111: =L81 -> 8 | M111: =N81 -> 3 | O111: =P81 -> 3 | Q111: =R81 | S111: =T81 | U111: =V81 | W111: =X81 -> 3 | Y111: =Z81 | AA111: =AB81 | AC111: =AD81 | AE111: =AF81 -> 3 | AG111: =AH81 | AI111: =AJ81 | AK111: =AL81 | AM111: =AN81 | AO111: =AP81 | AQ111: =AR81 -> 9 | AS111: =AT81 -> 2 | AU111: =AV81 -> 2 | AW111: =AX81 | AY111: =SUM(E111:AX111) -> 41
A112: =A82 -> 13 | B112: =B82 -> 822 | C112: =C82 | D112: =D82 -> Хлеб | E112: =F82 -> 10 | G112: =H82 | I112: =J82 | K112: =L82 -> 13 | M112: =N82 -> 3 | O112: =P82 -> 8 | Q112: =R82 | S112: =T82 | U112: =V82 | W112: =X82 -> 8 | Y112: =Z82 | AA112: =AB82 | AC112: =AD82 | AE112: =AF82 -> 5 | AG112: =AH82 | AI112: =AJ82 | AK112: =AL82 | AM112: =AN82 | AO112: =AP82 | AQ112: =AR82 | AS112: =AT82 -> 3 | AU112: =AV82 -> 3 | AW112: =AX82 | AY112: =SUM(E112:AX112) -> 53
... A125: =A95 -> 26 | B125: =B95 | C125: =C95 | D125: =D95 | E125: =F95 | G125: =H95 | I125: =J95 | K125: =L95 | M125: =N95 | O125: =P95 | Q125: =R95 | S125: =T95 | U125: =V95 | W125: =X95 | Y125: =Z95 | AA125: =AB95 | AC125: =AD95 | AE125: =AF95 | AG125: =AH95 | AI125: =AJ95 | AK125: =AL95 | AM125: =AN95 | AO125: =AP95 | AQ125: =AR95 | AS125: =AT95 | AU125: =AV95 | AW125: =AX95 | AY125: =SUM(E125:AX125) -> 0
AW126: ИТОГО | AY126: =SUM(AY101:AY125) -> 826
A128: Дата: | C128: 46030 | D128: План на день кухня ЧЕТВЕРГ
A129: № | B129: Код | C129: Вид | D129: Название блюда | E129: Т 1 | F129: Ф 1 | G129: Т2 | H129: Ф2 | I129: Т 3 | J129: Ф 3 | K129: Т 4 | L129: Ф 4 | M129: Т 5 | N129: Ф 5 | O129: Т 6 | P129: Ф 6 | Q129: Т 7 | R129: Ф7 | S129: Т8 | T129: Ф8 | U129: Т9 | V129: Ф9 | W129: Т10 | X129: Ф10 | Y129: Т11 | Z129: Ф11 | AA129: Т12 | AB129: Ф12 | AC129: Т13 | AD129: Ф13 | AE129: Т14 | AF129: Ф14 | AG129: Т15 | AH129: Ф15 | AI129: Т16 | AJ129: Ф16 | AK129: Т17 | AL129: Ф17 | AM129: Т18 | AN129: Ф18 | AO129: Т19 | AP129: Ф19 | AQ129: Т20 | AR129: Ф20 | AS129: Т21 | AT129: Ф21 | AU129: Т22 | AV129: Ф22 | AW129: БПЮ | AX129: ФБПЮ | AY129: ПЛАН | AZ129: ФАКТ | BC129: Выход | BD129: Масса
...

Sheet Рабочие дни в праздники
A2: № точки | B2: Адреса | C2: 29.30.12 | D2: 46021 | E2: 46022 | F2: 46023 | G2: 46024 | H2: 46025 | I2: 46026 | J2: 46027 | K2: 46028 | L2: 46029 | M2: 46030 | N2: 46031 | O2: 46032 | P2: 46033 | Q2: 46034 | R2: Информация
A3: 1 | B3: "Лемана Про" ул. Тобольский тракт д.103 | E3: 100-105 | H3: В обычном режиме | J3: В обычном режиме | L3: В обычном режиме | N3: В обычном режиме | P3: В обычном режиме | R3: С 31.12 - 04.01 НЕ БУДЕТ РАБОТАТЬ СТОЛОВАЯ 31 магазин работает с 9 до 18, 1 числа выходной и с 2 числа как обычно
A4: 2 | B4: Пермякова 1Г, Очаково
A5: 3 | B5: Велижанский тракт 6 км, ст9 "ЗапСибГазпром Газификация" | R5: с 31.12 по 11.01 отдыхают, 12.01 на работу
A6: 4 | B6: Старый Тобольский тракт 2 километр, 8 ст25 "Технологии офс" | E6: ~40 | F6: ~40 | G6: ~40 | H6: ~40 | I6: ~40 | J6: ~40 | K6: ~40 | L6: ~40 | M6: ~40 | N6: ~40 | O6: ~40 | P6: ~40 | R6: Все праздники работает только круглосуточный персонал, около 30 человек
A7: 5 | B7: "Бентек" Старый Тобольский тракт 2 километр, 8а | J7: ~20 | K7: ~20 | L7: ~20 | M7: ~20 | N7: ~20 | O7: ~20 | P7: ~20 | R7: 31-4 выходные, с 5го по 11е работают примерно по 20 чел
A8: 6 | B8: "ОФС" Тобольский тракт 23 км | R8: 31.12 - сокращеный день до 16:00, 1.01 - выходной у всех, с 02.01 - цех работает, кроме начальства и технологического отдела. с 12.01 в штатном режиме
A9: 7 | B9: ул. Сергея Ильюшина,1 Металл Профиль | C9: ~30 | D9: ~30 | R9: 29-30 крайние рабочие дни будет 30 чел., половина сотрудников в эти дни не выйдут на работу, тк берут за свой счет. На работу выходим 12.01
A10: 8 | B10: Тубдиспансер, Курортная 2а | R10: Загрузка по выходному дню
A11: 9 | B11: ул. Камчатская, 194 "АИРТО" | R11: как и во все праздничные дни мы в праздники будем отдыхать. И Арендаторы (большинство) тоже.
A12: 10 | B12: Станция скорой помощи, Суходольская д. 25 | F12: В обычном режиме | H12: В обычном режиме | J12: В обычном режиме | L12: В обычном режиме | N12: В обычном режиме | P12: В обычном режиме | R12: Работают в обычном режиме
A13: 11 | B13: Катрен, Гилёвская Роща д.10 | R13: 30.12, 31.12, 01.01 и 7.01 - выходные дни, остальные рабочие (загруженость на 7-10% сеньше чем обчно)
A14: 12 | B14: ул. Республики, 250 "Сантехкомплект" (малое АБК) | R14: Работают по производственному календарю
A15: 13 | B15: ул. Республики, 250 "Сантехкомплект"
A16: 14 | B16: ул. Республики, 142 "Технопарк" | E16: ~15-20 | F16: ~15-20 | G16: ~15-20 | H16: ~15-20 | I16: ~15-20 | J16: ~15-20 | K16: ~15-20 | L16: ~15-20 | M16: ~15-20 | N16: ~15-20 | O16: ~15-20 | P16: ~15-20 | R16: Примерно будут работать 15/20 человек в смену, загрузка выходного дня
A17: 15 | B17: ул. Депутатская 91, к. 3 "АТМ Альянс" | R17: с 31.12 по 11.01 отдыхают, 12.01 на работу
A18: 16 | B18: ул. Первомайская 19 "Запсибгазпром" | R18: с 31.12 по 11.01 отдыхают, 12.01 на работу
A19: 17 | B19: Республики 211 а | E19: ~30 | F19: ~10-15 | G19: ~10-15 | H19: ~10-15 | I19: ~10-15 | J19: ~30-50 | K19: ~30-50 | L19: ~30-50 | M19: ~30-50 | N19: ~30-50 | O19: ~30-50 | P19: ~30-50
A20: 18 | B20: Тюмень прибор, Индустриальный парк Боровский Промзона Южная, ст5 | R20: с 31.12 по 11.01 отдыхают, 12.01 на работу
A21: 19 | B21: ул. Республики, 142 "Технопарк"2 | R21: с 31.12 по 11.01 отдыхают, 12.01 на работу
A22: 20 | B22: ул. Даудельная 1к3 | F22: В обычном режиме | H22: В обычном режиме | J22: В обычном режиме | L22: В обычном режиме | N22: В обычном режиме | P22: В обычном режиме | R22: Работают в обычном режиме
A23: 21 | B23: "Шлюмберже" ул. Дружбы, 124 | I23: 20 | J23: 20 | K23: 20 | L23: 20 | M23: 20 | N23: 20 | O23: 20 | P23: 20 | R23: с 31.12 по 03.01 отдыхают, с 04.01 будут работать по 20 человек, остальные выходят 12.01
A24: 22 | B24: "Лемана Про" ул. Менделеева 1 | H24: В обычном режиме | J24: В обычном режиме | L24: В обычном режиме | N24: В обычном режиме | P24: В обычном режиме
A25: СПК | B25: СПК завод, Республики 250 (обеденная загрузка) | R25: Работают по производственному календарю
A26: БАХАРЕВА | C26: 15 | D26: 15 | E26: 15 | F26: 45780 | G26: 45780 | H26: 45780 | I26: 45780 | J26: 45780 | R26: С 1-5 ПРИМЕРНО 3-5 ЧЕЛ. ЕСЛИ НЕ РАБОТАЕМ - ЧЕМ НАКОРМИТЬ РЗБЕРУТСЯ
E28: Выходные
E29: Короткий день до 18:00
E30: Короткий день до 16:00

Sheet Детали
A1: Код блюда | B1: Название блюда | C1: Код белка | D1: Белок | E1: Код гарнира | F1: Гарнир | G1: Статус | H1: Комментарий
A2: 1050 | B2: Азу ''По-татарски'' | C2: 3906 | D2: Азу из свинины с грибами б/100гр | G2: не найден гарнир
A3: 3025 | B3: Азу ''По-татарски'' (Столовая) | C3: 3906 | D3: Азу из свинины с грибами б/100гр | G3: не найден гарнир
A4: 3362 | B4: Азу из говядины с гречкой | E4: 2263 | F4: Гречка г/200гр | G4: не найден белок
A5: 3351 | B5: Азу из говядины с макаронами | E5: 2278 | F5: Макароны г/200гр | G5: не найден белок
A6: 3462 | B6: Азу из говядины с пюре | E6: 2247 | F6: Картофельное пюре г/200гр | G6: не найден белок
A7: 3361 | B7: Азу из говядины с рисом | E7: 487 | F7: Рис г/150гр | G7: не найден белок
A8: 3352 | B8: Азу из курицы с картофелем | E8: 2247 | F8: Картофельное пюре г/200гр | G8: не найден белок
A9: 3405 | B9: Азу из курицы с рисом | E9: 487 | F9: Рис г/150гр | G9: не найден белок
A10: 3303 | B10: Азу из курицы со спагетти | E10: 2264 | F10: Спагетти г/150гр | G10: не найден белок
A11: 3541 | B11: Азу из курочки с гречкой | E11: 2263 | F11: Гречка г/200гр | G11: не найден белок
A12: 2163 | B12: Азу из курочки с макаронами | E12: 2278 | F12: Макароны г/200гр | G12: не найден белок
A13: 3307 | B13: Азу из курочки с соленым огурчиком (столовая) | G13: не найдено
A14: 219 | B14: Азу из свинины с грибами с рисом | C14: 3906 | D14: Азу из свинины с грибами б/100гр | E14: 487 | F14: Рис г/150гр | G14: авто
A15: 737 | B15: Айран 150 мл | G15: не найдено
A16: 2904 | B16: Ассорти сэндвич (пепперони/ветчина) | G16: не найдено
A17: 384 | B17: Бедро в сметанном соусе с картофелем | C17: 2249 | D17: Бедро запеченное б/шт | E17: 2247 | F17: Картофельное пюре г/200гр | G17: авто
A18: 804 | B18: Бедро в соусе сациви с гречкой | C18: 2249 | D18: Бедро запеченное б/шт | E18: 2263 | F18: Гречка г/200гр | G18: авто
A19: 642 | B19: Бедро в соусе сациви с рисом | C19: 2249 | D19: Бедро запеченное б/шт | E19: 487 | F19: Рис г/150гр | G19: авто
A20: 370 | B20: Бедро жареное | G20: не найдено
A21: 886 | B21: Бедро запеченное с гречкой | C21: 2249 | D21: Бедро запеченное б/шт | E21: 2263 | F21: Гречка г/200гр | G21: авто
A22: 372 | B22: Бедро запеченное с картофелем | C22: 2249 | D22: Бедро запеченное б/шт | E22: 2247 | F22: Картофельное пюре г/200гр | G22: авто
A23: 984 | B23: Бедро запеченное с картофельным пюре | C23: 2249 | D23: Бедро запеченное б/шт | E23: 2247 | F23: Картофельное пюре г/200гр | G23: авто
A24: 859 | B24: Бедро запеченное с макаронами | C24: 2249 | D24: Бедро запеченное б/шт | E24: 2278 | F24: Макароны г/200гр | G24: авто
A25: 885 | B25: Бедро запеченное с рисом | C25: 2249 | D25: Бедро запеченное б/шт | E25: 487 | F25: Рис г/150гр | G25: авто
A26: 1080 | B26: Бедро запеченное с тушеной капустой | C26: 2249 | D26: Бедро запеченное б/шт | E26: 2248 | F26: Капуста тушеная г/150гр | G26: авто
A27: 2019 | B27: Бедро запеченное со ''сложным гарниром'' | C27: 2249 | D27: Бедро запеченное б/шт | G27: не найден гарнир
A28: 1122 | B28: Бедро запеченное со спагетти | C28: 2249 | D28: Бедро запеченное б/шт | E28: 2264 | F28: Спагетти г/150гр | G28: авто
A29: 2249 | B29: Бедро запеченое (горячее) Столовая | C29: 2249 | D29: Бедро запеченное б/шт | G29: не найден гарнир
A30: 143 | B30: Бедро под шапочкой с овощным сотэ | G30: не найдено
A31: 146 | B31: Бедро под шапочкой со спагетти | E31: 2264 | F31: Спагетти г/150гр | G31: не найден белок
A32: 1040 | B32: Бедрышки жареные с пюре | E32: 2247 | F32: Картофельное пюре г/200гр | G32: не найден белок
A33: 1345 | B33: Беляш | G33: не найдено
A34: 681 | B34: Бефстроганов из курочки со спагетти | E34: 2264 | F34: Спагетти г/150гр | G34: не найден белок
A35: 606 | B35: Бефстроганов с гречкой | E35: 2263 | F35: Гречка г/200гр | G35: не найден белок
A36: 2092 | B36: Бефстроганов со сливочным пюре | E36: 2247 | F36: Картофельное пюре г/200гр | G36: не найден белок
A37: 762 | B37: Бигус со свининой | G37: не найдено
A38: 439 | B38: Биточек ''по-селянски'' с лапшой | C38: 1269 | D38: Биточек куриный б/шт | G38: не найден гарнир
A39: 436 | B39: Биточек ''по-селянски'' со спагетти | C39: 1269 | D39: Биточек куриный б/шт | E39: 2264 | F39: Спагетти г/150гр | G39: авто
A40: 2895 | B40: Биточек ''Солнышко'' (Столовая) | G40: не найдено
A41: 3008 | B41: Биточек ''Солнышко'' с гречкой | E41: 2263 | F41: Гречка г/200гр | G41: не найден белок
A42: 2992 | B42: Биточек ''Солнышко'' с картофелем | E42: 2247 | F42: Картофельное пюре г/200гр | G42: не найден белок
A43: 2829 | B43: Биточек ''Солнышко'' с картофельным пюре | E43: 2247 | F43: Картофельное пюре г/200гр | G43: не найден белок
A44: 2959 | B44: Биточек ''Солнышко'' с макаронами | E44: 2278 | F44: Макароны г/200гр | G44: не найден белок
A45: 3198 | B45: Биточек ''Солнышко'' с тушеной капустой | E45: 2248 | F45: Капуста тушеная г/150гр | G45: не найден белок
A46: 1024 | B46: Биточек (курица) с грибами с рисом | E46: 487 | F46: Рис г/150гр | G46: не найден белок
A47: 1269 | B47: Биточек (с грибами) с картофелем | E47: 2247 | F47: Картофельное пюре г/200гр | G47: не найден белок
A48: 926 | B48: Биточек (с грибами) с картофельным пюре | E48: 2247 | F48: Картофельное пюре г/200гр | G48: не найден белок
A49: 1030 | B49: Биточек (с грибами) с макаронами | E49: 2278 | F49: Макароны г/200гр | G49: не найден белок
A50: 875 | B50: Биточек (с грибами) с рисом и перцем | E50: 487 | F50: Рис г/150гр | G50: не найден белок
A51: 3731 | B51: Биточек куриный с гречкой и соусом | C51: 1269 | D51: Биточек куриный б/шт | E51: 2263 | F51: Гречка г/200гр | G51: авто
A52: 3591 | B52: Биточек с макаронами | C52: 1269 | D52: Биточек куриный б/шт | E52: 2278 | F52: Макароны г/200гр | G52: авто
A53: 3671 | B53: Биточек с овощами и гречкой | C53: 1269 | D53: Биточек куриный б/шт | E53: 2263 | F53: Гречка г/200гр | G53: авто
A54: 3177 | B54: Бифштекс под печёным перцем с рисом | E54: 487 | F54: Рис г/150гр | G54: не найден белок
A55: 2553 | B55: Бифштекс с печёным перцем (столовая) | G55: не найдено
A56: 2562 | B56: Бифштекс с печёным перцем и картофелем | E56: 2247 | F56: Картофельное пюре г/200гр | G56: не найден белок
A57: 2532 | B57: Бифштекс с печёным перцем и пюре | E57: 2247 | F57: Картофельное пюре г/200гр | G57: не найден белок
A58: 2698 | B58: Бифштекс с печёным перцем и спагетти | E58: 2264 | F58: Спагетти г/150гр | G58: не найден белок
A59: 3441 | B59: Бифштекс с томленым луком и макаронами | E59: 2278 | F59: Макароны г/200гр | G59: не найден белок
A60: 3440 | B60: Бифштекс с томленым луком и пюре | E60: 2247 | F60: Картофельное пюре г/200гр | G60: не найден белок
A61: 89 | B61: Блин с ветчиной и сыром | G61: не найдено
A62: 88 | B62: Блин с красной рыбкой и творожным сыром | G62: не найдено
A63: 114 | B63: Блин с куриными сердечками и сметаной | G63: не найдено
A64: 101 | B64: Блин с мясом | G64: не найдено
A65: 596 | B65: Блинчик с бананом | G65: не найдено
A66: 1000 | B66: Блинчик с творогом и изюмом | G66: не найдено
A67: 2884 | B67: Блинчик с творогом и сметаной | G67: не найдено
A68: 1922 | B68: Блинчик фаршированный сочной курочкой | G68: не найдено
A69: 2388 | B69: Блинчики крем чиз варенка 180г | G69: не найдено
A70: 1916 | B70: Блинчики с абрикосовым конфитюром | G70: не найдено
A71: 1919 | B71: Блинчики с вареной сгущенкой из детства | G71: не найдено
A72: 2349 | B72: Блинчики с ветчиной и сыром | G72: не найдено
... A83: 1025 | B83: Блинчики с мясом | G83: не найдено
A84: 3446 | B84: Блинчики с мясом и рисом | E84: 487 | F84: Рис г/150гр | G84: не найден белок
A85: 1825 | B85: Блинчики с печенью | G85: не найдено
A86: 1556 | B86: Блинчики с творогом | G86: не найдено
A87: 2402 | B87: Блинчики с творогом 3 шт | G87: не найдено
A88: 758 | B88: Блинчики с творогом и вишней | G88: не найдено
A89: 3851 | B89: Блинчики с творогом и курагой | G89: не найдено
A90: 2377 | B90: Блинчики с фаршем и рисом 160г | E90: 487 | F90: Рис г/150гр | G90: не найден белок
A91: 2973 | B91: Блинчики с яблоком | G91: не найдено
A92: 1817 | B92: Блинчики со сгущенкой (покупные) | G92: не найдено
A93: 656 | B93: Блинчики фаршированные | G93: не найдено
A94: 2341 | B94: Блинчики Хачапури 180 гр | G94: не найдено
A95: 90 | B95: Блины | G95: не найдено
A96: 3546 | B96: Блины (4шт) с джемом | G96: не найдено
A97: 514 | B97: Блины (ингредиент) | G97: не найдено
A98: 2771 | B98: Блины с грибным жульеном | G98: не найдено
A99: 724 | B99: Блины с яблоками | G99: не найдено
A100: 1818 | B100: Блины с яблоками и корицей | G100: не найдено
A101: 2730 | B101: Блины со сгущенкой | G101: не найдено
A102: 1287 | B102: Блины со сметаной | G102: не найдено
A103: 2727 | B103: Блины со сметаной (Столовая) | G103: не найдено
A104: 1311 | B104: Борани из курицы с картофельным пюре | E104: 2247 | F104: Картофельное пюре г/200гр | G104: не найден белок
A105: 1212 | B105: Борани из курицы с овощами | E105: 2640 | F105: Овощное рагу г/200гр | G105: не найден белок
A106: 3782 | B106: Борщ с говядиной комбо | G106: не найдено
A107: 793 | B107: Борщ с курицей | G107: не найдено
A108: 2308 | B108: Борщ с курицей (столовая) | G108: не найдено
A109: 3819 | B109: Борщ с курицей комбо | G109: не найдено
A110: 2203 | B110: Борщ с мясом | G110: не найдено
...

Sheet Динамика 2 мес
A1: =IFERROR(__xludf.DUMMYFUNCTION("IMPORTRANGE(""https://docs.google.com/spreadsheets/d/1Yb5TdnkO_G1YtSRao6XpO7iTs35tl-2Ggkk8F2yHY3A/edit"",""_service_dashboard_vm!A1:s40"")"),"Период прошлый") -> Период прошлый | B1: =IFERROR(__xludf.DUMMYFUNCTION("""COMPUTED_VALUE"""),"01.07.2026 - 19.07.2026") -> 01.07.2026 - 19.07.2026 | O1: =IFERROR(__xludf.DUMMYFUNCTION("""COMPUTED_VALUE"""),"метрика") -> метрика | P1: =IFERROR(__xludf.DUMMYFUNCTION("""COMPUTED_VALUE"""),"прошлый") -> прошлый | Q1: =IFERROR(__xludf.DUMMYFUNCTION("""COMPUTED_VALUE"""),"текущий") -> текущий | R1: =IFERROR(__xludf.DUMMYFUNCTION("""COMPUTED_VALUE"""),"разница") -> разница | S1: =IFERROR(__xludf.DUMMYFUNCTION("""COMPUTED_VALUE"""),"разница %") -> разница %
A2: =IFERROR(__xludf.DUMMYFUNCTION("""COMPUTED_VALUE"""),"Период текущий") -> Период текущий | B2: =IFERROR(__xludf.DUMMYFUNCTION("""COMPUTED_VALUE"""),"01.08.2026 - 19.08.2026") -> 01.08.2026 - 19.08.2026 | O2: =IFERROR(__xludf.DUMMYFUNCTION("""COMPUTED_VALUE"""),"СР. Выручка") -> СР. Выручка | P2: =IFERROR(__xludf.DUMMYFUNCTION("""COMPUTED_VALUE"""),239437.90499223) -> 239437.9 | Q2: =IFERROR(__xludf.DUMMYFUNCTION("""COMPUTED_VALUE"""),248696.71209595964) -> 248696.71 | R2: =IFERROR(__xludf.DUMMYFUNCTION("""COMPUTED_VALUE"""),9258.807103729632) -> 9258.8071 | S2: =IFERROR(__xludf.DUMMYFUNCTION("""COMPUTED_VALUE"""),0.03866892797959492) -> 0.038668928
A3: =IFERROR(__xludf.DUMMYFUNCTION("""COMPUTED_VALUE"""),"Обновлено") -> Обновлено | B3: =IFERROR(__xludf.DUMMYFUNCTION("""COMPUTED_VALUE"""),46253.38116664352) -> 46253.381 | O3: =IFERROR(__xludf.DUMMYFUNCTION("""COMPUTED_VALUE"""),"СР. Кол-во чеков") -> СР. Кол-во чеков | P3: =IFERROR(__xludf.DUMMYFUNCTION("""COMPUTED_VALUE"""),1275.2971250971252) -> 1275.2971 | Q3: =IFERROR(__xludf.DUMMYFUNCTION("""COMPUTED_VALUE"""),1311.7416666666668) -> 1311.7417 | R3: =IFERROR(__xludf.DUMMYFUNCTION("""COMPUTED_VALUE"""),36.44454156954157) -> 36.444542 | S3: =IFERROR(__xludf.DUMMYFUNCTION("""COMPUTED_VALUE"""),0.028577294539706574) -> 0.028577295 | T3: =R3*Q4 -> 6760.9485 | U3: результат по количеству чеков
B4: =IFERROR(__xludf.DUMMYFUNCTION("""COMPUTED_VALUE"""),"СР. ВЫРУЧКА") -> СР. ВЫРУЧКА | D4: =IFERROR(__xludf.DUMMYFUNCTION("""COMPUTED_VALUE"""),-0.48823775531127006) -> -0.48823776 | E4: =IFERROR(__xludf.DUMMYFUNCTION("""COMPUTED_VALUE"""),"СР. КОЛ-ВО ЧЕКОВ") -> СР. КОЛ-ВО ЧЕКОВ | G4: =IFERROR(__xludf.DUMMYFUNCTION("""COMPUTED_VALUE"""),-0.9592566208111047) -> -0.95925662 | H4: =IFERROR(__xludf.DUMMYFUNCTION("""COMPUTED_VALUE"""),"СР. СРЕДНИЙ ЧЕК") -> СР. СРЕДНИЙ ЧЕК | J4: =IFERROR(__xludf.DUMMYFUNCTION("""COMPUTED_VALUE"""),0.44601209679013254) -> 0.4460121 | K4: =IFERROR(__xludf.DUMMYFUNCTION("""COMPUTED_VALUE"""),"СПИСАНИЯ") -> СПИСАНИЯ | M4: =IFERROR(__xludf.DUMMYFUNCTION("""COMPUTED_VALUE"""),4.721302653747017) -> 4.7213027 | O4: =IFERROR(__xludf.DUMMYFUNCTION("""COMPUTED_VALUE"""),"СР. Средний чек") -> СР. Средний чек | P4: =IFERROR(__xludf.DUMMYFUNCTION("""COMPUTED_VALUE"""),165.01639240410128) -> 165.01639 | Q4: =IFERROR(__xludf.DUMMYFUNCTION("""COMPUTED_VALUE"""),185.51333668847326) -> 185.51334 | R4: =IFERROR(__xludf.DUMMYFUNCTION("""COMPUTED_VALUE"""),20.496944284371978) -> 20.496944 | S4: =IFERROR(__xludf.DUMMYFUNCTION("""COMPUTED_VALUE"""),0.12421156459521866) -> 0.12421156 | T4: =Q3*R4 -> 26886.696 | U4: результат по среднему чеку
A5: =IFERROR(__xludf.DUMMYFUNCTION("""COMPUTED_VALUE"""),"Точка") -> Точка | B5: =IFERROR(__xludf.DUMMYFUNCTION("""COMPUTED_VALUE"""),"Прошлый") -> Прошлый | C5: =IFERROR(__xludf.DUMMYFUNCTION("""COMPUTED_VALUE"""),"Текущий") -> Текущий | D5: =IFERROR(__xludf.DUMMYFUNCTION("""COMPUTED_VALUE"""),"%") -> % | E5: =IFERROR(__xludf.DUMMYFUNCTION("""COMPUTED_VALUE"""),"Прошлый") -> Прошлый | F5: =IFERROR(__xludf.DUMMYFUNCTION("""COMPUTED_VALUE"""),"Текущий") -> Текущий | G5: =IFERROR(__xludf.DUMMYFUNCTION("""COMPUTED_VALUE"""),"%") -> % | H5: =IFERROR(__xludf.DUMMYFUNCTION("""COMPUTED_VALUE"""),"Прошлый") -> Прошлый | I5: =IFERROR(__xludf.DUMMYFUNCTION("""COMPUTED_VALUE"""),"Текущий") -> Текущий | J5: =IFERROR(__xludf.DUMMYFUNCTION("""COMPUTED_VALUE"""),"%") -> % | K5: =IFERROR(__xludf.DUMMYFUNCTION("""COMPUTED_VALUE"""),"Прошлый") -> Прошлый | L5: =IFERROR(__xludf.DUMMYFUNCTION("""COMPUTED_VALUE"""),"Текущий") -> Текущий | M5: =IFERROR(__xludf.DUMMYFUNCTION("""COMPUTED_VALUE"""),"%") -> % | N5: =IFERROR(__xludf.DUMMYFUNCTION("""COMPUTED_VALUE"""),"Активна") -> Активна | O5: =IFERROR(__xludf.DUMMYFUNCTION("""COMPUTED_VALUE"""),"Списания") -> Списания | P5: =IFERROR(__xludf.DUMMYFUNCTION("""COMPUTED_VALUE"""),208596.07) -> 208596.07 | Q5: =IFERROR(__xludf.DUMMYFUNCTION("""COMPUTED_VALUE"""),238274.44) -> 238274.44 | R5: =IFERROR(__xludf.DUMMYFUNCTION("""COMPUTED_VALUE"""),29678.369999999995) -> 29678.37 | S5: =IFERROR(__xludf.DUMMYFUNCTION("""COMPUTED_VALUE"""),0.14227674567406756) -> 0.14227675
A6: =IFERROR(__xludf.DUMMYFUNCTION("""COMPUTED_VALUE"""),"0") -> 0 | B6: =IFERROR(__xludf.DUMMYFUNCTION("""COMPUTED_VALUE"""),147.0) -> 147 | C6: =IFERROR(__xludf.DUMMYFUNCTION("""COMPUTED_VALUE"""),192.0) -> 192 | D6: =IFERROR(__xludf.DUMMYFUNCTION("""COMPUTED_VALUE"""),0.30612244897959184) -> 0.30612245 | E6: =IFERROR(__xludf.DUMMYFUNCTION("""COMPUTED_VALUE"""),1.0) -> 1 | F6: =IFERROR(__xludf.DUMMYFUNCTION("""COMPUTED_VALUE"""),1.0) -> 1 | G6: =IFERROR(__xludf.DUMMYFUNCTION("""COMPUTED_VALUE"""),0.0) -> 0 | H6: =IFERROR(__xludf.DUMMYFUNCTION("""COMPUTED_VALUE"""),147.0) -> 147 | I6: =IFERROR(__xludf.DUMMYFUNCTION("""COMPUTED_VALUE"""),192.0) -> 192 | J6: =IFERROR(__xludf.DUMMYFUNCTION("""COMPUTED_VALUE"""),0.30612244897959184) -> 0.30612245 | K6: =IFERROR(__xludf.DUMMYFUNCTION("""COMPUTED_VALUE"""),0.0) -> 0 | L6: =IFERROR(__xludf.DUMMYFUNCTION("""COMPUTED_VALUE"""),0.0) -> 0 | N6: =IFERROR(__xludf.DUMMYFUNCTION("""COMPUTED_VALUE"""),"нет") -> нет
A7: =IFERROR(__xludf.DUMMYFUNCTION("""COMPUTED_VALUE"""),"1") -> 1 | B7: =IFERROR(__xludf.DUMMYFUNCTION("""COMPUTED_VALUE"""),16876.603846153845) -> 16876.604 | C7: =IFERROR(__xludf.DUMMYFUNCTION("""COMPUTED_VALUE"""),16597.12916666667) -> 16597.129 | D7: =IFERROR(__xludf.DUMMYFUNCTION("""COMPUTED_VALUE"""),-0.016559888591025213) -> -0.016559889 | E7: =IFERROR(__xludf.DUMMYFUNCTION("""COMPUTED_VALUE"""),101.84615384615384) -> 101.84615 | F7: =IFERROR(__xludf.DUMMYFUNCTION("""COMPUTED_VALUE"""),99.0) -> 99 | G7: =IFERROR(__xludf.DUMMYFUNCTION("""COMPUTED_VALUE"""),-0.02794561933534737) -> -0.027945619 | H7: =IFERROR(__xludf.DUMMYFUNCTION("""COMPUTED_VALUE"""),166.2771121498758) -> 166.27711 | I7: =IFERROR(__xludf.DUMMYFUNCTION("""COMPUTED_VALUE"""),167.47542196011383) -> 167.47542 | J7: =IFERROR(__xludf.DUMMYFUNCTION("""COMPUTED_VALUE"""),0.007206703284321738) -> 0.0072067033 | K7: =IFERROR(__xludf.DUMMYFUNCTION("""COMPUTED_VALUE"""),39720.110000000015) -> 39720.11 | L7: =IFERROR(__xludf.DUMMYFUNCTION("""COMPUTED_VALUE"""),14923.240000000003) -> 14923.24 | M7: =IFERROR(__xludf.DUMMYFUNCTION("""COMPUTED_VALUE"""),-0.62429006364786) -> -0.62429006 | N7: =IFERROR(__xludf.DUMMYFUNCTION("""COMPUTED_VALUE"""),"да") -> да
A8: =IFERROR(__xludf.DUMMYFUNCTION("""COMPUTED_VALUE"""),"2") -> 2 | B8: =IFERROR(__xludf.DUMMYFUNCTION("""COMPUTED_VALUE"""),5142.2692307692305) -> 5142.2692 | C8: =IFERROR(__xludf.DUMMYFUNCTION("""COMPUTED_VALUE"""),4533.595833333334) -> 4533.5958 | D8: =IFERROR(__xludf.DUMMYFUNCTION("""COMPUTED_VALUE"""),-0.1183666918476078) -> -0.11836669 | E8: =IFERROR(__xludf.DUMMYFUNCTION("""COMPUTED_VALUE"""),25.307692307692307) -> 25.307692 | F8: =IFERROR(__xludf.DUMMYFUNCTION("""COMPUTED_VALUE"""),23.0) -> 23 | G8: =IFERROR(__xludf.DUMMYFUNCTION("""COMPUTED_VALUE"""),-0.09118541033434646) -> -0.09118541 | H8: =IFERROR(__xludf.DUMMYFUNCTION("""COMPUTED_VALUE"""),218.05265432030012) -> 218.05265 | I8: =IFERROR(__xludf.DUMMYFUNCTION("""COMPUTED_VALUE"""),198.84553974196209) -> 198.84554 | J8: =IFERROR(__xludf.DUMMYFUNCTION("""COMPUTED_VALUE"""),-0.08808475474976094) -> -0.088084755 | K8: =IFERROR(__xludf.DUMMYFUNCTION("""COMPUTED_VALUE"""),1385.8200000000002) -> 1385.82 | L8: =IFERROR(__xludf.DUMMYFUNCTION("""COMPUTED_VALUE"""),4491.51) -> 4491.51 | M8: =IFERROR(__xludf.DUMMYFUNCTION("""COMPUTED_VALUE"""),2.2410486210330345) -> 2.2410486 | N8: =IFERROR(__xludf.DUMMYFUNCTION("""COMPUTED_VALUE"""),"да") -> да
A9: =IFERROR(__xludf.DUMMYFUNCTION("""COMPUTED_VALUE"""),"3") -> 3 | B9: =IFERROR(__xludf.DUMMYFUNCTION("""COMPUTED_VALUE"""),0.0) -> 0 | C9: =IFERROR(__xludf.DUMMYFUNCTION("""COMPUTED_VALUE"""),7043.474999999999) -> 7043.475 | E9: =IFERROR(__xludf.DUMMYFUNCTION("""COMPUTED_VALUE"""),0.0) -> 0 | F9: =IFERROR(__xludf.DUMMYFUNCTION("""COMPUTED_VALUE"""),29.083333333333332) -> 29.083333 | H9: =IFERROR(__xludf.DUMMYFUNCTION("""COMPUTED_VALUE"""),0.0) -> 0 | I9: =IFERROR(__xludf.DUMMYFUNCTION("""COMPUTED_VALUE"""),243.5894689584179) -> 243.58947 | K9: =IFERROR(__xludf.DUMMYFUNCTION("""COMPUTED_VALUE"""),0.0) -> 0 | L9: =IFERROR(__xludf.DUMMYFUNCTION("""COMPUTED_VALUE"""),10464.830000000002) -> 10464.83 | N9: =IFERROR(__xludf.DUMMYFUNCTION("""COMPUTED_VALUE"""),"да") -> да
A10: =IFERROR(__xludf.DUMMYFUNCTION("""COMPUTED_VALUE"""),"4") -> 4 | B10: =IFERROR(__xludf.DUMMYFUNCTION("""COMPUTED_VALUE"""),6284.0) -> 6284 | C10: =IFERROR(__xludf.DUMMYFUNCTION("""COMPUTED_VALUE"""),5669.708333333333) -> 5669.7083 | D10: =IFERROR(__xludf.DUMMYFUNCTION("""COMPUTED_VALUE"""),-0.09775488011882033) -> -0.09775488 | E10: =IFERROR(__xludf.DUMMYFUNCTION("""COMPUTED_VALUE"""),20.3) -> 20.3 | F10: =IFERROR(__xludf.DUMMYFUNCTION("""COMPUTED_VALUE"""),20.833333333333332) -> 20.833333 | G10: =IFERROR(__xludf.DUMMYFUNCTION("""COMPUTED_VALUE"""),0.026272577996715833) -> 0.026272578 | H10: =IFERROR(__xludf.DUMMYFUNCTION("""COMPUTED_VALUE"""),312.32148700883516) -> 312.32149 | I10: =IFERROR(__xludf.DUMMYFUNCTION("""COMPUTED_VALUE"""),266.58490333199774) -> 266.5849 | J10: =IFERROR(__xludf.DUMMYFUNCTION("""COMPUTED_VALUE"""),-0.14644072079339068) -> -0.14644072 | K10: =IFERROR(__xludf.DUMMYFUNCTION("""COMPUTED_VALUE"""),36101.45999999999) -> 36101.46 | L10: =IFERROR(__xludf.DUMMYFUNCTION("""COMPUTED_VALUE"""),48620.31) -> 48620.31 | M10: =IFERROR(__xludf.DUMMYFUNCTION("""COMPUTED_VALUE"""),0.3467685240430722) -> 0.34676852 | N10: =IFERROR(__xludf.DUMMYFUNCTION("""COMPUTED_VALUE"""),"да") -> да
A11: =IFERROR(__xludf.DUMMYFUNCTION("""COMPUTED_VALUE"""),"5") -> 5 | B11: =IFERROR(__xludf.DUMMYFUNCTION("""COMPUTED_VALUE"""),16121.617692307693) -> 16121.618 | C11: =IFERROR(__xludf.DUMMYFUNCTION("""COMPUTED_VALUE"""),18237.170833333334) -> 18237.171 | D11: =IFERROR(__xludf.DUMMYFUNCTION("""COMPUTED_VALUE"""),0.13122461910476024) -> 0.13122462 | E11: =IFERROR(__xludf.DUMMYFUNCTION("""COMPUTED_VALUE"""),76.46153846153847) -> 76.461538 | F11: =IFERROR(__xludf.DUMMYFUNCTION("""COMPUTED_VALUE"""),86.66666666666667) -> 86.666667 | G11: =IFERROR(__xludf.DUMMYFUNCTION("""COMPUTED_VALUE"""),0.13346747149564048) -> 0.13346747 | H11: =IFERROR(__xludf.DUMMYFUNCTION("""COMPUTED_VALUE"""),211.26240215959908) -> 211.2624 | I11: =IFERROR(__xludf.DUMMYFUNCTION("""COMPUTED_VALUE"""),211.08324951303598) -> 211.08325 | J11: =IFERROR(__xludf.DUMMYFUNCTION("""COMPUTED_VALUE"""),-8.480100800319167E-4) -> -0.00084801008 | K11: =IFERROR(__xludf.DUMMYFUNCTION("""COMPUTED_VALUE"""),9070.5) -> 9070.5 | L11: =IFERROR(__xludf.DUMMYFUNCTION("""COMPUTED_VALUE"""),5315.47) -> 5315.47 | M11: =IFERROR(__xludf.DUMMYFUNCTION("""COMPUTED_VALUE"""),-0.4139826911416129) -> -0.41398269 | N11: =IFERROR(__xludf.DUMMYFUNCTION("""COMPUTED_VALUE"""),"да") -> да
A12: =IFERROR(__xludf.DUMMYFUNCTION("""COMPUTED_VALUE"""),"6") -> 6 | B12: =IFERROR(__xludf.DUMMYFUNCTION("""COMPUTED_VALUE"""),10940.215384615383) -> 10940.215 | C12: =IFERROR(__xludf.DUMMYFUNCTION("""COMPUTED_VALUE"""),13253.783333333335) -> 13253.783 | D12: =IFERROR(__xludf.DUMMYFUNCTION("""COMPUTED_VALUE"""),0.2114737112005485) -> 0.21147371 | E12: =IFERROR(__xludf.DUMMYFUNCTION("""COMPUTED_VALUE"""),58.69230769230769) -> 58.692308 | F12: =IFERROR(__xludf.DUMMYFUNCTION("""COMPUTED_VALUE"""),64.16666666666667) -> 64.166667 | G12: =IFERROR(__xludf.DUMMYFUNCTION("""COMPUTED_VALUE"""),0.09327217125382269) -> 0.093272171 | H12: =IFERROR(__xludf.DUMMYFUNCTION("""COMPUTED_VALUE"""),187.06136046075335) -> 187.06136 | I12: =IFERROR(__xludf.DUMMYFUNCTION("""COMPUTED_VALUE"""),208.52589486450992) -> 208.52589 | J12: =IFERROR(__xludf.DUMMYFUNCTION("""COMPUTED_VALUE"""),0.11474595475456284) -> 0.11474595 | K12: =IFERROR(__xludf.DUMMYFUNCTION("""COMPUTED_VALUE"""),6982.72) -> 6982.72 | L12: =IFERROR(__xludf.DUMMYFUNCTION("""COMPUTED_VALUE"""),12838.469999999998) -> 12838.47 | M12: =IFERROR(__xludf.DUMMYFUNCTION("""COMPUTED_VALUE"""),0.8386058727830984) -> 0.83860587 | N12: =IFERROR(__xludf.DUMMYFUNCTION("""COMPUTED_VALUE"""),"да") -> да
A13: =IFERROR(__xludf.DUMMYFUNCTION("""COMPUTED_VALUE"""),"7") -> 7 | B13: =IFERROR(__xludf.DUMMYFUNCTION("""COMPUTED_VALUE"""),7438.861538461539) -> 7438.8615 | C13: =IFERROR(__xludf.DUMMYFUNCTION("""COMPUTED_VALUE"""),6517.95) -> 6517.95 | D13: =IFERROR(__xludf.DUMMYFUNCTION("""COMPUTED_VALUE"""),-0.12379737594255535) -> -0.12379738 | E13: =IFERROR(__xludf.DUMMYFUNCTION("""COMPUTED_VALUE"""),39.69230769230769) -> 39.692308 | F13: =IFERROR(__xludf.DUMMYFUNCTION("""COMPUTED_VALUE"""),36.5) -> 36.5 | G13: =IFERROR(__xludf.DUMMYFUNCTION("""COMPUTED_VALUE"""),-0.08042635658914732) -> -0.080426357 | H13: =IFERROR(__xludf.DUMMYFUNCTION("""COMPUTED_VALUE"""),188.22640220257134) -> 188.2264 | I13: =IFERROR(__xludf.DUMMYFUNCTION("""COMPUTED_VALUE"""),178.50845954825323) -> 178.50846 | J13: =IFERROR(__xludf.DUMMYFUNCTION("""COMPUTED_VALUE"""),-0.051629009217631174) -> -0.051629009 | K13: =IFERROR(__xludf.DUMMYFUNCTION("""COMPUTED_VALUE"""),1867.94) -> 1867.94 | L13: =IFERROR(__xludf.DUMMYFUNCTION("""COMPUTED_VALUE"""),2241.21) -> 2241.21 | M13: =IFERROR(__xludf.DUMMYFUNCTION("""COMPUTED_VALUE"""),0.19982975898583466) -> 0.19982976 | N13: =IFERROR(__xludf.DUMMYFUNCTION("""COMPUTED_VALUE"""),"да") -> да
A14: =IFERROR(__xludf.DUMMYFUNCTION("""COMPUTED_VALUE"""),"8") -> 8 | B14: =IFERROR(__xludf.DUMMYFUNCTION("""COMPUTED_VALUE"""),7051.4) -> 7051.4 | C14: =IFERROR(__xludf.DUMMYFUNCTION("""COMPUTED_VALUE"""),7301.020833333333) -> 7301.0208 | D14: =IFERROR(__xludf.DUMMYFUNCTION("""COMPUTED_VALUE"""),0.0354001805787976) -> 0.035400181 | E14: =IFERROR(__xludf.DUMMYFUNCTION("""COMPUTED_VALUE"""),31.0) -> 31 | F14: =IFERROR(__xludf.DUMMYFUNCTION("""COMPUTED_VALUE"""),32.583333333333336) -> 32.583333 | G14: =IFERROR(__xludf.DUMMYFUNCTION("""COMPUTED_VALUE"""),0.05107526881720438) -> 0.051075269 | H14: =IFERROR(__xludf.DUMMYFUNCTION("""COMPUTED_VALUE"""),228.3518399967505) -> 228.35184 | I14: =IFERROR(__xludf.DUMMYFUNCTION("""COMPUTED_VALUE"""),224.74316044282656) -> 224.74316 | J14: =IFERROR(__xludf.DUMMYFUNCTION("""COMPUTED_VALUE"""),-0.015803155139784673) -> -0.015803155 | K14: =IFERROR(__xludf.DUMMYFUNCTION("""COMPUTED_VALUE"""),7761.619999999999) -> 7761.62 | L14: =IFERROR(__xludf.DUMMYFUNCTION("""COMPUTED_VALUE"""),1251.91) -> 1251.91 | M14: =IFERROR(__xludf.DUMMYFUNCTION("""COMPUTED_VALUE"""),-0.8387050641489792) -> -0.83870506 | N14: =IFERROR(__xludf.DUMMYFUNCTION("""COMPUTED_VALUE"""),"да") -> да
A15: =IFERROR(__xludf.DUMMYFUNCTION("""COMPUTED_VALUE"""),"9") -> 9 | B15: =IFERROR(__xludf.DUMMYFUNCTION("""COMPUTED_VALUE"""),11519.846153846154) -> 11519.846 | C15: =IFERROR(__xludf.DUMMYFUNCTION("""COMPUTED_VALUE"""),10049.729166666666) -> 10049.729 | D15: =IFERROR(__xludf.DUMMYFUNCTION("""COMPUTED_VALUE"""),-0.12761602607762754) -> -0.12761603 | E15: =IFERROR(__xludf.DUMMYFUNCTION("""COMPUTED_VALUE"""),54.07692307692308) -> 54.076923 | F15: =IFERROR(__xludf.DUMMYFUNCTION("""COMPUTED_VALUE"""),47.416666666666664) -> 47.416667 | G15: =IFERROR(__xludf.DUMMYFUNCTION("""COMPUTED_VALUE"""),-0.12316263632053115) -> -0.12316264 | H15: =IFERROR(__xludf.DUMMYFUNCTION("""COMPUTED_VALUE"""),214.04988906470783) -> 214.04989 | I15: =IFERROR(__xludf.DUMMYFUNCTION("""COMPUTED_VALUE"""),212.52589552027618) -> 212.5259 | J15: =IFERROR(__xludf.DUMMYFUNCTION("""COMPUTED_VALUE"""),-0.007119805345803941) -> -0.0071198053 | K15: =IFERROR(__xludf.DUMMYFUNCTION("""COMPUTED_VALUE"""),3226.8399999999997) -> 3226.84 | L15: =IFERROR(__xludf.DUMMYFUNCTION("""COMPUTED_VALUE"""),1296.0800000000002) -> 1296.08 | M15: =IFERROR(__xludf.DUMMYFUNCTION("""COMPUTED_VALUE"""),-0.5983438906174461) -> -0.59834389 | N15: =IFERROR(__xludf.DUMMYFUNCTION("""COMPUTED_VALUE"""),"да") -> да
A16: =IFERROR(__xludf.DUMMYFUNCTION("""COMPUTED_VALUE"""),"10") -> 10 | B16: =IFERROR(__xludf.DUMMYFUNCTION("""COMPUTED_VALUE"""),10807.815384615384) -> 10807.815 | C16: =IFERROR(__xludf.DUMMYFUNCTION("""COMPUTED_VALUE"""),7718.983333333334) -> 7718.9833 | D16: =IFERROR(__xludf.DUMMYFUNCTION("""COMPUTED_VALUE"""),-0.28579615226208566) -> -0.28579615 | E16: =IFERROR(__xludf.DUMMYFUNCTION("""COMPUTED_VALUE"""),64.53846153846153) -> 64.538462 | F16: =IFERROR(__xludf.DUMMYFUNCTION("""COMPUTED_VALUE"""),49.166666666666664) -> 49.166667 | G16: =IFERROR(__xludf.DUMMYFUNCTION("""COMPUTED_VALUE"""),-0.23818037346046878) -> -0.23818037 | H16: =IFERROR(__xludf.DUMMYFUNCTION("""COMPUTED_VALUE"""),166.61253626587208) -> 166.61254 | I16: =IFERROR(__xludf.DUMMYFUNCTION("""COMPUTED_VALUE"""),155.8213079395588) -> 155.82131 | J16: =IFERROR(__xludf.DUMMYFUNCTION("""COMPUTED_VALUE"""),-0.06476840559640219) -> -0.064768406 | K16: =IFERROR(__xludf.DUMMYFUNCTION("""COMPUTED_VALUE"""),14389.109999999999) -> 14389.11 | L16: =IFERROR(__xludf.DUMMYFUNCTION("""COMPUTED_VALUE"""),20016.840000000004) -> 20016.84 | M16: =IFERROR(__xludf.DUMMYFUNCTION("""COMPUTED_VALUE"""),0.39111036054349474) -> 0.39111036 | N16: =IFERROR(__xludf.DUMMYFUNCTION("""COMPUTED_VALUE"""),"да") -> да
A17: =IFERROR(__xludf.DUMMYFUNCTION("""COMPUTED_VALUE"""),"11") -> 11 | B17: =IFERROR(__xludf.DUMMYFUNCTION("""COMPUTED_VALUE"""),0.0) -> 0 | C17: =IFERROR(__xludf.DUMMYFUNCTION("""COMPUTED_VALUE"""),0.0) -> 0 | E17: =IFERROR(__xludf.DUMMYFUNCTION("""COMPUTED_VALUE"""),0.0) -> 0 | F17: =IFERROR(__xludf.DUMMYFUNCTION("""COMPUTED_VALUE"""),0.0) -> 0 | H17: =IFERROR(__xludf.DUMMYFUNCTION("""COMPUTED_VALUE"""),0.0) -> 0 | I17: =IFERROR(__xludf.DUMMYFUNCTION("""COMPUTED_VALUE"""),0.0) -> 0 | K17: =IFERROR(__xludf.DUMMYFUNCTION("""COMPUTED_VALUE"""),0.0) -> 0 | L17: =IFERROR(__xludf.DUMMYFUNCTION("""COMPUTED_VALUE"""),0.0) -> 0 | N17: =IFERROR(__xludf.DUMMYFUNCTION("""COMPUTED_VALUE"""),"нет") -> нет
A18: =IFERROR(__xludf.DUMMYFUNCTION("""COMPUTED_VALUE"""),"12") -> 12 | B18: =IFERROR(__xludf.DUMMYFUNCTION("""COMPUTED_VALUE"""),5888.050000000001) -> 5888.05 | C18: =IFERROR(__xludf.DUMMYFUNCTION("""COMPUTED_VALUE"""),5944.591666666667) -> 5944.5917 | D18: =IFERROR(__xludf.DUMMYFUNCTION("""COMPUTED_VALUE"""),0.009602783037960963) -> 0.009602783 | E18: =IFERROR(__xludf.DUMMYFUNCTION("""COMPUTED_VALUE"""),36.07692307692308) -> 36.076923 | F18: =IFERROR(__xludf.DUMMYFUNCTION("""COMPUTED_VALUE"""),36.833333333333336) -> 36.833333 | G18: =IFERROR(__xludf.DUMMYFUNCTION("""COMPUTED_VALUE"""),0.02096659559346124) -> 0.020966596 | H18: =IFERROR(__xludf.DUMMYFUNCTION("""COMPUTED_VALUE"""),162.5629272440798) -> 162.56293 | I18: =IFERROR(__xludf.DUMMYFUNCTION("""COMPUTED_VALUE"""),163.8922918942803) -> 163.89229 | J18: =IFERROR(__xludf.DUMMYFUNCTION("""COMPUTED_VALUE"""),0.008177538832113583) -> 0.0081775388 | K18: =IFERROR(__xludf.DUMMYFUNCTION("""COMPUTED_VALUE"""),2011.3500000000001) -> 2011.35 | L18: =IFERROR(__xludf.DUMMYFUNCTION("""COMPUTED_VALUE"""),1827.1799999999998) -> 1827.18 | M18: =IFERROR(__xludf.DUMMYFUNCTION("""COMPUTED_VALUE"""),-0.09156536654485807) -> -0.091565367 | N18: =IFERROR(__xludf.DUMMYFUNCTION("""COMPUTED_VALUE"""),"да") -> да
A19: =IFERROR(__xludf.DUMMYFUNCTION("""COMPUTED_VALUE"""),"13") -> 13 | B19: =IFERROR(__xludf.DUMMYFUNCTION("""COMPUTED_VALUE"""),6831.642307692307) -> 6831.6423 | C19: =IFERROR(__xludf.DUMMYFUNCTION("""COMPUTED_VALUE"""),5611.870833333334) -> 5611.8708 | D19: =IFERROR(__xludf.DUMMYFUNCTION("""COMPUTED_VALUE"""),-0.17854732719034955) -> -0.17854733 | E19: =IFERROR(__xludf.DUMMYFUNCTION("""COMPUTED_VALUE"""),45.46153846153846) -> 45.461538 | F19: =IFERROR(__xludf.DUMMYFUNCTION("""COMPUTED_VALUE"""),35.666666666666664) -> 35.666667 | G19: =IFERROR(__xludf.DUMMYFUNCTION("""COMPUTED_VALUE"""),-0.215454032712916) -> -0.21545403 | H19: =IFERROR(__xludf.DUMMYFUNCTION("""COMPUTED_VALUE"""),149.4781239019609) -> 149.47812 | I19: =IFERROR(__xludf.DUMMYFUNCTION("""COMPUTED_VALUE"""),157.44163266973518) -> 157.44163 | J19: =IFERROR(__xludf.DUMMYFUNCTION("""COMPUTED_VALUE"""),0.053275412882471986) -> 0.053275413 | K19: =IFERROR(__xludf.DUMMYFUNCTION("""COMPUTED_VALUE"""),2094.07) -> 2094.07 | L19: =IFERROR(__xludf.DUMMYFUNCTION("""COMPUTED_VALUE"""),2986.06) -> 2986.06 | M19: =IFERROR(__xludf.DUMMYFUNCTION("""COMPUTED_VALUE"""),0.42595997268477165) -> 0.42595997 | N19: =IFERROR(__xludf.DUMMYFUNCTION("""COMPUTED_VALUE"""),"да") -> да
A20: =IFERROR(__xludf.DUMMYFUNCTION("""COMPUTED_VALUE"""),"14") -> 14 | B20: =IFERROR(__xludf.DUMMYFUNCTION("""COMPUTED_VALUE"""),11159.126153846153) -> 11159.126 | C20: =IFERROR(__xludf.DUMMYFUNCTION("""COMPUTED_VALUE"""),10919.699999999999) -> 10919.7 | D20: =IFERROR(__xludf.DUMMYFUNCTION("""COMPUTED_VALUE"""),-0.02145563644906304) -> -0.021455636 | E20: =IFERROR(__xludf.DUMMYFUNCTION("""COMPUTED_VALUE"""),66.92307692307692) -> 66.923077 | F20: =IFERROR(__xludf.DUMMYFUNCTION("""COMPUTED_VALUE"""),60.083333333333336) -> 60.083333 | G20: =IFERROR(__xludf.DUMMYFUNCTION("""COMPUTED_VALUE"""),-0.10220306513409953) -> -0.10220307 | H20: =IFERROR(__xludf.DUMMYFUNCTION("""COMPUTED_VALUE"""),166.29457998483397) -> 166.29458 | I20: =IFERROR(__xludf.DUMMYFUNCTION("""COMPUTED_VALUE"""),182.81174232199615) -> 182.81174 | J20: =IFERROR(__xludf.DUMMYFUNCTION("""COMPUTED_VALUE"""),0.0993247184524507) -> 0.099324718 | K20: =IFERROR(__xludf.DUMMYFUNCTION("""COMPUTED_VALUE"""),8889.91) -> 8889.91 | L20: =IFERROR(__xludf.DUMMYFUNCTION("""COMPUTED_VALUE"""),8578.08) -> 8578.08 | M20: =IFERROR(__xludf.DUMMYFUNCTION("""COMPUTED_VALUE"""),-0.03507684554736774) -> -0.035076846 | N20: =IFERROR(__xludf.DUMMYFUNCTION("""COMPUTED_VALUE"""),"да") -> да
A21: =IFERROR(__xludf.DUMMYFUNCTION("""COMPUTED_VALUE"""),"15") -> 15 | B21: =IFERROR(__xludf.DUMMYFUNCTION("""COMPUTED_VALUE"""),8412.27692307692) -> 8412.2769 | C21: =IFERROR(__xludf.DUMMYFUNCTION("""COMPUTED_VALUE"""),8074.3916666666655) -> 8074.3917 | D21: =IFERROR(__xludf.DUMMYFUNCTION("""COMPUTED_VALUE"""),-0.04016573152547486) -> -0.040165732 | E21: =IFERROR(__xludf.DUMMYFUNCTION("""COMPUTED_VALUE"""),45.53846153846154) -> 45.538462 | F21: =IFERROR(__xludf.DUMMYFUNCTION("""COMPUTED_VALUE"""),46.583333333333336) -> 46.583333 | G21: =IFERROR(__xludf.DUMMYFUNCTION("""COMPUTED_VALUE"""),0.022944819819819835) -> 0.02294482 | H21: =IFERROR(__xludf.DUMMYFUNCTION("""COMPUTED_VALUE"""),185.18263293044717) -> 185.18263 | I21: =IFERROR(__xludf.DUMMYFUNCTION("""COMPUTED_VALUE"""),173.4674174575952) -> 173.46742 | J21: =IFERROR(__xludf.DUMMYFUNCTION("""COMPUTED_VALUE"""),-0.0632630354556634) -> -0.063263035 | K21: =IFERROR(__xludf.DUMMYFUNCTION("""COMPUTED_VALUE"""),4048.69) -> 4048.69 | L21: =IFERROR(__xludf.DUMMYFUNCTION("""COMPUTED_VALUE"""),6551.860000000001) -> 6551.86 | M21: =IFERROR(__xludf.DUMMYFUNCTION("""COMPUTED_VALUE"""),0.6182666492124614) -> 0.61826665 | N21: =IFERROR(__xludf.DUMMYFUNCTION("""COMPUTED_VALUE"""),"да") -> да
A22: =IFERROR(__xludf.DUMMYFUNCTION("""COMPUTED_VALUE"""),"16") -> 16 | B22: =IFERROR(__xludf.DUMMYFUNCTION("""COMPUTED_VALUE"""),8094.173076923077) -> 8094.1731 | C22: =IFERROR(__xludf.DUMMYFUNCTION("""COMPUTED_VALUE"""),8079.212500000001) -> 8079.2125 | D22: =IFERROR(__xludf.DUMMYFUNCTION("""COMPUTED_VALUE"""),-0.0018483144332223382) -> -0.0018483144 | E22: =IFERROR(__xludf.DUMMYFUNCTION("""COMPUTED_VALUE"""),39.30769230769231) -> 39.307692 | F22: =IFERROR(__xludf.DUMMYFUNCTION("""COMPUTED_VALUE"""),38.75) -> 38.75 | G22: =IFERROR(__xludf.DUMMYFUNCTION("""COMPUTED_VALUE"""),-0.014187866927592928) -> -0.014187867 | H22: =IFERROR(__xludf.DUMMYFUNCTION("""COMPUTED_VALUE"""),210.25151252798676) -> 210.25151 | I22: =IFERROR(__xludf.DUMMYFUNCTION("""COMPUTED_VALUE"""),209.86746593542907) -> 209.86747 | J22: =IFERROR(__xludf.DUMMYFUNCTION("""COMPUTED_VALUE"""),-0.0018266056112513068) -> -0.0018266056 | K22: =IFERROR(__xludf.DUMMYFUNCTION("""COMPUTED_VALUE"""),3714.35) -> 3714.35 | L22: =IFERROR(__xludf.DUMMYFUNCTION("""COMPUTED_VALUE"""),2413.1400000000003) -> 2413.14 | M22: =IFERROR(__xludf.DUMMYFUNCTION("""COMPUTED_VALUE"""),-0.35031970600508827) -> -0.35031971 | N22: =IFERROR(__xludf.DUMMYFUNCTION("""COMPUTED_VALUE"""),"да") -> да
A23: =IFERROR(__xludf.DUMMYFUNCTION("""COMPUTED_VALUE"""),"17") -> 17 | B23: =IFERROR(__xludf.DUMMYFUNCTION("""COMPUTED_VALUE"""),6459.430769230769) -> 6459.4308 | C23: =IFERROR(__xludf.DUMMYFUNCTION("""COMPUTED_VALUE"""),5901.233333333334) -> 5901.2333 | D23: =IFERROR(__xludf.DUMMYFUNCTION("""COMPUTED_VALUE"""),-0.08641588645185054) -> -0.086415886 | E23: =IFERROR(__xludf.DUMMYFUNCTION("""COMPUTED_VALUE"""),35.30769230769231) -> 35.307692 | F23: =IFERROR(__xludf.DUMMYFUNCTION("""COMPUTED_VALUE"""),31.333333333333332) -> 31.333333 | G23: =IFERROR(__xludf.DUMMYFUNCTION("""COMPUTED_VALUE"""),-0.11256354393609296) -> -0.11256354 | H23: =IFERROR(__xludf.DUMMYFUNCTION("""COMPUTED_VALUE"""),184.74137050685692) -> 184.74137 | I23: =IFERROR(__xludf.DUMMYFUNCTION("""COMPUTED_VALUE"""),189.62472785907937) -> 189.62473 | J23: =IFERROR(__xludf.DUMMYFUNCTION("""COMPUTED_VALUE"""),0.026433480161073043) -> 0.02643348 | K23: =IFERROR(__xludf.DUMMYFUNCTION("""COMPUTED_VALUE"""),7746.450000000001) -> 7746.45 | L23: =IFERROR(__xludf.DUMMYFUNCTION("""COMPUTED_VALUE"""),5838.180000000001) -> 5838.18 | M23: =IFERROR(__xludf.DUMMYFUNCTION("""COMPUTED_VALUE"""),-0.246341227271847) -> -0.24634123 | N23: =IFERROR(__xludf.DUMMYFUNCTION("""COMPUTED_VALUE"""),"да") -> да
A24: =IFERROR(__xludf.DUMMYFUNCTION("""COMPUTED_VALUE"""),"18") -> 18 | B24: =IFERROR(__xludf.DUMMYFUNCTION("""COMPUTED_VALUE"""),0.0) -> 0 | C24: =IFERROR(__xludf.DUMMYFUNCTION("""COMPUTED_VALUE"""),5101.725) -> 5101.725 | E24: =IFERROR(__xludf.DUMMYFUNCTION("""COMPUTED_VALUE"""),0.0) -> 0 | F24: =IFERROR(__xludf.DUMMYFUNCTION("""COMPUTED_VALUE"""),32.5) -> 32.5 | H24: =IFERROR(__xludf.DUMMYFUNCTION("""COMPUTED_VALUE"""),0.0) -> 0 | I24: =IFERROR(__xludf.DUMMYFUNCTION("""COMPUTED_VALUE"""),175.48208333333332) -> 175.48208 | K24: =IFERROR(__xludf.DUMMYFUNCTION("""COMPUTED_VALUE"""),0.0) -> 0 | L24: =IFERROR(__xludf.DUMMYFUNCTION("""COMPUTED_VALUE"""),588.5899999999999) -> 588.59 | N24: =IFERROR(__xludf.DUMMYFUNCTION("""COMPUTED_VALUE"""),"да") -> да
A25: =IFERROR(__xludf.DUMMYFUNCTION("""COMPUTED_VALUE"""),"19") -> 19 | B25: =IFERROR(__xludf.DUMMYFUNCTION("""COMPUTED_VALUE"""),6901.323076923077) -> 6901.3231 | C25: =IFERROR(__xludf.DUMMYFUNCTION("""COMPUTED_VALUE"""),6915.916666666667) -> 6915.9167 | D25: =IFERROR(__xludf.DUMMYFUNCTION("""COMPUTED_VALUE"""),0.0021146075297342384) -> 0.0021146075 | E25: =IFERROR(__xludf.DUMMYFUNCTION("""COMPUTED_VALUE"""),40.15384615384615) -> 40.153846 | F25: =IFERROR(__xludf.DUMMYFUNCTION("""COMPUTED_VALUE"""),40.333333333333336) -> 40.333333 | G25: =IFERROR(__xludf.DUMMYFUNCTION("""COMPUTED_VALUE"""),0.004469987228607991) -> 0.0044699872 | H25: =IFERROR(__xludf.DUMMYFUNCTION("""COMPUTED_VALUE"""),172.68991523573933) -> 172.68992 | I25: =IFERROR(__xludf.DUMMYFUNCTION("""COMPUTED_VALUE"""),173.28967447120064) -> 173.28967 | J25: =IFERROR(__xludf.DUMMYFUNCTION("""COMPUTED_VALUE"""),0.0034730414607163) -> 0.0034730415 | K25: =IFERROR(__xludf.DUMMYFUNCTION("""COMPUTED_VALUE"""),4755.34) -> 4755.34 | L25: =IFERROR(__xludf.DUMMYFUNCTION("""COMPUTED_VALUE"""),4045.04) -> 4045.04 | M25: =IFERROR(__xludf.DUMMYFUNCTION("""COMPUTED_VALUE"""),-0.14936891999310253) -> -0.14936892 | N25: =IFERROR(__xludf.DUMMYFUNCTION("""COMPUTED_VALUE"""),"да") -> да
A26: =IFERROR(__xludf.DUMMYFUNCTION("""COMPUTED_VALUE"""),"20") -> 20 | B26: =IFERROR(__xludf.DUMMYFUNCTION("""COMPUTED_VALUE"""),17171.56923076923) -> 17171.569 | C26: =IFERROR(__xludf.DUMMYFUNCTION("""COMPUTED_VALUE"""),13837.749999999998) -> 13837.75 | D26: =IFERROR(__xludf.DUMMYFUNCTION("""COMPUTED_VALUE"""),-0.1941476160952989) -> -0.19414762 | E26: =IFERROR(__xludf.DUMMYFUNCTION("""COMPUTED_VALUE"""),79.92307692307692) -> 79.923077 | F26: =IFERROR(__xludf.DUMMYFUNCTION("""COMPUTED_VALUE"""),61.25) -> 61.25 | G26: =IFERROR(__xludf.DUMMYFUNCTION("""COMPUTED_VALUE"""),-0.23363811357074107) -> -0.23363811 | H26: =IFERROR(__xludf.DUMMYFUNCTION("""COMPUTED_VALUE"""),214.76928579361066) -> 214.76929 | I26: =IFERROR(__xludf.DUMMYFUNCTION("""COMPUTED_VALUE"""),225.55725072346658) -> 225.55725 | J26: =IFERROR(__xludf.DUMMYFUNCTION("""COMPUTED_VALUE"""),0.05023048286440247) -> 0.050230483 | K26: =IFERROR(__xludf.DUMMYFUNCTION("""COMPUTED_VALUE"""),8994.869999999999) -> 8994.87 | L26: =IFERROR(__xludf.DUMMYFUNCTION("""COMPUTED_VALUE"""),23536.72) -> 23536.72 | M26: =IFERROR(__xludf.DUMMYFUNCTION("""COMPUTED_VALUE"""),1.6166826202046283) -> 1.6166826 | N26: =IFERROR(__xludf.DUMMYFUNCTION("""COMPUTED_VALUE"""),"да") -> да
A27: =IFERROR(__xludf.DUMMYFUNCTION("""COMPUTED_VALUE"""),"21") -> 21 | B27: =IFERROR(__xludf.DUMMYFUNCTION("""COMPUTED_VALUE"""),8136.075) -> 8136.075 | C27: =IFERROR(__xludf.DUMMYFUNCTION("""COMPUTED_VALUE"""),8647.765) -> 8647.765 | D27: =IFERROR(__xludf.DUMMYFUNCTION("""COMPUTED_VALUE"""),0.06289150481036614) -> 0.062891505 | E27: =IFERROR(__xludf.DUMMYFUNCTION("""COMPUTED_VALUE"""),41.333333333333336) -> 41.333333 | F27: =IFERROR(__xludf.DUMMYFUNCTION("""COMPUTED_VALUE"""),40.166666666666664) -> 40.166667 | G27: =IFERROR(__xludf.DUMMYFUNCTION("""COMPUTED_VALUE"""),-0.028225806451613017) -> -0.028225806 | H27: =IFERROR(__xludf.DUMMYFUNCTION("""COMPUTED_VALUE"""),197.81932787922074) -> 197.81933 | I27: =IFERROR(__xludf.DUMMYFUNCTION("""COMPUTED_VALUE"""),215.24244975440953) -> 215.24245 | J27: =IFERROR(__xludf.DUMMYFUNCTION("""COMPUTED_VALUE"""),0.08807593303434204) -> 0.088075933 | K27: =IFERROR(__xludf.DUMMYFUNCTION("""COMPUTED_VALUE"""),2561.97) -> 2561.97 | L27: =IFERROR(__xludf.DUMMYFUNCTION("""COMPUTED_VALUE"""),3870.22) -> 3870.22 | M27: =IFERROR(__xludf.DUMMYFUNCTION("""COMPUTED_VALUE"""),0.5106422011186704) -> 0.5106422 | N27: =IFERROR(__xludf.DUMMYFUNCTION("""COMPUTED_VALUE"""),"да") -> да
A28: =IFERROR(__xludf.DUMMYFUNCTION("""COMPUTED_VALUE"""),"22") -> 22 | B28: =IFERROR(__xludf.DUMMYFUNCTION("""COMPUTED_VALUE"""),5936.8125) -> 5936.8125 | C28: =IFERROR(__xludf.DUMMYFUNCTION("""COMPUTED_VALUE"""),6232.418181818182) -> 6232.4182 | D28: =IFERROR(__xludf.DUMMYFUNCTION("""COMPUTED_VALUE"""),0.04979198548348669) -> 0.049791985 | E28: =IFERROR(__xludf.DUMMYFUNCTION("""COMPUTED_VALUE"""),38.916666666666664) -> 38.916667 | F28: =IFERROR(__xludf.DUMMYFUNCTION("""COMPUTED_VALUE"""),40.45454545454545) -> 40.454545 | G28: =IFERROR(__xludf.DUMMYFUNCTION("""COMPUTED_VALUE"""),0.03951722795405882) -> 0.039517228 | H28: =IFERROR(__xludf.DUMMYFUNCTION("""COMPUTED_VALUE"""),152.86269053016602) -> 152.86269 | I28: =IFERROR(__xludf.DUMMYFUNCTION("""COMPUTED_VALUE"""),151.99394332745575) -> 151.99394 | J28: =IFERROR(__xludf.DUMMYFUNCTION("""COMPUTED_VALUE"""),-0.005683186653965298) -> -0.0056831867 | K28: =IFERROR(__xludf.DUMMYFUNCTION("""COMPUTED_VALUE"""),6747.249999999999) -> 6747.25 | L28: =IFERROR(__xludf.DUMMYFUNCTION("""COMPUTED_VALUE"""),8539.78) -> 8539.78 | M28: =IFERROR(__xludf.DUMMYFUNCTION("""COMPUTED_VALUE"""),0.26566823520693644) -> 0.26566824 | N28: =IFERROR(__xludf.DUMMYFUNCTION("""COMPUTED_VALUE"""),"да") -> да
A29: =IFERROR(__xludf.DUMMYFUNCTION("""COMPUTED_VALUE"""),"23") -> 23 | B29: =IFERROR(__xludf.DUMMYFUNCTION("""COMPUTED_VALUE"""),9033.562500000002) -> 9033.5625 | C29: =IFERROR(__xludf.DUMMYFUNCTION("""COMPUTED_VALUE"""),9980.863636363638) -> 9980.8636 | D29: =IFERROR(__xludf.DUMMYFUNCTION("""COMPUTED_VALUE"""),0.10486462415726197) -> 0.10486462 | E29: =IFERROR(__xludf.DUMMYFUNCTION("""COMPUTED_VALUE"""),46.75) -> 46.75 | F29: =IFERROR(__xludf.DUMMYFUNCTION("""COMPUTED_VALUE"""),48.54545454545455) -> 48.545455 | G29: =IFERROR(__xludf.DUMMYFUNCTION("""COMPUTED_VALUE"""),0.03840544482255715) -> 0.038405445 | H29: =IFERROR(__xludf.DUMMYFUNCTION("""COMPUTED_VALUE"""),194.3823501075941) -> 194.38235 | I29: =IFERROR(__xludf.DUMMYFUNCTION("""COMPUTED_VALUE"""),205.1582955470051) -> 205.1583 | J29: =IFERROR(__xludf.DUMMYFUNCTION("""COMPUTED_VALUE"""),0.05543685130592528) -> 0.055436851 | K29: =IFERROR(__xludf.DUMMYFUNCTION("""COMPUTED_VALUE"""),5786.959999999999) -> 5786.96 | L29: =IFERROR(__xludf.DUMMYFUNCTION("""COMPUTED_VALUE"""),7071.31) -> 7071.31 | M29: =IFERROR(__xludf.DUMMYFUNCTION("""COMPUTED_VALUE"""),0.22193863444710202) -> 0.22193863 | N29: =IFERROR(__xludf.DUMMYFUNCTION("""COMPUTED_VALUE"""),"да") -> да
A30: =IFERROR(__xludf.DUMMYFUNCTION("""COMPUTED_VALUE"""),"24") -> 24 | B30: =IFERROR(__xludf.DUMMYFUNCTION("""COMPUTED_VALUE"""),6660.015384615384) -> 6660.0154 | C30: =IFERROR(__xludf.DUMMYFUNCTION("""COMPUTED_VALUE"""),7010.24) -> 7010.24 | D30: =IFERROR(__xludf.DUMMYFUNCTION("""COMPUTED_VALUE"""),0.052586157112134185) -> 0.052586157 | E30: =IFERROR(__xludf.DUMMYFUNCTION("""COMPUTED_VALUE"""),40.76923076923077) -> 40.769231 | F30: =IFERROR(__xludf.DUMMYFUNCTION("""COMPUTED_VALUE"""),38.7) -> 38.7 | G30: =IFERROR(__xludf.DUMMYFUNCTION("""COMPUTED_VALUE"""),-0.050754716981131945) -> -0.050754717 | H30: =IFERROR(__xludf.DUMMYFUNCTION("""COMPUTED_VALUE"""),160.55116089397129) -> 160.55116 | I30: =IFERROR(__xludf.DUMMYFUNCTION("""COMPUTED_VALUE"""),182.3981657846161) -> 182.39817 | J30: =IFERROR(__xludf.DUMMYFUNCTION("""COMPUTED_VALUE"""),0.1360750353282882) -> 0.13607504 | K30: =IFERROR(__xludf.DUMMYFUNCTION("""COMPUTED_VALUE"""),11487.050000000001) -> 11487.05 | L30: =IFERROR(__xludf.DUMMYFUNCTION("""COMPUTED_VALUE"""),5861.07) -> 5861.07 | M30: =IFERROR(__xludf.DUMMYFUNCTION("""COMPUTED_VALUE"""),-0.48976717259870906) -> -0.48976717 | N30: =IFERROR(__xludf.DUMMYFUNCTION("""COMPUTED_VALUE"""),"да") -> да
A31: =IFERROR(__xludf.DUMMYFUNCTION("""COMPUTED_VALUE"""),"25") -> 25 | B31: =IFERROR(__xludf.DUMMYFUNCTION("""COMPUTED_VALUE"""),0.0) -> 0 | C31: =IFERROR(__xludf.DUMMYFUNCTION("""COMPUTED_VALUE"""),6070.79) -> 6070.79 | E31: =IFERROR(__xludf.DUMMYFUNCTION("""COMPUTED_VALUE"""),0.0) -> 0 | F31: =IFERROR(__xludf.DUMMYFUNCTION("""COMPUTED_VALUE"""),37.7) -> 37.7 | H31: =IFERROR(__xludf.DUMMYFUNCTION("""COMPUTED_VALUE"""),0.0) -> 0 | I31: =IFERROR(__xludf.DUMMYFUNCTION("""COMPUTED_VALUE"""),169.20135452920513) -> 169.20135 | K31: =IFERROR(__xludf.DUMMYFUNCTION("""COMPUTED_VALUE"""),0.0) -> 0 | L31: =IFERROR(__xludf.DUMMYFUNCTION("""COMPUTED_VALUE"""),7416.21) -> 7416.21 | N31: =IFERROR(__xludf.DUMMYFUNCTION("""COMPUTED_VALUE"""),"нет") -> нет
A32: =IFERROR(__xludf.DUMMYFUNCTION("""COMPUTED_VALUE"""),"26") -> 26 | B32: =IFERROR(__xludf.DUMMYFUNCTION("""COMPUTED_VALUE"""),3888.272727272728) -> 3888.2727 | C32: =IFERROR(__xludf.DUMMYFUNCTION("""COMPUTED_VALUE"""),4175.4400000000005) -> 4175.44 | D32: =IFERROR(__xludf.DUMMYFUNCTION("""COMPUTED_VALUE"""),0.07385471464309924) -> 0.073854715 | E32: =IFERROR(__xludf.DUMMYFUNCTION("""COMPUTED_VALUE"""),22.90909090909091) -> 22.909091 | F32: =IFERROR(__xludf.DUMMYFUNCTION("""COMPUTED_VALUE"""),24.7) -> 24.7 | G32: =IFERROR(__xludf.DUMMYFUNCTION("""COMPUTED_VALUE"""),0.07817460317460309) -> 0.078174603 | H32: =IFERROR(__xludf.DUMMYFUNCTION("""COMPUTED_VALUE"""),170.29069223989475) -> 170.29069 | I32: =IFERROR(__xludf.DUMMYFUNCTION("""COMPUTED_VALUE"""),169.94637769093652) -> 169.94638 | J32: =IFERROR(__xludf.DUMMYFUNCTION("""COMPUTED_VALUE"""),-0.0020219223049090036) -> -0.0020219223 | K32: =IFERROR(__xludf.DUMMYFUNCTION("""COMPUTED_VALUE"""),2992.4800000000005) -> 2992.48 | L32: =IFERROR(__xludf.DUMMYFUNCTION("""COMPUTED_VALUE"""),3229.75) -> 3229.75 | M32: =IFERROR(__xludf.DUMMYFUNCTION("""COMPUTED_VALUE"""),0.07928875046783922) -> 0.07928875 | N32: =IFERROR(__xludf.DUMMYFUNCTION("""COMPUTED_VALUE"""),"да") -> да
A33: =IFERROR(__xludf.DUMMYFUNCTION("""COMPUTED_VALUE"""),"27") -> 27 | B33: =IFERROR(__xludf.DUMMYFUNCTION("""COMPUTED_VALUE"""),11031.285) -> 11031.285 | C33: =IFERROR(__xludf.DUMMYFUNCTION("""COMPUTED_VALUE"""),9402.130000000001) -> 9402.13 | D33: =IFERROR(__xludf.DUMMYFUNCTION("""COMPUTED_VALUE"""),-0.14768497051794047) -> -0.14768497 | E33: =IFERROR(__xludf.DUMMYFUNCTION("""COMPUTED_VALUE"""),59.9) -> 59.9 | F33: =IFERROR(__xludf.DUMMYFUNCTION("""COMPUTED_VALUE"""),54.6) -> 54.6 | G33: =IFERROR(__xludf.DUMMYFUNCTION("""COMPUTED_VALUE"""),-0.08848080133555922) -> -0.088480801 | H33: =IFERROR(__xludf.DUMMYFUNCTION("""COMPUTED_VALUE"""),184.169455533656) -> 184.16946 | I33: =IFERROR(__xludf.DUMMYFUNCTION("""COMPUTED_VALUE"""),171.29193490916253) -> 171.29193 | J33: =IFERROR(__xludf.DUMMYFUNCTION("""COMPUTED_VALUE"""),-0.06992213006863214) -> -0.06992213 | K33: =IFERROR(__xludf.DUMMYFUNCTION("""COMPUTED_VALUE"""),6543.3) -> 6543.3 | L33: =IFERROR(__xludf.DUMMYFUNCTION("""COMPUTED_VALUE"""),8538.16) -> 8538.16 | M33: =IFERROR(__xludf.DUMMYFUNCTION("""COMPUTED_VALUE"""),0.3048706310271575) -> 0.30487063 | N33: =IFERROR(__xludf.DUMMYFUNCTION("""COMPUTED_VALUE"""),"да") -> да
A34: =IFERROR(__xludf.DUMMYFUNCTION("""COMPUTED_VALUE"""),"28") -> 28 | B34: =IFERROR(__xludf.DUMMYFUNCTION("""COMPUTED_VALUE"""),6438.466666666667) -> 6438.4667 | C34: =IFERROR(__xludf.DUMMYFUNCTION("""COMPUTED_VALUE"""),7305.400000000001) -> 7305.4 | D34: =IFERROR(__xludf.DUMMYFUNCTION("""COMPUTED_VALUE"""),0.13464903652008242) -> 0.13464904 | E34: =IFERROR(__xludf.DUMMYFUNCTION("""COMPUTED_VALUE"""),37.55555555555556) -> 37.555556 | F34: =IFERROR(__xludf.DUMMYFUNCTION("""COMPUTED_VALUE"""),45.333333333333336) -> 45.333333 | G34: =IFERROR(__xludf.DUMMYFUNCTION("""COMPUTED_VALUE"""),0.20710059171597633) -> 0.20710059 | H34: =IFERROR(__xludf.DUMMYFUNCTION("""COMPUTED_VALUE"""),170.86926577085703) -> 170.86927 | I34: =IFERROR(__xludf.DUMMYFUNCTION("""COMPUTED_VALUE"""),162.65924862472448) -> 162.65925 | J34: =IFERROR(__xludf.DUMMYFUNCTION("""COMPUTED_VALUE"""),-0.0480485306066834) -> -0.048048531 | K34: =IFERROR(__xludf.DUMMYFUNCTION("""COMPUTED_VALUE"""),4212.68) -> 4212.68 | L34: =IFERROR(__xludf.DUMMYFUNCTION("""COMPUTED_VALUE"""),8601.779999999999) -> 8601.78 | M34: =IFERROR(__xludf.DUMMYFUNCTION("""COMPUTED_VALUE"""),1.0418783292345961) -> 1.0418783 | N34: =IFERROR(__xludf.DUMMYFUNCTION("""COMPUTED_VALUE"""),"да") -> да
A35: =IFERROR(__xludf.DUMMYFUNCTION("""COMPUTED_VALUE"""),"29") -> 29 | B35: =IFERROR(__xludf.DUMMYFUNCTION("""COMPUTED_VALUE"""),11940.638888888889) -> 11940.639 | C35: =IFERROR(__xludf.DUMMYFUNCTION("""COMPUTED_VALUE"""),9652.727777777778) -> 9652.7278 | D35: =IFERROR(__xludf.DUMMYFUNCTION("""COMPUTED_VALUE"""),-0.19160709342278814) -> -0.19160709 | E35: =IFERROR(__xludf.DUMMYFUNCTION("""COMPUTED_VALUE"""),62.22222222222222) -> 62.222222 | F35: =IFERROR(__xludf.DUMMYFUNCTION("""COMPUTED_VALUE"""),48.666666666666664) -> 48.666667 | G35: =IFERROR(__xludf.DUMMYFUNCTION("""COMPUTED_VALUE"""),-0.2178571428571429) -> -0.21785714 | H35: =IFERROR(__xludf.DUMMYFUNCTION("""COMPUTED_VALUE"""),192.25691602367974) -> 192.25692 | I35: =IFERROR(__xludf.DUMMYFUNCTION("""COMPUTED_VALUE"""),198.97902491691184) -> 198.97902 | J35: =IFERROR(__xludf.DUMMYFUNCTION("""COMPUTED_VALUE"""),0.03496419807547605) -> 0.034964198 | K35: =IFERROR(__xludf.DUMMYFUNCTION("""COMPUTED_VALUE"""),5026.719999999999) -> 5026.72 | L35: =IFERROR(__xludf.DUMMYFUNCTION("""COMPUTED_VALUE"""),7321.4400000000005) -> 7321.44 | M35: =IFERROR(__xludf.DUMMYFUNCTION("""COMPUTED_VALUE"""),0.456504440271191) -> 0.45650444 | N35: =IFERROR(__xludf.DUMMYFUNCTION("""COMPUTED_VALUE"""),"да") -> да
A36: =IFERROR(__xludf.DUMMYFUNCTION("""COMPUTED_VALUE"""),"901") -> 901 | B36: =IFERROR(__xludf.DUMMYFUNCTION("""COMPUTED_VALUE"""),13125.555555555555) -> 13125.556 | C36: =IFERROR(__xludf.DUMMYFUNCTION("""COMPUTED_VALUE"""),12718.0) -> 12718 | D36: =IFERROR(__xludf.DUMMYFUNCTION("""COMPUTED_VALUE"""),-0.031050537543384348) -> -0.031050538 | E36: =IFERROR(__xludf.DUMMYFUNCTION("""COMPUTED_VALUE"""),63.333333333333336) -> 63.333333 | F36: =IFERROR(__xludf.DUMMYFUNCTION("""COMPUTED_VALUE"""),60.125) -> 60.125 | G36: =IFERROR(__xludf.DUMMYFUNCTION("""COMPUTED_VALUE"""),-0.05065789473684214) -> -0.050657895 | H36: =IFERROR(__xludf.DUMMYFUNCTION("""COMPUTED_VALUE"""),207.12027379331798) -> 207.12027 | I36: =IFERROR(__xludf.DUMMYFUNCTION("""COMPUTED_VALUE"""),212.9050537711766) -> 212.90505 | J36: =IFERROR(__xludf.DUMMYFUNCTION("""COMPUTED_VALUE"""),0.027929568998306554) -> 0.027929569 | K36: =IFERROR(__xludf.DUMMYFUNCTION("""COMPUTED_VALUE"""),476.51) -> 476.51 | L36: =IFERROR(__xludf.DUMMYFUNCTION("""COMPUTED_VALUE"""),0.0) -> 0 | M36: =IFERROR(__xludf.DUMMYFUNCTION("""COMPUTED_VALUE"""),-1.0) -> -1 | N36: =IFERROR(__xludf.DUMMYFUNCTION("""COMPUTED_VALUE"""),"да") -> да

Sheet Справочник
A1: АА | D1: По букве
A2: Код | B2: Цена | C2: Название блюда | E2: Проверка дублей | F2: Строки с дублями
A3: 1050 | B3: 235 | C3: Азу ''По-татарски''
A4: 3025 | B4: 150 | C4: Азу ''По-татарски'' (Столовая)
A5: 3362 | B5: 225 | C5: Азу из говядины с гречкой
A6: 3351 | B6: 225 | C6: Азу из говядины с макаронами
A7: 3462 | B7: 225 | C7: Азу из говядины с картофельным пюре
A8: 3361 | B8: 205 | C8: Азу из говядины с рисом
A9: 3352 | B9: 198 | C9: Азу из курицы с запеченным картофелем
A10: 3405 | B10: 198 | C10: Азу из курицы с рисом
A11: 3303 | B11: 198 | C11: Азу из курицы со спагетти
A12: 3541 | B12: 198 | C12: Азу из курочки с гречкой
A13: 2163 | B13: 198 | C13: Азу из курочки с макаронами
A14: 3307 | B14: 130 | C14: Азу из курицы
... A1585: 3895 | B1585: 210 | C1585: Азу из свинины с грибами с пюре
A1586: 3903 | C1586: Отбивная из курицы с томатом б/шт
A1587: 3906 | C1587: Азу из свинины с грибами б/100гр
A1588: 3904 | C1588: Горбуша в сырной корочке б/шт
A1589: 2277 | C1589: Котлета куриная б/шт
A1590: 3915 | C1590: Тефтели рыбные б/шт
A1591: 3913 | C1591: Свинина в томатном соусе б/100гр
A1592: 3914 | C1592: Говядина томленая б/100гр
A1593: 3911 | C1593: Филе "Сочное с сыром" б/шт
A1594: 3912 | C1594: Куриный рулет с овощами б/шт
A1595: 3918 | C1595: Говядина по-венгерски б/100гр
A1596: 3920 | C1596: Люля-кебаб куриный б/шт
A1597: 3291 | C1597: Отбивная из свинины с овощами б/шт
... A1612: 2938 | C1612: Паприкаш из говядины б/100гр
A1613: 2859 | B1613: 208 | C1613: Обед ''Студенческий''
A1614: 3996 | B1614: 98 | C1614: Морс вишневый 0,5 л
A1615: 3999 | B1615: 98 | C1615: Морс ягодный 0,5 л
A1616: 3998 | B1616: 98 | C1616: Морс из ч/смородины 0,5 л
A1617: 3997 | B1617: 98 | C1617: Морс облепиховый 0,5 л
A1618: 4000 | B1618: 98 | C1618: Компот из сухофруктов 0,5 л
A1619: 4013 | B1619: 258 | C1619: Фаршированная куриная ножка с макаронами
A1620: 4014 | B1620: 241 | C1620: Филе с сыром и печеным картофелем
A1621: 4015 | B1621: 187 | C1621: Свинина с тмином со сложным гарниром
A1622: 4016 | B1622: 148 | C1622: Плов с грибами
A1623: 4017 | B1623: 248 | C1623: Удон с курицей в азиатском соусе
A1624: 4018 | B1624: 147 | C1624: Сэндвич со сливочным крабом
... A1675: 4184 | B1675: 188 | C1675: Салат "Любовница" 220 гр
A1676: 4185 | C1676: Окрошка
A1677: 4119 | B1677: 258 | C1677: Курица по-табасарански
A1678: 4186 | B1678: 268 | C1678: Хоровац армянский из печеных овощей
A1679: 4185 | B1679: 150 | C1679: Окрошка с квасом
A1680: 4192 | B1680: 272 | C1680: Фаршированные перцы по-азербайджански
A1681: 4193 | B1681: 214 | C1681: Бигус с охотничьими колбасками
A1682: 4196 | B1682: 243 | C1682: Филе с сыром и макаронами
A1683: 4197 | B1683: 208 | C1683: Хот-дог датский
A1684: 4201 | B1684: 212 | C1684: Филе с томатом и моцареллой с отварным картофелем
A1685: 4207 | B1685: 186 | C1685: Драники с рыбой и соусом ранч
A1686: 4205 | B1686: 138 | C1686: Венский штрудель с творогом и смородиной
A1687: 4206 | B1687: 172 | C1687: Венский штрудель с курочкой и сыром
A1688: 4224 | B1688: 281 | C1688: Курица Пармиджано с овощным соте
... A1698: 4239 | B1698: 172 | C1698: Сэндвич с запеченной курочкой и соусом Релиш
C1699: Кабачки фаршированные
A1700: 4065 | B1700: 187 | C1700: Запеканка с ананасом
A1701: 4242 | B1701: 158 | C1701: Яичный рулет с овощами
A1702: 4244 | B1702: 163 | C1702: Профитроли с террином из мяса птицы
B1703: 100 | C1703: Трайфл "Шоколадный"
A1704: 4246 | B1704: 100 | C1704: Каша "3 злака" на апельсиновом соке
A1706: 4252 | B1706: 203 | C1706: Бигус с курицей и беконом
A1707: 4254 | B1707: 186 | C1707: Творожный чизкейк
A1708: 4253 | B1708: 185 | C1708: Венский штрудель с грибами
A1709: 4257 | B1709: 237 | C1709: Куриный биточек с цукини и овощами
A1710: 4259 | B1710: 265 | C1710: Котлета из щуки с овощным гарниром
A1711: 4260 | B1711: 238 | C1711: Зеленый боул с курицей и овощами
A1712: 2941 | B1712: 278 | C1712: Лапша соба с курицей в соусе том-ям
A1713: 4265 | B1713: 128 | C1713: Трайфл "Маковый"
A1714: 4266 | B1714: 131 | C1714: Закуска с селёдкой 170гр
A1715: 4267 | B1715: 208 | C1715: Биточек ''Столичный'' (филе кур) с макаронами
A1716: 4268 | B1716: 269 | C1716: Индейка су-вид с овощами и соусом чили
... A1738: 4328 | B1738: 211 | C1738: Курочка с овощной сальсой с макаронами
A1739: 4346 | B1739: 184 | C1739: Трайфл с вишней
A1740: 4354 | C1740: Лазанья из кабачка с курицей
A1741: 4355 | C1741: Филе с томатом и сыром с зеленым рисом

Sheet Матрица 4 недели
B2: Матрица блюд ПЕРВАЯ неделя
C3: код | D3: Завтрак | E3: Шт | G3: Салат | H3: Шт | I3: код | J3: Суп | K3: Шт | L3: код | M3: Второе | N3: Шт | O3: код | P3: Выпечка | Q3: Шт | R3: код | S3: Сэндвич | T3: Шт | U3: код | V3: Япония | W3: Шт
A4: 46173 | B4: Вс. | C4: 4323 | D4: Груша запеченая с творожным кремом | F4: 3076 | G4: Салат ''Оливье'' (колбаса варен) | I4: 2203 | J4: Борщ с мясом | L4: 4233 | M4: Свинина с тмином с тушеной капустой | O4: 2079 | P4: Вафельная трубочка с вареной сгущенкой | R4: 33 | S4: Сэндвич с копчёной курицей и сыром | U4: 3738 | V4: Ролл сэндвич с крабом | X4: Птица
C5: 1557 | D5: Каша пшенная (на молоке) | F5: 4009 | G5: Салат "Маковый" (курица, мак) | I5: 100 | J5: Крем-суп овощной с курицей | L5: 4014 | M5: Филе с сыром и печеным картофелем | O5: 3518 | P5: Слойка ''Нежная'' с сыром 100 г | R5: 5 | S5: Сэндвич с ветчиной и сыром | U5: 3999 | V5: Морс ягодный 0,5 л | X5: Свинина
C6: 1550 | D6: Омлет с овощами и сыром | F6: 3170 | G6: Салат ''Фунчоза'' 120 г | L6: 4196 | M6: Филе с сыром и макаронами | N6: СПК | O6: 822 | P6: Хлеб пшеничный | X6: Рыба
F7: 2621 | G7: Салат ''Цезарь с курицей'' | L7: 4324 | M7: Спагетти в сливочном соусе с грибами | X7: Покупное
L8: 3054 | M8: Минтай под овощами с рисом | N8: только СПК | X8: Говядина
L9: 3239 | M9: Минтай под овощами с рисом Радуга | N9: СПК
L10: 4283 | M10: Плов ташкентский с говядиной
C12: код | D12: Завтрак | E12: Шт | F12: код | G12: Салат | H12: Шт | I12: код | J12: Суп | K12: Шт | L12: код | M12: Второе | N12: Шт | O12: код | P12: Выпечка | Q12: Шт | R12: код | S12: Сэндвич | T12: Шт | U12: код | V12: Япония | W12: Шт
A13: 46174 | B13: пн | C13: 3196 | D13: Манник ''Маковый'' | F13: 4024 | G13: Салат "Чешский" (колбаса п/к) | I13: 8 | J13: Суп гороховый 250 мл | L13: 48 | M13: Голубец с картофельным пюре | O13: 3435 | P13: Булочка с повидлом 80 г | R13: 3330 | S13: Сэндвич с курицей и соусом Барбекю | U13: 2929 | V13: Ролл сэндвич с курицей
C14: 4235 | D14: Киш с курицей | F14: 3379 | G14: Салат ''Зайка'' 120 г | L14: 3407 | M14: Минтай в кляре с булгуром | O14: 3455 | P14: Слойка с ветчиной и сыром 100г | R14: 3408 | S14: Сэндвич ''Крем-чиз с рыбой'' | U14: 4173 | V14: Морс клюквенный 0,5 л
C15: 4254 | D15: Творожный чизкейк | F15: 3244 | G15: Салат ''Крабик'' с рисом | L15: 4030 | M15: Курочка с овощной сальсой и спагетти | O15: 822 | P15: Хлеб пшеничный
F16: 3343 | G16: Боул с тунцом , бобами эдамаме и овощами | L16: 886 | M16: Бедро запеченное с гречкой | N16: СПК
L17: 958 | M17: Поджарка из курицы с рисом | N17: только СПК
L18: 4029 | M18: Жаркое по-домашнему со свининой | N18: только СПК
L19: 4286 | M19: Фунчоза с овощами и креветками
C21: код | D21: Завтрак | E21: Шт | F21: код | G21: Салат | H21: Шт | I21: код | J21: Суп | K21: Шт | L21: код | M21: Второе | N21: Шт | O21: код | P21: Выпечка | Q21: Шт | R21: код | S21: Сэндвич | T21: Шт | U21: код | V21: Япония | W21: Шт
A22: 46175 | B22: Вт. | C22: 1404 | D22: Драники со сметаной | F22: 3230 | G22: Салат ''Винегрет с капустой'' 120 г | I22: 386 | J22: Суп ''Харчо'' с курицей | L22: 761 | M22: Бризоль с рисом и овощами | O22: 3375 | P22: Самса с куриной грудкой 150 грамм | R22: 3486 | S22: Сэндвич с курицей и соусом карри | U22: 2943 | V22: Онигири с куриным филе в соусе спайси
C23: 4036 | D23: Каша рисовая с вишней | F23: 3301 | G23: Салат ''Блинный'' (ветчина куриная) | I23: 4274 | J23: Крем-суп из брокколи | L23: 4172 | M23: Свинина в соусе тонкацу со спагетти | O23: 822 | P23: Хлеб пшеничный | R23: 3140 | S23: Сэндвич ''Снежный краб'' с соусом спайси | U23: 4000 | V23: Компот из сухофруктов 0,5 л
C24: 2762 | D24: Запеканка творожная с курагой | F24: 4038 | G24: Салат "Гавайский" (курица, ананас) | L24: 4237 | M24: Свинина в соусе тонкацу с картофелем | N24: только спк
F25: 4034 | G25: Гранатовый браслет 220гр | L25: 3437 | M25: Макароны по-флотски | N25: только спк
L26: 763 | M26: Котлета куриная с картофельным пюре | N26: СПК
L27: 4354 | M27: Лазанья из кабачка с курицей
L28: 4017 | M28: Удон с курицей в азиатском соусе
C30: код | D30: Завтрак | E30: Шт | F30: код | G30: Салат | H30: Шт | I30: код | J30: Суп | K30: Шт | L30: код | M30: Второе | N30: Шт | O30: код | P30: Выпечка | Q30: Шт | R30: код | S30: Сэндвич | T30: Шт | U30: код | V30: Япония | W30: Шт
A31: 46176 | B31: Ср. | C31: 4045 | D31: Панкейки шоколадные с вареньем | F31: 3316 | G31: Салат ''Витаминный с крабом'' 120 г | I31: 380 | J31: Солянка | L31: 4120 | M31: Курочка в сливочном соусе со спагетти | N31: СПК | O31: 3527 | P31: Хачапури 100 гр | R31: 2904 | S31: Ассорти сэндвич (пепперони/ветчина)
C32: 1922 | D32: Блины фаршированные сочной курочкой | F32: 31 | G32: Салат ''Прага'' (ветчина кур.) | I32: 3832 | J32: Суп Минестроне | L32: 1873 | M32: Колбаса ''Баварская'' с пюре и тушеной капустой | O32: 3454 | P32: Рулетик с корицей 100 гр | R32: 4239 | S32: Сэндвич с запеченной курочкой и соусом Релиш | U32: 3194 | V32: Морс из вишни 0.5
C33: 385 | D33: Омлет воздушный | F33: 4055 | G33: Салат "Чикаго" (кура копченая) | L33: 1151 | M33: Тефтели куриные с гречкой | N33: СПК | O33: 2079 | P33: Вафельная трубочка с вареной сгущенкой | Q33: 200
F34: 3306 | G34: Боул с курицей, бобами эдамаме и овощами | L34: 4238 | M34: Тефтели куриные с овощами на пару | O34: 822 | P34: Хлеб пшеничный
L35: 3515 | M35: Тилапия в соусе сальса с пюре
L36: 1051 | M36: Горбуша жареная с рисом | N36: только СПК
L37: 4032 | M37: Печень по-царски со сливочным пюре
C39: код | D39: Завтрак | E39: Шт | F39: код | G39: Салат | H39: Шт | I39: код | J39: Суп | K39: Шт | L39: код | M39: Второе | N39: Шт | O39: код | P39: Выпечка | Q39: Шт | R39: код | S39: Сэндвич | T39: Шт | U39: код | V39: Япония | W39: Шт
A40: 46177 | B40: Чт. | C40: 3970 | D40: Каша овсяная (на молоке) | F40: 3323 | G40: Салат ''Морковь с чесноком'' 120гр | I40: 2288 | J40: Суп картофельный с курицей | L40: 383 | M40: Перец фаршированный с картофелем | O40: 3528 | P40: Сырная палочка 80 гр | R40: 3 | S40: Сэндвич с курочкой и скремблом
C41: 4037 | D41: Шарлотка с яблоком | F41: 4058 | G41: Салат "Городской"(колбаса вареная) | L41: 4069 | M41: Бефстроганов (говядина) с картофелем | N41: СПК | O41: 822 | P41: Хлеб пшеничный | R41: 2364 | S41: Сэндвич с ветчиной и сыром | U41: 3998 | V41: Морс из ч/смородины 0,5 л
C42: 4242 | D42: Яичный рулет с овощами | F42: 2706 | G42: Салат ''Фасолька'' с курицей | L42: 4067 | M42: Бефстроганов (говядина) с рисом | N42: СПК
F43: 3823 | G43: Салат "Мимоза" с рыбой 220гр | L43: 4068 | M43: Бефстроганов (говядина) с макаронами | N43: СПК
L44: 1092 | M44: Шашлык (кура) с картошкой по деревенски
L45: 3051 | M45: Шашлык куриный с овощным соте
L46: 3008 | M46: Биточек ''Солнышко'' с гречкой
L47: 113 | M47: Спагетти ''Болоньезе''
N48: ,
B49: Матрица блюд ВТОРАЯ неделя
C50: код | D50: Завтрак | E50: Шт | F50: код | G50: Салат | H50: Шт | I50: код | J50: Суп | K50: Шт | M50: Второе | N50: Шт | O50: код | P50: Выпечка | Q50: Шт | R50: код | S50: Сэндвич | T50: Шт | U50: код | V50: Япония | W50: Шт
A51: 46180 | B51: Вс. | C51: 2898 | D51: Каша рисовая с курагой | E51: 137 | F51: 2686 | G51: Салат ''Коул Слоу'' 120 гр | H51: 217 | I51: 793 | J51: Борщ с курицей | K51: 209 | L51: 3737 | M51: Чкмерули из курицы со спагетти | N51: СПК | O51: 4224 | P51: Курица Пармиджано с овощным соте | Q51: 206 | R51: 4239 | S51: Сэндвич с запеченной курочкой и соусом Релиш | T51: 94 | U51: 2943 | V51: Онигири с куриным филе в соусе спайси | W51: 91 | X51: Птица
C52: 4206 | D52: Венский штрудель с курочкой и сыром | E52: 142 | F52: 884 | G52: Салат ''Интрига'' (колбаса в/к.) | H52: 200 | I52: 822 | J52: Хлеб пшеничный | L52: 1009 | M52: Свинина по-баварски с картофелем | N52: СПК | Q52: 25 | R52: 2364 | S52: Сэндвич с ветчиной и томатом | T52: 99 | U52: 3996 | V52: Морс вишневый 0,5 л | X52: Свинина
C53: 4098 | D53: Шоколадный пирог с вишней | E53: 79 | F53: 3165 | G53: Салат ''Красное море'' (крабовые палочки) | H53: 132 | I53: 1237 | J53: Суп грибной | L53: 546 | M53: Филе с грибами и рисом | U53: 2079 | V53: Вафельная трубочка с вареной сгущенкой | X53: Рыба
F54: 4184 | G54: Салат "Любовница" 220 гр | H54: 57 | L54: 4294 | M54: Пангасиус запеченый с картофельным пюре | N54: только СПК | X54: Покупное
L55: 4295 | M55: Щука жареная с картофельным пюре | X55: Говядина
C59: код | D59: Завтрак | E59: Шт | F59: код | G59: Салат | H59: Шт | I59: код | J59: Суп | K59: Шт | L59: код | M59: Второе | N59: Шт | O59: код | P59: Выпечка | Q59: Шт | R59: код | S59: Сэндвич | T59: Шт | U59: код | V59: Япония | W59: Шт
A60: 46181 | B60: Пн. | C60: 1550 | D60: Омлет с овощами и сыром | E60: 110 | F60: 3189 | G60: Салат Свекла с сыром и чесноком 120гр | H60: 159 | I60: 386 | J60: Суп ''Харчо'' с курицей | K60: 181 | L60: 4080 | M60: Мясные гнёзда с овощами и картофелем | N60: СПК | Q60: 20 | R60: 654 | S60: Сэндвич с бужениной и соусом Релиш | T60: 84 | U60: 4115 | V60: Хот-дог | W60: 76
C61: 2847 | D61: Запеканка творожная | E61: 94 | F61: 3301 | G61: Салат ''Блинный'' (ветчина куриная) | H61: 159 | K61: 25 | L61: 4259 | M61: Котлета из щуки с овощным гарниром | Q61: 25 | R61: 2904 | S61: Ассорти сэндвич (пепперони/ветчина) | T61: 114 | U61: 3999 | V61: Морс ягодный 0,5 л | W61: 61
C62: 3014 | D62: Драники картофельные с цукини со сметаной | E62: 69 | F62: 3260 | G62: Салат ''Купеческий'' (филе кур., шампиньоны) | H62: 158 | L62: 1982 | M62: Вок с курицей и рисом
F63: 3430 | G63: Боул с крабом, бобами эдамаме и овощами | H63: 82 | L63: 1267 | M63: Печень куриная с овощами с гречкой | N63: СПК
L64: 2976 | M64: Курочка в томатном соусе с рисом | N64: только СПК
L66: 3759 | M66: Грудка су-вид с кус-кусом
C68: код | D68: Завтрак | E68: Шт | F68: код | G68: Салат | H68: Шт | I68: код | J68: Суп | K68: Шт | L68: код | M68: Второе | N68: Шт | O68: код | P68: Выпечка | Q68: Шт | R68: код | S68: Сэндвич | T68: Шт | U68: код | V68: Япония | W68: Шт
A69: 46182 | B69: Вт. | C69: 1287 | D69: Блины со сметаной | F69: 4319 | G69: Салат "Морковный с изюмом" | I69: 2288 | J69: Суп картофельный с курицей | L69: 813 | M69: Котлета по-киевски с макаронами | O69: 2483 | P69: Самса с курицей 110 грамм | Q69: 20 | R69: 3 | S69: Сэндвич с курочкой и скремблом | U69: 2943 | V69: Онигири с куриным филе в соусе спайси | W69: ?
C70: 3970 | D70: Каша овсяная (на молоке) | F70: 3216 | G70: Салат ''Таврия'' (колбаса вареная) | I70: 4274 | J70: Крем-суп из брокколи | L70: 4105 | M70: Свинина по-гавайски с картофелем | R70: 54 | S70: Сэндвич с тунцом с соусом Том Ям | U70: 4000 | V70: Компот из сухофруктов 0,5 л | W70: 78
C71: 4226 | D71: Курник (курица, картофель) | F71: 2303 | G71: Салат ''Жар-птица'' (филе кур) | L71: 26 | M71: Плов по-узбекски с цыпленком б/250гр | N71: СПК
F72: 2067 | G72: Салат "Греческий'' | L72: 4100 | M72: Курочка по-купечески с гречкой | N72: СПК
L73: 3474 | M73: Свинина в томатном соусе с макаронами | N73: только СПК
L75: 3751 | M75: Томленая говядина с птитим
C77: код | D77: Завтрак | E77: Шт | F77: код | G77: Салат | H77: Шт | I77: код | J77: Суп | K77: Шт | L77: код | M77: Второе | N77: Шт | O77: код | P77: Выпечка | Q77: Шт | R77: код | S77: Сэндвич | T77: Шт | U77: код | V77: Япония | W77: Шт
A78: 46183 | B78: Ср. | C78: 3196 | D78: Манник ''Маковый'' | F78: 3109 | G78: Салат ''Витаминный'' 120 г | I78: 380 | J78: Солянка | L78: 3889 | M78: Купаты куриные с овощным гарниром | O78: 3454 | P78: Рулетик с корицей 100 гр | R78: 2083 | S78: Сэндвич ''Цезарь'' | U78: 4265 | V78: Трайфл "Маковый" | W78: 70
C79: 3645 | D79: Драники с рыбой и творожным сыром | E79: 124 | F79: 1160 | G79: Салат ''Пикник'' (печень) | L79: 1899 | M79: Горбуша в сырной корочке с картофелем | O79: 3527 | P79: Хачапури 100 гр | R79: 2782 | S79: Сэндвич с пепперони и сыром | U79: 4173 | V79: Морс клюквенный 0,5 л
C80: 758 | D80: Блинчики с творогом и вишней | F80: 31 | G80: Салат ''Прага'' (ветчина кур.) | L80: 965 | M80: Гуляш из свинины с макаронами | N80: СПК | O80: 2079 | P80: Вафельная трубочка с вареной сгущенкой
F81: 4260 | G81: Зеленый боул с курицей и овощами | L81: 4176 | M81: Курочка в сырном соусе с картофелем
L82: 4099 | M82: Курочка в сырном соусе со спагетти
L83: 2022 | M83: Горбуша в томатном соусе с рисом | N83: только СПК
L84: 4257 | M84: Куриный биточек с цукини и овощами
L85: 1826 | M85: Купаты куриные с картофелем
C86: код | D86: Завтрак | E86: Шт | F86: код | G86: Салат | H86: Шт | I86: код | J86: Суп | K86: Шт | L86: код | M86: Второе | N86: Шт | O86: код | P86: Выпечка | Q86: Шт | R86: код | S86: Сэндвич | T86: Шт | U86: код | V86: Япония | W86: Шт
A87: 46184 | B87: Чт. | C87: 89 | D87: Блин с ветчиной и сыром | F87: 3433 | G87: Салат ''Спаржа с курицей' 110 гр | I87: 8 | J87: Суп гороховый 250 мл | L87: 3768 | M87: Паприкаш из говядины с гречкой | N87: только СПК | O87: 3528 | P87: Сырная палочка 80 гр | R87: 5 | S87: Сэндвич с ветчиной и сыром | U87: 4327 | V87: Морс вишня/клубника 0,5 л | W87: 70
C88: 385 | D88: Омлет воздушный | F88: 3180 | G88: Салат ''Морковь по-корейски'' 120 г | I88: 1106 | J88: Суп-крем из тыквы | L88: 3770 | M88: Паприкаш из говядины с картофельным пюре | N88: только СПК | R88: 3330 | S88: Сэндвич с курицей и соусом Барбекю | U88: 4197 | V88: Хот-дог датский
C89: 138 | D89: Каша рисовая (на молоке) | F89: 41 | G89: Закуска с селёдкой 120 г | L89: 3769 | M89: Паприкаш из говядины с макаронами | N89: только СПК
F90: 4089 | G90: Салат "Генеральский" (курица, грецкий орех) 220гр | L90: 3437 | M90: Макароны по-флотски | U90: 4266 | V90: Закуска с селёдкой 170гр
F91: 3141 | G91: Салат из свежей капусты 120 г | H91: только СПК | L91: 657 | M91: Перец фаршированный с пюре
L92: 3122 | M92: Люля-кебаб куриный с овощным соте
L93: 1896 | M93: Манты со сметаной
L94: 372 | M94: Бедро запеченное с картофелем
B96: Матрица блюд ТРЕТЬЯ неделя
C97: код | D97: Завтрак | E97: Шт | F97: код | G97: Салат | H97: Шт | I97: код | J97: Суп | K97: Шт | L97: код | M97: Второе | N97: Шт | O97: код | P97: Выпечка | Q97: Шт | R97: код | S97: Сэндвич | T97: Шт | U97: код | V97: Япония | W97: Шт
A98: 46186 | B98: Вс. | C98: 4323 | D98: Груша запеченая с творожным кремом | E98: 113 | F98: 3076 | G98: Салат ''Оливье'' (колбаса варен) | H98: 172 | I98: 793 | J98: Борщ с курицей | K98: 177 | L98: 763 | M98: Котлета куриная с картофельным пюре | N98: 118 | O98: 3518 | P98: Слойка ''Нежная'' с сыром 100 г | Q98: 0 | R98: 5 | S98: Сэндвич с ветчиной и сыром | T98: 119 | U98: 3999 | V98: Морс ягодный 0,5 л | W98: 110 | X98: Птица
C99: 3290 | D99: Каша пшенная с курагой | E99: 90 | F99: 4009 | G99: Салат "Маковый" (курица, мак) | H99: 174 | K99: 42 | L99: 4014 | M99: Филе с сыром и печеным картофелем | O99: 2079 | P99: Вафельная трубочка с вареной сгущенкой | R99: 33 | S99: Сэндвич с копчёной курицей и сыром | T99: 122 | U99: 3738 | V99: Ролл сэндвич с крабом | W99: 91 | X99: Свинина
C100: 1550 | D100: Омлет с овощами и сыром | E100: 118 | F100: 3170 | G100: Салат ''Фунчоза'' 120 г | H100: 182 | L100: 3054 | M100: Минтай под овощами с рисом | N100: только спк | X100: Рыба
F101: 3306 | G101: Боул с курицей, бобами эдамаме и овощами | H101: 66 | L101: 4233 | M101: Свинина с тмином с тушеной капустой | N101: СПК | X101: Покупное
L102: 4196 | M102: Филе с сыром и макаронами | N102: только СПК | X102: Говядина
L103: 4267 | M103: Биточек ''Столичный'' (филе кур) с макаронами | X103: Премиум
L104: 4324 | M104: Спагетти в сливочном соусе с грибами | N104: 76
L105: 3239 | M105: Минтай под овощами с рисом Радуга
C106: код | D106: Завтрак | E106: Шт | F106: код | G106: Салат | H106: Шт | I106: код | J106: Суп | K106: Шт | L106: код | M106: Второе | N106: Шт | Q106: Шт | R106: код | S106: Сэндвич | T106: Шт | U106: код | V106: Япония | W106: Шт
A107: 46187 | B107: пн | C107: 2936 | D107: Манник | E107: 118 | F107: 4024 | G107: Салат "Чешский" (колбаса п/к) | H107: 180 | I107: 8 | J107: Суп гороховый 250 мл | K107: 182 | L107: 48 | M107: Голубец с картофельным пюре | O107: 3435 | P107: Булочка с повидлом 80 г | Q107: 25 | R107: 3330 | S107: Сэндвич с курицей и соусом Барбекю | T107: 118 | U107: 3996 | V107: Морс вишневый 0,5 л | W107: 118
C108: 4235 | D108: Киш с курицей | E108: 72 | F108: 1995 | G108: Салат ''Дачный'' (редис, огурец,) | H108: 194 | I108: 1106 | J108: Суп-крем из тыквы | L108: 3407 | M108: Минтай в кляре с булгуром | N108: 119 | O108: 3455 | P108: Слойка с ветчиной и сыром 100г | Q108: 25 | R108: 3408 | S108: Сэндвич ''Крем-чиз с рыбой'' | T108: 117 | W108: 83
C109: 4318 | D109: Ватрушка Царская | E109: 136 | F109: 3244 | G109: Салат ''Крабик'' с рисом | H109: 173 | L109: 4328 | M109: Курочка с овощной сальсой с макаронами | O109: 4312 | P109: Фруктовый набор (арбуз/дыня) | Q109: 150
F110: 2621 | G110: Салат ''Цезарь с курицей'' | H110: 87 | L110: 4025 | M110: Бедро в пряном соусе с гречкой | N110: СПК
L111: 958 | M111: Поджарка из курицы с рисом | N111: только СПК
L113: 4029 | M113: Жаркое по-домашнему со свининой | N113: СПК
L114: 4268 | M114: Индейка су-вид с овощами и соусом чили
...

Sheet План 1-я неделя
A2: Дата: | D2: 46257 | E2: План на день кухня ВОСКРЕСЕНЬЕ
A3: по плану | B3: Код | C3: Цена | D3: категория | E3: Название блюда | F3: Т1 | G3: Ф1 | H3: Т2 | I3: Ф2 | J3: Т3 | K3: Ф3 | L3: Т4 | M3: Ф4 | N3: Т5 | O3: Ф5 | P3: Т6 | Q3: Ф6 | R3: Т7 | S3: Ф7 | T3: Т8 | U3: Ф8 | V3: Т9 | W3: Ф9 | X3: Т10 | Y3: Ф10 | Z3: Т11 | AA3: Ф11 | AB3: Т12 | AC3: Ф12 | AD3: Т13 | AE3: Ф13 | AF3: Т14 | AG3: Ф14 | AH3: Т15 | AI3: Ф15 | AJ3: Т16 | AK3: Ф16 | AL3: Т17 | AM3: Ф17 | AN3: Т18 | AO3: Ф18 | AP3: Т19 | AQ3: Ф19 | AR3: Т20 | AS3: Ф20 | AT3: Т21 | AU3: Ф21 | AV3: Т22 | AW3: Ф22 | AX3: Т23 | AY3: Ф23 | AZ3: Т24 | BA3: Ф24 | BB3: Т25 | BC3: Ф25 | BD3: Т26 | BE3: Ф26 | BF3: Т27 | BG3: Ф27 | BH3: Т28 | BI3: Ф28 | BJ3: Т29 | BK3: Ф29 | BL3: ТСПК | BM3: ФСПК | BN3: Стол | BO3: Ф.Стол | BP3: ПЛАН | BQ3: СДАЛИ | BR3: Ф.Цена | BS3: Пл.цена
B4: 4323 | C4: 210 | D4: Завтрак | E4: ='Матрица 4 недели'!D4 -> Груша запеченая с творожным кремом | F4: 3 | H4: 6 | J4: 2 | L4: 4 | N4: 4 | P4: 2 | R4: 2 | T4: 2 | V4: 3 | X4: 3 | AB4: 2 | AD4: 3 | AF4: 4 | AH4: 2 | AJ4: 2 | AL4: 2 | AN4: 3 | AP4: 2 | AR4: 3 | AT4: 2 | AV4: 2 | AX4: 8 | AZ4: 2 | BB4: 3 | BD4: 3 | BF4: 2 | BH4: 2 | BJ4: 2 | BN4: 10 | BP4: =(F4+H4+J4+L4+N4+P4+R4+T4+V4+X4+Z4+AB4+AF4+AH4+AJ4+AR4+BL4+AL4+AD4+AN4+AP4+AT4+AV4+AX4+AZ4+BB4+BD4+BF4+BH4+BJ4)+1 -> 81 | BQ4: =G4+I4+K4+M4+O4+Q4+S4+W4+U4+Y4+AA4+BM4+AC4+AG4+AI4+AK4+AS4+AE4+AM4+AO4+AQ4+AU4+AW4+AY4+BA4+BC4+BE4+BG4+BI4+BK4 -> 0 | BR4: =BQ4*C4 -> 0 | BS4: =BP4*C4 -> 17010
B5: 1557 | C5: 98 | D5: Завтрак | E5: ='Матрица 4 недели'!D5 -> Каша пшенная (на молоке) | F5: 3 | H5: 2 | J5: 5 | L5: 2 | N5: 5 | P5: 3 | R5: 1 | T5: 2 | V5: 0 | X5: 2 | AB5: 0 | AD5: 3 | AF5: 5 | AH5: 3 | AJ5: 2 | AL5: 0 | AN5: 3 | AP5: 1 | AR5: 2 | AT5: 1 | AV5: 1 | AX5: 1 | AZ5: 2 | BB5: 1 | BD5: 1 | BF5: 1 | BH5: 0 | BJ5: 3 | BP5: =(F5+H5+J5+L5+N5+P5+R5+T5+V5+X5+Z5+AB5+AF5+AH5+AJ5+AR5+BL5+AL5+AD5+AN5+AP5+AT5+AV5+AX5+AZ5+BB5+BD5+BF5+BH5+BJ5)+1 -> 56 | BQ5: =G5+I5+K5+M5+O5+Q5+S5+W5+U5+Y5+AA5+BM5+AC5+AG5+AI5+AK5+AS5+AE5+AM5+AO5+AQ5+AU5+AW5+AY5+BA5+BC5+BE5+BG5+BI5+BK5 -> 0 | BR5: =BQ5*C5 -> 0 | BS5: =BP5*C5 -> 5488
B6: 1550 | C6: 158 | D6: Завтрак | E6: ='Матрица 4 недели'!D6 -> Омлет с овощами и сыром | F6: 3 | H6: 3 | J6: 4 | L6: 2 | N6: 6 | P6: 2 | R6: 2 | T6: 7 | V6: 4 | X6: 5 | AB6: 3 | AD6: 3 | AF6: 6 | AH6: 4 | AJ6: 9 | AL6: 5 | AN6: 3 | AP6: 2 | AR6: 8 | AT6: 4 | AV6: 4 | AX6: 5 | AZ6: 2 | BB6: 4 | BD6: 3 | BF6: 4 | BH6: 9 | BJ6: 5 | BP6: =(F6+H6+J6+L6+N6+P6+R6+T6+V6+X6+Z6+AB6+AF6+AH6+AJ6+AR6+BL6+AL6+AD6+AN6+AP6+AT6+AV6+AX6+AZ6+BB6+BD6+BF6+BH6+BJ6)+1 -> 122 | BQ6: =G6+I6+K6+M6+O6+Q6+S6+W6+U6+Y6+AA6+BM6+AC6+AG6+AI6+AK6+AS6+AE6+AM6+AO6+AQ6+AU6+AW6+AY6+BA6+BC6+BE6+BG6+BI6+BK6 -> 0 | BR6: =BQ6*C6 -> 0 | BS6: =BP6*C6 -> 19276
B7: 3076 | C7: 98 | D7: Салат | E7: ='Матрица 4 недели'!G4 -> Салат ''Оливье'' (колбаса варен) | F7: 8 | H7: 2 | J7: 4 | L7: 2 | N7: 4 | P7: 5 | R7: 2 | T7: 3 | V7: 2 | X7: 3 | AB7: 2 | AD7: 2 | AF7: 2 | AH7: 2 | AJ7: 1 | AL7: 2 | AN7: 3 | AP7: 1 | AR7: 9 | AT7: 3 | AV7: 5 | AX7: 2 | AZ7: 2 | BB7: 2 | BD7: 4 | BF7: 3 | BH7: 3 | BJ7: 2 | BL7: 44 | BN7: 5 | BP7: =(F7+H7+J7+L7+N7+P7+R7+T7+V7+X7+Z7+AB7+AF7+AH7+AJ7+AR7+BL7+AL7+AD7+AN7+AP7+AT7+AV7+AX7+AZ7+BB7+BD7+BF7+BH7+BJ7)+1 -> 130 | BQ7: =G7+I7+K7+M7+O7+Q7+S7+W7+U7+Y7+AA7+BM7+AC7+AG7+AI7+AK7+AS7+AE7+AM7+AO7+AQ7+AU7+AW7+AY7+BA7+BC7+BE7+BG7+BI7+BK7 -> 0 | BR7: =BQ7*C7 -> 0 | BS7: =BP7*C7 -> 12740
B8: 4009 | C8: 98 | D8: Салат | E8: ='Матрица 4 недели'!G5 -> Салат "Маковый" (курица, мак) | F8: 3 | H8: 1 | J8: 4 | L8: 3 | N8: 5 | P8: 1 | R8: 2 | T8: 2 | V8: 1 | X8: 0 | AB8: 1 | AD8: 2 | AF8: 3 | AH8: 2 | AJ8: 2 | AL8: 2 | AN8: 3 | AP8: 2 | AR8: 4 | AT8: 5 | AV8: 0 | AX8: 4 | AZ8: 2 | BB8: 1 | BD8: 1 | BF8: 5 | BH8: 2 | BJ8: 1 | BL8: 43 | BP8: =(F8+H8+J8+L8+N8+P8+R8+T8+V8+X8+Z8+AB8+AF8+AH8+AJ8+AR8+BL8+AL8+AD8+AN8+AP8+AT8+AV8+AX8+AZ8+BB8+BD8+BF8+BH8+BJ8)+1 -> 108 | BQ8: =G8+I8+K8+M8+O8+Q8+S8+W8+U8+Y8+AA8+BM8+AC8+AG8+AI8+AK8+AS8+AE8+AM8+AO8+AQ8+AU8+AW8+AY8+BA8+BC8+BE8+BG8+BI8+BK8 -> 0 | BR8: =BQ8*C8 -> 0 | BS8: =BP8*C8 -> 10584
B9: 3170 | C9: 98 | D9: Салат | E9: ='Матрица 4 недели'!G6 -> Салат ''Фунчоза'' 120 г | F9: 6 | H9: 3 | J9: 4 | L9: 2 | N9: 4 | P9: 6 | R9: 2 | T9: 1 | V9: 2 | X9: 1 | AB9: 2 | AD9: 2 | AF9: 5 | AH9: 3 | AJ9: 4 | AL9: 4 | AN9: 3 | AP9: 3 | AR9: 6 | AT9: 2 | AV9: 4 | AX9: 4 | AZ9: 3 | BB9: 2 | BD9: 2 | BF9: 5 | BH9: 2 | BJ9: 2 | BL9: 43 | BN9: 5 | BP9: =(F9+H9+J9+L9+N9+P9+R9+T9+V9+X9+Z9+AB9+AF9+AH9+AJ9+AR9+BL9+AL9+AD9+AN9+AP9+AT9+AV9+AX9+AZ9+BB9+BD9+BF9+BH9+BJ9)+1 -> 133 | BQ9: =G9+I9+K9+M9+O9+Q9+S9+W9+U9+Y9+AA9+BM9+AC9+AG9+AI9+AK9+AS9+AE9+AM9+AO9+AQ9+AU9+AW9+AY9+BA9+BC9+BE9+BG9+BI9+BK9 -> 0 | BR9: =BQ9*C9 -> 0 | BS9: =BP9*C9 -> 13034
B10: 2621 | C10: 244 | D10: Премиум | E10: ='Матрица 4 недели'!G7 -> Салат ''Цезарь с курицей'' | F10: 5 | H10: 0 | J10: 0 | L10: 2 | N10: 5 | P10: 5 | R10: 0 | T10: 2 | V10: 4 | X10: 1 | AB10: 3 | AD10: 3 | AF10: 6 | AH10: 2 | AJ10: 2 | AL10: 3 | AN10: 2 | AP10: 1 | AR10: 3 | AT10: 2 | AV10: 3 | AX10: 0 | AZ10: 2 | BB10: 1 | BD10: 0 | BF10: 3 | BH10: 2 | BJ10: 3 | BP10: =(F10+H10+J10+L10+N10+P10+R10+T10+V10+X10+Z10+AB10+AF10+AH10+AJ10+AR10+BL10+AL10+AD10+AN10+AP10+AT10+AV10+AX10+AZ10+BB10+BD10+BF10+BH10+BJ10)+1 -> 66 | BQ10: =G10+I10+K10+M10+O10+Q10+S10+W10+U10+Y10+AA10+BM10+AC10+AG10+AI10+AK10+AS10+AE10+AM10+AO10+AQ10+AU10+AW10+AY10+BA10+BC10+BE10+BG10+BI10+BK10 -> 0 | BR10: =BQ10*C10 -> 0 | BS10: =BP10*C10 -> 16104
B11: 2203 | C11: 96 | D11: Суп | E11: ='Матрица 4 недели'!J4 -> Борщ с мясом | BL11: 120 | BN11: 15 | BP11: =(F11+H11+J11+L11+N11+P11+R11+T11+V11+X11+Z11+AB11+AF11+AH11+AJ11+AR11+BL11+AL11+AD11+AN11+AP11+AT11+AV11+AX11+AZ11+BB11+BD11+BF11+BH11+BJ11)+1 -> 121 | BQ11: =G11+I11+K11+M11+O11+Q11+S11+W11+U11+Y11+AA11+BM11+AC11+AG11+AI11+AK11+AS11+AE11+AM11+AO11+AQ11+AU11+AW11+AY11+BA11+BC11+BE11+BG11+BI11+BK11 -> 0 | BR11: =BQ11*C11 -> 0 | BS11: =BP11*C11 -> 11616
B12: 100 | C12: 90 | D12: Суп | E12: ='Матрица 4 недели'!J5 -> Крем-суп овощной с курицей | F12: 3 | H12: 3 | J12: 3 | L12: 4 | N12: 3 | P12: 2 | R12: 2 | T12: 3 | V12: 3 | X12: 2 | AB12: 2 | AD12: 2 | AF12: 3 | AH12: 2 | AJ12: 2 | AL12: 2 | AN12: 2 | AP12: 2 | AR12: 2 | AT12: 2 | AV12: 2 | AX12: 3 | AZ12: 2 | BB12: 2 | BD12: 2 | BF12: 2 | BH12: 2 | BJ12: 3 | BN12: 10 | BP12: =(F12+H12+J12+L12+N12+P12+R12+T12+V12+X12+Z12+AB12+AF12+AH12+AJ12+AR12+BL12+AL12+AD12+AN12+AP12+AT12+AV12+AX12+AZ12+BB12+BD12+BF12+BH12+BJ12)+1 -> 68 | BQ12: =G12+I12+K12+M12+O12+Q12+S12+W12+U12+Y12+AA12+BM12+AC12+AG12+AI12+AK12+AS12+AE12+AM12+AO12+AQ12+AU12+AW12+AY12+BA12+BC12+BE12+BG12+BI12+BK12 -> 0 | BR12: =BQ12*C12 -> 0 | BS12: =BP12*C12 -> 6120
B13: 4233 | C13: 211 | D13: Второе | E13: ='Матрица 4 недели'!M4 -> Свинина с тмином с тушеной капустой | F13: 0 | H13: 1 | J13: 4 | L13: 5 | N13: 9 | P13: 5 | R13: 3 | T13: 0 | V13: 4 | X13: 0 | AB13: 0 | AD13: 3 | AF13: 3 | AH13: 2 | AJ13: 3 | AL13: 0 | AN13: 3 | AP13: 2 | AR13: 3 | AT13: 4 | AV13: 2 | AX13: 3 | AZ13: 2 | BB13: 2 | BD13: 1 | BF13: 2 | BH13: 3 | BJ13: 3 | BL13: 25 | BN13: 10 | BP13: =(F13+H13+J13+L13+N13+P13+R13+T13+V13+X13+Z13+AB13+AF13+AH13+AJ13+AR13+BL13+AL13+AD13+AN13+AP13+AT13+AV13+AX13+AZ13+BB13+BD13+BF13+BH13+BJ13)+1 -> 98 | BQ13: =G13+I13+K13+M13+O13+Q13+S13+W13+U13+Y13+AA13+BM13+AC13+AG13+AI13+AK13+AS13+AE13+AM13+AO13+AQ13+AU13+AW13+AY13+BA13+BC13+BE13+BG13+BI13+BK13 -> 0 | BR13: =BQ13*C13 -> 0 | BS13: =BP13*C13 -> 20678
B14: 4014 | C14: 241 | D14: Второе | E14: ='Матрица 4 недели'!M5 -> Филе с сыром и печеным картофелем | F14: 10 | H14: 5 | J14: 8 | L14: 2 | N14: 10 | P14: 9 | R14: 4 | T14: 4 | V14: 5 | X14: 5 | AB14: 6 | AD14: 4 | AF14: 12 | AH14: 4 | AJ14: 8 | AL14: 4 | AN14: 3 | AP14: 3 | AR14: 7 | AT14: 6 | AV14: 5 | AX14: 4 | AZ14: 3 | BB14: 2 | BD14: 3 | BF14: 7 | BH14: 5 | BJ14: 9 | BP14: =(F14+H14+J14+L14+N14+P14+R14+T14+V14+X14+Z14+AB14+AF14+AH14+AJ14+AR14+BL14+AL14+AD14+AN14+AP14+AT14+AV14+AX14+AZ14+BB14+BD14+BF14+BH14+BJ14)+1 -> 158 | BQ14: =G14+I14+K14+M14+O14+Q14+S14+W14+U14+Y14+AA14+BM14+AC14+AG14+AI14+AK14+AS14+AE14+AM14+AO14+AQ14+AU14+AW14+AY14+BA14+BC14+BE14+BG14+BI14+BK14 -> 0 | BR14: =BQ14*C14 -> 0 | BS14: =BP14*C14 -> 38078
B15: 4196 | C15: 243 | D15: Второе | E15: ='Матрица 4 недели'!M6 -> Филе с сыром и макаронами | BL15: 80 | BN15: 10 | BP15: =(F15+H15+J15+L15+N15+P15+R15+T15+V15+X15+Z15+AB15+AF15+AH15+AJ15+AR15+BL15+AL15+AD15+AN15+AP15+AT15+AV15+AX15+AZ15+BB15+BD15+BF15+BH15+BJ15)+1 -> 81 | BQ15: =G15+I15+K15+M15+O15+Q15+S15+W15+U15+Y15+AA15+BM15+AC15+AG15+AI15+AK15+AS15+AE15+AM15+AO15+AQ15+AU15+AW15+AY15+BA15+BC15+BE15+BG15+BI15+BK15 -> 0 | BR15: =BQ15*C15 -> 0 | BS15: =BP15*C15 -> 19683
B16: 4324 | C16: 208 | D16: Второе | E16: ='Матрица 4 недели'!M7 -> Спагетти в сливочном соусе с грибами | F16: 9 | H16: 3 | J16: 4 | L16: 3 | N16: 7 | P16: 7 | R16: 4 | T16: 5 | V16: 3 | X16: 7 | AB16: 4 | AD16: 4 | AF16: 5 | AH16: 6 | AJ16: 8 | AL16: 4 | AN16: 3 | AP16: 3 | AR16: 9 | AT16: 4 | AV16: 6 | AX16: 3 | AZ16: 3 | BB16: 3 | BD16: 5 | BF16: 7 | BH16: 4 | BJ16: 7 | BN16: 10 | BP16: =(F16+H16+J16+L16+N16+P16+R16+T16+V16+X16+Z16+AB16+AF16+AH16+AJ16+AR16+BL16+AL16+AD16+AN16+AP16+AT16+AV16+AX16+AZ16+BB16+BD16+BF16+BH16+BJ16)+1 -> 141 | BQ16: =G16+I16+K16+M16+O16+Q16+S16+W16+U16+Y16+AA16+BM16+AC16+AG16+AI16+AK16+AS16+AE16+AM16+AO16+AQ16+AU16+AW16+AY16+BA16+BC16+BE16+BG16+BI16+BK16 -> 0 | BR16: =BQ16*C16 -> 0 | BS16: =BP16*C16 -> 29328
B17: 3054 | C17: 198 | D17: Второе | E17: ='Матрица 4 недели'!M8 -> Минтай под овощами с рисом | BL17: 25 | BP17: =(F17+H17+J17+L17+N17+P17+R17+T17+V17+X17+Z17+AB17+AF17+AH17+AJ17+AR17+BL17+AL17+AD17+AN17+AP17+AT17+AV17+AX17+AZ17+BB17+BD17+BF17+BH17+BJ17)+1 -> 26 | BQ17: =G17+I17+K17+M17+O17+Q17+S17+W17+U17+Y17+AA17+BM17+AC17+AG17+AI17+AK17+AS17+AE17+AM17+AO17+AQ17+AU17+AW17+AY17+BA17+BC17+BE17+BG17+BI17+BK17 -> 0 | BR17: =BQ17*C17 -> 0 | BS17: =BP17*C17 -> 5148
B18: 3239 | C18: 215 | D18: Второе | E18: ='Матрица 4 недели'!M9 -> Минтай под овощами с рисом Радуга | F18: 3 | H18: 2 | J18: 6 | L18: 2 | N18: 5 | P18: 3 | R18: 0 | T18: 3 | V18: 3 | X18: 3 | AB18: 2 | AD18: 4 | AF18: 4 | AH18: 4 | AJ18: 2 | AL18: 4 | AN18: 3 | AP18: 2 | AR18: 8 | AT18: 5 | AV18: 2 | AX18: 3 | AZ18: 2 | BB18: 3 | BD18: 2 | BF18: 2 | BH18: 4 | BJ18: 6 | BP18: =(F18+H18+J18+L18+N18+P18+R18+T18+V18+X18+Z18+AB18+AF18+AH18+AJ18+AR18+BL18+AL18+AD18+AN18+AP18+AT18+AV18+AX18+AZ18+BB18+BD18+BF18+BH18+BJ18)+1 -> 93 | BQ18: =G18+I18+K18+M18+O18+Q18+S18+W18+U18+Y18+AA18+BM18+AC18+AG18+AI18+AK18+AS18+AE18+AM18+AO18+AQ18+AU18+AW18+AY18+BA18+BC18+BE18+BG18+BI18+BK18 -> 0 | BR18: =BQ18*C18 -> 0 | BS18: =BP18*C18 -> 19995
B19: 4283 | C19: 288 | D19: Премиум | E19: ='Матрица 4 недели'!M10 -> Плов ташкентский с говядиной | F19: 2 | H19: 3 | J19: 3 | L19: 2 | N19: 2 | P19: 3 | R19: 2 | T19: 3 | V19: 2 | X19: 1 | AB19: 1 | AD19: 3 | AF19: 3 | AH19: 3 | AJ19: 2 | AL19: 2 | AN19: 2 | AP19: 3 | AR19: 2 | AT19: 3 | AV19: 2 | AX19: 3 | AZ19: 3 | BB19: 0 | BD19: 2 | BF19: 2 | BH19: 3 | BJ19: 3 | BP19: =(F19+H19+J19+L19+N19+P19+R19+T19+V19+X19+Z19+AB19+AF19+AH19+AJ19+AR19+BL19+AL19+AD19+AN19+AP19+AT19+AV19+AX19+AZ19+BB19+BD19+BF19+BH19+BJ19)+1 -> 66 | BQ19: =G19+I19+K19+M19+O19+Q19+S19+W19+U19+Y19+AA19+BM19+AC19+AG19+AI19+AK19+AS19+AE19+AM19+AO19+AQ19+AU19+AW19+AY19+BA19+BC19+BE19+BG19+BI19+BK19 -> 0 | BR19: =BQ19*C19 -> 0 | BS19: =BP19*C19 -> 19008
E20: ='Матрица 4 недели'!M11 | BP20: =(F20+H20+J20+L20+N20+P20+R20+T20+V20+X20+Z20+AB20+AF20+AH20+AJ20+AR20+BL20+AL20+AD20+AN20+AP20+AT20+AV20+AX20+AZ20+BB20+BD20+BF20+BH20+BJ20)+1 -> 1 | BQ20: =G20+I20+K20+M20+O20+Q20+S20+W20+U20+Y20+AA20+BM20+AC20+AG20+AI20+AK20+AS20+AE20+AM20+AO20+AQ20+AU20+AW20+AY20+BA20+BC20+BE20+BG20+BI20+BK20 -> 0 | BR20: =BQ20*C20 -> 0 | BS20: =BP20*C20 -> 0
B21: 33 | C21: 155 | D21: Сэндвич | E21: ='Матрица 4 недели'!S4 -> Сэндвич с копчёной курицей и сыром | F21: 10 | H21: 4 | J21: 2 | L21: 2 | N21: 6 | P21: 7 | R21: 3 | T21: 3 | V21: 3 | X21: 9 | AB21: 3 | AD21: 2 | AF21: 6 | AH21: 4 | AJ21: 4 | AL21: 3 | AN21: 3 | AP21: 4 | AR21: 5 | AT21: 3 | AV21: 2 | AX21: 2 | AZ21: 2 | BB21: 7 | BD21: 2 | BF21: 4 | BH21: 3 | BJ21: 2 | BP21: =(F21+H21+J21+L21+N21+P21+R21+T21+V21+X21+Z21+AB21+AF21+AH21+AJ21+AR21+BL21+AL21+AD21+AN21+AP21+AT21+AV21+AX21+AZ21+BB21+BD21+BF21+BH21+BJ21)+1 -> 111 | BQ21: =G21+I21+K21+M21+O21+Q21+S21+W21+U21+Y21+AA21+BM21+AC21+AG21+AI21+AK21+AS21+AE21+AM21+AO21+AQ21+AU21+AW21+AY21+BA21+BC21+BE21+BG21+BI21+BK21 -> 0 | BR21: =BQ21*C21 -> 0 | BS21: =BP21*C21 -> 17205
B22: 5 | C22: 155 | D22: Сэндвич | E22: ='Матрица 4 недели'!S5 -> Сэндвич с ветчиной и сыром | F22: 10 | H22: 3 | J22: 3 | L22: 4 | N22: 6 | P22: 7 | R22: 3 | T22: 2 | V22: 5 | X22: 10 | AB22: 4 | AD22: 4 | AF22: 7 | AH22: 5 | AJ22: 3 | AL22: 4 | AN22: 3 | AP22: 5 | AR22: 14 | AT22: 3 | AV22: 5 | AX22: 8 | AZ22: 3 | BB22: 8 | BD22: 3 | BF22: 6 | BH22: 5 | BJ22: 3 | BP22: =(F22+H22+J22+L22+N22+P22+R22+T22+V22+X22+Z22+AB22+AF22+AH22+AJ22+AR22+BL22+AL22+AD22+AN22+AP22+AT22+AV22+AX22+AZ22+BB22+BD22+BF22+BH22+BJ22)+1 -> 147 | BQ22: =G22+I22+K22+M22+O22+Q22+S22+W22+U22+Y22+AA22+BM22+AC22+AG22+AI22+AK22+AS22+AE22+AM22+AO22+AQ22+AU22+AW22+AY22+BA22+BC22+BE22+BG22+BI22+BK22 -> 0 | BR22: =BQ22*C22 -> 0 | BS22: =BP22*C22 -> 22785
B23: 3738 | C23: 173 | D23: Япония | E23: ='Матрица 4 недели'!V4 -> Ролл сэндвич с крабом | F23: 11 | H23: 4 | J23: 0 | L23: 2 | N23: 5 | P23: 2 | R23: 0 | T23: 2 | V23: 2 | X23: 4 | AB23: 2 | AD23: 0 | AF23: 1 | AH23: 1 | AJ23: 3 | AL23: 0 | AN23: 2 | AP23: 2 | AR23: 0 | AT23: 2 | AV23: 2 | AX23: 2 | AZ23: 2 | BB23: 2 | BD23: 2 | BF23: 5 | BH23: 2 | BJ23: 3 | BP23: =(F23+H23+J23+L23+N23+P23+R23+T23+V23+X23+Z23+AB23+AF23+AH23+AJ23+AR23+BL23+AL23+AD23+AN23+AP23+AT23+AV23+AX23+AZ23+BB23+BD23+BF23+BH23+BJ23)+1 -> 66 | BQ23: =G23+I23+K23+M23+O23+Q23+S23+W23+U23+Y23+AA23+BM23+AC23+AG23+AI23+AK23+AS23+AE23+AM23+AO23+AQ23+AU23+AW23+AY23+BA23+BC23+BE23+BG23+BI23+BK23 -> 0 | BR23: =BQ23*C23 -> 0 | BS23: =BP23*C23 -> 11418
BP24: =(F24+H24+J24+L24+N24+P24+R24+T24+V24+X24+Z24+AB24+AF24+AH24+AJ24+AR24+BL24+AL24+AD24+AN24+AP24+AT24+AV24+AX24+AZ24+BB24+BD24+BF24+BH24+BJ24)+1 -> 1 | BQ24: =G24+I24+K24+M24+O24+Q24+S24+W24+U24+Y24+AA24+BM24+AC24+AG24+AI24+AK24+AS24+AE24+AM24+AO24+AQ24+AU24+AW24+AY24+BA24+BC24+BE24+BG24+BI24+BK24 -> 0 | BR24: =BQ24*C24 -> 0 | BS24: =BP24*C24 -> 0
B25: 2079 | C25: 105 | D25: Выпечка | E25: ='Матрица 4 недели'!P4 -> Вафельная трубочка с вареной сгущенкой | F25: 36 | H25: 4 | J25: 3 | L25: 8 | N25: 8 | P25: 6 | R25: 7 | T25: 7 | V25: 16 | X25: 10 | AB25: 9 | AD25: 17 | AF25: 21 | AH25: 8 | AJ25: 9 | AL25: 4 | AN25: 5 | AP25: 18 | AR25: 4 | AT25: 8 | AV25: 7 | AX25: 9 | AZ25: 13 | BB25: 7 | BD25: 4 | BF25: 8 | BH25: 7 | BJ25: 7 | BP25: =(F25+H25+J25+L25+N25+P25+R25+T25+V25+X25+Z25+AB25+AF25+AH25+AJ25+AR25+BL25+AL25+AD25+AN25+AP25+AT25+AV25+AX25+AZ25+BB25+BD25+BF25+BH25+BJ25)+1 -> 271 | BQ25: =G25+I25+K25+M25+O25+Q25+S25+W25+U25+Y25+AA25+BM25+AC25+AG25+AI25+AK25+AS25+AE25+AM25+AO25+AQ25+AU25+AW25+AY25+BA25+BC25+BE25+BG25+BI25+BK25 -> 0 | BR25: =BQ25*C25 -> 0 | BS25: =BP25*C25 -> 28455
B26: 3518 | C26: 85 | D26: Выпечка | E26: ='Матрица 4 недели'!P5 -> Слойка ''Нежная'' с сыром 100 г | BP26: =(F26+H26+J26+L26+N26+P26+R26+T26+V26+X26+Z26+AB26+AF26+AH26+AJ26+AR26+BL26+AL26+AD26+AN26+AP26+AT26+AV26+AX26+AZ26+BB26+BD26+BF26+BH26+BJ26)+1 -> 1 | BQ26: =G26+I26+K26+M26+O26+Q26+S26+W26+U26+Y26+AA26+BM26+AC26+AG26+AI26+AK26+AS26+AE26+AM26+AO26+AQ26+AU26+AW26+AY26+BA26+BC26+BE26+BG26+BI26+BK26 -> 0 | BR26: =BQ26*C26 -> 0 | BS26: =BP26*C26 -> 85
B27: 3999 | C27: 98 | D27: Япония | E27: ='Матрица 4 недели'!V5 -> Морс ягодный 0,5 л | F27: 11 | H27: 5 | J27: 5 | L27: 6 | N27: 5 | P27: 16 | R27: 7 | T27: 0 | V27: 0 | X27: 5 | AB27: 0 | AD27: 0 | AF27: 5 | AH27: 5 | AJ27: 0 | AL27: 0 | AN27: 0 | AP27: 0 | AR27: 25 | AT27: 6 | AV27: 6 | AX27: 11 | AZ27: 10 | BB27: 7 | BD27: 9 | BF27: 17 | BH27: 11 | BJ27: 10 | BP27: =(F27+H27+J27+L27+N27+P27+R27+T27+V27+X27+Z27+AB27+AF27+AH27+AJ27+AR27+BL27+AL27+AD27+AN27+AP27+AT27+AV27+AX27+AZ27+BB27+BD27+BF27+BH27+BJ27)+1 -> 183 | BQ27: =G27+I27+K27+M27+O27+Q27+S27+W27+U27+Y27+AA27+BM27+AC27+AG27+AI27+AK27+AS27+AE27+AM27+AO27+AQ27+AU27+AW27+AY27+BA27+BC27+BE27+BG27+BI27+BK27 -> 0 | BR27: =BQ27*C27 -> 0 | BS27: =BP27*C27 -> 17934
B28: 822 | C28: 5 | D28: Выпечка | E28: ='Матрица 4 недели'!P6 -> Хлеб пшеничный | F28: 6 | H28: 3 | J28: 3 | L28: 3 | N28: 3 | P28: 5 | R28: 4 | T28: 3 | V28: 3 | X28: 3 | AB28: 3 | AD28: 3 | AF28: 5 | AH28: 3 | AJ28: 3 | AL28: 4 | AN28: 3 | AP28: 4 | AR28: 0 | AT28: 3 | AV28: 3 | AX28: 3 | AZ28: 15 | BB28: 3 | BD28: 3 | BF28: 6 | BH28: 8 | BJ28: 4 | BL28: 125 | BP28: =(F28+H28+J28+L28+N28+P28+R28+T28+V28+X28+Z28+AB28+AF28+AH28+AJ28+AR28+BL28+AL28+AD28+AN28+AP28+AT28+AV28+AX28+AZ28+BB28+BD28+BF28+BH28+BJ28)+1 -> 238 | BQ28: =G28+I28+K28+M28+O28+Q28+S28+W28+U28+Y28+AA28+BM28+AC28+AG28+AI28+AK28+AS28+AE28+AM28+AO28+AQ28+AU28+AW28+AY28+BA28+BC28+BE28+BG28+BI28+BK28 -> 0 | BR28: =BQ28*C28 -> 0 | BS28: =BP28*C28 -> 1190
E29: ='Матрица 4 недели'!V7 | BP29: =(F29+H29+J29+L29+N29+P29+R29+T29+V29+X29+Z29+AB29+AF29+AH29+AJ29+AR29+BL29+AL29+AD29+AN29+AP29+AT29+AV29+AX29+AZ29+BB29+BD29+BF29+BH29+BJ29)+1 -> 1 | BQ29: =G29+I29+K29+M29+O29+Q29+S29+W29+U29+Y29+AA29+BM29+AC29+AG29+AI29+AK29+AS29+AE29+AM29+AO29+AQ29+AU29+AW29+AY29+BA29+BC29+BE29+BG29+BI29+BK29 -> 0 | BR29: =BQ29*C29 -> 0 | BS29: =BP29*C29 -> 0
BN30: 20 | BP30: =(F30+H30+J30+L30+N30+P30+R30+T30+V30+X30+Z30+AB30+AF30+AH30+AJ30+AR30+BL30+AL30+AD30+AN30+AP30+AT30+AV30+AX30+AZ30+BB30+BD30+BF30+BH30+BJ30)+1 -> 1 | BQ30: =G30+I30+K30+M30+O30+Q30+S30+W30+U30+Y30+AA30+BM30+AC30+AG30+AI30+AK30+AS30+AE30+AM30+AO30+AQ30+AU30+AW30+AY30+BA30+BC30+BE30+BG30+BI30+BK30 -> 0 | BR30: =BQ30*C30 -> 0 | BS30: =BP30*C30 -> 0 | BT30: факт-план
BL31: ИТОГО | BP31: =SUM(BP4:BP30) -> 2569 | BQ31: =SUM(BQ4:BQ30) -> 0 | BR31: =SUM(BR4:BR30) -> 0 | BS31: =SUM(BS4:BS30) -> 362962 | BT31: =BR31-BS31 -> -362962
A33: Дата: | D33: 46257 | E33: Участок комплектации | J33: Выгружаем дату производства:
A34: по плану | C34: Цена | D34: категория | E34: Название блюда | F34: Т1 | H34: Т2 | J34: Т3 | L34: Т4 | N34: Т5 | P34: Т6 | R34: Т7 | T34: Т8 | V34: Т9 | X34: Т10 | Z34: Т11 | AB34: Т12 | AD34: Т13 | AF34: Т14 | AH34: Т15 | AJ34: Т16 | AL34: Т17 | AN34: Т18 | AP34: Т19 | AR34: Т20 | AT34: Т21 | AV34: Т22 | AX34: Т23 | AZ34: Т24 | BB34: Т25 | BD34: Т26 | BF34: Т27 | BH34: Т28 | BJ34: Т29 | BL34: СПК | BN34: ИТОГ
A35: =A4 | B35: 4323 | C35: 210 | E35: =E4 -> Груша запеченая с творожным кремом | F35: =G4 | H35: =I4 | J35: =K4 | L35: =M4 | N35: =O4 | P35: =Q4 | R35: =S4 | T35: =U4 | V35: =W4 | X35: =Y4 | Z35: =AA4 | AB35: =AC4 | AD35: =AE4 | AF35: =AG4 | AH35: =AI4 | AJ35: =AK4 | AL35: =AM4 | AN35: =AO4 | AP35: =AQ4 | AR35: =AS4 | AT35: =AU4 | AV35: =AW4 | AX35: =AY4 | AZ35: =BA4 | BB35: =BC4 | BD35: =BE4 | BF35: =BG4 | BH35: =BI4 | BJ35: =BK4 | BL35: =BM4 | BN35: =SUM(F35:BM35) -> 0
A36: =A5 | B36: 1557 | C36: 98 | E36: =E5 -> Каша пшенная (на молоке) | F36: =G5 | H36: =I5 | J36: =K5 | L36: =M5 | N36: =O5 | P36: =Q5 | R36: =S5 | T36: =U5 | V36: =W5 | X36: =Y5 | Z36: =AA5 | AB36: =AC5 | AD36: =AE5 | AF36: =AG5 | AH36: =AI5 | AJ36: =AK5 | AL36: =AM5 | AN36: =AO5 | AP36: =AQ5 | AR36: =AS5 | AT36: =AU5 | AV36: =AW5 | AX36: =AY5 | AZ36: =BA5 | BB36: =BC5 | BD36: =BE5 | BF36: =BG5 | BH36: =BI5 | BJ36: =BK5 | BL36: =BM5 | BN36: =SUM(F36:BM36) -> 0
A37: =A6 | B37: 1550 | C37: 158 | E37: =E6 -> Омлет с овощами и сыром | F37: =G6 | H37: =I6 | J37: =K6 | L37: =M6 | N37: =O6 | P37: =Q6 | R37: =S6 | T37: =U6 | V37: =W6 | X37: =Y6 | Z37: =AA6 | AB37: =AC6 | AD37: =AE6 | AF37: =AG6 | AH37: =AI6 | AJ37: =AK6 | AL37: =AM6 | AN37: =AO6 | AP37: =AQ6 | AR37: =AS6 | AT37: =AU6 | AV37: =AW6 | AX37: =AY6 | AZ37: =BA6 | BB37: =BC6 | BD37: =BE6 | BF37: =BG6 | BH37: =BI6 | BJ37: =BK6 | BL37: =BM6 | BN37: =SUM(F37:BM37) -> 0
A38: =A7 | B38: 3076 | C38: 98 | E38: =E7 -> Салат ''Оливье'' (колбаса варен) | F38: =G7 | H38: =I7 | J38: =K7 | L38: =M7 | N38: =O7 | P38: =Q7 | R38: =S7 | T38: =U7 | V38: =W7 | X38: =Y7 | Z38: =AA7 | AB38: =AC7 | AD38: =AE7 | AF38: =AG7 | AH38: =AI7 | AJ38: =AK7 | AL38: =AM7 | AN38: =AO7 | AP38: =AQ7 | AR38: =AS7 | AT38: =AU7 | AV38: =AW7 | AX38: =AY7 | AZ38: =BA7 | BB38: =BC7 | BD38: =BE7 | BF38: =BG7 | BH38: =BI7 | BJ38: =BK7 | BL38: =BM7 | BN38: =SUM(F38:BM38) -> 0
A39: =A8 | B39: 4009 | C39: 98 | E39: =E8 -> Салат "Маковый" (курица, мак) | F39: =G8 | H39: =I8 | J39: =K8 | L39: =M8 | N39: =O8 | P39: =Q8 | R39: =S8 | T39: =U8 | V39: =W8 | X39: =Y8 | Z39: =AA8 | AB39: =AC8 | AD39: =AE8 | AF39: =AG8 | AH39: =AI8 | AJ39: =AK8 | AL39: =AM8 | AN39: =AO8 | AP39: =AQ8 | AR39: =AS8 | AT39: =AU8 | AV39: =AW8 | AX39: =AY8 | AZ39: =BA8 | BB39: =BC8 | BD39: =BE8 | BF39: =BG8 | BH39: =BI8 | BJ39: =BK8 | BL39: =BM8 | BN39: =SUM(F39:BM39) -> 0
A40: =A9 | B40: 3170 | C40: 98 | E40: =E9 -> Салат ''Фунчоза'' 120 г | F40: =G9 | H40: =I9 | J40: =K9 | L40: =M9 | N40: =O9 | P40: =Q9 | R40: =S9 | T40: =U9 | V40: =W9 | X40: =Y9 | Z40: =AA9 | AB40: =AC9 | AD40: =AE9 | AF40: =AG9 | AH40: =AI9 | AJ40: =AK9 | AL40: =AM9 | AN40: =AO9 | AP40: =AQ9 | AR40: =AS9 | AT40: =AU9 | AV40: =AW9 | AX40: =AY9 | AZ40: =BA9 | BB40: =BC9 | BD40: =BE9 | BF40: =BG9 | BH40: =BI9 | BJ40: =BK9 | BL40: =BM9 | BN40: =SUM(F40:BM40) -> 0
A41: =A10 | B41: 2621 | C41: 244 | E41: =E10 -> Салат ''Цезарь с курицей'' | F41: =G10 | H41: =I10 | J41: =K10 | L41: =M10 | N41: =O10 | P41: =Q10 | R41: =S10 | T41: =U10 | V41: =W10 | X41: =Y10 | Z41: =AA10 | AB41: =AC10 | AD41: =AE10 | AF41: =AG10 | AH41: =AI10 | AJ41: =AK10 | AL41: =AM10 | AN41: =AO10 | AP41: =AQ10 | AR41: =AS10 | AT41: =AU10 | AV41: =AW10 | AX41: =AY10 | AZ41: =BA10 | BB41: =BC10 | BD41: =BE10 | BF41: =BG10 | BH41: =BI10 | BJ41: =BK10 | BL41: =BM10 | BN41: =SUM(F41:BM41) -> 0
A42: =A11 | B42: 2203 | C42: 96 | E42: =E11 -> Борщ с мясом | F42: =G11 | H42: =I11 | J42: =K11 | L42: =M11 | N42: =O11 | P42: =Q11 | R42: =S11 | T42: =U11 | V42: =W11 | X42: =Y11 | Z42: =AA11 | AB42: =AC11 | AD42: =AE11 | AF42: =AG11 | AH42: =AI11 | AJ42: =AK11 | AL42: =AM11 | AN42: =AO11 | AP42: =AQ11 | AR42: =AS11 | AT42: =AU11 | AV42: =AW11 | AX42: =AY11 | AZ42: =BA11 | BB42: =BC11 | BD42: =BE11 | BF42: =BG11 | BH42: =BI11 | BJ42: =BK11 | BL42: =BM11 | BN42: =SUM(F42:BM42) -> 0
A43: =A12 | B43: 100 | C43: 90 | E43: =E12 -> Крем-суп овощной с курицей | F43: =G12 | H43: =I12 | J43: =K12 | L43: =M12 | N43: =O12 | P43: =Q12 | R43: =S12 | T43: =U12 | V43: =W12 | X43: =Y12 | Z43: =AA12 | AB43: =AC12 | AD43: =AE12 | AF43: =AG12 | AH43: =AI12 | AJ43: =AK12 | AL43: =AM12 | AN43: =AO12 | AP43: =AQ12 | AR43: =AS12 | AT43: =AU12 | AV43: =AW12 | AX43: =AY12 | AZ43: =BA12 | BB43: =BC12 | BD43: =BE12 | BF43: =BG12 | BH43: =BI12 | BJ43: =BK12 | BL43: =BM12 | BN43: =SUM(F43:BM43) -> 0
A44: =A13 | B44: 4233 | C44: 211 | E44: =E13 -> Свинина с тмином с тушеной капустой | F44: =G13 | H44: =I13 | J44: =K13 | L44: =M13 | N44: =O13 | P44: =Q13 | R44: =S13 | T44: =U13 | V44: =W13 | X44: =Y13 | Z44: =AA13 | AB44: =AC13 | AD44: =AE13 | AF44: =AG13 | AH44: =AI13 | AJ44: =AK13 | AL44: =AM13 | AN44: =AO13 | AP44: =AQ13 | AR44: =AS13 | AT44: =AU13 | AV44: =AW13 | AX44: =AY13 | AZ44: =BA13 | BB44: =BC13 | BD44: =BE13 | BF44: =BG13 | BH44: =BI13 | BJ44: =BK13 | BL44: =BM13 | BN44: =SUM(F44:BM44) -> 0
A45: =A14 | B45: 4014 | C45: 241 | E45: =E14 -> Филе с сыром и печеным картофелем | F45: =G14 | H45: =I14 | J45: =K14 | L45: =M14 | N45: =O14 | P45: =Q14 | R45: =S14 | T45: =U14 | V45: =W14 | X45: =Y14 | Z45: =AA14 | AB45: =AC14 | AD45: =AE14 | AF45: =AG14 | AH45: =AI14 | AJ45: =AK14 | AL45: =AM14 | AN45: =AO14 | AP45: =AQ14 | AR45: =AS14 | AT45: =AU14 | AV45: =AW14 | AX45: =AY14 | AZ45: =BA14 | BB45: =BC14 | BD45: =BE14 | BF45: =BG14 | BH45: =BI14 | BJ45: =BK14 | BL45: =BM14 | BN45: =SUM(F45:BM45) -> 0
A46: =A15 | B46: 4196 | C46: 243 | E46: =E15 -> Филе с сыром и макаронами | F46: =G15 | H46: =I15 | J46: =K15 | L46: =M15 | N46: =O15 | P46: =Q15 | R46: =S15 | T46: =U15 | V46: =W15 | X46: =Y15 | Z46: =AA15 | AB46: =AC15 | AD46: =AE15 | AF46: =AG15 | AH46: =AI15 | AJ46: =AK15 | AL46: =AM15 | AN46: =AO15 | AP46: =AQ15 | AR46: =AS15 | AT46: =AU15 | AV46: =AW15 | AX46: =AY15 | AZ46: =BA15 | BB46: =BC15 | BD46: =BE15 | BF46: =BG15 | BH46: =BI15 | BJ46: =BK15 | BL46: =BM15 | BN46: =SUM(F46:BM46) -> 0
A47: =A16 | B47: 4324 | C47: 208 | E47: =E16 -> Спагетти в сливочном соусе с грибами | F47: =G16 | H47: =I16 | J47: =K16 | L47: =M16 | N47: =O16 | P47: =Q16 | R47: =S16 | T47: =U16 | V47: =W16 | X47: =Y16 | Z47: =AA16 | AB47: =AC16 | AD47: =AE16 | AF47: =AG16 | AH47: =AI16 | AJ47: =AK16 | AL47: =AM16 | AN47: =AO16 | AP47: =AQ16 | AR47: =AS16 | AT47: =AU16 | AV47: =AW16 | AX47: =AY16 | AZ47: =BA16 | BB47: =BC16 | BD47: =BE16 | BF47: =BG16 | BH47: =BI16 | BJ47: =BK16 | BL47: =BM16 | BN47: =SUM(F47:BM47) -> 0
A48: =A18 | B48: 3054 | C48: 198 | E48: =E17 -> Минтай под овощами с рисом | F48: =G17 | H48: =I17 | J48: =K17 | L48: =M17 | N48: =O17 | P48: =Q17 | R48: =S17 | T48: =U17 | V48: =W17 | X48: =Y17 | Z48: =AA17 | AB48: =AC17 | AD48: =AE17 | AF48: =AG17 | AH48: =AI17 | AJ48: =AK17 | AL48: =AM17 | AN48: =AO17 | AP48: =AQ17 | AR48: =AS17 | AT48: =AU17 | AV48: =AW17 | AX48: =AY17 | AZ48: =BA17 | BB48: =BC17 | BD48: =BE17 | BF48: =BG17 | BH48: =BI17 | BJ48: =BK17 | BL48: =BM17 | BN48: =SUM(F48:BM48) -> 0
A49: =A19 | B49: 3239 | C49: 215 | E49: =E18 -> Минтай под овощами с рисом Радуга | F49: =G18 | H49: =I18 | J49: =K18 | L49: =M18 | N49: =O18 | P49: =Q18 | R49: =S18 | T49: =U18 | V49: =W18 | X49: =Y18 | Z49: =AA18 | AB49: =AC18 | AD49: =AE18 | AF49: =AG18 | AH49: =AI18 | AJ49: =AK18 | AL49: =AM18 | AN49: =AO18 | AP49: =AQ18 | AR49: =AS18 | AT49: =AU18 | AV49: =AW18 | AX49: =AY18 | AZ49: =BA18 | BB49: =BC18 | BD49: =BE18 | BF49: =BG18 | BH49: =BI18 | BJ49: =BK18 | BL49: =BM18 | BN49: =SUM(F49:BM49) -> 0
A50: =A20 | B50: 4283 | C50: 288 | E50: =E19 -> Плов ташкентский с говядиной | F50: =G19 | H50: =I19 | J50: =K19 | L50: =M19 | N50: =O19 | P50: =Q19 | R50: =S19 | T50: =U19 | V50: =W19 | X50: =Y19 | Z50: =AA19 | AB50: =AC19 | AD50: =AE19 | AF50: =AG19 | AH50: =AI19 | AJ50: =AK19 | AL50: =AM19 | AN50: =AO19 | AP50: =AQ19 | AR50: =AS19 | AT50: =AU19 | AV50: =AW19 | AX50: =AY19 | AZ50: =BA19 | BB50: =BC19 | BD50: =BE19 | BF50: =BG19 | BH50: =BI19 | BJ50: =BK19 | BL50: =BM19 | BN50: =SUM(F50:BM50) -> 0
A51: =A21 | E51: =E20 | F51: =G20 | H51: =I20 | J51: =K20 | L51: =M20 | N51: =O20 | P51: =Q20 | R51: =S20 | T51: =U20 | V51: =W20 | X51: =Y20 | Z51: =AA20 | AB51: =AC20 | AD51: =AE20 | AF51: =AG20 | AH51: =AI20 | AJ51: =AK20 | AL51: =AM20 | AN51: =AO20 | AP51: =AQ20 | AR51: =AS20 | AT51: =AU20 | AV51: =AW20 | AX51: =AY20 | AZ51: =BA20 | BB51: =BC20 | BD51: =BE20 | BF51: =BG20 | BH51: =BI20 | BJ51: =BK20 | BL51: =BM20 | BN51: =SUM(F51:BM51) -> 0
A52: =A22 | B52: 33 | C52: 155 | E52: =E21 -> Сэндвич с копчёной курицей и сыром | F52: =G21 | H52: =I21 | J52: =K21 | L52: =M21 | N52: =O21 | P52: =Q21 | R52: =S21 | T52: =U21 | V52: =W21 | X52: =Y21 | Z52: =AA21 | AB52: =AC21 | AD52: =AE21 | AF52: =AG21 | AH52: =AI21 | AJ52: =AK21 | AL52: =AM21 | AN52: =AO21 | AP52: =AQ21 | AR52: =AS21 | AT52: =AU21 | AV52: =AW21 | AX52: =AY21 | AZ52: =BA21 | BB52: =BC21 | BD52: =BE21 | BF52: =BG21 | BH52: =BI21 | BJ52: =BK21 | BL52: =BM21 | BN52: =SUM(F52:BM52) -> 0
A53: =A23 | B53: 5 | C53: 155 | E53: =E22 -> Сэндвич с ветчиной и сыром | F53: =G22 | H53: =I22 | J53: =K22 | L53: =M22 | N53: =O22 | P53: =Q22 | R53: =S22 | T53: =U22 | V53: =W22 | X53: =Y22 | Z53: =AA22 | AB53: =AC22 | AD53: =AE22 | AF53: =AG22 | AH53: =AI22 | AJ53: =AK22 | AL53: =AM22 | AN53: =AO22 | AP53: =AQ22 | AR53: =AS22 | AT53: =AU22 | AV53: =AW22 | AX53: =AY22 | AZ53: =BA22 | BB53: =BC22 | BD53: =BE22 | BF53: =BG22 | BH53: =BI22 | BJ53: =BK22 | BL53: =BM22 | BN53: =SUM(F53:BM53) -> 0
A54: =A24 | B54: 3738 | C54: 173 | E54: =E23 -> Ролл сэндвич с крабом | F54: =G23 | H54: =I23 | J54: =K23 | L54: =M23 | N54: =O23 | P54: =Q23 | R54: =S23 | T54: =U23 | V54: =W23 | X54: =Y23 | Z54: =AA23 | AB54: =AC23 | AD54: =AE23 | AF54: =AG23 | AH54: =AI23 | AJ54: =AK23 | AL54: =AM23 | AN54: =AO23 | AP54: =AQ23 | AR54: =AS23 | AT54: =AU23 | AV54: =AW23 | AX54: =AY23 | AZ54: =BA23 | BB54: =BC23 | BD54: =BE23 | BF54: =BG23 | BH54: =BI23 | BJ54: =BK23 | BL54: =BM23 | BN54: =SUM(F54:BM54) -> 0
A55: =A25 | E55: =E24 | F55: =G24 | H55: =I24 | J55: =K24 | L55: =M24 | N55: =O24 | P55: =Q24 | R55: =S24 | T55: =U24 | V55: =W24 | X55: =Y24 | Z55: =AA24 | AB55: =AC24 | AD55: =AE24 | AF55: =AG24 | AH55: =AI24 | AJ55: =AK24 | AL55: =AM24 | AN55: =AO24 | AP55: =AQ24 | AR55: =AS24 | AT55: =AU24 | AV55: =AW24 | AX55: =AY24 | AZ55: =BA24 | BB55: =BC24 | BD55: =BE24 | BF55: =BG24 | BH55: =BI24 | BJ55: =BK24 | BL55: =BM24 | BN55: =SUM(F55:BM55) -> 0
A56: =A26 | B56: 2079 | C56: 105 | E56: =E25 -> Вафельная трубочка с вареной сгущенкой | F56: =G25 | H56: =I25 | J56: =K25 | L56: =M25 | N56: =O25 | P56: =Q25 | R56: =S25 | T56: =U25 | V56: =W25 | X56: =Y25 | Z56: =AA25 | AB56: =AC25 | AD56: =AE25 | AF56: =AG25 | AH56: =AI25 | AJ56: =AK25 | AL56: =AM25 | AN56: =AO25 | AP56: =AQ25 | AR56: =AS25 | AT56: =AU25 | AV56: =AW25 | AX56: =AY25 | AZ56: =BA25 | BB56: =BC25 | BD56: =BE25 | BF56: =BG25 | BH56: =BI25 | BJ56: =BK25 | BL56: =BM25 | BN56: =SUM(F56:BM56) -> 0
A57: =A27 | B57: 3518 | C57: 85 | E57: =E26 -> Слойка ''Нежная'' с сыром 100 г | F57: =G26 | H57: =I26 | J57: =K26 | L57: =M26 | N57: =O26 | P57: =Q26 | R57: =S26 | T57: =U26 | V57: =W26 | X57: =Y26 | Z57: =AA26 | AB57: =AC26 | AD57: =AE26 | AF57: =AG26 | AH57: =AI26 | AJ57: =AK26 | AL57: =AM26 | AN57: =AO26 | AP57: =AQ26 | AR57: =AS26 | AT57: =AU26 | AV57: =AW26 | AX57: =AY26 | AZ57: =BA26 | BB57: =BC26 | BD57: =BE26 | BF57: =BG26 | BH57: =BI26 | BJ57: =BK26 | BL57: =BM26 | BN57: =SUM(F57:BM57) -> 0
A58: =A28 | B58: 3999 | C58: 98 | E58: =E27 -> Морс ягодный 0,5 л | F58: =G27 | H58: =I27 | J58: =K27 | L58: =M27 | N58: =O27 | P58: =Q27 | R58: =S27 | T58: =U27 | V58: =W27 | X58: =Y27 | Z58: =AA27 | AB58: =AC27 | AD58: =AE27 | AF58: =AG27 | AH58: =AI27 | AJ58: =AK27 | AL58: =AM27 | AN58: =AO27 | AP58: =AQ27 | AR58: =AS27 | AT58: =AU27 | AV58: =AW27 | AX58: =AY27 | AZ58: =BA27 | BB58: =BC27 | BD58: =BE27 | BF58: =BG27 | BH58: =BI27 | BJ58: =BK27 | BL58: =BM27 | BN58: =SUM(F58:BM58) -> 0
A59: =A29 | B59: 822 | C59: 5 | E59: =E28 -> Хлеб пшеничный | F59: =G28 | H59: =I28 | J59: =K28 | L59: =M28 | N59: =O28 | P59: =Q28 | R59: =S28 | T59: =U28 | V59: =W28 | X59: =Y28 | Z59: =AA28 | AB59: =AC28 | AD59: =AE28 | AF59: =AG28 | AH59: =AI28 | AJ59: =AK28 | AL59: =AM28 | AN59: =AO28 | AP59: =AQ28 | AR59: =AS28 | AT59: =AU28 | AV59: =AW28 | AX59: =AY28 | AZ59: =BA28 | BB59: =BC28 | BD59: =BE28 | BF59: =BG28 | BH59: =BI28 | BJ59: =BK28 | BL59: =BM28 | BN59: =SUM(F59:BM59) -> 0
E60: =E29 | F60: =G29 | H60: =I29 | J60: =K29 | L60: =M29 | N60: =O29 | P60: =Q29 | R60: =S29 | T60: =U29 | V60: =W29 | X60: =Y29 | Z60: =AA29 | AB60: =AC29 | AD60: =AE29 | AF60: =AG29 | AH60: =AI29 | AJ60: =AK29 | AL60: =AM29 | AN60: =AO29 | AP60: =AQ29 | AR60: =AS29 | AT60: =AU29 | AV60: =AW29 | AX60: =AY29 | AZ60: =BA29 | BB60: =BC29 | BD60: =BE29 | BF60: =BG29 | BH60: =BI29 | BJ60: =BK29 | BL60: =BM29 | BN60: =SUM(F60:BM60) -> 0
A61: =A30 | E61: =E30 | BN61: =SUM(F61:BM61) -> 0
BL62: ИТОГО | BN62: =SUM(BN35:BN58) -> 0
A64: Дата: | D64: 46230 | E64: План на день кухня ПОНЕДЕЛЬНИК
A65: по плану | B65: Код | C65: Цена | D65: категория | E65: Название блюда | F65: Т1 | G65: Ф1 | H65: Т2 | I65: Ф2 | J65: Т3 | K65: Ф3 | L65: Т4 | M65: Ф4 | N65: Т5 | O65: Ф5 | P65: Т6 | Q65: Ф6 | R65: Т7 | S65: Ф7 | T65: Т8 | U65: Ф8 | V65: Т9 | W65: Ф9 | X65: Т10 | Y65: Ф10 | Z65: Т11 | AA65: Ф11 | AB65: Т12 | AC65: Ф12 | AD65: Т13 | AE65: Ф13 | AF65: Т14 | AG65: Ф14 | AH65: Т15 | AI65: Ф15 | AJ65: Т16 | AK65: Ф16 | AL65: Т17 | AM65: Ф17 | AN65: Т18 | AO65: Ф18 | AP65: Т19 | AQ65: Ф19 | AR65: Т20 | AS65: Ф20 | AT65: Т21 | AU65: Ф21 | AV65: Т22 | AW65: Ф22 | AX65: Т23 | AY65: Ф23 | AZ65: Т24 | BA65: Ф24 | BB65: Т25 | BC65: Ф25 | BD65: Т26 | BE65: Ф26 | BF65: Т27 | BG65: Ф27 | BH65: Т28 | BI65: Ф28 | BJ65: Т29 | BK65: Ф29 | BL65: ТСПК | BM65: ФСПК | BN65: Стол | BO65: Ф.Стол | BP65: ПЛАН | BQ65: СДАЛИ | BR65: Ф.Цена | BS65: Пл.цена
B66: 3196 | C66: 97 | D66: Завтрак | E66: ='Матрица 4 недели'!D13 -> Манник ''Маковый'' | F66: 5 | H66: 2 | J66: 2 | L66: 3 | N66: 8 | P66: 4 | R66: 2 | T66: 3 | V66: 3 | X66: 3 | AB66: 3 | AD66: 5 | AF66: 8 | AH66: 3 | AJ66: 3 | AL66: 2 | AN66: 3 | AP66: 4 | AR66: 12 | AT66: 6 | AV66: 3 | AX66: 3 | AZ66: 2 | BB66: 2 | BD66: 2 | BF66: 3 | BH66: 4 | BJ66: 6 | BP66: =(F66+H66+J66+L66+N66+P66+R66+T66+V66+X66+Z66+AB66+AD66+AF66+AH66+AJ66+AL66+AR66+BL66+AN66+AP66+AT66+AV66+AX66+AZ66+BB66+BD66+BF66+BH66+BJ66)+1 -> 110 | BQ66: =G66+I66+K66+M66+O66+Q66+S66+U66+W66+Y66+AA66+AC66+AE66+AG66+AI66+AK66+AM66+AO66+AQ66+AU66+AW66+BM66+AS66+AY66+BA66+BC66+BE66+BG66+BI66+BK66 -> 0 | BS66: =BP66*C66 -> 10670
B67: 4235 | C67: 158 | D67: Завтрак | E67: ='Матрица 4 недели'!D14 -> Киш с курицей | F67: 7 | H67: 2 | J67: 3 | L67: 4 | N67: 6 | P67: 2 | R67: 3 | T67: 4 | V67: 5 | X67: 2 | AB67: 3 | AD67: 1 | AF67: 8 | AH67: 5 | AJ67: 5 | AL67: 2 | AN67: 3 | AP67: 4 | AR67: 14 | AT67: 2 | AV67: 3 | AX67: 6 | AZ67: 2 | BB67: 2 | BD67: 2 | BF67: 3 | BH67: 4 | BJ67: 2 | BP67: =(F67+H67+J67+L67+N67+P67+R67+T67+V67+X67+Z67+AB67+AD67+AF67+AH67+AJ67+AL67+AR67+BL67+AN67+AP67+AT67+AV67+AX67+AZ67+BB67+BD67+BF67+BH67+BJ67)+1 -> 110 | BQ67: =G67+I67+K67+M67+O67+Q67+S67+U67+W67+Y67+AA67+AC67+AE67+AG67+AI67+AK67+AM67+AO67+AQ67+AU67+AW67+BM67+AS67+AY67+BA67+BC67+BE67+BG67+BI67+BK67 -> 0 | BR67: =BQ67*C67 -> 0 | BS67: =BP67*C67 -> 17380
B68: 4254 | C68: 186 | D68: Завтрак | E68: ='Матрица 4 недели'!D15 -> Творожный чизкейк | F68: 6 | H68: 2 | J68: 2 | L68: 2 | N68: 6 | P68: 2 | R68: 3 | T68: 4 | V68: 5 | X68: 2 | AB68: 2 | AD68: 3 | AF68: 6 | AH68: 5 | AJ68: 4 | AL68: 2 | AN68: 3 | AP68: 3 | AR68: 9 | AT68: 3 | AV68: 3 | AX68: 5 | AZ68: 2 | BB68: 2 | BD68: 2 | BF68: 3 | BH68: 2 | BJ68: 2 | BP68: =(F68+H68+J68+L68+N68+P68+R68+T68+V68+X68+Z68+AB68+AD68+AF68+AH68+AJ68+AL68+AR68+BL68+AN68+AP68+AT68+AV68+AX68+AZ68+BB68+BD68+BF68+BH68+BJ68)+1 -> 96 | BQ68: =G68+I68+K68+M68+O68+Q68+S68+U68+W68+Y68+AA68+AC68+AE68+AG68+AI68+AK68+AM68+AO68+AQ68+AU68+AW68+BM68+AS68+AY68+BA68+BC68+BE68+BG68+BI68+BK68 -> 0 | BR68: =BQ68*C68 -> 0 | BS68: =BP68*C68 -> 17856
B69: 4024 | C69: 98 | D69: Салат | E69: ='Матрица 4 недели'!G13 -> Салат "Чешский" (колбаса п/к) | F69: 3 | H69: 1 | J69: 2 | L69: 4 | N69: 6 | P69: 6 | R69: 2 | T69: 2 | V69: 2 | X69: 2 | AB69: 1 | AD69: 3 | AF69: 4 | AH69: 2 | AJ69: 4 | AL69: 2 | AN69: 2 | AP69: 2 | AR69: 5 | AT69: 4 | AV69: 0 | AX69: 2 | AZ69: 0 | BB69: 3 | BD69: 0 | BF69: 1 | BH69: 0 | BJ69: 3 | BL69: 44 | BP69: =(F69+H69+J69+L69+N69+P69+R69+T69+V69+X69+Z69+AB69+AD69+AF69+AH69+AJ69+AL69+AR69+BL69+AN69+AP69+AT69+AV69+AX69+AZ69+BB69+BD69+BF69+BH69+BJ69)+1 -> 113 | BQ69: =G69+I69+K69+M69+O69+Q69+S69+U69+W69+Y69+AA69+AC69+AE69+AG69+AI69+AK69+AM69+AO69+AQ69+AU69+AW69+BM69+AS69+AY69+BA69+BC69+BE69+BG69+BI69+BK69 -> 0 | BR69: =BQ69*C69 -> 0 | BS69: =BP69*C69 -> 11074
B70: 3379 | C70: 98 | D70: Салат | E70: ='Матрица 4 недели'!G14 -> Салат ''Зайка'' 120 г | F70: 7 | H70: 3 | J70: 2 | L70: 2 | N70: 10 | P70: 4 | R70: 5 | T70: 2 | V70: 2 | X70: 2 | AB70: 1 | AD70: 4 | AF70: 6 | AH70: 2 | AJ70: 2 | AL70: 6 | AN70: 2 | AP70: 4 | AR70: 12 | AT70: 6 | AV70: 2 | AX70: 3 | AZ70: 3 | BB70: 2 | BD70: 1 | BF70: 6 | BH70: 3 | BJ70: 4 | BL70: 43 | BP70: =(F70+H70+J70+L70+N70+P70+R70+T70+V70+X70+Z70+AB70+AD70+AF70+AH70+AJ70+AL70+AR70+BL70+AN70+AP70+AT70+AV70+AX70+AZ70+BB70+BD70+BF70+BH70+BJ70)+1 -> 152 | BQ70: =G70+I70+K70+M70+O70+Q70+S70+U70+W70+Y70+AA70+AC70+AE70+AG70+AI70+AK70+AM70+AO70+AQ70+AU70+AW70+BM70+AS70+AY70+BA70+BC70+BE70+BG70+BI70+BK70 -> 0 | BR70: =BQ70*C70 -> 0 | BS70: =BP70*C70 -> 14896
B71: 3244 | C71: 98 | D71: Салат | E71: ='Матрица 4 недели'!G15 -> Салат ''Крабик'' с рисом | F71: 8 | H71: 1 | J71: 2 | L71: 4 | N71: 4 | P71: 7 | R71: 3 | T71: 5 | V71: 4 | X71: 2 | AB71: 3 | AD71: 3 | AF71: 5 | AH71: 3 | AJ71: 6 | AL71: 6 | AN71: 2 | AP71: 9 | AR71: 11 | AT71: 5 | AV71: 2 | AX71: 8 | AZ71: 2 | BB71: 3 | BD71: 3 | BF71: 8 | BH71: 2 | BJ71: 6 | BL71: 43 | BP71: =(F71+H71+J71+L71+N71+P71+R71+T71+V71+X71+Z71+AB71+AD71+AF71+AH71+AJ71+AL71+AR71+BL71+AN71+AP71+AT71+AV71+AX71+AZ71+BB71+BD71+BF71+BH71+BJ71)+1 -> 171 | BQ71: =G71+I71+K71+M71+O71+Q71+S71+U71+W71+Y71+AA71+AC71+AE71+AG71+AI71+AK71+AM71+AO71+AQ71+AU71+AW71+BM71+AS71+AY71+BA71+BC71+BE71+BG71+BI71+BK71 -> 0 | BR71: =BQ71*C71 -> 0 | BS71: =BP71*C71 -> 16758
B72: 3343 | C72: 272 | D72: Премиум | E72: ='Матрица 4 недели'!G16 -> Боул с тунцом , бобами эдамаме и овощами | F72: 4 | H72: 1 | J72: 5 | L72: 3 | N72: 4 | P72: 2 | R72: 1 | T72: 1 | V72: 2 | X72: 0 | AB72: 2 | AD72: 0 | AF72: 3 | AH72: 2 | AJ72: 1 | AL72: 0 | AN72: 2 | AP72: 2 | AR72: 2 | AT72: 2 | AV72: 2 | AX72: 3 | AZ72: 1 | BB72: 0 | BD72: 1 | BF72: 2 | BH72: 2 | BJ72: 5 | BP72: =(F72+H72+J72+L72+N72+P72+R72+T72+V72+X72+Z72+AB72+AD72+AF72+AH72+AJ72+AL72+AR72+BL72+AN72+AP72+AT72+AV72+AX72+AZ72+BB72+BD72+BF72+BH72+BJ72)+1 -> 56 | BQ72: =G72+I72+K72+M72+O72+Q72+S72+U72+W72+Y72+AA72+AC72+AE72+AG72+AI72+AK72+AM72+AO72+AQ72+AU72+AW72+BM72+AS72+AY72+BA72+BC72+BE72+BG72+BI72+BK72 -> 0 | BR72: =BQ72*C72 -> 0 | BS72: =BP72*C72 -> 15232
B73: 8 | C73: 104 | D73: Суп | E73: ='Матрица 4 недели'!J13 -> Суп гороховый 250 мл | BL73: 110 | BP73: =(F73+H73+J73+L73+N73+P73+R73+T73+V73+X73+Z73+AB73+AD73+AF73+AH73+AJ73+AL73+AR73+BL73+AN73+AP73+AT73+AV73+AX73+AZ73+BB73+BD73+BF73+BH73+BJ73)+1 -> 111 | BQ73: =G73+I73+K73+M73+O73+Q73+S73+U73+W73+Y73+AA73+AC73+AE73+AG73+AI73+AK73+AM73+AO73+AQ73+AU73+AW73+BM73+AS73+AY73+BA73+BC73+BE73+BG73+BI73+BK73 -> 0 | BR73: =BQ73*C73 -> 0 | BS73: =BP73*C73 -> 11544
E74: ='Матрица 4 недели'!J14 | BP74: =(F74+H74+J74+L74+N74+P74+R74+T74+V74+X74+Z74+AB74+AD74+AF74+AH74+AJ74+AL74+AR74+BL74+AN74+AP74+AT74+AV74+AX74+AZ74+BB74+BD74+BF74+BH74+BJ74)+1 -> 1 | BQ74: =G74+I74+K74+M74+O74+Q74+S74+U74+W74+Y74+AA74+AC74+AE74+AG74+AI74+AK74+AM74+AO74+AQ74+AU74+AW74+BM74+AS74+AY74+BA74+BC74+BE74+BG74+BI74+BK74 -> 0 | BR74: =BQ74*C74 -> 0 | BS74: =BP74*C74 -> 0
